Workbook
Name _____Rt12: #REF!
Name _____Rt12: #REF!
Name _____Rt12: #REF!
Name _____Rt12: #REF!
Name _____Rt12: #REF!
Name _____Rt12: #REF!
Name ____Rt12: #REF!
Name ____Rt12: #REF!
Name ____Rt12: #REF!
Name ____Rt12: #REF!
Name ____Rt12: #REF!
Name ____Rt12: #REF!
Name ___Rt12: #REF!
Name ___Rt12: #REF!
Name ___Rt12: #REF!
Name ___Rt12: #REF!
Name ___Rt12: #REF!
Name ___Rt12: #REF!
Name __Rt12: #REF!
Name __Rt12: #REF!
Name __Rt12: #REF!
Name __Rt12: #REF!
Name __Rt12: #REF!
Name __Rt12: #REF!
Name __xlfn_SUMIFS: NA()
Name _Rt12: #REF!
Name _Rt12: #REF!
Name _Rt12: #REF!
Name _Rt12: #REF!
Name _Rt12: #REF!
Name _Rt12: #REF!
Name AJUSTES: #REF!
Name AJUSTES: #REF!
Name AJUSTES: #REF!
Name AJUSTES: #REF!
Name AJUSTES: #REF!
Name AJUSTES: #REF!
Name AJUSTES: #REF!
Name Assumptions: #REF!
Name Assumptions: #REF!
Name Assumptions: #REF!
Name Assumptions: #REF!
Name Assumptions: #REF!
Name Assumptions: #REF!
Name BuiltIn_Print_Area: #REF!
Name BuiltIn_Print_Area: #REF!
Name BuiltIn_Print_Area: #REF!
Name BuiltIn_Print_Area: #REF!
Name BuiltIn_Print_Area: #REF!
Name BuiltIn_Print_Area: #REF!
Name BuiltIn_Print_Area___0: #REF!
Name BuiltIn_Print_Area___0: #REF!
Name BuiltIn_Print_Area___0: #REF!
Name BuiltIn_Print_Area___0: #REF!
Name BuiltIn_Print_Area___0: #REF!
Name BuiltIn_Print_Area___0: #REF!
Name BuiltIn_Print_Titles: #REF!
Name BuiltIn_Print_Titles: #REF!
Name BuiltIn_Print_Titles: #REF!
Name BuiltIn_Print_Titles: #REF!

Sheet Mov_Analizados_Sept25 - Nov 25
G2: Ver Telefonos
G3: Ver Gastos devengados | I3: $ | J3: USD | K3: TC
G4: Ver Luz Devengada | H4: Food & Wine | I4: =+SUMIF($E$10:$E$371,H4,$I$10:$I$371) -> 13187448 | J4: =+SUMIF($E$10:$E$371,H4,$J$10:$J$371) -> 9389.8586 | K4: =+I4/J4 -> 1404.4352
G7: =+IF(I7+J7=0,"Ok","Check") -> Ok | I7: =ROUND(SUM(I10:I1080),0) -> 0 | J7: =ROUND(SUM(J10:J1080),0) -> 0
E8: Rubro | G8: =+Resumen_Base!C1 -> Ok
B9: =+F9&G9 | D9: DEL | E9: =+VLOOKUP(F9,Resumen_Base!$B$6:$F$69,5,0) -> #N/A | H9: =+D9&F9 -> DEL | I9: =SUM(I10:I371) -> 97836924 | J9: =SUM(J10:J371) -> 69488.431
A10: AJUSTES | B10: Cuenta Anterior | D10: Lodge | E10: Concepto | F10: Codigo Cuenta | G10: Cuenta Contable | I10: Saldo - $ | J10: Saldo - u$s | K10: Tipo cambio | L10: Fecha | M10: Modulo | N10: Cod Centro Costo | O10: gestionid | P10: Detalle | Q10: Observaciones | R10: Observación Adicional | S10: Número | T10: Ejercicio | AA10: tc | AC10: Fecha | AD10: Subdiario | AE10: Div | AF10: Datos del comprobante | AG10: Sujeto | AH10: CUIT | AI10: Observación asiento | AJ10: Clase de Asiento | AK10: Origen del comprobante | AL10: Observación del comprobante | AM10: Comentario renglón asiento | AN10: Asiento
A12: 12020103 | B12: 5226 | D12: DEL | E12: =+VLOOKUP(F12,Resumen_Base!$B$6:$F$69,5,0) -> Fixed Asset's Payments (Investments) Mejoras/equipamiento Lodge | F12: 12020103 | G12: Mejoras de Inmueb y Terrenos | H12: =+D12&F12 -> DEL12020103 | I12: 100000 | J12: 66.666667 | K12: 1500 | L12: 26/10/2025 | M12: CAJA | N12: 0141 | O12: TE001500000062 | P12: Asiento de CAJA (01/09/2025 - 31/08/2026) | Q12: Extracción de Caja 001500000062 Obs: 26-10-2025 Mov Lodge | R12: DT - Adicional padre de rolando por labores en la laguna | S12: 000000000061 | T12: Ejercicio 2025/2026
A13: 12020103 | B13: 5226 | D13: DEL | E13: =+VLOOKUP(F13,Resumen_Base!$B$6:$F$69,5,0) -> Fixed Asset's Payments (Investments) Mejoras/equipamiento Lodge | F13: 12020103 | G13: Mejoras de Inmueb y Terrenos | H13: =+D13&F13 -> DEL12020103 | I13: 15000 | J13: 10.791367 | K13: 1390 | L13: 30/09/2025 | M13: CAJA | N13: 0141 | O13: TE001500000030 | P13: Asiento de CAJA (01/09/2025 - 31/08/2026) | Q13: Extracción de Caja 001500000030 Obs: 30-09-2025 Mov Lodge | R13: DT - Noel le paga a constructor de lancha Laffranchi por ir a buscar el mismo los parlantes de la la | S13: 000000000036 | T13: Ejercicio 2025/2026
A14: 12020103 | B14: 5226 | D14: DEL | E14: =+VLOOKUP(F14,Resumen_Base!$B$6:$F$69,5,0) -> Fixed Asset's Payments (Investments) Mejoras/equipamiento Lodge | F14: 12020103 | G14: Mejoras de Inmueb y Terrenos | H14: =+D14&F14 -> DEL12020103 | I14: 300000 | J14: 200 | K14: 1500 | L14: 26/10/2025 | M14: CAJA | N14: 0141 | O14: TE001500000060 | P14: Asiento de CAJA (01/09/2025 - 31/08/2026) | Q14: Extracción de Caja 001500000060 Obs: 26-10-2025 INCOME OF MONEY | R14: DT - Noel paga adicional al padre de rolando por detalles en obra de laguna | S14: 000000000059 | T14: Ejercicio 2025/2026
D15: DEL | E15: =+VLOOKUP(F15,Resumen_Base!$B$6:$F$69,5,0) -> Fixed Asset's Payments (Investments) Mejoras/equipamiento Lodge | F15: 12020103 | G15: Mejoras de Inmueb y Terrenos | H15: =+D15&F15 -> DEL12020103 | I15: 7800000 | J15: 6000 | K15: 1300 | L15: 03/09/2025 | M15: CAJA | N15: 0141 | O15: TE001500000018 | P15: Asiento de CAJA | Q15: Extracción de Caja 001500000018 Obs: 14-09-2025 Mov Lodge | R15: DEL - Noel le paga adelantó a constructor rolando por obra de la Laguna | S15: 000000000016 | T15: Ejercicio 2025/2026
D16: DEL | E16: =+VLOOKUP(F16,Resumen_Base!$B$6:$F$69,5,0) -> Fixed Asset's Payments (Investments) Mejoras/equipamiento Lodge | F16: 12020103 | G16: Mejoras de Inmueb y Terrenos | H16: =+D16&F16 -> DEL12020103 | I16: 100000 | J16: 70.921986 | K16: 1410 | L16: 05/10/2025 | M16: CAJA | N16: 0141 | O16: TE001500000037 | P16: Asiento de CAJA (01/09/2025 - 31/08/2026) | Q16: Extracción de Caja 001500000037 Obs: 05-10-2025 Mov Lodge | R16: DT - Árboles para la Laguna | S16: 000000000039 | T16: Ejercicio 2025/2026
D17: DEL | E17: =+VLOOKUP(F17,Resumen_Base!$B$6:$F$69,5,0) -> Fixed Asset's Payments (Investments) Mejoras/equipamiento Lodge | F17: 12020103 | G17: Mejoras de Inmueb y Terrenos | H17: =+D17&F17 -> DEL12020103 | I17: 2860000 | J17: 2000 | K17: 1430 | L17: 12/10/2025 | M17: CAJA | N17: 0141 | O17: TE001500000047 | P17: Asiento de CAJA (01/09/2025 - 31/08/2026) | Q17: Extracción de Caja 001500000047 Obs: 12-10-2025 Mov Lodge | R17: DT - Noel le paga a Rolando constructor en concepto de adelanto por obra de Laguna | S17: 000000000044 | T17: Ejercicio 2025/2026
D18: DEL | E18: =+VLOOKUP(F18,Resumen_Base!$B$6:$F$69,5,0) -> Fixed Asset's Payments (Investments) Mejoras/equipamiento Lodge | F18: 12020103 | G18: Mejoras de Inmueb y Terrenos | H18: =+D18&F18 -> DEL12020103 | I18: 300000 | J18: 215.82734 | K18: 1390 | L18: 30/09/2025 | M18: CAJA | N18: 0141 | O18: TE001500000030 | P18: Asiento de CAJA (01/09/2025 - 31/08/2026) | Q18: Extracción de Caja 001500000030 Obs: 30-09-2025 Mov Lodge | R18: DT - Noel le paga adicional al padre de constructor rolando por agravar un canal en la obra de la La | S18: 000000000036 | T18: Ejercicio 2025/2026
D19: DEL | E19: =+VLOOKUP(F19,Resumen_Base!$B$6:$F$69,5,0) -> Fixed Asset's Payments (Investments) Mejoras/equipamiento Lodge | F19: 12020103 | G19: Mejoras de Inmueb y Terrenos | H19: =+D19&F19 -> DEL12020103 | I19: 450000 | J19: 316.90141 | K19: 1420 | L19: 30/11/2025 | M19: CAJA | N19: 0141 | O19: TE001500000085 | P19: Asiento de CAJA (01/09/2025 - 31/08/2026) | Q19: Extracción de Caja 001500000085 Obs: 30-11-2025 Mov Lodge | R19: DT - Noel paga al padre de rolando por agrandar un sector de la laguna | S19: 000000000083 | T19: Ejercicio 2025/2026
D20: DEL | E20: =+VLOOKUP(F20,Resumen_Base!$B$6:$F$69,5,0) -> Fixed Asset's Payments (Investments) Mejoras/equipamiento Lodge | F20: 12020103 | G20: Mejoras de Inmueb y Terrenos | H20: =+D20&F20 -> DEL12020103 | I20: 1050000 | J20: 700 | K20: 1500 | L20: 26/10/2025 | M20: CAJA | N20: 0141 | O20: TE001500000060 | P20: Asiento de CAJA (01/09/2025 - 31/08/2026) | Q20: Extracción de Caja 001500000060 Obs: 26-10-2025 INCOME OF MONEY | R20: DT - Obra de la escalera detrás de casa Noel | S20: 000000000059 | T20: Ejercicio 2025/2026
D21: DEL | E21: =+VLOOKUP(F21,Resumen_Base!$B$6:$F$69,5,0) -> Fixed Asset's Payments (Investments) Mejoras/equipamiento Lodge | F21: 12020103 | G21: Mejoras de Inmueb y Terrenos | H21: =+D21&F21 -> DEL12020103 | I21: 620000 | J21: 446.04317 | K21: 1390 | L21: 30/09/2025 | M21: CAJA | N21: 0141 | O21: TE001500000030 | P21: Asiento de CAJA (01/09/2025 - 31/08/2026) | Q21: Extracción de Caja 001500000030 Obs: 30-09-2025 Mov Lodge | R21: DT - Pago a Rolando por cañería para la Laguna | S21: 000000000036 | T21: Ejercicio 2025/2026
D22: DEL | E22: =+VLOOKUP(F22,Resumen_Base!$B$6:$F$69,5,0) -> Fixed Asset's Payments (Investments) Mejoras/equipamiento Lodge | F22: 12020103 | G22: Mejoras de Inmueb y Terrenos | H22: =+D22&F22 -> DEL12020103 | I22: 150000 | J22: 107.91367 | K22: 1390 | L22: 30/09/2025 | M22: CAJA | N22: 0141 | O22: TE001500000030 | P22: Asiento de CAJA (01/09/2025 - 31/08/2026) | Q22: Extracción de Caja 001500000030 Obs: 30-09-2025 Mov Lodge | R22: DT - Pago por tarea adicional en obre de Laguna, el padre del constructor de rolando le agrego un pe | S22: 000000000036 | T22: Ejercicio 2025/2026
D23: DEL | E23: =+VLOOKUP(F23,Resumen_Base!$B$6:$F$69,5,0) -> Fixed Asset's Payments (Investments) Mejoras/equipamiento Lodge | F23: 12020103 | G23: Mejoras de Inmueb y Terrenos | H23: =+D23&F23 -> DEL12020103 | I23: 9000 | J23: 6.2937063 | K23: 1430 | L23: 12/10/2025 | M23: CAJA | N23: 0141 | O23: TE001500000046 | P23: Asiento de CAJA (01/09/2025 - 31/08/2026) | Q23: Extracción de Caja 001500000046 Obs: 12-10-2025 Mov Lodge | R23: DT - Plantas agramaticas | S23: 000000000043 | T23: Ejercicio 2025/2026
D24: DEL | E24: =+VLOOKUP(F24,Resumen_Base!$B$6:$F$69,5,0) -> Fixed Asset's Payments (Investments) Mejoras/equipamiento Lodge | F24: 12020103 | G24: Mejoras de Inmueb y Terrenos | H24: =+D24&F24 -> DEL12020103 | I24: 76600 | J24: 51.066667 | K24: 1500 | L24: 26/10/2025 | M24: CAJA | N24: 0141 | O24: TE001500000062 | P24: Asiento de CAJA (01/09/2025 - 31/08/2026) | Q24: Extracción de Caja 001500000062 Obs: 26-10-2025 Mov Lodge | R24: DT - Plantas aromáticas | S24: 000000000061 | T24: Ejercicio 2025/2026
D25: DEL | E25: =+VLOOKUP(F25,Resumen_Base!$B$6:$F$69,5,0) -> Fixed Asset's Payments (Investments) Mejoras/equipamiento Lodge | F25: 12020103 | G25: Mejoras de Inmueb y Terrenos | H25: =+D25&F25 -> DEL12020103 | I25: 42000 | J25: 29.370629 | K25: 1430 | L25: 12/10/2025 | M25: CAJA | N25: 0141 | O25: TE001500000046 | P25: Asiento de CAJA (01/09/2025 - 31/08/2026) | Q25: Extracción de Caja 001500000046 Obs: 12-10-2025 Mov Lodge | R25: DT - Vivero plantas varias para el lodge | S25: 000000000043 | T25: Ejercicio 2025/2026
D26: DEL | E26: =+VLOOKUP(F26,Resumen_Base!$B$6:$F$69,5,0) -> Fixed Asset's Payments (Investments) Mejoras/equipamiento Lodge | F26: 12020103 | G26: Mejoras de Inmueb y Terrenos | H26: =+D26&F26 -> DEL12020103 | I26: 150000 | J26: 102.73973 | K26: 1460 | L26: 31/10/2025 | M26: CAJA | N26: 0141 | O26: TE001500000066 | P26: Asiento de CAJA (01/09/2025 - 31/08/2026) | Q26: Extracción de Caja 001500000066 Obs: Movimiento_Cajas_Bancos_Semana 25-26 al 31-10-2025 | R26: DT-Embalsado de madera para agregar a la laguna F.Fijo Oper. Al 31-10-2025 | S26: 000000000067 | T26: Ejercicio 2025/2026
... D30: DEL | E30: =+VLOOKUP(F30,Resumen_Base!$B$6:$F$69,5,0) -> Fixed Asset's Payments (Investments) Mejoras/equipamiento Lodge | F30: 12020103 | G30: Mejoras de Inmueb y Terrenos | H30: =+D30&F30 -> DEL12020103 | I30: 150000 | J30: 102.73973 | K30: 1460 | L30: 31/10/2025 | M30: CAJA | N30: 0141 | O30: TE001500000066 | P30: Asiento de CAJA (01/09/2025 - 31/08/2026) | Q30: Extracción de Caja 001500000066 Obs: Movimiento_Cajas_Bancos_Semana 25-26 al 31-10-2025 | R30: DT-Instalacion electrica en galpon nuevo detrás de casa staff F.Fijo Oper. Al 31-10-2025 | S30: 000000000067 | T30: Ejercicio 2025/2026
A31: 12020201 | B31: 5252 | D31: DEL | E31: =+VLOOKUP(F31,Resumen_Base!$B$6:$F$69,5,0) -> Fixed Asset's Payments (Investments) Mejoras/equipamiento Lodge | F31: 12020201 | G31: Instalaciones | H31: =+D31&F31 -> DEL12020201 | I31: 556000 | J31: 400 | K31: 1390 | L31: 30/09/2025 | M31: CAJA | N31: 0141 | O31: TE001500000033 | P31: Asiento de CAJA (01/09/2025 - 31/08/2026) | Q31: Extracción de Caja 001500000033 Obs: 30-09-2025 Mov Lodge | R31: DT - Pago a constructor rolando por instalar bomba presurizadora nueva debajo de calefon cocina nuev | S31: 000000000037 | T31: Ejercicio 2025/2026
D32: DEL | E32: =+VLOOKUP(F32,Resumen_Base!$B$6:$F$69,5,0) -> Fixed Asset's Payments (Investments) Mejoras/equipamiento Lodge | F32: 12020201 | G32: Instalaciones | H32: =+D32&F32 -> DEL12020201 | I32: 3748970.4 | J32: 2640.12 | K32: 1420 | L32: 14/11/2025 | M32: CAJA | N32: 0141 | O32: TE001500000077 | P32: Asiento de CAJA (01/09/2025 - 31/08/2026) | Q32: Extracción de Caja 001500000077 Obs: Movimiento_Cajas_Bancos_Semana 25-26 al 14-11-2025 | R32: DEL- Saldo Proyecto Salores Nexo 25/26 | S32: 000000000078 | T32: Ejercicio 2025/2026
D33: DEL | E33: =+VLOOKUP(F33,Resumen_Base!$B$6:$F$69,5,0) -> Fixed Asset's Payments (Investments) Mejoras/equipamiento Lodge | F33: 12020301 | G33: Movilidad y Viáticos - Locales | H33: =+D33&F33 -> DEL12020301 | I33: 240000 | J33: 160 | K33: 1500 | L33: 26/10/2025 | M33: CAJA | N33: 0141 | O33: TE001500000062 | P33: Asiento de CAJA (01/09/2025 - 31/08/2026) | Q33: Extracción de Caja 001500000062 Obs: 26-10-2025 Mov Lodge | R33: DT - Sillón nuevo para muelle de atrás | S33: 000000000061 | T33: Ejercicio 2025/2026
A34: 12020301 | B34: 5218 | D34: DEL | E34: =+VLOOKUP(F34,Resumen_Base!$B$6:$F$69,5,0) -> Fixed Asset's Payments (Investments) Mejoras/equipamiento Lodge | F34: 12020301 | G34: Muebles y útiles | H34: =+D34&F34 -> DEL12020301 | I34: 15000 | J34: 10 | K34: 1500 | L34: 26/10/2025 | M34: CAJA | N34: 0141 | O34: TE001500000062 | P34: Asiento de CAJA (01/09/2025 - 31/08/2026) | Q34: Extracción de Caja 001500000062 Obs: 26-10-2025 Mov Lodge | R34: DT - Flete para sillón del muelle de atrás | S34: 000000000061 | T34: Ejercicio 2025/2026
A35: 12020301 | B35: 5218 | D35: DEL | E35: =+VLOOKUP(F35,Resumen_Base!$B$6:$F$69,5,0) -> Fixed Asset's Payments (Investments) Mejoras/equipamiento Lodge | F35: 12020301 | G35: Muebles y útiles | H35: =+D35&F35 -> DEL12020301 | I35: 42000 | J35: 30 | K35: 1400 | L35: 17/10/2025 | M35: CAJA | N35: 0141 | O35: TE001500000052 | P35: Asiento de CAJA (01/09/2025 - 31/08/2026) | Q35: Extracción de Caja 001500000052 Obs: Movimiento_Cajas_Bancos_Semana 25-26 al 17-10-2025 | R35: DT-Flete envío Heladera Vertical - San Cristobal - Guarderia La Baie F.Fijo Oper. Al 17-10-2025 | S35: 000000000052 | T35: Ejercicio 2025/2026
D36: DEL | E36: =+VLOOKUP(F36,Resumen_Base!$B$6:$F$69,5,0) -> Fixed Asset's Payments (Investments) Mejoras/equipamiento Lodge | F36: 12020301 | G36: Muebles y útiles | H36: =+D36&F36 -> DEL12020301 | I36: 58000 | J36: 38.666667 | K36: 1500 | L36: 26/10/2025 | M36: CAJA | N36: 0141 | O36: TE001500000062 | P36: Asiento de CAJA (01/09/2025 - 31/08/2026) | Q36: Extracción de Caja 001500000062 Obs: 26-10-2025 Mov Lodge | R36: DT - Corderitos para sillón nuevo en muelle de atrás | S36: 000000000061 | T36: Ejercicio 2025/2026
D37: DEL | E37: =+VLOOKUP(F37,Resumen_Base!$B$6:$F$69,5,0) -> Fixed Asset's Payments (Investments) Mejoras/equipamiento Lodge | F37: 12020301 | G37: Muebles y útiles | H37: =+D37&F37 -> DEL12020301 | I37: 380000 | J37: 267.60563 | K37: 1420 | L37: 30/11/2025 | M37: CAJA | N37: 0141 | O37: TE001500000085 | P37: Asiento de CAJA (01/09/2025 - 31/08/2026) | Q37: Extracción de Caja 001500000085 Obs: 30-11-2025 Mov Lodge | R37: DT - Mesa ratona para muelle de atrás | S37: 000000000083 | T37: Ejercicio 2025/2026
D38: DEL | E38: =+VLOOKUP(F38,Resumen_Base!$B$6:$F$69,5,0) -> Fixed Asset's Payments (Investments) Mejoras/equipamiento Lodge | F38: 12020301 | G38: Muebles y útiles | H38: =+D38&F38 -> DEL12020301 | I38: 72700 | J38: 51.197183 | K38: 1420 | L38: 30/11/2025 | M38: CAJA | N38: 0141 | O38: TE001500000085 | P38: Asiento de CAJA (01/09/2025 - 31/08/2026) | Q38: Extracción de Caja 001500000085 Obs: 30-11-2025 Mov Lodge | R38: DT - Mueble mesa de apoyo hab 3 y 4 + 1 canasto mimbre | S38: 000000000083 | T38: Ejercicio 2025/2026
D39: DEL | E39: =+VLOOKUP(F39,Resumen_Base!$B$6:$F$69,5,0) -> Fixed Asset's Payments (Investments) Mejoras/equipamiento Lodge | F39: 12020301 | G39: Muebles y útiles | H39: =+D39&F39 -> DEL12020301 | I39: 900 | J39: 0.62937063 | K39: 1430 | L39: 12/10/2025 | M39: CAJA | N39: 0141 | O39: TE001500000046 | P39: Asiento de CAJA (01/09/2025 - 31/08/2026) | Q39: Extracción de Caja 001500000046 Obs: 12-10-2025 Mov Lodge | R39: DT - Peaje auto Noel | S39: 000000000043 | T39: Ejercicio 2025/2026
D40: DEL | E40: =+VLOOKUP(F40,Resumen_Base!$B$6:$F$69,5,0) -> Fixed Asset's Payments (Investments) Mejoras/equipamiento Lodge | F40: 12020301 | G40: Muebles y útiles | H40: =+D40&F40 -> DEL12020301 | I40: 90000 | J40: 62.937063 | K40: 1430 | L40: 12/10/2025 | M40: CAJA | N40: 0141 | O40: TE001500000046 | P40: Asiento de CAJA (01/09/2025 - 31/08/2026) | Q40: Extracción de Caja 001500000046 Obs: 12-10-2025 Mov Lodge | R40: DT - Tablón para superficie de apoyo cuarto de huéspedes | S40: 000000000043 | T40: Ejercicio 2025/2026
D41: DEL | E41: =+VLOOKUP(F41,Resumen_Base!$B$6:$F$69,5,0) -> Fixed Asset's Payments (Investments) Mejoras/equipamiento Lodge | F41: 12020301 | G41: Muebles y útiles | H41: =+D41&F41 -> DEL12020301 | I41: 77987 | J41: 59.99 | K41: 1300 | L41: 05/09/2025 | M41: CAJA | N41: 0141 | O41: TE001500000016 | P41: Asiento de CAJA | Q41: Extracción de Caja 001500000016 Obs: Movimiento_Cajas_Bancos_Semana 25-26 al 05-09-2025 | R41: DT- Reel - ValleySW- DEBIT PURCHASE MERCHANT PURCHASE TERMINAL 420429 eBay O 12 13467 06 671 San | S41: 000000000015 | T41: Ejercicio 2025/2026
D42: DEL | E42: =+VLOOKUP(F42,Resumen_Base!$B$6:$F$69,5,0) -> Fixed Asset's Payments (Investments) Mejoras/equipamiento Lodge | F42: 12020301 | G42: Muebles y útiles | H42: =+D42&F42 -> DEL12020301 | I42: 68822 | J42: 52.94 | K42: 1300 | L42: 05/09/2025 | M42: CAJA | N42: 0141 | O42: TE001500000016 | P42: Asiento de CAJA | Q42: Extracción de Caja 001500000016 Obs: Movimiento_Cajas_Bancos_Semana 25-26 al 05-09-2025 | R42: DT- Reel - ValleySW- DEBIT PURCHASE MERCHANT PURCHASE TERMINAL 420429 eBay O 12 13467 06 672 San | S42: 000000000015 | T42: Ejercicio 2025/2026
D43: DEL | E43: =+VLOOKUP(F43,Resumen_Base!$B$6:$F$69,5,0) -> Fixed Asset's Payments (Investments) Mejoras/equipamiento Lodge | F43: 12020301 | G43: Muebles y útiles | H43: =+D43&F43 -> DEL12020301 | I43: 92586 | J43: 71.22 | K43: 1300 | L43: 05/09/2025 | M43: CAJA | N43: 0141 | O43: TE001500000016 | P43: Asiento de CAJA | Q43: Extracción de Caja 001500000016 Obs: Movimiento_Cajas_Bancos_Semana 25-26 al 05-09-2025 | R43: DT- Reel - ValleySW- DEBIT PURCHASE MERCHANT PURCHASE TERMINAL 420429 eBay O 12 13467 06 673 San | S43: 000000000015 | T43: Ejercicio 2025/2026
D44: DEL | E44: =+VLOOKUP(F44,Resumen_Base!$B$6:$F$69,5,0) -> Fixed Asset's Payments (Investments) Mejoras/equipamiento Lodge | F44: 12020301 | G44: Muebles y útiles | H44: =+D44&F44 -> DEL12020301 | I44: 87685 | J44: 67.45 | K44: 1300 | L44: 05/09/2025 | M44: CAJA | N44: 0141 | O44: TE001500000016 | P44: Asiento de CAJA | Q44: Extracción de Caja 001500000016 Obs: Movimiento_Cajas_Bancos_Semana 25-26 al 05-09-2025 | R44: DT- Reel - ValleySW- DEBIT PURCHASE MERCHANT PURCHASE TERMINAL 420429 eBay O 12 13467 06 674 San | S44: 000000000015 | T44: Ejercicio 2025/2026
D45: DEL | E45: =+VLOOKUP(F45,Resumen_Base!$B$6:$F$69,5,0) -> Fixed Asset's Payments (Investments) Mejoras/equipamiento Lodge | F45: 12020301 | G45: Muebles y útiles | H45: =+D45&F45 -> DEL12020301 | I45: 800000 | J45: 533.33333 | K45: 1500 | L45: 24/10/2025 | M45: CAJA | N45: 0141 | O45: TE001500000061 | P45: Asiento de CAJA (01/09/2025 - 31/08/2026) | Q45: Extracción de Caja 001500000061 Obs: Movimiento_Cajas_Bancos_Semana 25-26 al 24-10-2025 | R45: DT-Compra 2 bancos hierro para Hab 1 y 2 F.Fijo Oper. Al 24-10-2025 | S45: 000000000060 | T45: Ejercicio 2025/2026
D46: DEL | E46: =+VLOOKUP(F46,Resumen_Base!$B$6:$F$69,5,0) -> Fixed Asset's Payments (Investments) Mejoras/equipamiento Lodge | F46: 12020301 | G46: Muebles y útiles | H46: =+D46&F46 -> DEL12020301 | I46: 159600 | J46: 109.31507 | K46: 1460 | L46: 14/11/2025 | M46: CAJA | N46: 0141 | O46: TE001500000078 | P46: Asiento de CAJA (01/09/2025 - 31/08/2026) | Q46: Extracción de Caja 001500000078 Obs: Movimiento_Cajas_Bancos_Semana 25-26 al 14-11-2025 | R46: DT-Compra de 2 cañas (compra realizada el 5/11) Pagos Depsa Valores. Al 14-11-2025 | S46: 000000000079 | T46: Ejercicio 2025/2026
D47: DEL | E47: =+VLOOKUP(F47,Resumen_Base!$B$6:$F$69,5,0) -> Fixed Asset's Payments (Investments) Mejoras/equipamiento Lodge | F47: 12020301 | G47: Muebles y útiles | H47: =+D47&F47 -> DEL12020301 | I47: 964079 | J47: 688.62786 | K47: 1400 | L47: 17/10/2025 | M47: CAJA | N47: 0141 | O47: TE001500000052 | P47: Asiento de CAJA (01/09/2025 - 31/08/2026) | Q47: Extracción de Caja 001500000052 Obs: Movimiento_Cajas_Bancos_Semana 25-26 al 17-10-2025 | R47: DT-Compra Heladera Exhibidora Vertical Inelro Mt - 450 437 Lts 1 Puerta - Gastro Hogar F.Fijo Oper. | S47: 000000000052 | T47: Ejercicio 2025/2026
... D58: DEL | E58: =+VLOOKUP(F58,Resumen_Base!$B$6:$F$69,5,0) -> Fixed Asset's Payments (Investments) Mejoras/equipamiento Lodge | F58: 12020901 | G58: Vajillas | H58: =+D58&F58 -> DEL12020901 | I58: -189458.5 | J58: -134.36773 | K58: 1410 | L58: 03/10/2025 | M58: CAJA | N58: 0141 | O58: TI001500000039 | P58: Asiento de CAJA (01/09/2025 - 31/08/2026) | Q58: Ingreso a Caja 001500000039 Obs: Movimiento_Cajas_Bancos_Semana 25-26 al 03-10-2025 | R58: DT-Recupero -Compra 5 platos de pan - Goldfarb - rendido FF 01-08 F.Fijo Oper. Al 03-10-2025 | S58: 000000000048 | T58: Ejercicio 2025/2026
A59: 12021001Maquinarias y Herramientas | B59: 5252 | D59: DEL | E59: =+VLOOKUP(F59,Resumen_Base!$B$6:$F$69,5,0) -> Fixed Asset's Payments (Investments) Mejoras/equipamiento Lodge | F59: 12021001 | G59: Maquinarias y Herramientas | H59: =+D59&F59 -> DEL12021001 | I59: 35000 | J59: 24.822695 | K59: 1410 | L59: 05/10/2025 | M59: CAJA | N59: 0141 | O59: TE001500000037 | P59: Asiento de CAJA (01/09/2025 - 31/08/2026) | Q59: Extracción de Caja 001500000037 Obs: 05-10-2025 Mov Lodge | R59: DT - Artículos de ferretería | S59: 000000000039 | T59: Ejercicio 2025/2026
A60: 12021001Maquinarias y Herramientas | B60: 12020301 | D60: DEL | E60: =+VLOOKUP(F60,Resumen_Base!$B$6:$F$69,5,0) -> Fixed Asset's Payments (Investments) Mejoras/equipamiento Lodge | F60: 12021001 | G60: Maquinarias y Herramientas | H60: =+D60&F60 -> DEL12021001 | I60: 199000 | J60: 141.13475 | K60: 1410 | L60: 05/10/2025 | M60: CAJA | N60: 0141 | O60: TE001500000037 | P60: Asiento de CAJA (01/09/2025 - 31/08/2026) | Q60: Extracción de Caja 001500000037 Obs: 05-10-2025 Mov Lodge | R60: DT - Aspiradora para la lancha del lodge | S60: 000000000039 | T60: Ejercicio 2025/2026
A61: 12021001Maquinarias y Herramientas | B61: 12020103 | D61: DEL | E61: =+VLOOKUP(F61,Resumen_Base!$B$6:$F$69,5,0) -> Fixed Asset's Payments (Investments) Mejoras/equipamiento Lodge | F61: 12021001 | G61: Maquinarias y Herramientas | H61: =+D61&F61 -> DEL12021001 | I61: 286000 | J61: 200 | K61: 1430 | L61: 12/10/2025 | M61: CAJA | N61: 0141 | O61: TE001500000047 | P61: Asiento de CAJA (01/09/2025 - 31/08/2026) | Q61: Extracción de Caja 001500000047 Obs: 12-10-2025 Mov Lodge | R61: DT - Pago a Eduardo por servicio general a los 2 generadores del lodge | S61: 000000000044 | T61: Ejercicio 2025/2026
A62: 5208 | B62: 5226 | D62: DEL | E62: =+VLOOKUP(F62,Resumen_Base!$B$6:$F$69,5,0) -> Canon Lodge/Labor Permits: | F62: 5208 | G62: Alquileres y Canon | H62: =+D62&F62 -> DEL5208 | I62: 5000 | J62: 3.4965035 | K62: 1430 | L62: 12/10/2025 | M62: CAJA | N62: 0141 | O62: TE001500000046 | P62: Asiento de CAJA (01/09/2025 - 31/08/2026) | Q62: Extracción de Caja 001500000046 Obs: 12-10-2025 Mov Lodge | R62: DT - Propina en guardería la baie | S62: 000000000043 | T62: Ejercicio 2025/2026
A63: 5208 | B63: 5226 | D63: DEL | E63: =+VLOOKUP(F63,Resumen_Base!$B$6:$F$69,5,0) -> Canon Lodge/Labor Permits: | F63: 5208 | G63: Alquileres y Canon | H63: =+D63&F63 -> DEL5208 | I63: 2000 | J63: 1.3986014 | K63: 1430 | L63: 12/10/2025 | M63: CAJA | N63: 0141 | O63: TE001500000046 | P63: Asiento de CAJA (01/09/2025 - 31/08/2026) | Q63: Extracción de Caja 001500000046 Obs: 12-10-2025 Mov Lodge | R63: DT - Propina ypf | S63: 000000000043 | T63: Ejercicio 2025/2026
A64: 5208 | B64: 5263 | D64: DEL | E64: =+VLOOKUP(F64,Resumen_Base!$B$6:$F$69,5,0) -> Canon Lodge/Labor Permits: | F64: 5208 | G64: Alquileres y Canon | H64: =+D64&F64 -> DEL5208 | I64: 10000 | J64: 7.6923077 | K64: 1300 | L64: 07/09/2025 | M64: CAJA | N64: 0141 | O64: TE001500000001 | P64: Asiento de CAJA | Q64: Extracción de Caja 001500000001 Obs: 07-09-2025 DT - DIV 141-BASE2 Mov Lodge | R64: DT - Noel paga a personal de guardería un adicional | S64: 000000000008 | T64: Ejercicio 2025/2026
D65: DEL | E65: =+VLOOKUP(F65,Resumen_Base!$B$6:$F$69,5,0) -> Canon Lodge/Labor Permits: | F65: 5208 | G65: Alquileres y Canon | H65: =+D65&F65 -> DEL5208 | I65: 28000 | J65: 19.58042 | K65: 1430 | L65: 10/10/2025 | M65: CAJA | N65: 0141 | O65: TE001500000043 | P65: Asiento de CAJA (01/09/2025 - 31/08/2026) | Q65: Extracción de Caja 001500000043 Obs: Movimiento_Cajas_Bancos_Semana 25-26 al 10-10-2025 | R65: DT-Diferencia por aumento de precio cuota octubre - Guarderia La Baie F.Fijo Oper. Al 10-10-2025 | S65: 000000000041 | T65: Ejercicio 2025/2026
D66: DEL | E66: =+VLOOKUP(F66,Resumen_Base!$B$6:$F$69,5,0) -> Canon Lodge/Labor Permits: | F66: 5208 | G66: Alquileres y Canon | H66: =+D66&F66 -> DEL5208 | I66: 307000 | J66: 236.15385 | K66: 1300 | L66: 05/09/2025 | M66: CAJA | N66: 0141 | O66: TE001500000002 | P66: Asiento de CAJA | Q66: Extracción de Caja 001500000002 Obs: Movimiento_Cajas_Bancos_Semana 25-26 al 05-09-2025 | R66: DT-Guarderia La Baie - cuota Agosto - 5208 Alquileres y Canon Pagos Depsa Valores. Al 05-09-2025 | S66: 000000000009 | T66: Ejercicio 2025/2026
D67: DEL | E67: =+VLOOKUP(F67,Resumen_Base!$B$6:$F$69,5,0) -> Canon Lodge/Labor Permits: | F67: 5208 | G67: Alquileres y Canon | H67: =+D67&F67 -> DEL5208 | I67: 335000 | J67: 235.91549 | K67: 1420 | L67: 30/11/2025 | M67: CAJA | N67: 0141 | O67: TE001500000097 | P67: Asiento de CAJA (01/09/2025 - 31/08/2026) | Q67: Extracción de Caja 001500000097 Obs: Movimiento_Cajas_Bancos_Semana 25-26 al 05-12-2025 | R67: DT-Guarderia La Baie - cuota Noviembre Pagos Depsa Valores. Al 05-12-2025 | S67: 000000000089 | T67: Ejercicio 2025/2026
D68: DEL | E68: =+VLOOKUP(F68,Resumen_Base!$B$6:$F$69,5,0) -> Canon Lodge/Labor Permits: | F68: 5208 | G68: Alquileres y Canon | H68: =+D68&F68 -> DEL5208 | I68: 307000 | J68: 214.68531 | K68: 1430 | L68: 10/10/2025 | M68: CAJA | N68: 0141 | O68: TE001500000043 | P68: Asiento de CAJA (01/09/2025 - 31/08/2026) | Q68: Extracción de Caja 001500000043 Obs: Movimiento_Cajas_Bancos_Semana 25-26 al 10-10-2025 | R68: DT-Guarderia La Baie - cuota Octubre Pagos Alcorta Partners. Al 10-10-2025 | S68: 000000000041 | T68: Ejercicio 2025/2026
D69: DEL | E69: =+VLOOKUP(F69,Resumen_Base!$B$6:$F$69,5,0) -> Canon Lodge/Labor Permits: | F69: 5208 | G69: Alquileres y Canon | H69: =+D69&F69 -> DEL5208 | I69: 335000 | J69: 229.45205 | K69: 1460 | L69: 31/10/2025 | M69: CAJA | N69: 0141 | O69: TE001500000070 | P69: Asiento de CAJA (01/09/2025 - 31/08/2026) | Q69: Extracción de Caja 001500000070 Obs: Movimiento_Cajas_Bancos_Semana 25-26 al 07-11-2025 | R69: DT-Guarderia La Baie - cuota Octubre Pagos Depsa Valores. Al 07-11-2025 | S69: 000000000068 | T69: Ejercicio 2025/2026
D70: DEL | E70: =+VLOOKUP(F70,Resumen_Base!$B$6:$F$69,5,0) -> Canon Lodge/Labor Permits: | F70: 5208 | G70: Alquileres y Canon | H70: =+D70&F70 -> DEL5208 | I70: 174712 | J70: 134.39385 | K70: 1300 | L70: 05/09/2025 | M70: CAJA | N70: 0141 | O70: TE001500000002 | P70: Asiento de CAJA | Q70: Extracción de Caja 001500000002 Obs: Movimiento_Cajas_Bancos_Semana 25-26 al 05-09-2025 | R70: DT-Guarderia La Bita - cuota Agosto - 5208 Alquileres y Canon Pagos Depsa Valores. Al 05-09-2025 | S70: 000000000009 | T70: Ejercicio 2025/2026
D71: DEL | E71: =+VLOOKUP(F71,Resumen_Base!$B$6:$F$69,5,0) -> Canon Lodge/Labor Permits: | F71: 5208 | G71: Alquileres y Canon | H71: =+D71&F71 -> DEL5208 | I71: 170000 | J71: 118.88112 | K71: 1430 | L71: 10/10/2025 | M71: CAJA | N71: 0141 | O71: TE001500000043 | P71: Asiento de CAJA (01/09/2025 - 31/08/2026) | Q71: Extracción de Caja 001500000043 Obs: Movimiento_Cajas_Bancos_Semana 25-26 al 10-10-2025 | R71: DT-Guarderia La Bita - cuota Octubre Pagos Alcorta Partners. Al 10-10-2025 | S71: 000000000041 | T71: Ejercicio 2025/2026
D72: DEL | E72: =+VLOOKUP(F72,Resumen_Base!$B$6:$F$69,5,0) -> Canon Lodge/Labor Permits: | F72: 5208 | G72: Alquileres y Canon | H72: =+D72&F72 -> DEL5208 | I72: 172312 | J72: 118.02192 | K72: 1460 | L72: 31/10/2025 | M72: CAJA | N72: 0141 | O72: TE001500000070 | P72: Asiento de CAJA (01/09/2025 - 31/08/2026) | Q72: Extracción de Caja 001500000070 Obs: Movimiento_Cajas_Bancos_Semana 25-26 al 07-11-2025 | R72: DT-Guarderia La Bita - cuota Octubre Pagos Depsa Valores. Al 07-11-2025 | S72: 000000000068 | T72: Ejercicio 2025/2026
D73: DEL | E73: =+VLOOKUP(F73,Resumen_Base!$B$6:$F$69,5,0) -> Communications - Phone, internet and satellite TV | F73: 5209 | G73: Comunicaciones e Internet | H73: =+D73&F73 -> DEL5209 | I73: 5489.6 | J73: 3.76 | K73: 1460 | L73: 31/10/2025 | M73: CAJA | N73: 0141 | O73: TE001500000081 | P73: Asiento de CAJA (01/09/2025 - 31/08/2026) | Q73: Extracción de Caja 001500000081 Obs: Movimiento_Cajas_Bancos_Semana 25-26 al 21-11-2025 | R73: DT- TriSW- AMEX - Oct 25- =DLOSPOTIFY CABA AR- spotify-09/27/2025 | S73: 000000000080 | T73: Ejercicio 2025/2026
D74: DEL | E74: =+VLOOKUP(F74,Resumen_Base!$B$6:$F$69,5,0) -> Communications - Phone, internet and satellite TV | F74: 5209 | G74: Comunicaciones e Internet | H74: =+D74&F74 -> DEL5209 | I74: -1649.8 | J74: -1.13 | K74: 1460 | L74: 31/10/2025 | M74: CAJA | N74: 0141 | O74: TI001500000079 | P74: Asiento de CAJA (01/09/2025 - 31/08/2026) | Q74: Ingreso a Caja 001500000079 Obs: Movimiento_Cajas_Bancos_Semana 25-26 al 21-11-2025 | R74: DT- TriSW- AMEX - Oct 25- REFUND USD TOURIST BCIUDAD AUTONOMA DE BAR- -09/27/2025 | S74: 000000000093 | T74: Ejercicio 2025/2026
D75: DEL | E75: =+VLOOKUP(F75,Resumen_Base!$B$6:$F$69,5,0) -> Communications - Phone, internet and satellite TV | F75: 5209 | G75: Comunicaciones e Internet | H75: =+D75&F75 -> DEL5209 | I75: -146 | J75: -0.1 | K75: 1460 | L75: 31/10/2025 | M75: CAJA | N75: 0141 | O75: TI001500000079 | P75: Asiento de CAJA (01/09/2025 - 31/08/2026) | Q75: Ingreso a Caja 001500000079 Obs: Movimiento_Cajas_Bancos_Semana 25-26 al 21-11-2025 | R75: DT- TriSW- AMEX - Oct 25- REFUND USD TOURIST BCIUDAD AUTONOMA DE BAR- -09/27/2025 | S75: 000000000093 | T75: Ejercicio 2025/2026
D76: DEL | E76: =+VLOOKUP(F76,Resumen_Base!$B$6:$F$69,5,0) -> Communications - Phone, internet and satellite TV | F76: 5209 | G76: Comunicaciones e Internet | H76: =+D76&F76 -> DEL5209 | I76: 59042.4 | J76: 40.44 | K76: 1460 | L76: 31/10/2025 | M76: CAJA | N76: 0141 | O76: TE001500000081 | P76: Asiento de CAJA (01/09/2025 - 31/08/2026) | Q76: Extracción de Caja 001500000081 Obs: Movimiento_Cajas_Bancos_Semana 25-26 al 21-11-2025 | R76: DT- TriSW- AMEX - Oct 25- STARLINK 99999999 CABA- -10/19/2025 | S76: 000000000080 | T76: Ejercicio 2025/2026
... D129: DEL | E129: =+VLOOKUP(F129,Resumen_Base!$B$6:$F$69,5,0) -> Manager | F129: 5228 | G129: Remuneraciones Managers | H129: =+D129&F129 -> DEL5228 | I129: 1278000 | J129: 900 | K129: 1420 | L129: 28/11/2025 | M129: CAJA | N129: 0141 | O129: TE001500000089 | P129: Asiento de CAJA (01/09/2025 - 31/08/2026) | Q129: Extracción de Caja 001500000089 Obs: Movimiento_Cajas_Bancos_Semana 25-26 al 28-11-2025 | R129: DT-Honorarios Alejandro manager ( (Periodo del 26/11 al 13/12) F.Fijo Oper. Al 28-11-2025 | S129: 000000000086 | T129: Ejercicio 2025/2026
D130: DEL | E130: =+VLOOKUP(F130,Resumen_Base!$B$6:$F$69,5,0) -> Manager | F130: 5228 | G130: Remuneraciones Managers | H130: =+D130&F130 -> DEL5228 | I130: 3742700 | J130: 2879 | K130: 1300 | L130: 01/09/2025 | N130: 0141 | Q130: DEL- Recupero sueldo Alejandro abonado de mas x Banco 24/25 Neto del Bono | R130: DEL- Recupero sueldo Alejandro abonado de mas x Banco 24/25 Neto del Bono | S130: 000000000027 | T130: Ejercicio 2025/2026
D131: DEL | E131: =+VLOOKUP(F131,Resumen_Base!$B$6:$F$69,5,0) -> Social Security Contributions | F131: 5235 | G131: Cargas Sociales Servicios | H131: =+D131&F131 -> DEL5235 | I131: 184428 | J131: 130.8 | K131: 1410 | L131: 10/10/2025 | M131: CAJA | N131: 0141 | O131: TE001500000044 | P131: Asiento de CAJA (01/09/2025 - 31/08/2026) | Q131: Extracción de Caja 001500000044 Obs: Movimiento_Cajas_Bancos_Semana 25-26 al 10-10-2025 | R131: DEL- Reintegro Cargas Sociales TA 09/2025 - Servicios | S131: 000000000042 | T131: Ejercicio 2025/2026
D132: DEL | E132: =+VLOOKUP(F132,Resumen_Base!$B$6:$F$69,5,0) -> Social Security Contributions | F132: 5235 | G132: Cargas Sociales Servicios | H132: =+D132&F132 -> DEL5235 | I132: 190968 | J132: 130.8 | K132: 1460 | L132: 31/10/2025 | M132: CAJA | N132: 0141 | O132: TE001500000065 | P132: Asiento de CAJA (01/09/2025 - 31/08/2026) | Q132: Extracción de Caja 001500000065 Obs: Movimiento_Cajas_Bancos_Semana 25-26 al 31-10-2025 | R132: DEL- Reintegro Cargas Sociales TA 10-2025 - Servicios | S132: 000000000066 | T132: Ejercicio 2025/2026
D133: DEL | E133: =+VLOOKUP(F133,Resumen_Base!$B$6:$F$69,5,0) -> Social Security Contributions | F133: 5235 | G133: Cargas Sociales Servicios | H133: =+D133&F133 -> DEL5235 | I133: 651780 | J133: 459 | K133: 1420 | L133: 28/11/2025 | M133: CAJA | N133: 0141 | O133: TE001500000089 | P133: Asiento de CAJA (01/09/2025 - 31/08/2026) | Q133: Extracción de Caja 001500000089 Obs: Movimiento_Cajas_Bancos_Semana 25-26 al 28-11-2025 | R133: DEL- Reintegro Cargas Sociales TA 11-2025 - Servicios | S133: 000000000086 | T133: Ejercicio 2025/2026
D134: DEL | E134: =+VLOOKUP(F134,Resumen_Base!$B$6:$F$69,5,0) -> Social Security Contributions | F134: 5237 | G134: Cargas Sociales Managers | H134: =+D134&F134 -> DEL5237 | I134: 276642 | J134: 196.2 | K134: 1410 | L134: 10/10/2025 | M134: CAJA | N134: 0141 | O134: TE001500000044 | P134: Asiento de CAJA (01/09/2025 - 31/08/2026) | Q134: Extracción de Caja 001500000044 Obs: Movimiento_Cajas_Bancos_Semana 25-26 al 10-10-2025 | R134: DEL- Reintegro Cargas Sociales TA 09/2025 - Managers | S134: 000000000042 | T134: Ejercicio 2025/2026
D135: DEL | E135: =+VLOOKUP(F135,Resumen_Base!$B$6:$F$69,5,0) -> Social Security Contributions | F135: 5237 | G135: Cargas Sociales Managers | H135: =+D135&F135 -> DEL5237 | I135: 286452 | J135: 196.2 | K135: 1460 | L135: 31/10/2025 | M135: CAJA | N135: 0141 | O135: TE001500000065 | P135: Asiento de CAJA (01/09/2025 - 31/08/2026) | Q135: Extracción de Caja 001500000065 Obs: Movimiento_Cajas_Bancos_Semana 25-26 al 31-10-2025 | R135: DEL- Reintegro Cargas Sociales TA 10-2025 - Managers | S135: 000000000066 | T135: Ejercicio 2025/2026
D136: DEL | E136: =+VLOOKUP(F136,Resumen_Base!$B$6:$F$69,5,0) -> Social Security Contributions | F136: 5237 | G136: Cargas Sociales Managers | H136: =+D136&F136 -> DEL5237 | I136: 269800 | J136: 190 | K136: 1420 | L136: 28/11/2025 | M136: CAJA | N136: 0141 | O136: TE001500000089 | P136: Asiento de CAJA (01/09/2025 - 31/08/2026) | Q136: Extracción de Caja 001500000089 Obs: Movimiento_Cajas_Bancos_Semana 25-26 al 28-11-2025 | R136: DEL- Reintegro Cargas Sociales TA 11-2025 - Managers | S136: 000000000086 | T136: Ejercicio 2025/2026
D137: DEL | E137: =+VLOOKUP(F137,Resumen_Base!$B$6:$F$69,5,0) -> Electricity | F137: 5247 | G137: Combustible y Lub- Elect-Gener | H137: =+D137&F137 -> DEL5247 | I137: 76000 | J137: 54.676259 | K137: 1390 | L137: 30/09/2025 | M137: CAJA | N137: 0141 | O137: TE001500000030 | P137: Asiento de CAJA (01/09/2025 - 31/08/2026) | Q137: Extracción de Caja 001500000030 Obs: 30-09-2025 Mov Lodge | R137: DT - Nafta | S137: 000000000036 | T137: Ejercicio 2025/2026
D138: DEL | E138: =+VLOOKUP(F138,Resumen_Base!$B$6:$F$69,5,0) -> Electricity | F138: 5247 | G138: Combustible y Lub- Elect-Gener | H138: =+D138&F138 -> DEL5247 | I138: 99050 | J138: 69.753521 | K138: 1420 | L138: 30/11/2025 | M138: CAJA | N138: 0141 | O138: TE001500000085 | P138: Asiento de CAJA (01/09/2025 - 31/08/2026) | Q138: Extracción de Caja 001500000085 Obs: 30-11-2025 Mov Lodge | R138: DT - Nafta generador | S138: 000000000083 | T138: Ejercicio 2025/2026
D139: DEL | E139: =+VLOOKUP(F139,Resumen_Base!$B$6:$F$69,5,0) -> Electricity | F139: 5247 | G139: Combustible y Lub- Elect-Gener | H139: =+D139&F139 -> DEL5247 | I139: 33000 | J139: 23.404255 | K139: 1410 | L139: 05/10/2025 | M139: CAJA | N139: 0141 | O139: TE001500000037 | P139: Asiento de CAJA (01/09/2025 - 31/08/2026) | Q139: Extracción de Caja 001500000037 Obs: 05-10-2025 Mov Lodge | R139: DT - Nafta generador ypf Luján | S139: 000000000039 | T139: Ejercicio 2025/2026
D140: DEL | E140: =+VLOOKUP(F140,Resumen_Base!$B$6:$F$69,5,0) -> Electricity - Gas for Boats & Vehicles | F140: 5248 | G140: Combustible y Lub-Vehiculo Bot | H140: =+D140&F140 -> DEL5248 | I140: 55781 | J140: 37.187333 | K140: 1500 | L140: 26/10/2025 | M140: CAJA | N140: 0141 | O140: TE001500000062 | P140: Asiento de CAJA (01/09/2025 - 31/08/2026) | Q140: Extracción de Caja 001500000062 Obs: 26-10-2025 Mov Lodge | R140: DT - Acta lancha Noel | S140: 000000000061 | T140: Ejercicio 2025/2026
D141: DEL | E141: =+VLOOKUP(F141,Resumen_Base!$B$6:$F$69,5,0) -> Electricity - Gas for Boats & Vehicles | F141: 5248 | G141: Combustible y Lub-Vehiculo Bot | H141: =+D141&F141 -> DEL5248 | I141: 185922 | J141: 130.93099 | K141: 1420 | L141: 30/11/2025 | M141: CAJA | N141: 0141 | O141: TE001500000085 | P141: Asiento de CAJA (01/09/2025 - 31/08/2026) | Q141: Extracción de Caja 001500000085 Obs: 30-11-2025 Mov Lodge | R141: DT - Nafta ancha lodge | S141: 000000000083 | T141: Ejercicio 2025/2026
D142: DEL | E142: =+VLOOKUP(F142,Resumen_Base!$B$6:$F$69,5,0) -> Electricity - Gas for Boats & Vehicles | F142: 5248 | G142: Combustible y Lub-Vehiculo Bot | H142: =+D142&F142 -> DEL5248 | I142: 281200 | J142: 187.46667 | K142: 1500 | L142: 26/10/2025 | M142: CAJA | N142: 0141 | O142: TE001500000062 | P142: Asiento de CAJA (01/09/2025 - 31/08/2026) | Q142: Extracción de Caja 001500000062 Obs: 26-10-2025 Mov Lodge | R142: DT - Nafta guía Matías que uso para 5 fd y 1 HD | S142: 000000000061 | T142: Ejercicio 2025/2026
... D163: DEL | E163: =+VLOOKUP(F163,Resumen_Base!$B$6:$F$69,5,0) -> Propane | F163: 5249 | G163: Combustible y Lub- Gas | H163: =+D163&F163 -> DEL5249 | I163: 52000 | J163: 36.619718 | K163: 1420 | L163: 30/11/2025 | M163: CAJA | N163: 0141 | O163: TE001500000085 | P163: Asiento de CAJA (01/09/2025 - 31/08/2026) | Q163: Extracción de Caja 001500000085 Obs: 30-11-2025 Mov Lodge | R163: DT - Garrafas x 2 recarga | S163: 000000000083 | T163: Ejercicio 2025/2026
A164: 5250 | B164: 5257 | D164: DEL | E164: =+VLOOKUP(F164,Resumen_Base!$B$6:$F$69,5,0) -> Food & Wine | F164: 5250 | G164: Comidas y refrigerios | H164: =+D164&F164 -> DEL5250 | I164: 45000 | J164: 31.914894 | K164: 1410 | L164: 05/10/2025 | M164: CAJA | N164: 0141 | O164: TE001500000037 | P164: Asiento de CAJA (01/09/2025 - 31/08/2026) | Q164: Extracción de Caja 001500000037 Obs: 05-10-2025 Mov Lodge | R164: DT - Compra de bidones de agua en súper chino | S164: 000000000039 | T164: Ejercicio 2025/2026
D165: DEL | E165: =+VLOOKUP(F165,Resumen_Base!$B$6:$F$69,5,0) -> Food & Wine | F165: 5250 | G165: Comidas y Refrigerios | H165: =+D165&F165 -> DEL5250 | I165: 220200 | J165: 158.41727 | K165: 1390 | L165: 30/09/2025 | M165: CAJA | N165: 0141 | O165: TE001500000083 | P165: Asiento de CAJA (01/09/2025 - 31/08/2026) | Q165: Extracción de Caja 001500000083 Obs: 30-09-2025 Mov Lodge | R165: DT - Verduleria | S165: 000000000082 | T165: Ejercicio 2025/2026
D166: DEL | E166: =+VLOOKUP(F166,Resumen_Base!$B$6:$F$69,5,0) -> Food & Wine | F166: 5250 | G166: Comidas y Refrigerios | H166: =+D166&F166 -> DEL5250 | I166: 19000 | J166: 13.669065 | K166: 1390 | L166: 30/09/2025 | M166: CAJA | N166: 0141 | O166: TE001500000030 | P166: Asiento de CAJA (01/09/2025 - 31/08/2026) | Q166: Extracción de Caja 001500000030 Obs: 30-09-2025 Mov Lodge | R166: DT - aguas | S166: 000000000036 | T166: Ejercicio 2025/2026
D167: DEL | E167: =+VLOOKUP(F167,Resumen_Base!$B$6:$F$69,5,0) -> Food & Wine | F167: 5250 | G167: Comidas y Refrigerios | H167: =+D167&F167 -> DEL5250 | I167: 4000 | J167: 2.8776978 | K167: 1390 | L167: 30/09/2025 | M167: CAJA | N167: 0141 | O167: TE001500000030 | P167: Asiento de CAJA (01/09/2025 - 31/08/2026) | Q167: Extracción de Caja 001500000030 Obs: 30-09-2025 Mov Lodge | R167: DT - Almacén | S167: 000000000036 | T167: Ejercicio 2025/2026
D168: DEL | E168: =+VLOOKUP(F168,Resumen_Base!$B$6:$F$69,5,0) -> Food & Wine | F168: 5250 | G168: Comidas y Refrigerios | H168: =+D168&F168 -> DEL5250 | I168: 31400 | J168: 22.589928 | K168: 1390 | L168: 30/09/2025 | M168: CAJA | N168: 0141 | O168: TE001500000030 | P168: Asiento de CAJA (01/09/2025 - 31/08/2026) | Q168: Extracción de Caja 001500000030 Obs: 30-09-2025 Mov Lodge | R168: DT - Almacén | S168: 000000000036 | T168: Ejercicio 2025/2026
D169: DEL | E169: =+VLOOKUP(F169,Resumen_Base!$B$6:$F$69,5,0) -> Food & Wine | F169: 5250 | G169: Comidas y Refrigerios | H169: =+D169&F169 -> DEL5250 | I169: 1300 | J169: 0.9352518 | K169: 1390 | L169: 30/09/2025 | M169: CAJA | N169: 0141 | O169: TE001500000030 | P169: Asiento de CAJA (01/09/2025 - 31/08/2026) | Q169: Extracción de Caja 001500000030 Obs: 30-09-2025 Mov Lodge | R169: DT - Almacén-cacao | S169: 000000000036 | T169: Ejercicio 2025/2026
D170: DEL | E170: =+VLOOKUP(F170,Resumen_Base!$B$6:$F$69,5,0) -> Food & Wine | F170: 5250 | G170: Comidas y Refrigerios | H170: =+D170&F170 -> DEL5250 | I170: 522400 | J170: 370.49645 | K170: 1410 | L170: 05/10/2025 | M170: CAJA | N170: 0141 | O170: TE001500000037 | P170: Asiento de CAJA (01/09/2025 - 31/08/2026) | Q170: Extracción de Caja 001500000037 Obs: 05-10-2025 Mov Lodge | R170: DT - Artículos de almacén mayorista | S170: 000000000039 | T170: Ejercicio 2025/2026
D171: DEL | E171: =+VLOOKUP(F171,Resumen_Base!$B$6:$F$69,5,0) -> Food & Wine | F171: 5250 | G171: Comidas y Refrigerios | H171: =+D171&F171 -> DEL5250 | I171: 35000 | J171: 25 | K171: 1400 | L171: 19/10/2025 | M171: CAJA | N171: 0141 | O171: TE001500000057 | P171: Asiento de CAJA (01/09/2025 - 31/08/2026) | Q171: Extracción de Caja 001500000057 Obs: 19-10-2025 Mov Lodge | R171: DT - Bidones de agua | S171: 000000000054 | T171: Ejercicio 2025/2026
D172: DEL | E172: =+VLOOKUP(F172,Resumen_Base!$B$6:$F$69,5,0) -> Food & Wine | F172: 5250 | G172: Comidas y Refrigerios | H172: =+D172&F172 -> DEL5250 | I172: 11400 | J172: 7.6 | K172: 1500 | L172: 26/10/2025 | M172: CAJA | N172: 0141 | O172: TE001500000062 | P172: Asiento de CAJA (01/09/2025 - 31/08/2026) | Q172: Extracción de Caja 001500000062 Obs: 26-10-2025 Mov Lodge | R172: DT - Bidones de agua | S172: 000000000061 | T172: Ejercicio 2025/2026
D173: DEL | E173: =+VLOOKUP(F173,Resumen_Base!$B$6:$F$69,5,0) -> Food & Wine | F173: 5250 | G173: Comidas y Refrigerios | H173: =+D173&F173 -> DEL5250 | I173: 15400 | J173: 10.84507 | K173: 1420 | L173: 30/11/2025 | M173: CAJA | N173: 0141 | O173: TE001500000085 | P173: Asiento de CAJA (01/09/2025 - 31/08/2026) | Q173: Extracción de Caja 001500000085 Obs: 30-11-2025 Mov Lodge | R173: DT - Bombones apertura | S173: 000000000083 | T173: Ejercicio 2025/2026
D174: DEL | E174: =+VLOOKUP(F174,Resumen_Base!$B$6:$F$69,5,0) -> Food & Wine | F174: 5250 | G174: Comidas y Refrigerios | H174: =+D174&F174 -> DEL5250 | I174: 18000 | J174: 12.676056 | K174: 1420 | L174: 30/11/2025 | M174: CAJA | N174: 0141 | O174: TE001500000085 | P174: Asiento de CAJA (01/09/2025 - 31/08/2026) | Q174: Extracción de Caja 001500000085 Obs: 30-11-2025 Mov Lodge | R174: DT - Bombones apertura | S174: 000000000083 | T174: Ejercicio 2025/2026
D175: DEL | E175: =+VLOOKUP(F175,Resumen_Base!$B$6:$F$69,5,0) -> Food & Wine | F175: 5250 | G175: Comidas y Refrigerios | H175: =+D175&F175 -> DEL5250 | I175: 37600 | J175: 27.05036 | K175: 1390 | L175: 30/09/2025 | M175: CAJA | N175: 0141 | O175: TE001500000030 | P175: Asiento de CAJA (01/09/2025 - 31/08/2026) | Q175: Extracción de Caja 001500000030 Obs: 30-09-2025 Mov Lodge | R175: DT - Bombones para aperturas | S175: 000000000036 | T175: Ejercicio 2025/2026
D176: DEL | E176: =+VLOOKUP(F176,Resumen_Base!$B$6:$F$69,5,0) -> Food & Wine | F176: 5250 | G176: Comidas y Refrigerios | H176: =+D176&F176 -> DEL5250 | I176: 257220 | J176: 185.05036 | K176: 1390 | L176: 30/09/2025 | M176: CAJA | N176: 0141 | O176: TE001500000083 | P176: Asiento de CAJA (01/09/2025 - 31/08/2026) | Q176: Extracción de Caja 001500000083 Obs: 30-09-2025 Mov Lodge | R176: DT - Carnicería | S176: 000000000082 | T176: Ejercicio 2025/2026
... D218: DEL | E218: =+VLOOKUP(F218,Resumen_Base!$B$6:$F$69,5,0) -> Food & Wine | F218: 5251 | G218: Artículos de Limpieza | H218: =+D218&F218 -> DEL5251 | I218: 103906 | J218: 73.692199 | K218: 1410 | L218: 05/10/2025 | M218: CAJA | N218: 0141 | O218: TE001500000037 | P218: Asiento de CAJA (01/09/2025 - 31/08/2026) | Q218: Extracción de Caja 001500000037 Obs: 05-10-2025 Mov Lodge | R218: DT - Mayorista, artículos de limpieza | S218: 000000000039 | T218: Ejercicio 2025/2026
A219: 5252 | B219: 12020201 | D219: DEL | E219: =+VLOOKUP(F219,Resumen_Base!$B$6:$F$69,5,0) -> Maintenance Lodge | F219: 5252 | G219: Mantenimiento y reposiciones - Lodge | H219: =+D219&F219 -> DEL5252 | I219: 78000 | J219: 54.545455 | K219: 1430 | L219: 12/10/2025 | M219: CAJA | N219: 0141 | O219: TE001500000046 | P219: Asiento de CAJA (01/09/2025 - 31/08/2026) | Q219: Extracción de Caja 001500000046 Obs: 12-10-2025 Mov Lodge | R219: DT - Artículos de ferretería | S219: 000000000043 | T219: Ejercicio 2025/2026
A220: 5252 | B220: 12020201 | D220: DEL | E220: =+VLOOKUP(F220,Resumen_Base!$B$6:$F$69,5,0) -> Maintenance Lodge | F220: 5252 | G220: Mantenimiento y reposiciones - Lodge | H220: =+D220&F220 -> DEL5252 | I220: 82500 | J220: 58.510638 | K220: 1410 | L220: 05/10/2025 | M220: CAJA | N220: 0141 | O220: TE001500000037 | P220: Asiento de CAJA (01/09/2025 - 31/08/2026) | Q220: Extracción de Caja 001500000037 Obs: 05-10-2025 Mov Lodge | R220: DT - Grifería nueva para la cocina de andres | S220: 000000000039 | T220: Ejercicio 2025/2026
A221: 5252 | B221: 12020201 | D221: DEL | E221: =+VLOOKUP(F221,Resumen_Base!$B$6:$F$69,5,0) -> Maintenance Lodge | F221: 5252 | G221: Mantenimiento y reposiciones - Lodge | H221: =+D221&F221 -> DEL5252 | I221: 90000 | J221: 60 | K221: 1500 | L221: 26/10/2025 | M221: CAJA | N221: 0141 | O221: TE001500000062 | P221: Asiento de CAJA (01/09/2025 - 31/08/2026) | Q221: Extracción de Caja 001500000062 Obs: 26-10-2025 Mov Lodge | R221: DT - Mármoles para espacio de apoyo en habitaciones | S221: 000000000061 | T221: Ejercicio 2025/2026
A222: 5252 | B222: 12020201 | D222: DEL | E222: =+VLOOKUP(F222,Resumen_Base!$B$6:$F$69,5,0) -> Maintenance Lodge | F222: 5252 | G222: Mantenimiento y reposiciones - Lodge | H222: =+D222&F222 -> DEL5252 | I222: 48450 | J222: 32.3 | K222: 1500 | L222: 26/10/2025 | M222: CAJA | N222: 0141 | O222: TE001500000062 | P222: Asiento de CAJA (01/09/2025 - 31/08/2026) | Q222: Extracción de Caja 001500000062 Obs: 26-10-2025 Mov Lodge | R222: DT - Me sumas para mármoles de habitaciónes huéspedes | S222: 000000000061 | T222: Ejercicio 2025/2026
A223: 5252 | B223: 12020601 | D223: DEL | E223: =+VLOOKUP(F223,Resumen_Base!$B$6:$F$69,5,0) -> Maintenance Lodge | F223: 5252 | G223: Mantenimiento y reposiciones - Lodge | H223: =+D223&F223 -> DEL5252 | I223: 122500 | J223: 85.664336 | K223: 1430 | L223: 12/10/2025 | M223: CAJA | N223: 0141 | O223: TE001500000046 | P223: Asiento de CAJA (01/09/2025 - 31/08/2026) | Q223: Extracción de Caja 001500000046 Obs: 12-10-2025 Mov Lodge | R223: DT - Lavandería | S223: 000000000043 | T223: Ejercicio 2025/2026
A224: 5252 | B224: 5263 | D224: DEL | E224: =+VLOOKUP(F224,Resumen_Base!$B$6:$F$69,5,0) -> Maintenance Lodge | F224: 5252 | G224: Mantenimiento y reposiciones - Lodge | H224: =+D224&F224 -> DEL5252 | I224: 10000 | J224: 7.6923077 | K224: 1300 | L224: 07/09/2025 | M224: CAJA | N224: 0141 | O224: TE001500000001 | P224: Asiento de CAJA | Q224: Extracción de Caja 001500000001 Obs: 07-09-2025 DT - DIV 141-BASE2 Mov Lodge | R224: DT - Noel pago logística blanqueria | S224: 000000000008 | T224: Ejercicio 2025/2026
A225: 5252 | B225: 5263 | D225: DEL | E225: =+VLOOKUP(F225,Resumen_Base!$B$6:$F$69,5,0) -> Maintenance Lodge | F225: 5252 | G225: Mantenimiento y reposiciones - Lodge | H225: =+D225&F225 -> DEL5252 | I225: 5000 | J225: 3.5211268 | K225: 1420 | L225: 30/11/2025 | M225: CAJA | N225: 0141 | O225: TE001500000085 | P225: Asiento de CAJA (01/09/2025 - 31/08/2026) | Q225: Extracción de Caja 001500000085 Obs: 30-11-2025 Mov Lodge | R225: DT - Pago a personal de Baie por ayuda y lavado de coolers | S225: 000000000083 | T225: Ejercicio 2025/2026
D226: DEL | E226: =+VLOOKUP(F226,Resumen_Base!$B$6:$F$69,5,0) -> Maintenance Lodge | F226: 5252 | G226: Mantenimiento Rep-Lodge | H226: =+D226&F226 -> DEL5252 | I226: 8400 | J226: 5.915493 | K226: 1420 | L226: 30/11/2025 | M226: CAJA | N226: 0141 | O226: TE001500000085 | P226: Asiento de CAJA (01/09/2025 - 31/08/2026) | Q226: Extracción de Caja 001500000085 Obs: 30-11-2025 Mov Lodge | R226: DT - Focos de luz | S226: 000000000083 | T226: Ejercicio 2025/2026
D227: DEL | E227: =+VLOOKUP(F227,Resumen_Base!$B$6:$F$69,5,0) -> Maintenance Lodge | F227: 5252 | G227: Mantenimiento Rep-Lodge | H227: =+D227&F227 -> DEL5252 | I227: 14000 | J227: 9.8591549 | K227: 1420 | L227: 30/11/2025 | M227: CAJA | N227: 0141 | O227: TE001500000085 | P227: Asiento de CAJA (01/09/2025 - 31/08/2026) | Q227: Extracción de Caja 001500000085 Obs: 30-11-2025 Mov Lodge | R227: DT - 2 flores de ducha hab de huéspedes | S227: 000000000083 | T227: Ejercicio 2025/2026
D228: DEL | E228: =+VLOOKUP(F228,Resumen_Base!$B$6:$F$69,5,0) -> Maintenance Lodge | F228: 5252 | G228: Mantenimiento Rep-Lodge | H228: =+D228&F228 -> DEL5252 | I228: 238680 | J228: 168.08451 | K228: 1420 | L228: 30/11/2025 | M228: CAJA | N228: 0141 | O228: TE001500000085 | P228: Asiento de CAJA (01/09/2025 - 31/08/2026) | Q228: Extracción de Caja 001500000085 Obs: 30-11-2025 Mov Lodge | R228: DT - Artículos de colombraro, contenedores de plástico grandes para blanqueria, broches. | S228: 000000000083 | T228: Ejercicio 2025/2026
D229: DEL | E229: =+VLOOKUP(F229,Resumen_Base!$B$6:$F$69,5,0) -> Maintenance Lodge | F229: 5252 | G229: Mantenimiento Rep-Lodge | H229: =+D229&F229 -> DEL5252 | I229: 3207 | J229: 2.2744681 | K229: 1410 | L229: 05/10/2025 | M229: CAJA | N229: 0141 | O229: TE001500000037 | P229: Asiento de CAJA (01/09/2025 - 31/08/2026) | Q229: Extracción de Caja 001500000037 Obs: 05-10-2025 Mov Lodge | R229: DT - Artículos de farmacia para botiquínes | S229: 000000000039 | T229: Ejercicio 2025/2026
D230: DEL | E230: =+VLOOKUP(F230,Resumen_Base!$B$6:$F$69,5,0) -> Maintenance Lodge | F230: 5252 | G230: Mantenimiento Rep-Lodge | H230: =+D230&F230 -> DEL5252 | I230: 5840 | J230: 4.141844 | K230: 1410 | L230: 05/10/2025 | M230: CAJA | N230: 0141 | O230: TE001500000037 | P230: Asiento de CAJA (01/09/2025 - 31/08/2026) | Q230: Extracción de Caja 001500000037 Obs: 05-10-2025 Mov Lodge | R230: DT - Artículos de farmacia para botiquínes | S230: 000000000039 | T230: Ejercicio 2025/2026
...

Sheet Mov_Analizados_Dic25
G2: Ver Telefonos
G3: Ver Gastos devengados | I3: $ | J3: USD | K3: TC
G4: Ver Luz Devengada | H4: Food & Wine | I4: =+SUMIF($E$10:$E$371,H4,$I$10:$I$371) -> 3013697 | J4: =+SUMIF($E$10:$E$371,H4,$J$10:$J$371) -> 2105.2849 | K4: =+I4/J4 -> 1431.4913
G7: =+IF(I7+J7=0,"Ok","Check") -> Ok | I7: =ROUND(SUM(I10:I364),0) -> 0 | J7: =ROUND(SUM(J10:J364),0) -> 0
E8: Rubro | G8: =+Resumen_Base!C1 -> Ok
B9: =+F9&G9 | D9: DEL | E9: =+VLOOKUP(F9,Resumen_Base!$B$6:$F$69,5,0) -> #N/A | H9: =+D9&F9 -> DEL | I9: =SUM(I10:I130) -> 25550567 | J9: =SUM(J10:J130) -> 17678.519
B10: Cuenta Anterior | D10: Lodge | E10: Concepto | F10: Cuenta | G10: Nombre | I10: monto $ | J10: monto USD | K10: TC | L10: Fecha | M10: Subdiario | N10: Div | O10: Datos del comprobante | P10: Sujeto | Q10: CUIT | R10: Observación asiento | S10: Clase de Asiento | T10: Origen del comprobante | U10: Observación del comprobante | V10: Comentario renglón asiento | W10: Asiento | X10: Control | Z10: monto USD | AA10: tc | AC10: Fecha | AD10: Subdiario | AE10: Div | AF10: Datos del comprobante | AG10: Sujeto | AH10: CUIT | AI10: Observación asiento | AJ10: Clase de Asiento | AK10: Origen del comprobante | AL10: Observación del comprobante | AM10: Comentario renglón asiento | AN10: Asiento
D12: DEL | E12: =+VLOOKUP(F12,Resumen_Base!$B$6:$F$69,5,0) -> Fixed Asset's Payments (Investments) Mejoras/equipamiento Lodge | F12: 12020301 | G12: Muebles y útiles | H12: =+D12&F12 -> DEL12020301 | I12: 53450 | J12: 37.640845 | K12: 1420 | L12: 14/12/2025 | M12: CAJA | N12: 0141 | O12: TE001500000101 | P12: Asiento de CAJA (01/09/2025 - 31/08/2026) | Q12: Extracción de Caja 001500000101 Obs: 14-12-2025 Mov Lodge | R12: DT - 2 mesas de apoyo para los baños de habitaciones huéspedes | S12: 000000000112 | T12: Ejercicio 2025/2026
D13: DEL | E13: =+VLOOKUP(F13,Resumen_Base!$B$6:$F$69,5,0) -> Fixed Asset's Payments (Investments) Mejoras/equipamiento Lodge | F13: 12020301 | G13: Muebles y útiles | H13: =+D13&F13 -> DEL12020301 | I13: 70000 | J13: 49.295775 | K13: 1420 | L13: 14/12/2025 | M13: CAJA | N13: 0141 | O13: TE001500000101 | P13: Asiento de CAJA (01/09/2025 - 31/08/2026) | Q13: Extracción de Caja 001500000101 Obs: 14-12-2025 Mov Lodge | R13: DT - Noel compra mesa de apoyo para living principal huéspedes | S13: 000000000112 | T13: Ejercicio 2025/2026
D14: DEL | E14: =+VLOOKUP(F14,Resumen_Base!$B$6:$F$69,5,0) -> Fixed Asset's Payments (Investments) Mejoras/equipamiento Lodge | F14: 12020301 | G14: Muebles y útiles | H14: =+D14&F14 -> DEL12020301 | I14: 142000 | J14: 100 | K14: 1420 | L14: 14/12/2025 | M14: CAJA | N14: 0141 | O14: TE001500000100 | P14: Asiento de CAJA (01/09/2025 - 31/08/2026) | Q14: Extracción de Caja 001500000100 Obs: 14-12-2025 Mov Lodge | R14: DT - Noel compra mueble mesa de apoyo para living de huéspedes | S14: 000000000111 | T14: Ejercicio 2025/2026
D15: DEL | E15: =+VLOOKUP(F15,Resumen_Base!$B$6:$F$69,5,0) -> Fixed Asset's Payments (Investments) Rodados/Lanchas | F15: 12020701 | G15: Lanchas y Botes | H15: =+D15&F15 -> DEL12020701 | I15: 1374000 | J15: 967.60563 | K15: 1420 | L15: 19/12/2025 | M15: CAJA | N15: 0141 | O15: TE001500000111 | P15: Asiento de CAJA (01/09/2025 - 31/08/2026) | Q15: Extracción de Caja 001500000111 Obs: Movimiento_Cajas_Bancos_Semana 25-26 al 19-12-2025 | R15: DT-Flete Pira Jagua (itati - Bella vista - Bs As) 930km Pagos Frank Garrahan-. Al 19-12-2025 | S15: 000000000116 | T15: Ejercicio 2025/2026
D16: DEL | E16: =+VLOOKUP(F16,Resumen_Base!$B$6:$F$69,5,0) -> Shop | F16: 4104 | G16: Ventas Shop | H16: =+D16&F16 -> DEL4104 | I16: -85200 | J16: -60 | K16: 1420 | L16: 07/12/2025 | M16: VENTAS | N16: 0141 | O16: VF000000002775B | P16: Asiento de VENTAS (01/09/2025 - 31/08/2026) | Q16: F B 000000002775 | R16: Ref. nota de Venta: DEL20 Obs.:07-12-2025_CLIENTES | S16: 000000000100 | T16: Ejercicio 2025/2026
D17: DEL | E17: =+VLOOKUP(F17,Resumen_Base!$B$6:$F$69,5,0) -> Shop | F17: 4104 | G17: Ventas Shop | H17: =+D17&F17 -> DEL4104 | I17: -85200 | J17: -60 | K17: 1420 | L17: 07/12/2025 | M17: VENTAS | N17: 0141 | O17: VF000000002776B | P17: Asiento de VENTAS (01/09/2025 - 31/08/2026) | Q17: F B 000000002776 | R17: Ref. nota de Venta: DEL42 Obs.:07-12-2025_CLIENTES | S17: 000000000101 | T17: Ejercicio 2025/2026
D18: DEL | E18: =+VLOOKUP(F18,Resumen_Base!$B$6:$F$69,5,0) -> Shop | F18: 4104 | G18: Ventas Shop | H18: =+D18&F18 -> DEL4104 | I18: -56800 | J18: -40 | K18: 1420 | L18: 07/12/2025 | M18: VENTAS | N18: 0141 | O18: VF000000002777B | P18: Asiento de VENTAS (01/09/2025 - 31/08/2026) | Q18: F B 000000002777 | R18: Ref. nota de Venta: DEL50 Obs.:07-12-2025_CLIENTES | S18: 000000000102 | T18: Ejercicio 2025/2026
D19: DEL | E19: =+VLOOKUP(F19,Resumen_Base!$B$6:$F$69,5,0) -> Shop | F19: 4104 | G19: Ventas Shop | H19: =+D19&F19 -> DEL4104 | I19: -42600 | J19: -30 | K19: 1420 | L19: 07/12/2025 | M19: VENTAS | N19: 0141 | O19: VF000000002778B | P19: Asiento de VENTAS (01/09/2025 - 31/08/2026) | Q19: F B 000000002778 | R19: Ref. nota de Venta: DEL50 Obs.:07-12-2025_CLIENTES | S19: 000000000103 | T19: Ejercicio 2025/2026
D20: DEL | E20: =+VLOOKUP(F20,Resumen_Base!$B$6:$F$69,5,0) -> Shop | F20: 4104 | G20: Ventas Shop | H20: =+D20&F20 -> DEL4104 | I20: -42600 | J20: -30 | K20: 1420 | L20: 07/12/2025 | M20: VENTAS | N20: 0141 | O20: VF000000002778B | P20: Asiento de VENTAS (01/09/2025 - 31/08/2026) | Q20: F B 000000002778 | R20: Ref. nota de Venta: DEL50 Obs.:07-12-2025_CLIENTES | S20: 000000000103 | T20: Ejercicio 2025/2026
D21: DEL | E21: =+VLOOKUP(F21,Resumen_Base!$B$6:$F$69,5,0) -> Shop | F21: 4104 | G21: Ventas Shop | H21: =+D21&F21 -> DEL4104 | I21: -176400 | J21: -120 | K21: 1470 | L21: 31/12/2025 | M21: VENTAS | N21: 0141 | O21: VF000000003173B | P21: Asiento de VENTAS (01/09/2025 - 31/08/2026) | Q21: F B 000000003173 | R21: Ref. nota de Venta: DEL6 Obs.:31-12-2025_CLIENTES | S21: 000000000147 | T21: Ejercicio 2025/2026
D22: DEL | E22: =+VLOOKUP(F22,Resumen_Base!$B$6:$F$69,5,0) -> Canon Lodge/Labor Permits: | F22: 5208 | G22: Alquileres y Canon | H22: =+D22&F22 -> DEL5208 | I22: 17000 | J22: 11.564626 | K22: 1470 | L22: 31/12/2025 | M22: CAJA | N22: 0141 | O22: TE001500000137 | P22: Asiento de CAJA (01/09/2025 - 31/08/2026) | Q22: Extracción de Caja 001500000137 Obs: Movimiento_Cajas_Bancos_Semana 25-26 al 02-01-2026 | R22: DT-Saldo pendiente por aumento de cuota Diciembre - guarderia La Baie F.Fijo Oper. Al 02-02-2026 | S22: 000000000130 | T22: Ejercicio 2025/2026
D23: DEL | E23: =+VLOOKUP(F23,Resumen_Base!$B$6:$F$69,5,0) -> Work uniforms for personnel (employees) | F23: 5220 | G23: Uniformes | H23: =+D23&F23 -> DEL5220 | I23: 50402.05 | J23: 34.287109 | K23: 1470 | L23: 26/12/2025 | M23: CAJA | N23: 0141 | O23: TE001500000115 | P23: Asiento de CAJA (01/09/2025 - 31/08/2026) | Q23: Extracción de Caja 001500000115 Obs: Movimiento_Cajas_Bancos_Semana 25-26 al 26-12-2025 | R23: DT-Compra 1 par de zuecos gastronomicos - Andres F.Fijo Oper. Al 26-12-2025 | S23: 000000000120 | T23: Ejercicio 2025/2026
A24: 5210 | B24: 5226 | D24: DEL | E24: =+VLOOKUP(F24,Resumen_Base!$B$6:$F$69,5,0) -> Services/House | F24: 5226 | G24: Remuneraciones Servicios | H24: =+D24&F24 -> DEL5226 | I24: 80000 | J24: 54.421769 | K24: 1470 | L24: 31/12/2025 | M24: CAJA | N24: 0141 | O24: TE001500000120 | P24: Asiento de CAJA (01/09/2025 - 31/08/2026) | Q24: Extracción de Caja 001500000120 Obs: 31-12-2025 Mov Lodge | R24: DT - Noel le paga a Alexis por 1 Transfer realizado | S24: 000000000122 | T24: Ejercicio 2025/2026
A25: 5253 | B25: 5226 | D25: DEL | E25: =+VLOOKUP(F25,Resumen_Base!$B$6:$F$69,5,0) -> Services/House | F25: 5226 | G25: Remuneraciones Servicios | H25: =+D25&F25 -> DEL5226 | I25: 100000 | J25: 68.027211 | K25: 1470 | L25: 31/12/2025 | M25: CAJA | N25: 0141 | O25: TE001500000120 | P25: Asiento de CAJA (01/09/2025 - 31/08/2026) | Q25: Extracción de Caja 001500000120 Obs: 31-12-2025 Mov Lodge | R25: DT - Noel paga a Alexis casero por remolcar lancha del Lodge hasta la guardería náutica | S25: 000000000122 | T25: Ejercicio 2025/2026
D26: DEL | E26: =+VLOOKUP(F26,Resumen_Base!$B$6:$F$69,5,0) -> Services/House | F26: 5226 | G26: Remuneraciones Servicios | H26: =+D26&F26 -> DEL5226 | I26: 499800 | J26: 340 | K26: 1470 | L26: 31/12/2025 | M26: CAJA | N26: 0141 | O26: TE001500000119 | P26: Asiento de CAJA (01/09/2025 - 31/08/2026) | Q26: Extracción de Caja 001500000119 Obs: 31-12-2025 Mov Lodge | R26: DT - Pago a Karina por 6 full day (le incluyo 10 usd que le debia de la vez anterior) | S26: 000000000121 | T26: Ejercicio 2025/2026
D27: DEL | E27: =+VLOOKUP(F27,Resumen_Base!$B$6:$F$69,5,0) -> Services/House | F27: 5226 | G27: Remuneraciones Servicios | H27: =+D27&F27 -> DEL5226 | I27: 588000 | J27: 400 | K27: 1470 | L27: 31/12/2025 | M27: CAJA | N27: 0141 | O27: TE001500000119 | P27: Asiento de CAJA (01/09/2025 - 31/08/2026) | Q27: Extracción de Caja 001500000119 Obs: 31-12-2025 Mov Lodge | R27: DT - Pago a Lucia por ayuda en cocina | S27: 000000000121 | T27: Ejercicio 2025/2026
D28: DEL | E28: =+VLOOKUP(F28,Resumen_Base!$B$6:$F$69,5,0) -> Services/House | F28: 5226 | G28: Remuneraciones Servicios | H28: =+D28&F28 -> DEL5226 | I28: 20000 | J28: 13.605442 | K28: 1470 | L28: 31/12/2025 | M28: CAJA | N28: 0141 | O28: TE001500000120 | P28: Asiento de CAJA (01/09/2025 - 31/08/2026) | Q28: Extracción de Caja 001500000120 Obs: 31-12-2025 Mov Lodge | R28: DT - Pago adicional a Alexis por hacer compras | S28: 000000000122 | T28: Ejercicio 2025/2026
D29: DEL | E29: =+VLOOKUP(F29,Resumen_Base!$B$6:$F$69,5,0) -> Services/House | F29: 5226 | G29: Remuneraciones Servicios | H29: =+D29&F29 -> DEL5226 | I29: 40000 | J29: 27.210884 | K29: 1470 | L29: 31/12/2025 | M29: CAJA | N29: 0141 | O29: TE001500000120 | P29: Asiento de CAJA (01/09/2025 - 31/08/2026) | Q29: Extracción de Caja 001500000120 Obs: 31-12-2025 Mov Lodge | R29: DT - Pago complementario lucia ayuda cocina | S29: 000000000122 | T29: Ejercicio 2025/2026
D30: DEL | E30: =+VLOOKUP(F30,Resumen_Base!$B$6:$F$69,5,0) -> Services/House | F30: 5226 | G30: Remuneraciones Servicios | H30: =+D30&F30 -> DEL5226 | I30: 1136000 | J30: 800 | K30: 1420 | L30: 14/12/2025 | M30: CAJA | N30: 0141 | O30: TE001500000100 | P30: Asiento de CAJA (01/09/2025 - 31/08/2026) | Q30: Extracción de Caja 001500000100 Obs: 14-12-2025 Mov Lodge | R30: DT - Pago salario Andrés del 26/11 al 13/12 | S30: 000000000111 | T30: Ejercicio 2025/2026
D31: DEL | E31: =+VLOOKUP(F31,Resumen_Base!$B$6:$F$69,5,0) -> Services/House | F31: 5226 | G31: Remuneraciones Servicios | H31: =+D31&F31 -> DEL5226 | I31: 573300 | J31: 390 | K31: 1470 | L31: 31/12/2025 | M31: CAJA | N31: 0141 | O31: TE001500000119 | P31: Asiento de CAJA (01/09/2025 - 31/08/2026) | Q31: Extracción de Caja 001500000119 Obs: 31-12-2025 Mov Lodge | R31: DT - Pago salario Andrés por 6 full day | S31: 000000000121 | T31: Ejercicio 2025/2026
D32: DEL | E32: =+VLOOKUP(F32,Resumen_Base!$B$6:$F$69,5,0) -> Services/House | F32: 5226 | G32: Remuneraciones Servicios | H32: =+D32&F32 -> DEL5226 | I32: 1022400 | J32: 720 | K32: 1420 | L32: 14/12/2025 | M32: CAJA | N32: 0141 | O32: TE001500000100 | P32: Asiento de CAJA (01/09/2025 - 31/08/2026) | Q32: Extracción de Caja 001500000100 Obs: 14-12-2025 Mov Lodge | R32: DT - Pago salario Karina del 26/11 al 13/12 | S32: 000000000111 | T32: Ejercicio 2025/2026
D33: DEL | E33: =+VLOOKUP(F33,Resumen_Base!$B$6:$F$69,5,0) -> Services/House | F33: 5226 | G33: Remuneraciones Servicios | H33: =+D33&F33 -> DEL5226 | I33: 161998 | J33: 114.0831 | K33: 1420 | L33: 19/12/2025 | M33: CAJA | N33: 0141 | O33: TE001500000111 | P33: Asiento de CAJA (01/09/2025 - 31/08/2026) | Q33: Extracción de Caja 001500000111 Obs: Movimiento_Cajas_Bancos_Semana 25-26 al 19-12-2025 | R33: DT-Alexis Carra - SAC DIC 25 - mantenimiento Pagos Frank Garrahan-. Al 19-12-2025 | S33: 000000000116 | T33: Ejercicio 2025/2026
D34: DEL | E34: =+VLOOKUP(F34,Resumen_Base!$B$6:$F$69,5,0) -> Services/House | F34: 5226 | G34: Remuneraciones Servicios | H34: =+D34&F34 -> DEL5226 | I34: 1176000 | J34: 800 | K34: 1470 | L34: 31/12/2025 | M34: CAJA | N34: 0141 | O34: TE001500000135 | P34: Asiento de CAJA (01/09/2025 - 31/08/2026) | Q34: Extracción de Caja 001500000135 Obs: Movimiento_Cajas_Bancos_Semana 25-26 al 02-01-2026 | R34: DT-Supervisión Luis Chua - 26/11 al 5/12 F.Fijo Oper. Al 02-02-2026 | S34: 000000000128 | T34: Ejercicio 2025/2026
D35: DEL | E35: =+VLOOKUP(F35,Resumen_Base!$B$6:$F$69,5,0) -> Services/House | F35: 5226 | G35: Remuneraciones Servicios | H35: =+D35&F35 -> DEL5226 | I35: 1136000 | J35: 800 | K35: 1420 | L35: 26/12/2025 | M35: CAJA | N35: 0141 | O35: TE001500000114 | P35: Asiento de CAJA (01/09/2025 - 31/08/2026) | Q35: Extracción de Caja 001500000114 Obs: Movimiento_Cajas_Bancos_Semana 25-26 al 26-12-2025 | R35: DT-Supervisión Luis Chua 26/11 al 5/12 - 10 dias a 80 usd F.Fijo Oper. Al 26-12-2025 | S35: 000000000119 | T35: Ejercicio 2025/2026
D36: DEL | E36: =+VLOOKUP(F36,Resumen_Base!$B$6:$F$69,5,0) -> Guides | F36: 5227 | G36: Remuneraciones Guías | H36: =+D36&F36 -> DEL5227 | I36: 2425500 | J36: 1650 | K36: 1470 | L36: 31/12/2025 | M36: CAJA | N36: 0141 | O36: TE001500000119 | P36: Asiento de CAJA (01/09/2025 - 31/08/2026) | Q36: Extracción de Caja 001500000119 Obs: 31-12-2025 Mov Lodge | R36: DT - Pago a Pablo guía | S36: 000000000121 | T36: Ejercicio 2025/2026
D37: DEL | E37: =+VLOOKUP(F37,Resumen_Base!$B$6:$F$69,5,0) -> Guides | F37: 5227 | G37: Remuneraciones Guías | H37: =+D37&F37 -> DEL5227 | I37: 30000 | J37: 21.126761 | K37: 1420 | L37: 14/12/2025 | M37: CAJA | N37: 0141 | O37: TE001500000101 | P37: Asiento de CAJA (01/09/2025 - 31/08/2026) | Q37: Extracción de Caja 001500000101 Obs: 14-12-2025 Mov Lodge | R37: DT - Pago complemento a Matías guía en pesos por falta de cambio en usd | S37: 000000000112 | T37: Ejercicio 2025/2026
... D80: DEL | E80: =+VLOOKUP(F80,Resumen_Base!$B$6:$F$69,5,0) -> Maintenance Lodge | F80: 5252 | G80: Mantenimiento Rep-Lodge | H80: =+D80&F80 -> DEL5252 | I80: 263966 | J80: 179.56871 | K80: 1470 | L80: 31/12/2025 | M80: CAJA | N80: 0141 | O80: TE001500000120 | P80: Asiento de CAJA (01/09/2025 - 31/08/2026) | Q80: Extracción de Caja 001500000120 Obs: 31-12-2025 Mov Lodge | R80: DT - Compras supermercado coto | S80: 000000000122 | T80: Ejercicio 2025/2026
A81: 5252 | B81: 5220 | D81: DEL | E81: =+VLOOKUP(F81,Resumen_Base!$B$6:$F$69,5,0) -> Maintenance Lodge | F81: 5252 | G81: Mantenimiento Rep-Lodge | H81: =+D81&F81 -> DEL5252 | I81: 139000 | J81: 94.557823 | K81: 1470 | L81: 31/12/2025 | M81: CAJA | N81: 0141 | O81: TE001500000120 | P81: Asiento de CAJA (01/09/2025 - 31/08/2026) | Q81: Extracción de Caja 001500000120 Obs: 31-12-2025 Mov Lodge | R81: DT - Indumentaria de trabajo para Alexis | S81: 000000000122 | T81: Ejercicio 2025/2026
D82: DEL | E82: =+VLOOKUP(F82,Resumen_Base!$B$6:$F$69,5,0) -> Maintenance Lodge | F82: 5252 | G82: Mantenimiento Rep-Lodge | H82: =+D82&F82 -> DEL5252 | I82: 28000 | J82: 19.71831 | K82: 1420 | L82: 07/12/2025 | M82: CAJA | N82: 0141 | O82: TE001500000091 | P82: Asiento de CAJA (01/09/2025 - 31/08/2026) | Q82: Extracción de Caja 001500000091 Obs: 07-12-2025 Mov Lodge | R82: DT - Lavadero las marias | S82: 000000000087 | T82: Ejercicio 2025/2026
D83: DEL | E83: =+VLOOKUP(F83,Resumen_Base!$B$6:$F$69,5,0) -> Maintenance Lodge | F83: 5252 | G83: Mantenimiento Rep-Lodge | H83: =+D83&F83 -> DEL5252 | I83: 131400 | J83: 89.387755 | K83: 1470 | L83: 31/12/2025 | M83: CAJA | N83: 0141 | O83: TE001500000120 | P83: Asiento de CAJA (01/09/2025 - 31/08/2026) | Q83: Extracción de Caja 001500000120 Obs: 31-12-2025 Mov Lodge | R83: DT - Pago a Ecosec por servicio de lavado de blanqueria | S83: 000000000122 | T83: Ejercicio 2025/2026
D84: DEL | E84: =+VLOOKUP(F84,Resumen_Base!$B$6:$F$69,5,0) -> Maintenance Lodge | F84: 5252 | G84: Mantenimiento Rep-Lodge | H84: =+D84&F84 -> DEL5252 | I84: 40000 | J84: 28.169014 | K84: 1420 | L84: 07/12/2025 | M84: CAJA | N84: 0141 | O84: TE001500000091 | P84: Asiento de CAJA (01/09/2025 - 31/08/2026) | Q84: Extracción de Caja 001500000091 Obs: 07-12-2025 Mov Lodge | R84: DT - Pago a gasista | S84: 000000000087 | T84: Ejercicio 2025/2026
D85: DEL | E85: =+VLOOKUP(F85,Resumen_Base!$B$6:$F$69,5,0) -> Maintenance Lodge | F85: 5252 | G85: Mantenimiento Rep-Lodge | H85: =+D85&F85 -> DEL5252 | I85: 20000 | J85: 14.084507 | K85: 1420 | L85: 07/12/2025 | M85: CAJA | N85: 0141 | O85: TE001500000091 | P85: Asiento de CAJA (01/09/2025 - 31/08/2026) | Q85: Extracción de Caja 001500000091 Obs: 07-12-2025 Mov Lodge | R85: DT - Pago a rolando por llevarse basura del Lodge | S85: 000000000087 | T85: Ejercicio 2025/2026
D86: DEL | E86: =+VLOOKUP(F86,Resumen_Base!$B$6:$F$69,5,0) -> Maintenance Lodge | F86: 5252 | G86: Mantenimiento Rep-Lodge | H86: =+D86&F86 -> DEL5252 | I86: 6000 | J86: 4.2253521 | K86: 1420 | L86: 14/12/2025 | M86: CAJA | N86: 0141 | O86: TE001500000101 | P86: Asiento de CAJA (01/09/2025 - 31/08/2026) | Q86: Extracción de Caja 001500000101 Obs: 14-12-2025 Mov Lodge | R86: DT - Pico manguera para riego | S86: 000000000112 | T86: Ejercicio 2025/2026
D87: DEL | E87: =+VLOOKUP(F87,Resumen_Base!$B$6:$F$69,5,0) -> Maintenance Lodge | F87: 5252 | G87: Mantenimiento Rep-Lodge | H87: =+D87&F87 -> DEL5252 | I87: 79615 | J87: 56.066901 | K87: 1420 | L87: 14/12/2025 | M87: CAJA | N87: 0141 | O87: TE001500000101 | P87: Asiento de CAJA (01/09/2025 - 31/08/2026) | Q87: Extracción de Caja 001500000101 Obs: 14-12-2025 Mov Lodge | R87: DT - Pintura para mesas nuevas de apoyo en hab de huéspedes | S87: 000000000112 | T87: Ejercicio 2025/2026
D88: DEL | E88: =+VLOOKUP(F88,Resumen_Base!$B$6:$F$69,5,0) -> Maintenance Lodge | F88: 5252 | G88: Mantenimiento Rep-Lodge | H88: =+D88&F88 -> DEL5252 | I88: 43000 | J88: 30.28169 | K88: 1420 | L88: 14/12/2025 | M88: CAJA | N88: 0141 | O88: TE001500000101 | P88: Asiento de CAJA (01/09/2025 - 31/08/2026) | Q88: Extracción de Caja 001500000101 Obs: 14-12-2025 Mov Lodge | R88: DT - Reflectores que iluminan laguna nueva | S88: 000000000112 | T88: Ejercicio 2025/2026
D89: DEL | E89: =+VLOOKUP(F89,Resumen_Base!$B$6:$F$69,5,0) -> Maintenance Lodge | F89: 5252 | G89: Mantenimiento Rep-Lodge | H89: =+D89&F89 -> DEL5252 | I89: 22100 | J89: 15.56338 | K89: 1420 | L89: 07/12/2025 | M89: CAJA | N89: 0141 | O89: TE001500000091 | P89: Asiento de CAJA (01/09/2025 - 31/08/2026) | Q89: Extracción de Caja 001500000091 Obs: 07-12-2025 Mov Lodge | R89: DT - Regadera | S89: 000000000087 | T89: Ejercicio 2025/2026
D90: DEL | E90: =+VLOOKUP(F90,Resumen_Base!$B$6:$F$69,5,0) -> Maintenance Lodge | F90: 5252 | G90: Mantenimiento Rep-Lodge | H90: =+D90&F90 -> DEL5252 | I90: 43500 | J90: 29.591837 | K90: 1470 | L90: 31/12/2025 | M90: CAJA | N90: 0141 | O90: TE001500000120 | P90: Asiento de CAJA (01/09/2025 - 31/08/2026) | Q90: Extracción de Caja 001500000120 Obs: 31-12-2025 Mov Lodge | R90: DT - Repuesto calefon cocina | S90: 000000000122 | T90: Ejercicio 2025/2026
D91: DEL | E91: =+VLOOKUP(F91,Resumen_Base!$B$6:$F$69,5,0) -> Maintenance Lodge | F91: 5252 | G91: Mantenimiento Rep-Lodge | H91: =+D91&F91 -> DEL5252 | I91: 26000 | J91: 18.309859 | K91: 1420 | L91: 07/12/2025 | M91: CAJA | N91: 0141 | O91: TE001500000091 | P91: Asiento de CAJA (01/09/2025 - 31/08/2026) | Q91: Extracción de Caja 001500000091 Obs: 07-12-2025 Mov Lodge | R91: DT - Repuesto calefon cocina casa Terwin | S91: 000000000087 | T91: Ejercicio 2025/2026
D92: DEL | E92: =+VLOOKUP(F92,Resumen_Base!$B$6:$F$69,5,0) -> Maintenance Lodge | F92: 5252 | G92: Mantenimiento Rep-Lodge | H92: =+D92&F92 -> DEL5252 | I92: 27500 | J92: 19.366197 | K92: 1420 | L92: 07/12/2025 | M92: CAJA | N92: 0141 | O92: TE001500000091 | P92: Asiento de CAJA (01/09/2025 - 31/08/2026) | Q92: Extracción de Caja 001500000091 Obs: 07-12-2025 Mov Lodge | R92: DT - Repuestos calefon cocina | S92: 000000000087 | T92: Ejercicio 2025/2026
D93: DEL | E93: =+VLOOKUP(F93,Resumen_Base!$B$6:$F$69,5,0) -> Maintenance Lodge | F93: 5252 | G93: Mantenimiento Rep-Lodge | H93: =+D93&F93 -> DEL5252 | I93: 258500 | J93: 175.85034 | K93: 1470 | L93: 31/12/2025 | M93: CAJA | N93: 0141 | O93: TE001500000120 | P93: Asiento de CAJA (01/09/2025 - 31/08/2026) | Q93: Extracción de Caja 001500000120 Obs: 31-12-2025 Mov Lodge | R93: DT - Servicio de lavandería de blanqueria | S93: 000000000122 | T93: Ejercicio 2025/2026
... D114: DEL | E114: =+VLOOKUP(F114,Resumen_Base!$B$6:$F$69,5,0) -> Miscellaneous & Shipping | F114: 5263 | G114: Servicios - Otros Operativos | H114: =+D114&F114 -> DEL5263 | I114: 8000 | J114: 5.4421769 | K114: 1470 | L114: 31/12/2025 | M114: CAJA | N114: 0141 | O114: TE001500000120 | P114: Asiento de CAJA (01/09/2025 - 31/08/2026) | Q114: Extracción de Caja 001500000120 Obs: 31-12-2025 Mov Lodge | R114: DT - Noel paga por ayuda de carga y descarga en guardería | S114: 000000000122 | T114: Ejercicio 2025/2026
A115: 5255 | B115: 5263 | D115: DEL | E115: =+VLOOKUP(F115,Resumen_Base!$B$6:$F$69,5,0) -> Miscellaneous & Shipping | F115: 5263 | G115: Servicios - Otros Operativos | H115: =+D115&F115 -> DEL5263 | I115: 7200 | J115: 5.0704225 | K115: 1420 | L115: 14/12/2025 | M115: CAJA | N115: 0141 | O115: TE001500000101 | P115: Asiento de CAJA (01/09/2025 - 31/08/2026) | Q115: Extracción de Caja 001500000101 Obs: 14-12-2025 Mov Lodge | R115: DT - Noel pago Remis para hacer compras | S115: 000000000112 | T115: Ejercicio 2025/2026
A116: 5255 | B116: 5263 | D116: DEL | E116: =+VLOOKUP(F116,Resumen_Base!$B$6:$F$69,5,0) -> Miscellaneous & Shipping | F116: 5263 | G116: Servicios - Otros Operativos | H116: =+D116&F116 -> DEL5263 | I116: 106000 | J116: 72.108844 | K116: 1470 | L116: 31/12/2025 | M116: CAJA | N116: 0141 | O116: TE001500000120 | P116: Asiento de CAJA (01/09/2025 - 31/08/2026) | Q116: Extracción de Caja 001500000120 Obs: 31-12-2025 Mov Lodge | R116: DT - Pago camioneta de Remis Madero para dia de compras | S116: 000000000122 | T116: Ejercicio 2025/2026
A117: 5252 | B117: 5263 | D117: DEL | E117: =+VLOOKUP(F117,Resumen_Base!$B$6:$F$69,5,0) -> Miscellaneous & Shipping | F117: 5263 | G117: Servicios - Otros Operativos | H117: =+D117&F117 -> DEL5263 | I117: 80000 | J117: 56.338028 | K117: 1420 | L117: 14/12/2025 | M117: CAJA | N117: 0141 | O117: TE001500000101 | P117: Asiento de CAJA (01/09/2025 - 31/08/2026) | Q117: Extracción de Caja 001500000101 Obs: 14-12-2025 Mov Lodge | R117: DT - Rolando logística residuos y blanqueria | S117: 000000000112 | T117: Ejercicio 2025/2026
A118: 5252 | B118: 5263 | D118: DEL | E118: =+VLOOKUP(F118,Resumen_Base!$B$6:$F$69,5,0) -> Miscellaneous & Shipping | F118: 5263 | G118: Servicios - Otros Operativos | H118: =+D118&F118 -> DEL5263 | I118: 10000 | J118: 6.8027211 | K118: 1470 | L118: 31/12/2025 | M118: CAJA | N118: 0141 | O118: TE001500000120 | P118: Asiento de CAJA (01/09/2025 - 31/08/2026) | Q118: Extracción de Caja 001500000120 Obs: 31-12-2025 Mov Lodge | R118: DT - Servicio de logística blanqueria Lodge | S118: 000000000122 | T118: Ejercicio 2025/2026
D119: DEL | E119: =+VLOOKUP(F119,Resumen_Base!$B$6:$F$69,5,0) -> Miscellaneous & Shipping | F119: 5263 | G119: Servicios - Otros Operativos | H119: =+D119&F119 -> DEL5263 | I119: 34000 | J119: 23.943662 | K119: 1420 | L119: 19/12/2025 | M119: CAJA | N119: 0141 | O119: TE001500000111 | P119: Asiento de CAJA (01/09/2025 - 31/08/2026) | Q119: Extracción de Caja 001500000111 Obs: Movimiento_Cajas_Bancos_Semana 25-26 al 19-12-2025 | R119: DT- F.Fijo Oper. Al 19-12-2025 | S119: 000000000116 | T119: Ejercicio 2025/2026
D120: DEL | E120: =+VLOOKUP(F120,Resumen_Base!$B$6:$F$69,5,0) -> Food & Wine | F120: 5289 | G120: Comidas Fuera Temp / Empleados | H120: =+D120&F120 -> DEL5289 | I120: 28000 | J120: 19.047619 | K120: 1470 | L120: 31/12/2025 | M120: CAJA | N120: 0141 | O120: TE001500000120 | P120: Asiento de CAJA (01/09/2025 - 31/08/2026) | Q120: Extracción de Caja 001500000120 Obs: 31-12-2025 Mov Lodge | R120: DT - Comida Noel | S120: 000000000122 | T120: Ejercicio 2025/2026
D121: DEL | E121: =+VLOOKUP(F121,Resumen_Base!$B$6:$F$69,5,0) -> Food & Wine | F121: 5289 | G121: Comidas Fuera Temp / Empleados | H121: =+D121&F121 -> DEL5289 | I121: 42200 | J121: 28.707483 | K121: 1470 | L121: 31/12/2025 | M121: CAJA | N121: 0141 | O121: TE001500000120 | P121: Asiento de CAJA (01/09/2025 - 31/08/2026) | Q121: Extracción de Caja 001500000120 Obs: 31-12-2025 Mov Lodge | R121: DT - Compras almacén fondeadero Noel | S121: 000000000122 | T121: Ejercicio 2025/2026
D122: DEL | E122: =+VLOOKUP(F122,Resumen_Base!$B$6:$F$69,5,0) -> Food & Wine | F122: 5289 | G122: Comidas Fuera Temp / Empleados | H122: =+D122&F122 -> DEL5289 | I122: 39300 | J122: 26.734694 | K122: 1470 | L122: 31/12/2025 | M122: CAJA | N122: 0141 | O122: TE001500000120 | P122: Asiento de CAJA (01/09/2025 - 31/08/2026) | Q122: Extracción de Caja 001500000120 Obs: 31-12-2025 Mov Lodge | R122: DT - Compras súper chino Noel | S122: 000000000122 | T122: Ejercicio 2025/2026
A123: 5250 | B123: 5291 | D123: DEL | E123: =+VLOOKUP(F123,Resumen_Base!$B$6:$F$69,5,0) -> Food & Wine | F123: 5291 | G123: Comida / Fletes | H123: =+D123&F123 -> DEL5291 | I123: 48180 | J123: 33.929577 | K123: 1420 | L123: 07/12/2025 | M123: CAJA | N123: 0141 | O123: TE001500000091 | P123: Asiento de CAJA (01/09/2025 - 31/08/2026) | Q123: Extracción de Caja 001500000091 Obs: 07-12-2025 Mov Lodge | R123: DT - Pescadería avenida cazón, 2kg de abadejo | S123: 000000000087 | T123: Ejercicio 2025/2026
A130: INSERT | B130: INSERT | C130: INSERT | D130: INSERT | E130: INSERT | F130: INSERT | G130: INSERT | H130: INSERT | I130: INSERT | J130: INSERT | K130: INSERT | L130: INSERT | M130: INSERT | N130: INSERT | O130: INSERT | P130: INSERT | Q130: INSERT | R130: INSERT | S130: INSERT | T130: INSERT | U130: INSERT | V130: INSERT | W130: INSERT
F132: 11010101 | G132: Caja $ Administración | I132: -34000 | J132: -23.943662 | K132: 1420 | L132: 19/12/2025 | M132: CAJA | N132: 0141 | O132: TE001500000111 | P132: Asiento de CAJA (01/09/2025 - 31/08/2026) | Q132: Extracción de Caja 001500000111 Obs: Movimiento_Cajas_Bancos_Semana 25-26 al 19-12-2025 | R132: DT- F.Fijo Oper. Al 19-12-2025 | S132: 000000000116 | T132: Ejercicio 2025/2026
F133: 11010101 | G133: Caja $ Administración | I133: -4100000 | J133: -2887.3239 | K133: 1420 | L133: 19/12/2025 | M133: CAJA | N133: 0141 | O133: TE001500000111 | P133: Asiento de CAJA (01/09/2025 - 31/08/2026) | Q133: Extracción de Caja 001500000111 Obs: Movimiento_Cajas_Bancos_Semana 25-26 al 19-12-2025 | R133: DT- F.Fijo Oper. Al 19-12-2025 | S133: 000000000116 | T133: Ejercicio 2025/2026
F134: 11010101 | G134: Caja $ Administración | I134: -340000 | J134: -239.43662 | K134: 1420 | L134: 19/12/2025 | M134: CAJA | N134: 0141 | O134: TE001500000111 | P134: Asiento de CAJA (01/09/2025 - 31/08/2026) | Q134: Extracción de Caja 001500000111 Obs: Movimiento_Cajas_Bancos_Semana 25-26 al 19-12-2025 | R134: DT- F.Fijo Oper. Al 19-12-2025 | S134: 000000000116 | T134: Ejercicio 2025/2026
F135: 11010101 | G135: Caja $ Administración | I135: -161998 | J135: -114.0831 | K135: 1420 | L135: 19/12/2025 | M135: CAJA | N135: 0141 | O135: TE001500000111 | P135: Asiento de CAJA (01/09/2025 - 31/08/2026) | Q135: Extracción de Caja 001500000111 Obs: Movimiento_Cajas_Bancos_Semana 25-26 al 19-12-2025 | R135: DT-Alexis Carra - SAC DIC 25 - mantenimiento Pagos Frank Garrahan-. Al 19-12-2025 | S135: 000000000116 | T135: Ejercicio 2025/2026
F136: 11010101 | G136: Caja $ Administración | I136: -50402.05 | J136: -34.287109 | K136: 1470 | L136: 26/12/2025 | M136: CAJA | N136: 0141 | O136: TE001500000115 | P136: Asiento de CAJA (01/09/2025 - 31/08/2026) | Q136: Extracción de Caja 001500000115 Obs: Movimiento_Cajas_Bancos_Semana 25-26 al 26-12-2025 | R136: DT-Compra 1 par de zuecos gastronomicos - Andres F.Fijo Oper. Al 26-12-2025 | S136: 000000000120 | T136: Ejercicio 2025/2026
F137: 11010101 | G137: Caja $ Administración | I137: -1399802 | J137: -985.77606 | K137: 1420 | L137: 12/12/2025 | M137: CAJA | N137: 0141 | O137: TE001500000104 | P137: Asiento de CAJA (01/09/2025 - 31/08/2026) | Q137: Extracción de Caja 001500000104 Obs: Movimiento_Cajas_Bancos_Semana 25-26 al 12-12-2025 | R137: DT-Compra carniceria - mes diciembre Pagos Depsa Valores. Al 12-12-2025 | S137: 000000000113 | T137: Ejercicio 2025/2026
F138: 11010101 | G138: Caja $ Administración | I138: -639045 | J138: -450.03169 | K138: 1420 | L138: 12/12/2025 | M138: CAJA | N138: 0141 | O138: TE001500000104 | P138: Asiento de CAJA (01/09/2025 - 31/08/2026) | Q138: Extracción de Caja 001500000104 Obs: Movimiento_Cajas_Bancos_Semana 25-26 al 12-12-2025 | R138: DT-Compra verduleria - mes diciembre Pagos Depsa Valores. Al 12-12-2025 | S138: 000000000113 | T138: Ejercicio 2025/2026
F139: 11010101 | G139: Caja $ Administración | I139: -1374000 | J139: -967.60563 | K139: 1420 | L139: 19/12/2025 | M139: CAJA | N139: 0141 | O139: TE001500000111 | P139: Asiento de CAJA (01/09/2025 - 31/08/2026) | Q139: Extracción de Caja 001500000111 Obs: Movimiento_Cajas_Bancos_Semana 25-26 al 19-12-2025 | R139: DT-Flete Pira Jagua (itati - Bella vista - Bs As) 930km Pagos Frank Garrahan-. Al 19-12-2025 | S139: 000000000116 | T139: Ejercicio 2025/2026
F140: 11010101 | G140: Caja $ Administración | I140: -270000 | J140: -190.14085 | K140: 1420 | L140: 12/12/2025 | M140: CAJA | N140: 0141 | O140: TE001500000104 | P140: Asiento de CAJA (01/09/2025 - 31/08/2026) | Q140: Extracción de Caja 001500000104 Obs: Movimiento_Cajas_Bancos_Semana 25-26 al 12-12-2025 | R140: DT-Mano de obra reemplazo de manguera de nafta de lancha del lodge Pagos Depsa Valores. Al 12-12-202 | S140: 000000000113 | T140: Ejercicio 2025/2026
F141: 11010101 | G141: Caja $ Administración | I141: -53800 | J141: -36.598639 | K141: 1470 | L141: 26/12/2025 | M141: CAJA | N141: 0141 | O141: TE001500000115 | P141: Asiento de CAJA (01/09/2025 - 31/08/2026) | Q141: Extracción de Caja 001500000115 Obs: Movimiento_Cajas_Bancos_Semana 25-26 al 26-12-2025 | R141: DT-Reembolso Viaticos Luis Chua - supervisión Delta 26/11 al 5/12 F.Fijo Oper. Al 26-12-2025 | S141: 000000000120 | T141: Ejercicio 2025/2026
F142: 11010101 | G142: Caja $ Administración | I142: -17000 | J142: -11.564626 | K142: 1470 | L142: 31/12/2025 | M142: CAJA | N142: 0141 | O142: TE001500000137 | P142: Asiento de CAJA (01/09/2025 - 31/08/2026) | Q142: Extracción de Caja 001500000137 Obs: Movimiento_Cajas_Bancos_Semana 25-26 al 02-01-2026 | R142: DT-Saldo pendiente por aumento de cuota Diciembre - guarderia La Baie F.Fijo Oper. Al 02-02-2026 | S142: 000000000130 | T142: Ejercicio 2025/2026
F143: 11010101 | G143: Caja $ Administración | I143: 800000 | J143: 563.38028 | K143: 1420 | L143: 05/12/2025 | M143: CAJA | N143: 0149 | O143: TA001500000095 | P143: Asiento de CAJA (01/09/2025 - 31/08/2026) | Q143: Canje de Valores 001500000095 Obs: DEL-Cambio $ 800,000 | R143: Canje de Valores 001500000095 Obs: DEL-Cambio $ 800,000 | S143: 000000000076 | T143: Ejercicio 2025/2026
... F357: 8101 | G357: Transferencias entre Lodges | I357: -3439800 | J357: -2340 | K357: 1470 | L357: 31/12/2025 | M357: CAJA | N357: 0141 | O357: TI001500000118 | P357: Asiento de CAJA (01/09/2025 - 31/08/2026) | Q357: Ingreso a Caja 001500000118 Obs: 31-12-2025 INCOME OF MONEY | R357: DT - Ingreso pedido de operaciones | S357: 000000000138 | T357: Ejercicio 2025/2026
A362: INSERT | B362: INSERT | C362: INSERT | D362: INSERT | E362: INSERT | F362: INSERT | G362: INSERT | H362: INSERT | I362: INSERT | J362: INSERT | K362: INSERT | L362: INSERT | M362: INSERT | N362: INSERT | O362: INSERT | P362: INSERT | Q362: INSERT | R362: INSERT | S362: INSERT | T362: INSERT | U362: INSERT | V362: INSERT | W362: INSERT

Sheet Mov_Analizados_Ene26
G2: Ver Telefonos
G3: Ver Gastos devengados | I3: $ | J3: USD | K3: TC
G4: Ver Luz Devengada | H4: Food & Wine | I4: =+SUMIF($E$10:$E$243,H4,$I$10:$I$243) -> 11715963 | J4: =+SUMIF($E$10:$E$243,H4,$J$10:$J$243) -> 7935.0283 | K4: =+I4/J4 -> 1476.4866
G7: =+IF(I7+J7=0,"Ok","Check") -> Ok | I7: =ROUND(SUM(I10:I625),0) -> 0 | J7: =ROUND(SUM(J10:J625),0) -> 0
E8: Rubro | G8: =+Resumen_Base!C1 -> Ok
B9: =+F9&G9 | D9: DEL | E9: =+VLOOKUP(F9,Resumen_Base!$B$6:$F$69,5,0) -> #N/A | H9: =+D9&F9 -> DEL | I9: =SUM(I10:I243) -> 41028183 | J9: =SUM(J10:J243) -> 30923.554
B10: Cuenta Anterior | D10: Lodge | E10: Concepto | F10: Cuenta | G10: Nombre | I10: monto $ | J10: monto USD | K10: TC | L10: Fecha | M10: Subdiario | N10: Div | O10: Datos del comprobante | P10: Sujeto | Q10: CUIT | R10: Observación asiento | S10: Clase de Asiento | T10: Origen del comprobante | U10: Observación del comprobante | V10: Comentario renglón asiento | W10: Asiento | X10: Control | Z10: monto USD | AA10: tc | AC10: Fecha | AD10: Subdiario | AE10: Div | AF10: Datos del comprobante | AG10: Sujeto | AH10: CUIT | AI10: Observación asiento | AJ10: Clase de Asiento | AK10: Origen del comprobante | AL10: Observación del comprobante | AM10: Comentario renglón asiento | AN10: Asiento
C12: =+VLOOKUP(F12,Resumen_Base!$B$7:$F$69,5,0) -> Fixed Asset's Payments (Investments) Mejoras/equipamiento Lodge | D12: DEL | E12: =+VLOOKUP(F12,Resumen_Base!$B$6:$F$69,5,0) -> Fixed Asset's Payments (Investments) Mejoras/equipamiento Lodge | F12: 12020301 | G12: Muebles y útiles | H12: =+D12&F12 -> DEL12020301 | I12: 179000 | J12: 120.94595 | K12: 1480 | L12: 23/01/2026 | M12: CAJA | N12: 0141 | O12: TE001500000148 | P12: Asiento de CAJA (01/09/2025 - 310126) | Q12: Extracción de Caja 001500000148 Obs: Movimiento_Cajas_Bancos_Semana 25-26 al 23-01-2026 | R12: DT-Compra 1 termo Stanley 1.5 litros F.Fijo Oper. Al 23-01-2026 | S12: 000000000163 | T12: Ejercicio 2025/2026
A13: 5252 | B13: 12020301 | C13: =+VLOOKUP(F13,Resumen_Base!$B$7:$F$69,5,0) -> Maintenance Lodge | D13: DEL | E13: =+VLOOKUP(F13,Resumen_Base!$B$6:$F$69,5,0) -> Maintenance Lodge | F13: 5252 | G13: Mantenimiento Rep-Lodge | H13: =+D13&F13 -> DEL5252 | I13: 49999 | J13: 34.012925 | K13: 1470 | L13: 09/01/2026 | M13: CAJA | N13: 0141 | O13: TE001500000123 | P13: Asiento de CAJA (01/09/2025 - 31/08/2026) | Q13: Extracción de Caja 001500000123 Obs: Movimiento_Cajas_Bancos_Semana 25-26 al 09-01-2026 | R13: DT-Compra licuadora de vaso 1.5 litros F.Fijo Oper. Al 09-01-2026 | S13: 000000000125 | T13: Ejercicio 2025/2026
C14: =+VLOOKUP(F14,Resumen_Base!$B$7:$F$69,5,0) -> Fixed Asset's Payments (Investments) Mejoras/equipamiento Lodge | D14: DEL | E14: =+VLOOKUP(F14,Resumen_Base!$B$6:$F$69,5,0) -> Fixed Asset's Payments (Investments) Mejoras/equipamiento Lodge | F14: 12020301 | G14: Muebles y útiles | H14: =+D14&F14 -> DEL12020301 | I14: 158175 | J14: 107.60204 | K14: 1470 | L14: 09/01/2026 | M14: CAJA | N14: 0141 | O14: TE001500000123 | P14: Asiento de CAJA (01/09/2025 - 31/08/2026) | Q14: Extracción de Caja 001500000123 Obs: Movimiento_Cajas_Bancos_Semana 25-26 al 09-01-2026 | R14: DT-Compra microondas Rca para staff F.Fijo Oper. Al 09-01-2026 | S14: 000000000125 | T14: Ejercicio 2025/2026
A15: 5252 | B15: 12020301 | C15: =+VLOOKUP(F15,Resumen_Base!$B$7:$F$69,5,0) -> Maintenance Lodge | D15: DEL | E15: =+VLOOKUP(F15,Resumen_Base!$B$6:$F$69,5,0) -> Maintenance Lodge | F15: 5252 | G15: Mantenimiento Rep-Lodge | H15: =+D15&F15 -> DEL5252 | I15: 55057.6 | J15: 37.201081 | K15: 1480 | L15: 23/01/2026 | M15: CAJA | N15: 0141 | O15: TE001500000148 | P15: Asiento de CAJA (01/09/2025 - 310126) | Q15: Extracción de Caja 001500000148 Obs: Movimiento_Cajas_Bancos_Semana 25-26 al 23-01-2026 | R15: DT-Compra tabla lazy susan marmol acacia F.Fijo Oper. Al 23-01-2026 | S15: 000000000163 | T15: Ejercicio 2025/2026
C16: =+VLOOKUP(F16,Resumen_Base!$B$7:$F$69,5,0) -> Fixed Asset's Payments (Investments) Mejoras/equipamiento Lodge | D16: DEL | E16: =+VLOOKUP(F16,Resumen_Base!$B$6:$F$69,5,0) -> Fixed Asset's Payments (Investments) Mejoras/equipamiento Lodge | F16: 12020601 | G16: Ropa Blanca | H16: =+D16&F16 -> DEL12020601 | I16: 2760000 | J16: 1877.551 | K16: 1470 | L16: 09/01/2026 | M16: CAJA | N16: 0141 | O16: TE001500000123 | P16: Asiento de CAJA (01/09/2025 - 31/08/2026) | Q16: Extracción de Caja 001500000123 Obs: Movimiento_Cajas_Bancos_Semana 25-26 al 09-01-2026 | R16: DT-16 paños para 4 habitación - cortiñas black out - Flopy Ganly F.Fijo Oper. Al 09-01-2026 | S16: 000000000125 | T16: Ejercicio 2025/2026
C17: =+VLOOKUP(F17,Resumen_Base!$B$7:$F$69,5,0) -> Fixed Asset's Payments (Investments) Rodados/Lanchas | D17: DEL | E17: =+VLOOKUP(F17,Resumen_Base!$B$6:$F$69,5,0) -> Fixed Asset's Payments (Investments) Rodados/Lanchas | F17: 12020701 | G17: Lanchas y Botes | H17: =+D17&F17 -> DEL12020701 | I17: 2960000 | J17: 2000 | K17: 1480 | L17: 16/01/2026 | M17: CAJA | N17: 0141 | O17: TE001500000141 | P17: Asiento de CAJA (01/09/2025 - 310126) | Q17: Extracción de Caja 001500000141 Obs: Movimiento_Cajas_Bancos_Semana 25-26 al 16-01-2026 | R17: DT-GPS / Ecosonda + Carta Nautica de Lancha Salminus -retiró Noel F.Fijo Oper. Al 16-01-2026 | S17: 000000000159 | T17: Ejercicio 2025/2026
C18: =+VLOOKUP(F18,Resumen_Base!$B$7:$F$69,5,0) -> Shop | D18: DEL | E18: =+VLOOKUP(F18,Resumen_Base!$B$6:$F$69,5,0) -> Shop | F18: 4104 | G18: Ventas Shop | H18: =+D18&F18 -> DEL4104 | I18: -88800 | J18: -60 | K18: 1480 | L18: 14/01/2026 | M18: VENTAS | N18: 0141 | O18: VF000000003704B | P18: Asiento de VENTAS (01/09/2025 - 31/1/2026) | Q18: F B 000000003704 | R18: Ref. nota de Venta: DEL10 Obs.:26-01-2026_CLIENTES | S18: 000000000196 | T18: Ejercicio 2025/2026
C19: =+VLOOKUP(F19,Resumen_Base!$B$7:$F$69,5,0) -> Shop | D19: DEL | E19: =+VLOOKUP(F19,Resumen_Base!$B$6:$F$69,5,0) -> Shop | F19: 4104 | G19: Ventas Shop | H19: =+D19&F19 -> DEL4104 | I19: -88800 | J19: -60 | K19: 1480 | L19: 15/01/2026 | M19: VENTAS | N19: 0141 | O19: VF000000003708B | P19: Asiento de VENTAS (01/09/2025 - 31/1/2026) | Q19: F B 000000003708 | R19: Ref. nota de Venta: DEL37 Obs.:26-01-2026_CLIENTES | S19: 000000000200 | T19: Ejercicio 2025/2026
C20: =+VLOOKUP(F20,Resumen_Base!$B$7:$F$69,5,0) -> Canon Lodge/Labor Permits: | D20: DEL | E20: =+VLOOKUP(F20,Resumen_Base!$B$6:$F$69,5,0) -> Canon Lodge/Labor Permits: | F20: 5208 | G20: Alquileres y Canon | H20: =+D20&F20 -> DEL5208 | I20: 352000 | J20: 239.45578 | K20: 1470 | L20: 09/01/2026 | M20: CAJA | N20: 0141 | O20: TE001500000123 | P20: Asiento de CAJA (01/09/2025 - 31/08/2026) | Q20: Extracción de Caja 001500000123 Obs: Movimiento_Cajas_Bancos_Semana 25-26 al 09-01-2026 | R20: DT-Guarderia La Baie - cuota Enero Pagos Frank Garrahan Al 09-01-2026 | S20: 000000000125 | T20: Ejercicio 2025/2026
C21: =+VLOOKUP(F21,Resumen_Base!$B$7:$F$69,5,0) -> Canon Lodge/Labor Permits: | D21: DEL | E21: =+VLOOKUP(F21,Resumen_Base!$B$6:$F$69,5,0) -> Canon Lodge/Labor Permits: | F21: 5208 | G21: Alquileres y Canon | H21: =+D21&F21 -> DEL5208 | I21: 352000 | J21: 237.83784 | K21: 1480 | L21: 31/01/2026 | M21: CAJA | N21: 0141 | O21: TE001500000170 | P21: Asiento de CAJA (01/09/2025 - 310126) | Q21: Extracción de Caja 001500000170 Obs: Movimiento_Cajas_Bancos_Semana 25-26 al 06-02-2026 | R21: DT-Guarderia La Baie - cuota Febrero 2026 Pagos Depsa Valores. Al 06-02-2026 | S21: 000000000173 | T21: Ejercicio 2025/2026
C22: =+VLOOKUP(F22,Resumen_Base!$B$7:$F$69,5,0) -> Food & Wine | D22: DEL | E22: =+VLOOKUP(F22,Resumen_Base!$B$6:$F$69,5,0) -> Food & Wine | F22: 5213 | G22: Vinos | H22: =+D22&F22 -> DEL5213 | I22: 66500 | J22: 45.238095 | K22: 1470 | L22: 12/01/2026 | M22: CAJA | N22: 0141 | O22: TE001500000125 | P22: Asiento de CAJA (01/09/2025 - 31/08/2026) | Q22: Extracción de Caja 001500000125 Obs: 12-01-2026 Mov Lodge | R22: DT - Súper chino vinos | S22: 000000000126 | T22: Ejercicio 2025/2026
C23: =+VLOOKUP(F23,Resumen_Base!$B$7:$F$69,5,0) -> Food & Wine | D23: DEL | E23: =+VLOOKUP(F23,Resumen_Base!$B$6:$F$69,5,0) -> Food & Wine | F23: 5213 | G23: Vinos | H23: =+D23&F23 -> DEL5213 | I23: 1304896.5 | J23: 881.6868 | K23: 1480 | L23: 31/01/2026 | M23: CAJA | N23: 0141 | O23: TE001500000170 | P23: Asiento de CAJA (01/09/2025 - 310126) | Q23: Extracción de Caja 001500000170 Obs: Movimiento_Cajas_Bancos_Semana 25-26 al 06-02-2026 | R23: DT-Mix de Vinos - Pago Bressia Wines F.Fijo Oper. Al 06-02-2026 | S23: 000000000173 | T23: Ejercicio 2025/2026
C24: =+VLOOKUP(F24,Resumen_Base!$B$7:$F$69,5,0) -> Food & Wine | D24: DEL | E24: =+VLOOKUP(F24,Resumen_Base!$B$6:$F$69,5,0) -> Food & Wine | F24: 5213 | G24: Vinos | H24: =+D24&F24 -> DEL5213 | I24: 881000 | J24: 595.27027 | K24: 1480 | L24: 23/01/2026 | M24: CAJA | N24: 0141 | O24: TE001500000148 | P24: Asiento de CAJA (01/09/2025 - 310126) | Q24: Extracción de Caja 001500000148 Obs: Movimiento_Cajas_Bancos_Semana 25-26 al 23-01-2026 | R24: DT-Pedido Catena - 18 cajas de vino F.Fijo Oper. Al 23-01-2026 | S24: 000000000163 | T24: Ejercicio 2025/2026
C25: =+VLOOKUP(F25,Resumen_Base!$B$7:$F$69,5,0) -> Miscellaneous & Shipping | D25: DEL | E25: =+VLOOKUP(F25,Resumen_Base!$B$6:$F$69,5,0) -> Miscellaneous & Shipping | F25: 5219 | G25: Gastos Varios | H25: =+D25&F25 -> DEL5219 | I25: 91340 | J25: 61.716216 | K25: 1480 | L25: 16/01/2026 | M25: CAJA | N25: 0141 | O25: TE001500000142 | P25: Asiento de CAJA (01/09/2025 - 310126) | Q25: Extracción de Caja 001500000142 Obs: Movimiento_Cajas_Bancos_Semana 25-26 al 16-01-2026 | R25: DT-Saldo 50 % - Latin Gráfica - impresión brochures x 20 unidades F.Fijo Oper. Al 16-01-2026 | S25: 000000000160 | T25: Ejercicio 2025/2026
C26: =+VLOOKUP(F26,Resumen_Base!$B$7:$F$69,5,0) -> Services/House | D26: DEL | E26: =+VLOOKUP(F26,Resumen_Base!$B$6:$F$69,5,0) -> Services/House | F26: 5226 | G26: Remuneraciones Servicios | H26: =+D26&F26 -> DEL5226 | I26: 1915120 | J26: 1294 | K26: 1480 | L26: 30/01/2026 | M26: CAJA | N26: 0141 | O26: TE001500000161 | P26: Asiento de CAJA (01/09/2025 - 310126) | Q26: Extracción de Caja 001500000161 Obs: Reversión de documento | R26: DEL- Reintegro Sueldos TA 01-2026 - Servicios | S26: 000000000168 | T26: Ejercicio 2025/2026
C27: =+VLOOKUP(F27,Resumen_Base!$B$7:$F$69,5,0) -> Services/House | D27: DEL | E27: =+VLOOKUP(F27,Resumen_Base!$B$6:$F$69,5,0) -> Services/House | F27: 5226 | G27: Remuneraciones Servicios | H27: =+D27&F27 -> DEL5226 | I27: 1915120 | J27: 1294 | K27: 1480 | L27: 30/01/2026 | M27: CAJA | N27: 0141 | O27: TE001500000165 | P27: Asiento de CAJA (01/09/2025 - 310126) | Q27: Extracción de Caja 001500000165 Obs: Movimiento_Cajas_Bancos_Semana 25-26 al 30-01-2026 | R27: DEL- Reintegro Sueldos TA 01-2026 - Servicios | S27: 000000000172 | T27: Ejercicio 2025/2026
... C29: =+VLOOKUP(F29,Resumen_Base!$B$7:$F$69,5,0) -> Services/House | D29: DEL | E29: =+VLOOKUP(F29,Resumen_Base!$B$6:$F$69,5,0) -> Services/House | F29: 5226 | G29: Remuneraciones Servicios | H29: =+D29&F29 -> DEL5226 | I29: 280000 | J29: 189.18919 | K29: 1480 | L29: 26/01/2026 | M29: CAJA | N29: 0141 | O29: TE001500000145 | P29: Asiento de CAJA (01/09/2025 - 310126) | Q29: Extracción de Caja 001500000145 Obs: 26-01-2026 Mov Lodge | R29: DT - Adicional a Alexis por cubrir 4 días a Noel | S29: 000000000161 | T29: Ejercicio 2025/2026
A30: 5252 | B30: 5226 | C30: =+VLOOKUP(F30,Resumen_Base!$B$7:$F$69,5,0) -> Maintenance Lodge | D30: DEL | E30: =+VLOOKUP(F30,Resumen_Base!$B$6:$F$69,5,0) -> Maintenance Lodge | F30: 5252 | G30: Mantenimiento Rep-Lodge | H30: =+D30&F30 -> DEL5252 | I30: 80000 | J30: 54.054054 | K30: 1480 | L30: 26/01/2026 | M30: CAJA | N30: 0141 | O30: TE001500000145 | P30: Asiento de CAJA (01/09/2025 - 310126) | Q30: Extracción de Caja 001500000145 Obs: 26-01-2026 Mov Lodge | R30: DT - Alexis corte de pasto y poda con su tío en días de descanso | S30: 000000000161 | T30: Ejercicio 2025/2026
A31: 5252 | B31: 5226 | C31: =+VLOOKUP(F31,Resumen_Base!$B$7:$F$69,5,0) -> Maintenance Lodge | D31: DEL | E31: =+VLOOKUP(F31,Resumen_Base!$B$6:$F$69,5,0) -> Maintenance Lodge | F31: 5252 | G31: Mantenimiento Rep-Lodge | H31: =+D31&F31 -> DEL5252 | I31: 20000 | J31: 13.513514 | K31: 1480 | L31: 26/01/2026 | M31: CAJA | N31: 0141 | O31: TE001500000145 | P31: Asiento de CAJA (01/09/2025 - 310126) | Q31: Extracción de Caja 001500000145 Obs: 26-01-2026 Mov Lodge | R31: DT - Alexis de hachero durante 1 servicio de 9 pax | S31: 000000000161 | T31: Ejercicio 2025/2026
C32: =+VLOOKUP(F32,Resumen_Base!$B$7:$F$69,5,0) -> Services/House | D32: DEL | E32: =+VLOOKUP(F32,Resumen_Base!$B$6:$F$69,5,0) -> Services/House | F32: 5226 | G32: Remuneraciones Servicios | H32: =+D32&F32 -> DEL5226 | I32: 444000 | J32: 300 | K32: 1480 | L32: 26/01/2026 | M32: CAJA | N32: 0141 | O32: TE001500000146 | P32: Asiento de CAJA (01/09/2025 - 310126) | Q32: Extracción de Caja 001500000146 Obs: 26-01-2026 Mov Lodge | R32: DT - Lucia ayudante de cocina 6fd | S32: 000000000162 | T32: Ejercicio 2025/2026
A33: 5291 | B33: 5226 | C33: =+VLOOKUP(F33,Resumen_Base!$B$7:$F$69,5,0) -> Food & Wine | D33: DEL | E33: =+VLOOKUP(F33,Resumen_Base!$B$6:$F$69,5,0) -> Food & Wine | F33: 5291 | G33: Comida / Fletes | H33: =+D33&F33 -> DEL5291 | I33: 20000 | J33: 13.605442 | K33: 1470 | L33: 12/01/2026 | M33: CAJA | N33: 0141 | O33: TE001500000125 | P33: Asiento de CAJA (01/09/2025 - 31/08/2026) | Q33: Extracción de Caja 001500000125 Obs: 12-01-2026 Mov Lodge | R33: DT - Pago a Alexis por 2 viajes añde compras que realizó | S33: 000000000126 | T33: Ejercicio 2025/2026
C34: =+VLOOKUP(F34,Resumen_Base!$B$7:$F$69,5,0) -> Services/House | D34: DEL | E34: =+VLOOKUP(F34,Resumen_Base!$B$6:$F$69,5,0) -> Services/House | F34: 5226 | G34: Remuneraciones Servicios | H34: =+D34&F34 -> DEL5226 | I34: 296000 | J34: 200 | K34: 1480 | L34: 31/01/2026 | M34: CAJA | N34: 0141 | O34: TE001500000153 | P34: Asiento de CAJA (01/09/2025 - 310126) | Q34: Extracción de Caja 001500000153 Obs: 31-01-2026 Mov Lodge | R34: DT - Pago a lucia por 4 full day | S34: 000000000166 | T34: Ejercicio 2025/2026
A35: 5291 | B35: 5226 | C35: =+VLOOKUP(F35,Resumen_Base!$B$7:$F$69,5,0) -> Food & Wine | D35: DEL | E35: =+VLOOKUP(F35,Resumen_Base!$B$6:$F$69,5,0) -> Food & Wine | F35: 5291 | G35: Comida / Fletes | H35: =+D35&F35 -> DEL5291 | I35: 20000 | J35: 13.605442 | K35: 1470 | L35: 12/01/2026 | M35: CAJA | N35: 0141 | O35: TE001500000125 | P35: Asiento de CAJA (01/09/2025 - 31/08/2026) | Q35: Extracción de Caja 001500000125 Obs: 12-01-2026 Mov Lodge | R35: DT - Pago a Rolando por ayudarnos con la carga y descarga día de compras | S35: 000000000126 | T35: Ejercicio 2025/2026
C36: =+VLOOKUP(F36,Resumen_Base!$B$7:$F$69,5,0) -> Services/House | D36: DEL | E36: =+VLOOKUP(F36,Resumen_Base!$B$6:$F$69,5,0) -> Services/House | F36: 5226 | G36: Remuneraciones Servicios | H36: =+D36&F36 -> DEL5226 | I36: 44850 | J36: 30.304054 | K36: 1480 | L36: 26/01/2026 | M36: CAJA | N36: 0141 | O36: TE001500000145 | P36: Asiento de CAJA (01/09/2025 - 310126) | Q36: Extracción de Caja 001500000145 Obs: 26-01-2026 Mov Lodge | R36: DT - Pago complementario a lucia por ayuda en cocina | S36: 000000000161 | T36: Ejercicio 2025/2026
C37: =+VLOOKUP(F37,Resumen_Base!$B$7:$F$69,5,0) -> Services/House | D37: DEL | E37: =+VLOOKUP(F37,Resumen_Base!$B$6:$F$69,5,0) -> Services/House | F37: 5226 | G37: Remuneraciones Servicios | H37: =+D37&F37 -> DEL5226 | I37: 29500 | J37: 19.932432 | K37: 1480 | L37: 31/01/2026 | M37: CAJA | N37: 0141 | O37: TE001500000152 | P37: Asiento de CAJA (01/09/2025 - 310126) | Q37: Extracción de Caja 001500000152 Obs: 31-01-2026 Mov Lodge | R37: DT - Pago complementario lucia por 4 full day 20-usd pago $ a cotización 1475 | S37: 000000000165 | T37: Ejercicio 2025/2026
C38: =+VLOOKUP(F38,Resumen_Base!$B$7:$F$69,5,0) -> Services/House | D38: DEL | E38: =+VLOOKUP(F38,Resumen_Base!$B$6:$F$69,5,0) -> Services/House | F38: 5226 | G38: Remuneraciones Servicios | H38: =+D38&F38 -> DEL5226 | I38: 317667 | J38: 216.1 | K38: 1470 | L38: 09/01/2026 | M38: CAJA | N38: 0141 | O38: TE001500000123 | P38: Asiento de CAJA (01/09/2025 - 31/08/2026) | Q38: Extracción de Caja 001500000123 Obs: Movimiento_Cajas_Bancos_Semana 25-26 al 09-01-2026 | R38: DT-Alexis Carra - Honorarios mantenimiento diciembre Pagos Frank Garrahan Al 09-01-2026 | S38: 000000000125 | T38: Ejercicio 2025/2026
C39: =+VLOOKUP(F39,Resumen_Base!$B$7:$F$69,5,0) -> Services/House | D39: DEL | E39: =+VLOOKUP(F39,Resumen_Base!$B$6:$F$69,5,0) -> Services/House | F39: 5226 | G39: Remuneraciones Servicios | H39: =+D39&F39 -> DEL5226 | I39: 309481 | J39: 209.10878 | K39: 1480 | L39: 31/01/2026 | M39: CAJA | N39: 0141 | O39: TE001500000170 | P39: Asiento de CAJA (01/09/2025 - 310126) | Q39: Extracción de Caja 001500000170 Obs: Movimiento_Cajas_Bancos_Semana 25-26 al 06-02-2026 | R39: DT-Alexis Carra - Honorarios mantenimiento Enero 2026 Pagos Depsa Valores. Al 06-02-2026 | S39: 000000000173 | T39: Ejercicio 2025/2026
C40: =+VLOOKUP(F40,Resumen_Base!$B$7:$F$69,5,0) -> Guides | D40: DEL | E40: =+VLOOKUP(F40,Resumen_Base!$B$6:$F$69,5,0) -> Guides | F40: 5227 | G40: Remuneraciones Guías | H40: =+D40&F40 -> DEL5227 | I40: 1184000 | J40: 800 | K40: 1480 | L40: 26/01/2026 | M40: CAJA | N40: 0141 | O40: TE001500000146 | P40: Asiento de CAJA (01/09/2025 - 310126) | Q40: Extracción de Caja 001500000146 Obs: 26-01-2026 Mov Lodge | R40: DT - Matías guía por 2 full day y 3 half day | S40: 000000000162 | T40: Ejercicio 2025/2026
C41: =+VLOOKUP(F41,Resumen_Base!$B$7:$F$69,5,0) -> Guides | D41: DEL | E41: =+VLOOKUP(F41,Resumen_Base!$B$6:$F$69,5,0) -> Guides | F41: 5227 | G41: Remuneraciones Guías | H41: =+D41&F41 -> DEL5227 | I41: 1332000 | J41: 900 | K41: 1480 | L41: 26/01/2026 | M41: CAJA | N41: 0141 | O41: TE001500000146 | P41: Asiento de CAJA (01/09/2025 - 310126) | Q41: Extracción de Caja 001500000146 Obs: 26-01-2026 Mov Lodge | R41: DT - Pablo guía 3 fd | S41: 000000000162 | T41: Ejercicio 2025/2026
C42: =+VLOOKUP(F42,Resumen_Base!$B$7:$F$69,5,0) -> Guides | D42: DEL | E42: =+VLOOKUP(F42,Resumen_Base!$B$6:$F$69,5,0) -> Guides | F42: 5227 | G42: Remuneraciones Guías | H42: =+D42&F42 -> DEL5227 | I42: 3848000 | J42: 2600 | K42: 1480 | L42: 26/01/2026 | M42: CAJA | N42: 0141 | O42: TE001500000146 | P42: Asiento de CAJA (01/09/2025 - 310126) | Q42: Extracción de Caja 001500000146 Obs: 26-01-2026 Mov Lodge | R42: DT - Pablo guía por 7 full day | S42: 000000000162 | T42: Ejercicio 2025/2026
C43: =+VLOOKUP(F43,Resumen_Base!$B$7:$F$69,5,0) -> Guides | D43: DEL | E43: =+VLOOKUP(F43,Resumen_Base!$B$6:$F$69,5,0) -> Guides | F43: 5227 | G43: Remuneraciones Guías | H43: =+D43&F43 -> DEL5227 | I43: 2960000 | J43: 2000 | K43: 1480 | L43: 30/01/2026 | M43: CAJA | N43: 0141 | O43: TE001500000161 | P43: Asiento de CAJA (01/09/2025 - 310126) | Q43: Extracción de Caja 001500000161 Obs: Reversión de documento | R43: DT- Fee Noel 01-2026 | S43: 000000000168 | T43: Ejercicio 2025/2026
C44: =+VLOOKUP(F44,Resumen_Base!$B$7:$F$69,5,0) -> Guides | D44: DEL | E44: =+VLOOKUP(F44,Resumen_Base!$B$6:$F$69,5,0) -> Guides | F44: 5227 | G44: Remuneraciones Guías | H44: =+D44&F44 -> DEL5227 | I44: 2960000 | J44: 2000 | K44: 1480 | L44: 30/01/2026 | M44: CAJA | N44: 0141 | O44: TE001500000165 | P44: Asiento de CAJA (01/09/2025 - 310126) | Q44: Extracción de Caja 001500000165 Obs: Movimiento_Cajas_Bancos_Semana 25-26 al 30-01-2026 | R44: DT- Fee Noel 01-2026 | S44: 000000000172 | T44: Ejercicio 2025/2026
C45: =+VLOOKUP(F45,Resumen_Base!$B$7:$F$69,5,0) -> Guides | D45: DEL | E45: =+VLOOKUP(F45,Resumen_Base!$B$6:$F$69,5,0) -> Guides | F45: 5227 | G45: Remuneraciones Guías | H45: =+D45&F45 -> DEL5227 | I45: -2960000 | J45: -2000 | K45: 1480 | L45: 30/01/2026 | M45: CAJA | N45: 0141 | O45: TI001500000158 | P45: Asiento de CAJA (01/09/2025 - 310126) | Q45: Ingreso a Caja 001500000158 Obs: Movimiento_Cajas_Bancos_Semana 25-26 al 30-01-2026 | R45: DT- Fee Noel 01-2026 | S45: 000000000180 | T45: Ejercicio 2025/2026
C46: =+VLOOKUP(F46,Resumen_Base!$B$7:$F$69,5,0) -> Manager | D46: DEL | E46: =+VLOOKUP(F46,Resumen_Base!$B$6:$F$69,5,0) -> Manager | F46: 5228 | G46: Remuneraciones Managers | H46: =+D46&F46 -> DEL5228 | I46: 677840 | J46: 458 | K46: 1480 | L46: 30/01/2026 | M46: CAJA | N46: 0141 | O46: TE001500000161 | P46: Asiento de CAJA (01/09/2025 - 310126) | Q46: Extracción de Caja 001500000161 Obs: Reversión de documento | R46: DEL- Reintegro Sueldos TA 01-2026 - Managers | S46: 000000000168 | T46: Ejercicio 2025/2026
C47: =+VLOOKUP(F47,Resumen_Base!$B$7:$F$69,5,0) -> Manager | D47: DEL | E47: =+VLOOKUP(F47,Resumen_Base!$B$6:$F$69,5,0) -> Manager | F47: 5228 | G47: Remuneraciones Managers | H47: =+D47&F47 -> DEL5228 | I47: 677840 | J47: 458 | K47: 1480 | L47: 30/01/2026 | M47: CAJA | N47: 0141 | O47: TE001500000165 | P47: Asiento de CAJA (01/09/2025 - 310126) | Q47: Extracción de Caja 001500000165 Obs: Movimiento_Cajas_Bancos_Semana 25-26 al 30-01-2026 | R47: DEL- Reintegro Sueldos TA 01-2026 - Managers | S47: 000000000172 | T47: Ejercicio 2025/2026
... C135: =+VLOOKUP(F135,Resumen_Base!$B$7:$F$69,5,0) -> Maintenance Lodge | D135: DEL | E135: =+VLOOKUP(F135,Resumen_Base!$B$6:$F$69,5,0) -> Maintenance Lodge | F135: 5252 | G135: Mantenimiento Rep-Lodge | H135: =+D135&F135 -> DEL5252 | I135: 43700 | J135: 29.527027 | K135: 1480 | L135: 26/01/2026 | M135: CAJA | N135: 0141 | O135: TE001500000145 | P135: Asiento de CAJA (01/09/2025 - 310126) | Q135: Extracción de Caja 001500000145 Obs: 26-01-2026 Mov Lodge | R135: DT - Artículos de ferretería, cinta aisladora, bolsa de clavos, veneno abejas, pinza pico de loro | S135: 000000000161 | T135: Ejercicio 2025/2026
A136: 5219 | B136: 5252 | C136: =+VLOOKUP(F136,Resumen_Base!$B$7:$F$69,5,0) -> Miscellaneous & Shipping | D136: DEL | E136: =+VLOOKUP(F136,Resumen_Base!$B$6:$F$69,5,0) -> Miscellaneous & Shipping | F136: 5219 | G136: Gastos Varios | H136: =+D136&F136 -> DEL5219 | I136: 18100 | J136: 12.312925 | K136: 1470 | L136: 12/01/2026 | M136: CAJA | N136: 0141 | O136: TE001500000125 | P136: Asiento de CAJA (01/09/2025 - 31/08/2026) | Q136: Extracción de Caja 001500000125 Obs: 12-01-2026 Mov Lodge | R136: DT - Artículos de librería | S136: 000000000126 | T136: Ejercicio 2025/2026
A137: 5219 | B137: 5252 | C137: =+VLOOKUP(F137,Resumen_Base!$B$7:$F$69,5,0) -> Miscellaneous & Shipping | D137: DEL | E137: =+VLOOKUP(F137,Resumen_Base!$B$6:$F$69,5,0) -> Miscellaneous & Shipping | F137: 5219 | G137: Gastos Varios | H137: =+D137&F137 -> DEL5219 | I137: 64440 | J137: 43.540541 | K137: 1480 | L137: 26/01/2026 | M137: CAJA | N137: 0141 | O137: TE001500000145 | P137: Asiento de CAJA (01/09/2025 - 310126) | Q137: Extracción de Caja 001500000145 Obs: 26-01-2026 Mov Lodge | R137: DT - Artículos de librería | S137: 000000000161 | T137: Ejercicio 2025/2026
C138: =+VLOOKUP(F138,Resumen_Base!$B$7:$F$69,5,0) -> Maintenance Lodge | D138: DEL | E138: =+VLOOKUP(F138,Resumen_Base!$B$6:$F$69,5,0) -> Maintenance Lodge | F138: 5252 | G138: Mantenimiento Rep-Lodge | H138: =+D138&F138 -> DEL5252 | I138: 12420 | J138: 8.3918919 | K138: 1480 | L138: 26/01/2026 | M138: CAJA | N138: 0141 | O138: TE001500000145 | P138: Asiento de CAJA (01/09/2025 - 310126) | Q138: Extracción de Caja 001500000145 Obs: 26-01-2026 Mov Lodge | R138: DT - Compra de 2 cuadros | S138: 000000000161 | T138: Ejercicio 2025/2026
C139: =+VLOOKUP(F139,Resumen_Base!$B$7:$F$69,5,0) -> Maintenance Lodge | D139: DEL | E139: =+VLOOKUP(F139,Resumen_Base!$B$6:$F$69,5,0) -> Maintenance Lodge | F139: 5252 | G139: Mantenimiento Rep-Lodge | H139: =+D139&F139 -> DEL5252 | I139: 102200 | J139: 69.054054 | K139: 1480 | L139: 26/01/2026 | M139: CAJA | N139: 0141 | O139: TE001500000145 | P139: Asiento de CAJA (01/09/2025 - 310126) | Q139: Extracción de Caja 001500000145 Obs: 26-01-2026 Mov Lodge | R139: DT - Compras vivero | S139: 000000000161 | T139: Ejercicio 2025/2026
C140: =+VLOOKUP(F140,Resumen_Base!$B$7:$F$69,5,0) -> Maintenance Lodge | D140: DEL | E140: =+VLOOKUP(F140,Resumen_Base!$B$6:$F$69,5,0) -> Maintenance Lodge | F140: 5252 | G140: Mantenimiento Rep-Lodge | H140: =+D140&F140 -> DEL5252 | I140: 4000 | J140: 2.7210884 | K140: 1470 | L140: 12/01/2026 | M140: CAJA | N140: 0141 | O140: TE001500000125 | P140: Asiento de CAJA (01/09/2025 - 31/08/2026) | Q140: Extracción de Caja 001500000125 Obs: 12-01-2026 Mov Lodge | R140: DT - Ferretería | S140: 000000000126 | T140: Ejercicio 2025/2026
C141: =+VLOOKUP(F141,Resumen_Base!$B$7:$F$69,5,0) -> Maintenance Lodge | D141: DEL | E141: =+VLOOKUP(F141,Resumen_Base!$B$6:$F$69,5,0) -> Maintenance Lodge | F141: 5252 | G141: Mantenimiento Rep-Lodge | H141: =+D141&F141 -> DEL5252 | I141: 34000 | J141: 23.129252 | K141: 1470 | L141: 12/01/2026 | M141: CAJA | N141: 0141 | O141: TE001500000125 | P141: Asiento de CAJA (01/09/2025 - 31/08/2026) | Q141: Extracción de Caja 001500000125 Obs: 12-01-2026 Mov Lodge | R141: DT - Ferretería, línea de acero para compuerta laguna, pinceles y diluyente | S141: 000000000126 | T141: Ejercicio 2025/2026
A142: 5219 | B142: 5252 | C142: =+VLOOKUP(F142,Resumen_Base!$B$7:$F$69,5,0) -> Miscellaneous & Shipping | D142: DEL | E142: =+VLOOKUP(F142,Resumen_Base!$B$6:$F$69,5,0) -> Miscellaneous & Shipping | F142: 5219 | G142: Gastos Varios | H142: =+D142&F142 -> DEL5219 | I142: 25500 | J142: 17.22973 | K142: 1480 | L142: 31/01/2026 | M142: CAJA | N142: 0141 | O142: TE001500000152 | P142: Asiento de CAJA (01/09/2025 - 310126) | Q142: Extracción de Caja 001500000152 Obs: 31-01-2026 Mov Lodge | R142: DT - Imprenta tigre plastificados de check list personal | S142: 000000000165 | T142: Ejercicio 2025/2026
C143: =+VLOOKUP(F143,Resumen_Base!$B$7:$F$69,5,0) -> Maintenance Lodge | D143: DEL | E143: =+VLOOKUP(F143,Resumen_Base!$B$6:$F$69,5,0) -> Maintenance Lodge | F143: 5252 | G143: Mantenimiento Rep-Lodge | H143: =+D143&F143 -> DEL5252 | I143: 8000 | J143: 5.4054054 | K143: 1480 | L143: 26/01/2026 | M143: CAJA | N143: 0141 | O143: TE001500000145 | P143: Asiento de CAJA (01/09/2025 - 310126) | Q143: Extracción de Caja 001500000145 Obs: 26-01-2026 Mov Lodge | R143: DT - Lámparas de luz | S143: 000000000161 | T143: Ejercicio 2025/2026
C144: =+VLOOKUP(F144,Resumen_Base!$B$7:$F$69,5,0) -> Maintenance Lodge | D144: DEL | E144: =+VLOOKUP(F144,Resumen_Base!$B$6:$F$69,5,0) -> Maintenance Lodge | F144: 5252 | G144: Mantenimiento Rep-Lodge | H144: =+D144&F144 -> DEL5252 | I144: 74500 | J144: 50.337838 | K144: 1480 | L144: 26/01/2026 | M144: CAJA | N144: 0141 | O144: TE001500000145 | P144: Asiento de CAJA (01/09/2025 - 310126) | Q144: Extracción de Caja 001500000145 Obs: 26-01-2026 Mov Lodge | R144: DT - Lavadero blanquueria | S144: 000000000161 | T144: Ejercicio 2025/2026
C145: =+VLOOKUP(F145,Resumen_Base!$B$7:$F$69,5,0) -> Maintenance Lodge | D145: DEL | E145: =+VLOOKUP(F145,Resumen_Base!$B$6:$F$69,5,0) -> Maintenance Lodge | F145: 5252 | G145: Mantenimiento Rep-Lodge | H145: =+D145&F145 -> DEL5252 | I145: 11500 | J145: 7.8231293 | K145: 1470 | L145: 12/01/2026 | M145: CAJA | N145: 0141 | O145: TE001500000125 | P145: Asiento de CAJA (01/09/2025 - 31/08/2026) | Q145: Extracción de Caja 001500000125 Obs: 12-01-2026 Mov Lodge | R145: DT - Librería | S145: 000000000126 | T145: Ejercicio 2025/2026
C146: =+VLOOKUP(F146,Resumen_Base!$B$7:$F$69,5,0) -> Maintenance Lodge | D146: DEL | E146: =+VLOOKUP(F146,Resumen_Base!$B$6:$F$69,5,0) -> Maintenance Lodge | F146: 5252 | G146: Mantenimiento Rep-Lodge | H146: =+D146&F146 -> DEL5252 | I146: 80000 | J146: 54.054054 | K146: 1480 | L146: 31/01/2026 | M146: CAJA | N146: 0141 | O146: TE001500000152 | P146: Asiento de CAJA (01/09/2025 - 310126) | Q146: Extracción de Caja 001500000152 Obs: 31-01-2026 Mov Lodge | R146: DT - Pago a Rolando por compra de termotanque y repuestos para reemplazar el termotanque de las habi | S146: 000000000165 | T146: Ejercicio 2025/2026
C147: =+VLOOKUP(F147,Resumen_Base!$B$7:$F$69,5,0) -> Maintenance Lodge | D147: DEL | E147: =+VLOOKUP(F147,Resumen_Base!$B$6:$F$69,5,0) -> Maintenance Lodge | F147: 5252 | G147: Mantenimiento Rep-Lodge | H147: =+D147&F147 -> DEL5252 | I147: 444000 | J147: 300 | K147: 1480 | L147: 31/01/2026 | M147: CAJA | N147: 0141 | O147: TE001500000153 | P147: Asiento de CAJA (01/09/2025 - 310126) | Q147: Extracción de Caja 001500000153 Obs: 31-01-2026 Mov Lodge | R147: DT - Pago por termotanque nuevo y materiales para su instalación | S147: 000000000166 | T147: Ejercicio 2025/2026
C148: =+VLOOKUP(F148,Resumen_Base!$B$7:$F$69,5,0) -> Maintenance Lodge | D148: DEL | E148: =+VLOOKUP(F148,Resumen_Base!$B$6:$F$69,5,0) -> Maintenance Lodge | F148: 5252 | G148: Mantenimiento Rep-Lodge | H148: =+D148&F148 -> DEL5252 | I148: 31000 | J148: 20.945946 | K148: 1480 | L148: 26/01/2026 | M148: CAJA | N148: 0141 | O148: TE001500000145 | P148: Asiento de CAJA (01/09/2025 - 310126) | Q148: Extracción de Caja 001500000145 Obs: 26-01-2026 Mov Lodge | R148: DT - Papel film y aluminio cocina | S148: 000000000161 | T148: Ejercicio 2025/2026
C149: =+VLOOKUP(F149,Resumen_Base!$B$7:$F$69,5,0) -> Maintenance Lodge | D149: DEL | E149: =+VLOOKUP(F149,Resumen_Base!$B$6:$F$69,5,0) -> Maintenance Lodge | F149: 5252 | G149: Mantenimiento Rep-Lodge | H149: =+D149&F149 -> DEL5252 | I149: 6000 | J149: 4.0540541 | K149: 1480 | L149: 31/01/2026 | M149: CAJA | N149: 0141 | O149: TE001500000152 | P149: Asiento de CAJA (01/09/2025 - 310126) | Q149: Extracción de Caja 001500000152 Obs: 31-01-2026 Mov Lodge | R149: DT - Papelera | S149: 000000000165 | T149: Ejercicio 2025/2026
C150: =+VLOOKUP(F150,Resumen_Base!$B$7:$F$69,5,0) -> Maintenance Lodge | D150: DEL | E150: =+VLOOKUP(F150,Resumen_Base!$B$6:$F$69,5,0) -> Maintenance Lodge | F150: 5252 | G150: Mantenimiento Rep-Lodge | H150: =+D150&F150 -> DEL5252 | I150: 7000 | J150: 4.7297297 | K150: 1480 | L150: 26/01/2026 | M150: CAJA | N150: 0141 | O150: TE001500000145 | P150: Asiento de CAJA (01/09/2025 - 310126) | Q150: Extracción de Caja 001500000145 Obs: 26-01-2026 Mov Lodge | R150: DT - Plantas aromáticas | S150: 000000000161 | T150: Ejercicio 2025/2026
C151: =+VLOOKUP(F151,Resumen_Base!$B$7:$F$69,5,0) -> Maintenance Lodge | D151: DEL | E151: =+VLOOKUP(F151,Resumen_Base!$B$6:$F$69,5,0) -> Maintenance Lodge | F151: 5252 | G151: Mantenimiento Rep-Lodge | H151: =+D151&F151 -> DEL5252 | I151: 16000 | J151: 10.810811 | K151: 1480 | L151: 26/01/2026 | M151: CAJA | N151: 0141 | O151: TE001500000145 | P151: Asiento de CAJA (01/09/2025 - 310126) | Q151: Extracción de Caja 001500000145 Obs: 26-01-2026 Mov Lodge | R151: DT - Soporte de teléfono para la lancha del Lodge | S151: 000000000161 | T151: Ejercicio 2025/2026
C152: =+VLOOKUP(F152,Resumen_Base!$B$7:$F$69,5,0) -> Maintenance Lodge | D152: DEL | E152: =+VLOOKUP(F152,Resumen_Base!$B$6:$F$69,5,0) -> Maintenance Lodge | F152: 5252 | G152: Mantenimiento Rep-Lodge | H152: =+D152&F152 -> DEL5252 | I152: 142000 | J152: 96.598639 | K152: 1470 | L152: 12/01/2026 | M152: CAJA | N152: 0141 | O152: TE001500000125 | P152: Asiento de CAJA (01/09/2025 - 31/08/2026) | Q152: Extracción de Caja 001500000125 Obs: 12-01-2026 Mov Lodge | R152: DT - Súper chino | S152: 000000000126 | T152: Ejercicio 2025/2026
C153: =+VLOOKUP(F153,Resumen_Base!$B$7:$F$69,5,0) -> Maintenance Lodge | D153: DEL | E153: =+VLOOKUP(F153,Resumen_Base!$B$6:$F$69,5,0) -> Maintenance Lodge | F153: 5252 | G153: Mantenimiento Rep-Lodge | H153: =+D153&F153 -> DEL5252 | I153: 50000 | J153: 33.783784 | K153: 1480 | L153: 26/01/2026 | M153: CAJA | N153: 0141 | O153: TE001500000145 | P153: Asiento de CAJA (01/09/2025 - 310126) | Q153: Extracción de Caja 001500000145 Obs: 26-01-2026 Mov Lodge | R153: DT - Tablas de repuesto que trajo Rolando para reparaciónes menores | S153: 000000000161 | T153: Ejercicio 2025/2026
C154: =+VLOOKUP(F154,Resumen_Base!$B$7:$F$69,5,0) -> Maintenance Lodge | D154: DEL | E154: =+VLOOKUP(F154,Resumen_Base!$B$6:$F$69,5,0) -> Maintenance Lodge | F154: 5252 | G154: Mantenimiento Rep-Lodge | H154: =+D154&F154 -> DEL5252 | I154: 10700 | J154: 7.2297297 | K154: 1480 | L154: 26/01/2026 | M154: CAJA | N154: 0141 | O154: TE001500000145 | P154: Asiento de CAJA (01/09/2025 - 310126) | Q154: Extracción de Caja 001500000145 Obs: 26-01-2026 Mov Lodge | R154: DT - Tapón bidón de nafta | S154: 000000000161 | T154: Ejercicio 2025/2026
... C209: =+VLOOKUP(F209,Resumen_Base!$B$7:$F$69,5,0) -> Electricity | D209: DEL | E209: =+VLOOKUP(F209,Resumen_Base!$B$6:$F$69,5,0) -> Electricity | F209: 5259 | G209: Combustible y Lub - Leña | H209: =+D209&F209 -> DEL5259 | I209: 38000 | J209: 25.85034 | K209: 1470 | L209: 12/01/2026 | M209: CAJA | N209: 0141 | O209: TE001500000125 | P209: Asiento de CAJA (01/09/2025 - 31/08/2026) | Q209: Extracción de Caja 001500000125 Obs: 12-01-2026 Mov Lodge | R209: DT - Carbón 10 bolsas | S209: 000000000126 | T209: Ejercicio 2025/2026
A210: 5291 | B210: 5263 | C210: =+VLOOKUP(F210,Resumen_Base!$B$7:$F$69,5,0) -> Food & Wine | D210: DEL | E210: =+VLOOKUP(F210,Resumen_Base!$B$6:$F$69,5,0) -> Food & Wine | F210: 5291 | G210: Comida / Fletes | H210: =+D210&F210 -> DEL5291 | I210: 20000 | J210: 13.513514 | K210: 1480 | L210: 26/01/2026 | M210: CAJA | N210: 0141 | O210: TE001500000145 | P210: Asiento de CAJA (01/09/2025 - 310126) | Q210: Extracción de Caja 001500000145 Obs: 26-01-2026 Mov Lodge | R210: DT - Alexis 2 salidas a hacer compras y traer insumos | S210: 000000000161 | T210: Ejercicio 2025/2026
A211: 5291 | B211: 5263 | C211: =+VLOOKUP(F211,Resumen_Base!$B$7:$F$69,5,0) -> Food & Wine | D211: DEL | E211: =+VLOOKUP(F211,Resumen_Base!$B$6:$F$69,5,0) -> Food & Wine | F211: 5291 | G211: Comida / Fletes | H211: =+D211&F211 -> DEL5291 | I211: 6000 | J211: 4.0816327 | K211: 1470 | L211: 12/01/2026 | M211: CAJA | N211: 0141 | O211: TE001500000125 | P211: Asiento de CAJA (01/09/2025 - 31/08/2026) | Q211: Extracción de Caja 001500000125 Obs: 12-01-2026 Mov Lodge | R211: DT - Ayuda carga y descarga guardería la Baie | S211: 000000000126 | T211: Ejercicio 2025/2026
A212: 5291 | B212: 5263 | C212: =+VLOOKUP(F212,Resumen_Base!$B$7:$F$69,5,0) -> Food & Wine | D212: DEL | E212: =+VLOOKUP(F212,Resumen_Base!$B$6:$F$69,5,0) -> Food & Wine | F212: 5291 | G212: Comida / Fletes | H212: =+D212&F212 -> DEL5291 | I212: 37000 | J212: 25.170068 | K212: 1470 | L212: 12/01/2026 | M212: CAJA | N212: 0141 | O212: TE001500000125 | P212: Asiento de CAJA (01/09/2025 - 31/08/2026) | Q212: Extracción de Caja 001500000125 Obs: 12-01-2026 Mov Lodge | R212: DT - Camioneta día de compras | S212: 000000000126 | T212: Ejercicio 2025/2026
A213: 5208 | B213: 5263 | C213: =+VLOOKUP(F213,Resumen_Base!$B$7:$F$69,5,0) -> Canon Lodge/Labor Permits: | D213: DEL | E213: =+VLOOKUP(F213,Resumen_Base!$B$6:$F$69,5,0) -> Canon Lodge/Labor Permits: | F213: 5208 | G213: Alquileres y Canon | H213: =+D213&F213 -> DEL5208 | I213: 30000 | J213: 20.27027 | K213: 1480 | L213: 26/01/2026 | M213: CAJA | N213: 0141 | O213: TE001500000145 | P213: Asiento de CAJA (01/09/2025 - 310126) | Q213: Extracción de Caja 001500000145 Obs: 26-01-2026 Mov Lodge | R213: DT - Noel paga en guardería por uso de su espacio para trabajar con la lancha que trajo Fabián guía | S213: 000000000161 | T213: Ejercicio 2025/2026
A214: 5252 | B214: 5263 | C214: =+VLOOKUP(F214,Resumen_Base!$B$7:$F$69,5,0) -> Maintenance Lodge | D214: DEL | E214: =+VLOOKUP(F214,Resumen_Base!$B$6:$F$69,5,0) -> Maintenance Lodge | F214: 5252 | G214: Mantenimiento Rep-Lodge | H214: =+D214&F214 -> DEL5252 | I214: 100000 | J214: 67.567568 | K214: 1480 | L214: 26/01/2026 | M214: CAJA | N214: 0141 | O214: TE001500000145 | P214: Asiento de CAJA (01/09/2025 - 310126) | Q214: Extracción de Caja 001500000145 Obs: 26-01-2026 Mov Lodge | R214: DT - Pago a Rolando por logística de blanqueria, residuos y traer maderas de stock para reparaciónes | S214: 000000000161 | T214: Ejercicio 2025/2026
A215: 5291 | B215: 5263 | C215: =+VLOOKUP(F215,Resumen_Base!$B$7:$F$69,5,0) -> Food & Wine | D215: DEL | E215: =+VLOOKUP(F215,Resumen_Base!$B$6:$F$69,5,0) -> Food & Wine | F215: 5291 | G215: Comida / Fletes | H215: =+D215&F215 -> DEL5291 | I215: 10000 | J215: 6.7567568 | K215: 1480 | L215: 31/01/2026 | M215: CAJA | N215: 0141 | O215: TE001500000152 | P215: Asiento de CAJA (01/09/2025 - 310126) | Q215: Extracción de Caja 001500000152 Obs: 31-01-2026 Mov Lodge | R215: DT - Pago adicional a Alexis por buscarnos bidones de agua y garrafas | S215: 000000000165 | T215: Ejercicio 2025/2026
A216: 5252 | B216: 5263 | C216: =+VLOOKUP(F216,Resumen_Base!$B$7:$F$69,5,0) -> Maintenance Lodge | D216: DEL | E216: =+VLOOKUP(F216,Resumen_Base!$B$6:$F$69,5,0) -> Maintenance Lodge | F216: 5252 | G216: Mantenimiento Rep-Lodge | H216: =+D216&F216 -> DEL5252 | I216: 70000 | J216: 47.297297 | K216: 1480 | L216: 26/01/2026 | M216: CAJA | N216: 0141 | O216: TE001500000145 | P216: Asiento de CAJA (01/09/2025 - 310126) | Q216: Extracción de Caja 001500000145 Obs: 26-01-2026 Mov Lodge | R216: DT - Pago adicional a Rolando | S216: 000000000161 | T216: Ejercicio 2025/2026
A217: 5208 | B217: 5263 | C217: =+VLOOKUP(F217,Resumen_Base!$B$7:$F$69,5,0) -> Canon Lodge/Labor Permits: | D217: DEL | E217: =+VLOOKUP(F217,Resumen_Base!$B$6:$F$69,5,0) -> Canon Lodge/Labor Permits: | F217: 5208 | G217: Alquileres y Canon | H217: =+D217&F217 -> DEL5208 | I217: 10000 | J217: 6.8027211 | K217: 1470 | L217: 12/01/2026 | M217: CAJA | N217: 0141 | O217: TE001500000125 | P217: Asiento de CAJA (01/09/2025 - 31/08/2026) | Q217: Extracción de Caja 001500000125 Obs: 12-01-2026 Mov Lodge | R217: DT - Pago por ayuda carga y descarga en la Baie | S217: 000000000126 | T217: Ejercicio 2025/2026
A218: 5252 | B218: 5263 | C218: =+VLOOKUP(F218,Resumen_Base!$B$7:$F$69,5,0) -> Maintenance Lodge | D218: DEL | E218: =+VLOOKUP(F218,Resumen_Base!$B$6:$F$69,5,0) -> Maintenance Lodge | F218: 5252 | G218: Mantenimiento Rep-Lodge | H218: =+D218&F218 -> DEL5252 | I218: 20000 | J218: 13.513514 | K218: 1480 | L218: 31/01/2026 | M218: CAJA | N218: 0141 | O218: TE001500000152 | P218: Asiento de CAJA (01/09/2025 - 310126) | Q218: Extracción de Caja 001500000152 Obs: 31-01-2026 Mov Lodge | R218: DT - Pago Remis Madero retiro y despacho de blanqueria en guardería | S218: 000000000165 | T218: Ejercicio 2025/2026
A219: 5291 | B219: 5263 | C219: =+VLOOKUP(F219,Resumen_Base!$B$7:$F$69,5,0) -> Food & Wine | D219: DEL | E219: =+VLOOKUP(F219,Resumen_Base!$B$6:$F$69,5,0) -> Food & Wine | F219: 5291 | G219: Comida / Fletes | H219: =+D219&F219 -> DEL5291 | I219: 15000 | J219: 10.135135 | K219: 1480 | L219: 31/01/2026 | M219: CAJA | N219: 0141 | O219: TE001500000152 | P219: Asiento de CAJA (01/09/2025 - 310126) | Q219: Extracción de Caja 001500000152 Obs: 31-01-2026 Mov Lodge | R219: DT - Pago Remis Madero si perro refuerzo de compras | S219: 000000000165 | T219: Ejercicio 2025/2026
A220: 5252 | B220: 5263 | C220: =+VLOOKUP(F220,Resumen_Base!$B$7:$F$69,5,0) -> Maintenance Lodge | D220: DEL | E220: =+VLOOKUP(F220,Resumen_Base!$B$6:$F$69,5,0) -> Maintenance Lodge | F220: 5252 | G220: Mantenimiento Rep-Lodge | H220: =+D220&F220 -> DEL5252 | I220: 10000 | J220: 6.7567568 | K220: 1480 | L220: 26/01/2026 | M220: CAJA | N220: 0141 | O220: TE001500000145 | P220: Asiento de CAJA (01/09/2025 - 310126) | Q220: Extracción de Caja 001500000145 Obs: 26-01-2026 Mov Lodge | R220: DT - Remis Madero transporte de blanqueria | S220: 000000000161 | T220: Ejercicio 2025/2026
A221: 5291 | B221: 5263 | C221: =+VLOOKUP(F221,Resumen_Base!$B$7:$F$69,5,0) -> Food & Wine | D221: DEL | E221: =+VLOOKUP(F221,Resumen_Base!$B$6:$F$69,5,0) -> Food & Wine | F221: 5291 | G221: Comida / Fletes | H221: =+D221&F221 -> DEL5291 | I221: 32000 | J221: 21.621622 | K221: 1480 | L221: 26/01/2026 | M221: CAJA | N221: 0141 | O221: TE001500000145 | P221: Asiento de CAJA (01/09/2025 - 310126) | Q221: Extracción de Caja 001500000145 Obs: 26-01-2026 Mov Lodge | R221: DT - Remises Madero soporte día de compras | S221: 000000000161 | T221: Ejercicio 2025/2026
C222: =+VLOOKUP(F222,Resumen_Base!$B$7:$F$69,5,0) -> Maintenance Lodge | D222: DEL | E222: =+VLOOKUP(F222,Resumen_Base!$B$6:$F$69,5,0) -> Maintenance Lodge | F222: 5283 | G222: Mantenimiento Comida Perros | H222: =+D222&F222 -> DEL5283 | I222: 79000 | J222: 53.378378 | K222: 1480 | L222: 26/01/2026 | M222: CAJA | N222: 0141 | O222: TE001500000145 | P222: Asiento de CAJA (01/09/2025 - 310126) | Q222: Extracción de Caja 001500000145 Obs: 26-01-2026 Mov Lodge | R222: DT - Alimentos dingo y Melchora | S222: 000000000161 | T222: Ejercicio 2025/2026
C223: =+VLOOKUP(F223,Resumen_Base!$B$7:$F$69,5,0) -> Food & Wine | D223: DEL | E223: =+VLOOKUP(F223,Resumen_Base!$B$6:$F$69,5,0) -> Food & Wine | F223: 5289 | G223: Comidas Fuera Temp / Empleados | H223: =+D223&F223 -> DEL5289 | I223: 24000 | J223: 16.326531 | K223: 1470 | L223: 12/01/2026 | M223: CAJA | N223: 0141 | O223: TE001500000125 | P223: Asiento de CAJA (01/09/2025 - 31/08/2026) | Q223: Extracción de Caja 001500000125 Obs: 12-01-2026 Mov Lodge | R223: DT - Alexis casero compra de milanesas | S223: 000000000126 | T223: Ejercicio 2025/2026
C224: =+VLOOKUP(F224,Resumen_Base!$B$7:$F$69,5,0) -> Food & Wine | D224: DEL | E224: =+VLOOKUP(F224,Resumen_Base!$B$6:$F$69,5,0) -> Food & Wine | F224: 5289 | G224: Comidas Fuera Temp / Empleados | H224: =+D224&F224 -> DEL5289 | I224: 24350 | J224: 16.452703 | K224: 1480 | L224: 31/01/2026 | M224: CAJA | N224: 0141 | O224: TE001500000152 | P224: Asiento de CAJA (01/09/2025 - 310126) | Q224: Extracción de Caja 001500000152 Obs: 31-01-2026 Mov Lodge | R224: DT - Budines personal desayuno | S224: 000000000165 | T224: Ejercicio 2025/2026
C225: =+VLOOKUP(F225,Resumen_Base!$B$7:$F$69,5,0) -> Food & Wine | D225: DEL | E225: =+VLOOKUP(F225,Resumen_Base!$B$6:$F$69,5,0) -> Food & Wine | F225: 5289 | G225: Comidas Fuera Temp / Empleados | H225: =+D225&F225 -> DEL5289 | I225: 16500 | J225: 11.22449 | K225: 1470 | L225: 12/01/2026 | M225: CAJA | N225: 0141 | O225: TE001500000125 | P225: Asiento de CAJA (01/09/2025 - 31/08/2026) | Q225: Extracción de Caja 001500000125 Obs: 12-01-2026 Mov Lodge | R225: DT - Comida Alexis casero Verduleria | S225: 000000000126 | T225: Ejercicio 2025/2026
C226: =+VLOOKUP(F226,Resumen_Base!$B$7:$F$69,5,0) -> Food & Wine | D226: DEL | E226: =+VLOOKUP(F226,Resumen_Base!$B$6:$F$69,5,0) -> Food & Wine | F226: 5289 | G226: Comidas Fuera Temp / Empleados | H226: =+D226&F226 -> DEL5289 | I226: 35800 | J226: 24.189189 | K226: 1480 | L226: 31/01/2026 | M226: CAJA | N226: 0141 | O226: TE001500000152 | P226: Asiento de CAJA (01/09/2025 - 310126) | Q226: Extracción de Caja 001500000152 Obs: 31-01-2026 Mov Lodge | R226: DT - Pan para personal | S226: 000000000165 | T226: Ejercicio 2025/2026
C227: =+VLOOKUP(F227,Resumen_Base!$B$7:$F$69,5,0) -> Food & Wine | D227: DEL | E227: =+VLOOKUP(F227,Resumen_Base!$B$6:$F$69,5,0) -> Food & Wine | F227: 5291 | G227: Comida / Fletes | H227: =+D227&F227 -> DEL5291 | I227: 23700 | J227: 16.122449 | K227: 1470 | L227: 12/01/2026 | M227: CAJA | N227: 0141 | O227: TE001500000125 | P227: Asiento de CAJA (01/09/2025 - 31/08/2026) | Q227: Extracción de Caja 001500000125 Obs: 12-01-2026 Mov Lodge | R227: DT - Panadería | S227: 000000000126 | T227: Ejercicio 2025/2026
A229: AJ EXTRACOBLE REPORTE DHA | C229: =+VLOOKUP(F229,Resumen_Base!$B$7:$F$69,5,0) -> Communications - Phone, internet and satellite TV | D229: DEL | E229: =+VLOOKUP(F229,Resumen_Base!$B$6:$F$69,5,0) -> Communications - Phone, internet and satellite TV | F229: 5209 | G229: Comunicaciones | H229: =+D229&F229 -> DEL5209 | J229: 3.44 | K229: Delta | L229: 46016 | N229: 141-BASE2 | R229: DT- TriSW- AMEX - =DLOSPOTIFY CABA AR- spotify
A230: AJ EXTRACOBLE REPORTE DHA | C230: =+VLOOKUP(F230,Resumen_Base!$B$7:$F$69,5,0) -> Services/House | D230: DEL | E230: =+VLOOKUP(F230,Resumen_Base!$B$6:$F$69,5,0) -> Services/House | F230: 5226 | G230: Remuneraciones Servicios | H230: =+D230&F230 -> DEL5226 | J230: 294 | K230: Delta | L230: 46022 | N230: 141-BASE2 | R230: DEL- Reintegro Sueldos TA SAC 12-2025 - Servicios
A231: AJ EXTRACOBLE REPORTE DHA | C231: =+VLOOKUP(F231,Resumen_Base!$B$7:$F$69,5,0) -> Services/House | D231: DEL | E231: =+VLOOKUP(F231,Resumen_Base!$B$6:$F$69,5,0) -> Services/House | F231: 5226 | G231: Remuneraciones Servicios | H231: =+D231&F231 -> DEL5226 | J231: 1283 | K231: Delta | L231: 46022 | N231: 141-BASE2 | R231: DEL- Reintegro Sueldos TA 12-2025 - Servicios
A232: AJ EXTRACOBLE REPORTE DHA | C232: =+VLOOKUP(F232,Resumen_Base!$B$7:$F$69,5,0) -> Manager | D232: DEL | E232: =+VLOOKUP(F232,Resumen_Base!$B$6:$F$69,5,0) -> Manager | F232: 5228 | G232: Remuneraciones Managers | H232: =+D232&F232 -> DEL5228 | J232: 218 | K232: Delta | L232: 46022 | N232: 141-BASE2 | R232: DEL- Reintegro Sueldos TA SAC 12-2025 - Managers
A233: AJ EXTRACOBLE REPORTE DHA | C233: =+VLOOKUP(F233,Resumen_Base!$B$7:$F$69,5,0) -> Manager | D233: DEL | E233: =+VLOOKUP(F233,Resumen_Base!$B$6:$F$69,5,0) -> Manager | F233: 5228 | G233: Remuneraciones Managers | H233: =+D233&F233 -> DEL5228 | J233: 446 | K233: Delta | L233: 46022 | N233: 141-BASE2 | R233: DEL- Reintegro Sueldos TA 12-2025 - Managers
A234: AJ EXTRACOBLE REPORTE DHA | C234: =+VLOOKUP(F234,Resumen_Base!$B$7:$F$69,5,0) -> Social Security Contributions | D234: DEL | E234: =+VLOOKUP(F234,Resumen_Base!$B$6:$F$69,5,0) -> Social Security Contributions | F234: 5235 | G234: Cargas Sociales Servicios | H234: =+D234&F234 -> DEL5235 | J234: 120 | K234: Delta | L234: 46022 | N234: 141-BASE2 | R234: DEL- Reintegro Cargas Sociales TA SAC 12-2025 - Servicios
A235: AJ EXTRACOBLE REPORTE DHA | C235: =+VLOOKUP(F235,Resumen_Base!$B$7:$F$69,5,0) -> Social Security Contributions | D235: DEL | E235: =+VLOOKUP(F235,Resumen_Base!$B$6:$F$69,5,0) -> Social Security Contributions | F235: 5235 | G235: Cargas Sociales Servicios | H235: =+D235&F235 -> DEL5235 | J235: 522 | K235: Delta | L235: 46022 | N235: 141-BASE2 | R235: DEL- Reintegro Cargas Sociales TA 12-2025 - Servicios
A236: AJ EXTRACOBLE REPORTE DHA | C236: =+VLOOKUP(F236,Resumen_Base!$B$7:$F$69,5,0) -> Social Security Contributions | D236: DEL | E236: =+VLOOKUP(F236,Resumen_Base!$B$6:$F$69,5,0) -> Social Security Contributions | F236: 5237 | G236: Cargas Sociales Managers | H236: =+D236&F236 -> DEL5237 | J236: 89 | K236: Delta | L236: 46022 | N236: 141-BASE2 | R236: DEL- Reintegro Cargas Sociales TA SAC 12-2025 - Managers
A237: AJ EXTRACOBLE REPORTE DHA | C237: =+VLOOKUP(F237,Resumen_Base!$B$7:$F$69,5,0) -> Social Security Contributions | D237: DEL | E237: =+VLOOKUP(F237,Resumen_Base!$B$6:$F$69,5,0) -> Social Security Contributions | F237: 5237 | G237: Cargas Sociales Managers | H237: =+D237&F237 -> DEL5237 | J237: 181 | K237: Delta | L237: 46022 | N237: 141-BASE2 | R237: DEL- Reintegro Cargas Sociales TA 12-2025 - Managers
A243: INSERT | B243: INSERT | C243: INSERT | D243: INSERT | E243: INSERT | F243: INSERT | G243: INSERT | H243: INSERT | I243: INSERT | J243: INSERT | K243: INSERT | L243: INSERT | M243: INSERT | N243: INSERT | O243: INSERT | P243: INSERT | Q243: INSERT | R243: INSERT | S243: INSERT | T243: INSERT | U243: INSERT | V243: INSERT | W243: INSERT
A245: VER!!!! | F245: 5258 | G245: Gastos para Cebo | I245: 30000 | J245: 20.27027 | K245: 1480 | L245: 26/01/2026 | M245: CAJA | N245: 0141 | O245: TE001500000145 | P245: Asiento de CAJA (01/09/2025 - 310126) | Q245: Extracción de Caja 001500000145 Obs: 26-01-2026 Mov Lodge | R245: DT - Compra maíz ceba | S245: 000000000161 | T245: Ejercicio 2025/2026
A247: AJ EXTRACOBLE REPORTE DHA | F247: 11010102 | G247: Caja U$S Administración | J247: -3156.44
A249: 5210 | B249: 5226 | F249: 5210 | G249: Traslado Aerop. Lodge | I249: 2352000 | J249: 1600 | K249: 1470 | L249: 12/01/2026 | M249: CAJA | N249: 0141 | O249: TE001500000130 | P249: Asiento de CAJA (01/09/2025 - 31/08/2026) | Q249: Extracción de Caja 001500000130 Obs: 12-01-2026 Mov Lodge | R249: DT - Pago a Rolando por 8 Transfers | S249: 000000000127 | T249: Ejercicio 2025/2026
F251: 11010101 | G251: Caja $ Administración | I251: -2760000 | J251: -1877.551 | K251: 1470 | L251: 09/01/2026 | M251: CAJA | N251: 0141 | O251: TE001500000123 | P251: Asiento de CAJA (01/09/2025 - 31/08/2026) | Q251: Extracción de Caja 001500000123 Obs: Movimiento_Cajas_Bancos_Semana 25-26 al 09-01-2026 | R251: DT-16 paños para 4 habitación - cortiñas black out - Flopy Ganly F.Fijo Oper. Al 09-01-2026 | S251: 000000000125 | T251: Ejercicio 2025/2026
F252: 11010101 | G252: Caja $ Administración | I252: -317667 | J252: -216.1 | K252: 1470 | L252: 09/01/2026 | M252: CAJA | N252: 0141 | O252: TE001500000123 | P252: Asiento de CAJA (01/09/2025 - 31/08/2026) | Q252: Extracción de Caja 001500000123 Obs: Movimiento_Cajas_Bancos_Semana 25-26 al 09-01-2026 | R252: DT-Alexis Carra - Honorarios mantenimiento diciembre Pagos Frank Garrahan Al 09-01-2026 | S252: 000000000125 | T252: Ejercicio 2025/2026
F253: 11010101 | G253: Caja $ Administración | I253: -309481 | J253: -209.10878 | K253: 1480 | L253: 31/01/2026 | M253: CAJA | N253: 0141 | O253: TE001500000170 | P253: Asiento de CAJA (01/09/2025 - 310126) | Q253: Extracción de Caja 001500000170 Obs: Movimiento_Cajas_Bancos_Semana 25-26 al 06-02-2026 | R253: DT-Alexis Carra - Honorarios mantenimiento Enero 2026 Pagos Depsa Valores. Al 06-02-2026 | S253: 000000000173 | T253: Ejercicio 2025/2026
F254: 11010101 | G254: Caja $ Administración | I254: -178000 | J254: -120.27027 | K254: 1480 | L254: 30/01/2026 | M254: CAJA | N254: 0141 | O254: TE001500000162 | P254: Asiento de CAJA (01/09/2025 - 310126) | Q254: Extracción de Caja 001500000162 Obs: Reversión de documento | R254: DT-Articulos de pesca Pagos Frank Garrahan. Al 30-01-2026 | S254: 000000000169 | T254: Ejercicio 2025/2026
F255: 11010101 | G255: Caja $ Administración | I255: -178000 | J255: -120.27027 | K255: 1480 | L255: 30/01/2026 | M255: CAJA | N255: 0141 | O255: TE001500000163 | P255: Asiento de CAJA (01/09/2025 - 310126) | Q255: Extracción de Caja 001500000163 Obs: Movimiento_Cajas_Bancos_Semana 25-26 al 30-01-2026 | R255: DT-Articulos de pesca Pagos Frank Garrahan. Al 30-01-2026 | S255: 000000000170 | T255: Ejercicio 2025/2026
F256: 11010101 | G256: Caja $ Administración | I256: 178000 | J256: 120.27027 | K256: 1480 | L256: 30/01/2026 | M256: CAJA | N256: 0141 | O256: TI001500000159 | P256: Asiento de CAJA (01/09/2025 - 310126) | Q256: Ingreso a Caja 001500000159 Obs: Movimiento_Cajas_Bancos_Semana 25-26 al 30-01-2026 | R256: DT-Articulos de pesca Pagos Frank Garrahan. Al 30-01-2026 | S256: 000000000181 | T256: Ejercicio 2025/2026
...

Sheet Mov_Analizados_Feb26
G2: Ver Telefonos
G3: Ver Gastos devengados | I3: $ | J3: USD | K3: TC
G4: Ver Luz Devengada | H4: Food & Wine | I4: =+SUMIF($E$10:$E$259,H4,$I$10:$I$259) -> 5481342.5 | J4: =+SUMIF($E$10:$E$259,H4,$J$10:$J$259) -> 3853.3284 | K4: =+I4/J4 -> 1422.4955
G7: =+IF(I7+J7=0,"Ok","Check") -> Ok | I7: =ROUND(SUM(I10:I612),0) -> 0 | J7: =ROUND(SUM(J10:J612),0) -> 0
E8: Rubro | G8: =+Resumen_Base!C1 -> Ok
B9: =+F9&G9 | D9: DEL | E9: =+VLOOKUP(F9,Resumen_Base!$B$6:$F$69,5,0) -> #N/A | H9: =+D9&F9 -> DEL | I9: =SUM(I10:I259) -> 30528432 | J9: =SUM(J10:J259) -> 20615.661
B10: Cuenta Anterior | D10: Lodge | E10: Concepto | F10: Cuenta | G10: Nombre | I10: monto $ | J10: monto USD | K10: TC | L10: Fecha | M10: Subdiario | N10: Div | O10: Datos del comprobante | P10: Sujeto | Q10: CUIT | R10: Observación asiento | S10: Clase de Asiento | T10: Origen del comprobante | U10: Observación del comprobante | V10: Comentario renglón asiento | W10: Asiento | X10: Control | Z10: monto USD | AA10: tc | AC10: Fecha | AD10: Subdiario | AE10: Div | AF10: Datos del comprobante | AG10: Sujeto | AH10: CUIT | AI10: Observación asiento | AJ10: Clase de Asiento | AK10: Origen del comprobante | AL10: Observación del comprobante | AM10: Comentario renglón asiento | AN10: Asiento
C12: Delta | D12: DEL | E12: =+VLOOKUP(F12,Resumen_Base!$B$6:$F$69,5,0) -> Fixed Asset's Payments (Investments) Mejoras/equipamiento Lodge | F12: 12020103 | G12: Mejoras de Inmueb y Terrenos | H12: =+D12&F12 -> DEL12020103 | I12: 424500 | J12: 300 | K12: 1415 | L12: 28/02/2026 | M12: CAJA | N12: 0141 | O12: TE001500000199 | P12: Asiento de CAJA (01/09/2025 - 280226) | Q12: Extracción de Caja 001500000199 Obs: Movimiento_Cajas_Bancos_Semana 25-26 al 06-03-2026 | R12: DT-Honorarios Hector Natera por visita Lodges - monitoreo deinversores F.Fijo Oper. Al 06-03-2026 | S12: 000000000222 | T12: Ejercicio 2025/2026
C13: Delta | D13: DEL | E13: =+VLOOKUP(F13,Resumen_Base!$B$6:$F$69,5,0) -> Fixed Asset's Payments (Investments) Mejoras/equipamiento Lodge | F13: 12020301 | G13: Muebles y útiles | H13: =+D13&F13 -> DEL12020301 | I13: 257724 | J13: 180.85895 | K13: 1425 | L13: 20/02/2026 | M13: CAJA | N13: 0141 | O13: TE001500000187 | P13: Asiento de CAJA (01/09/2025 - 280226) | Q13: Extracción de Caja 001500000187 Obs: Movimiento_Cajas_Bancos_Semana 25-26 al 20-02-2026 | R13: DT-2 Cámara de Seguridad Solar Gadnic Lente Dual FHD Conexion Inalambrica Panel Solar Visión Nocturn | S13: 000000000216 | T13: Ejercicio 2025/2026
C14: Delta | D14: DEL | E14: =+VLOOKUP(F14,Resumen_Base!$B$6:$F$69,5,0) -> Fixed Asset's Payments (Investments) Mejoras/equipamiento Lodge | F14: 12020301 | G14: Muebles y útiles | H14: =+D14&F14 -> DEL12020301 | I14: 665998 | J14: 470.66996 | K14: 1415 | L14: 27/02/2026 | M14: CAJA | N14: 0141 | O14: TE001500000195 | P14: Asiento de CAJA (01/09/2025 - 280226) | Q14: Extracción de Caja 001500000195 Obs: Movimiento_Cajas_Bancos_Semana 25-26 al 27-02-2026 | R14: DT-Compra 1 envasadora al vacio TS 2200+ 2 rollos bolsas al vacio - Turboblender F.Fijo Oper. Al 27- | S14: 000000000221 | T14: Ejercicio 2025/2026
C15: Delta | D15: DEL | E15: =+VLOOKUP(F15,Resumen_Base!$B$6:$F$69,5,0) -> Fixed Asset's Payments (Investments) Mejoras/equipamiento Lodge | F15: 12020301 | G15: Muebles y útiles | H15: =+D15&F15 -> DEL12020301 | I15: 269998 | J15: 190.81131 | K15: 1415 | L15: 28/02/2026 | M15: CAJA | N15: 0141 | O15: TE001500000201 | P15: Asiento de CAJA (01/09/2025 - 280226) | Q15: Extracción de Caja 001500000201 Obs: Movimiento_Cajas_Bancos_Semana 25-26 al 06-03-2026 | R15: DT-Compra 2 Cámara de Seguridad Solar Gadnic Lente Dual FHD Conexion Inalambrica Panel Solar Visión | S15: 000000000223 | T15: Ejercicio 2025/2026
C16: Delta | D16: DEL | E16: =+VLOOKUP(F16,Resumen_Base!$B$6:$F$69,5,0) -> Fixed Asset's Payments (Investments) Mejoras/equipamiento Lodge | F16: 12020301 | G16: Muebles y útiles | H16: =+D16&F16 -> DEL12020301 | I16: 288300 | J16: 202.31579 | K16: 1425 | L16: 20/02/2026 | M16: CAJA | N16: 0141 | O16: TE001500000187 | P16: Asiento de CAJA (01/09/2025 - 280226) | Q16: Extracción de Caja 001500000187 Obs: Movimiento_Cajas_Bancos_Semana 25-26 al 20-02-2026 | R16: DT-Compra de artículos de pesca 12/2 Pagos Depsa Valores. Al 20-02-2026 | S16: 000000000216 | T16: Ejercicio 2025/2026
C17: Delta | D17: DEL | E17: =+VLOOKUP(F17,Resumen_Base!$B$6:$F$69,5,0) -> Fixed Asset's Payments (Investments) Mejoras/equipamiento Lodge | F17: 12020301 | G17: Muebles y útiles | H17: =+D17&F17 -> DEL12020301 | I17: 288990.27 | J17: 204.23341 | K17: 1415 | L17: 27/02/2026 | M17: CAJA | N17: 0141 | O17: TE001500000195 | P17: Asiento de CAJA (01/09/2025 - 280226) | Q17: Extracción de Caja 001500000195 Obs: Movimiento_Cajas_Bancos_Semana 25-26 al 27-02-2026 | R17: DT-Compra freidora moretti fryer 8+ 4 cuba gen 11/6 *150 mm - Gastrobaires F.Fijo Oper. Al 27-02-202 | S17: 000000000221 | T17: Ejercicio 2025/2026
C18: Delta | D18: DEL | E18: =+VLOOKUP(F18,Resumen_Base!$B$6:$F$69,5,0) -> Shop | F18: 4104 | G18: Ventas Shop | H18: =+D18&F18 -> DEL4104 | I18: -171000 | J18: -120 | K18: 1425 | L18: 16/02/2026 | M18: VENTAS | N18: 0141 | O18: VF000000004422B | P18: Asiento de VENTAS (01/09/2025 - 28/2/2026) | Q18: F B 000000004422 | R18: Ref. nota de Venta: DEL16 Obs.:16-02-2026_CLIENTES | S18: 000000000234 | T18: Ejercicio 2025/2026
C19: Delta | D19: DEL | E19: =+VLOOKUP(F19,Resumen_Base!$B$6:$F$69,5,0) -> Shop | F19: 4104 | G19: Ventas Shop | H19: =+D19&F19 -> DEL4104 | I19: -85500 | J19: -60 | K19: 1425 | L19: 16/02/2026 | M19: VENTAS | N19: 0141 | O19: VF000000004422B | P19: Asiento de VENTAS (01/09/2025 - 28/2/2026) | Q19: F B 000000004422 | R19: Ref. nota de Venta: DEL16 Obs.:16-02-2026_CLIENTES | S19: 000000000234 | T19: Ejercicio 2025/2026
C20: Delta | D20: DEL | E20: =+VLOOKUP(F20,Resumen_Base!$B$6:$F$69,5,0) -> Shop | F20: 4104 | G20: Ventas Shop | H20: =+D20&F20 -> DEL4104 | I20: -34200 | J20: -24 | K20: 1425 | L20: 23/02/2026 | M20: VENTAS | N20: 0141 | O20: VF000000004826B | P20: Asiento de VENTAS (01/09/2025 - 28/2/2026) | Q20: F B 000000004826 | R20: Ref. nota de Venta: DEL29 Obs.:23-02-2026_CLIENTES | S20: 000000000235 | T20: Ejercicio 2025/2026
C21: Delta | D21: DEL | E21: =+VLOOKUP(F21,Resumen_Base!$B$6:$F$69,5,0) -> Shop | F21: 4104 | G21: Ventas Shop | H21: =+D21&F21 -> DEL4104 | I21: -42750 | J21: -30 | K21: 1425 | L21: 23/02/2026 | M21: VENTAS | N21: 0141 | O21: VF000000004826B | P21: Asiento de VENTAS (01/09/2025 - 28/2/2026) | Q21: F B 000000004826 | R21: Ref. nota de Venta: DEL29 Obs.:23-02-2026_CLIENTES | S21: 000000000235 | T21: Ejercicio 2025/2026
C22: Delta | D22: DEL | E22: =+VLOOKUP(F22,Resumen_Base!$B$6:$F$69,5,0) -> Shop | F22: 4104 | G22: Ventas Shop | H22: =+D22&F22 -> DEL4104 | I22: -42750 | J22: -30 | K22: 1425 | L22: 23/02/2026 | M22: VENTAS | N22: 0141 | O22: VF000000004826B | P22: Asiento de VENTAS (01/09/2025 - 28/2/2026) | Q22: F B 000000004826 | R22: Ref. nota de Venta: DEL29 Obs.:23-02-2026_CLIENTES | S22: 000000000235 | T22: Ejercicio 2025/2026
C23: Delta | D23: DEL | E23: =+VLOOKUP(F23,Resumen_Base!$B$6:$F$69,5,0) -> Shop | F23: 4104 | G23: Ventas Shop | H23: =+D23&F23 -> DEL4104 | I23: -85500 | J23: -60 | K23: 1425 | L23: 23/02/2026 | M23: VENTAS | N23: 0141 | O23: VF000000004826B | P23: Asiento de VENTAS (01/09/2025 - 28/2/2026) | Q23: F B 000000004826 | R23: Ref. nota de Venta: DEL29 Obs.:23-02-2026_CLIENTES | S23: 000000000235 | T23: Ejercicio 2025/2026
... C42: Delta | D42: DEL | E42: =+VLOOKUP(F42,Resumen_Base!$B$6:$F$69,5,0) -> Guides | F42: 5227 | G42: Remuneraciones Guías | H42: =+D42&F42 -> DEL5227 | I42: 855000 | J42: 600 | K42: 1425 | L42: 23/02/2026 | M42: CAJA | N42: 0141 | O42: TE001500000178 | P42: Asiento de CAJA (01/09/2025 - 280226) | Q42: Extracción de Caja 001500000178 Obs: 23-02-2026 Mov Lodge | R42: DT - Pago a Matías guía por 3 full day | S42: 000000000211 | T42: Ejercicio 2025/2026
A43: De este movimiento pasar usd 350 a costo transfers | B43: 5227Remuneraciones Guías | C43: Delta | D43: DEL | E43: =+VLOOKUP(F43,Resumen_Base!$B$6:$F$69,5,0) -> Guides | F43: 5227 | G43: Remuneraciones Guías | H43: =+D43&F43 -> DEL5227 | I43: =+J43*K43 -> 1296000 | J43: =1250-350 -> 900 | K43: 1440 | L43: 09/02/2026 | M43: CAJA | N43: 0141 | O43: TE001500000167 | P43: Asiento de CAJA (01/09/2025 - 280226) | Q43: Extracción de Caja 001500000167 Obs: 09-02-2026 Mov Lodge | R43: DT - Pago a Pablo guia por 3 full day + 1 Transfer | S43: 000000000207 | T43: Ejercicio 2025/2026
A44: Combusible Botes | B44: 5227Remuneraciones Guías | C44: Delta | D44: DEL | E44: =+VLOOKUP(F44,Resumen_Base!$B$6:$F$69,5,0) -> Electricity - Gas for Boats & Vehicles | F44: 5248 | G44: Combustibles y Lub. - Vehiculos y Botes | H44: =+D44&F44 -> DEL5248 | I44: 133280 | J44: 93.529825 | K44: 1425 | L44: 23/02/2026 | M44: CAJA | N44: 0141 | O44: TE001500000179 | P44: Asiento de CAJA (01/09/2025 - 280226) | Q44: Extracción de Caja 001500000179 Obs: 23-02-2026 Mov Lodge | R44: DT - Pago nafta de las guiadas de Matías guía | S44: 000000000212 | T44: Ejercicio 2025/2026
C45: Delta | D45: DEL | E45: =+VLOOKUP(F45,Resumen_Base!$B$6:$F$69,5,0) -> Guides | F45: 5227 | G45: Remuneraciones Guías | H45: =+D45&F45 -> DEL5227 | I45: 2830000 | J45: 2000 | K45: 1415 | L45: 27/02/2026 | M45: CAJA | N45: 0141 | O45: TE001500000194 | P45: Asiento de CAJA (01/09/2025 - 280226) | Q45: Extracción de Caja 001500000194 Obs: Movimiento_Cajas_Bancos_Semana 25-26 al 27-02-2026 | R45: DT- Fee Noel 02-2026 | S45: 000000000220 | T45: Ejercicio 2025/2026
C46: Delta | D46: DEL | E46: =+VLOOKUP(F46,Resumen_Base!$B$6:$F$69,5,0) -> Manager | F46: 5228 | G46: Remuneraciones Managers | H46: =+D46&F46 -> DEL5228 | I46: 670710 | J46: 474 | K46: 1415 | L46: 27/02/2026 | M46: CAJA | N46: 0141 | O46: TE001500000194 | P46: Asiento de CAJA (01/09/2025 - 280226) | Q46: Extracción de Caja 001500000194 Obs: Movimiento_Cajas_Bancos_Semana 25-26 al 27-02-2026 | R46: DEL- Reintegro Sueldos TA 02-2026 - Managers | S46: 000000000220 | T46: Ejercicio 2025/2026
C47: Delta | D47: DEL | E47: =+VLOOKUP(F47,Resumen_Base!$B$6:$F$69,5,0) -> Manager | F47: 5228 | G47: Remuneraciones Managers | H47: =+D47&F47 -> DEL5228 | I47: 2376000 | J47: 1650 | K47: 1440 | L47: 09/02/2026 | M47: CAJA | N47: 0141 | O47: TE001500000167 | P47: Asiento de CAJA (01/09/2025 - 280226) | Q47: Extracción de Caja 001500000167 Obs: 09-02-2026 Mov Lodge | R47: DT - Salario mío todo enero | S47: 000000000207 | T47: Ejercicio 2025/2026
C48: Delta | D48: DEL | E48: =+VLOOKUP(F48,Resumen_Base!$B$6:$F$69,5,0) -> Social Security Contributions | F48: 5235 | G48: Cargas Sociales Servicios | H48: =+D48&F48 -> DEL5235 | I48: 799475 | J48: 565 | K48: 1415 | L48: 27/02/2026 | M48: CAJA | N48: 0141 | O48: TE001500000194 | P48: Asiento de CAJA (01/09/2025 - 280226) | Q48: Extracción de Caja 001500000194 Obs: Movimiento_Cajas_Bancos_Semana 25-26 al 27-02-2026 | R48: DEL- Reintegro Cargas Sociales TA 02-2026 - Servicios | S48: 000000000220 | T48: Ejercicio 2025/2026
C49: Delta | D49: DEL | E49: =+VLOOKUP(F49,Resumen_Base!$B$6:$F$69,5,0) -> Social Security Contributions | F49: 5237 | G49: Cargas Sociales Managers | H49: =+D49&F49 -> DEL5237 | I49: 273095 | J49: 193 | K49: 1415 | L49: 27/02/2026 | M49: CAJA | N49: 0141 | O49: TE001500000194 | P49: Asiento de CAJA (01/09/2025 - 280226) | Q49: Extracción de Caja 001500000194 Obs: Movimiento_Cajas_Bancos_Semana 25-26 al 27-02-2026 | R49: DEL- Reintegro Cargas Sociales TA 02-2026 - Managers | S49: 000000000220 | T49: Ejercicio 2025/2026
C50: Delta | D50: DEL | E50: =+VLOOKUP(F50,Resumen_Base!$B$6:$F$69,5,0) -> Electricity | F50: 5247 | G50: Combustible y Lub- Elect-Gener | H50: =+D50&F50 -> DEL5247 | I50: 20000 | J50: 14.035088 | K50: 1425 | L50: 16/02/2026 | M50: CAJA | N50: 0141 | O50: TE001500000171 | P50: Asiento de CAJA (01/09/2025 - 280226) | Q50: Extracción de Caja 001500000171 Obs: 16-02-2026 Mov Lodge | R50: DT - Nafta generador | S50: 000000000208 | T50: Ejercicio 2025/2026
C51: Delta | D51: DEL | E51: =+VLOOKUP(F51,Resumen_Base!$B$6:$F$69,5,0) -> Electricity | F51: 5247 | G51: Combustible y Lub- Elect-Gener | H51: =+D51&F51 -> DEL5247 | I51: 94000 | J51: 65.964912 | K51: 1425 | L51: 23/02/2026 | M51: CAJA | N51: 0141 | O51: TE001500000179 | P51: Asiento de CAJA (01/09/2025 - 280226) | Q51: Extracción de Caja 001500000179 Obs: 23-02-2026 Mov Lodge | R51: DT - Nafta generador | S51: 000000000212 | T51: Ejercicio 2025/2026
C52: Delta | D52: DEL | E52: =+VLOOKUP(F52,Resumen_Base!$B$6:$F$69,5,0) -> Electricity | F52: 5247 | G52: Combustible y Lub- Elect-Gener | H52: =+D52&F52 -> DEL5247 | I52: 59365 | J52: 41.225694 | K52: 1440 | L52: 09/02/2026 | M52: CAJA | N52: 0141 | O52: TE001500000166 | P52: Asiento de CAJA (01/09/2025 - 280226) | Q52: Extracción de Caja 001500000166 Obs: 09-02-2026 Mov Lodge | R52: DT - Nafta generadores | S52: 000000000206 | T52: Ejercicio 2025/2026
C53: Delta | D53: DEL | E53: =+VLOOKUP(F53,Resumen_Base!$B$6:$F$69,5,0) -> Electricity | F53: 5247 | G53: Combustible y Lub- Elect-Gener | H53: =+D53&F53 -> DEL5247 | I53: 175418 | J53: 121.81806 | K53: 1440 | L53: 09/02/2026 | M53: CAJA | N53: 0141 | O53: TE001500000166 | P53: Asiento de CAJA (01/09/2025 - 280226) | Q53: Extracción de Caja 001500000166 Obs: 09-02-2026 Mov Lodge | R53: DT - Nafta generadores | S53: 000000000206 | T53: Ejercicio 2025/2026
C54: Delta | D54: DEL | E54: =+VLOOKUP(F54,Resumen_Base!$B$6:$F$69,5,0) -> Electricity | F54: 5247 | G54: Combustible y Lub- Elect-Gener | H54: =+D54&F54 -> DEL5247 | I54: 80000 | J54: 56.140351 | K54: 1425 | L54: 16/02/2026 | M54: CAJA | N54: 0141 | O54: TE001500000171 | P54: Asiento de CAJA (01/09/2025 - 280226) | Q54: Extracción de Caja 001500000171 Obs: 16-02-2026 Mov Lodge | R54: DT - Nafta generadores | S54: 000000000208 | T54: Ejercicio 2025/2026
C55: Delta | D55: DEL | E55: =+VLOOKUP(F55,Resumen_Base!$B$6:$F$69,5,0) -> Electricity | F55: 5247 | G55: Combustible y Lub- Elect-Gener | H55: =+D55&F55 -> DEL5247 | I55: 94000 | J55: 65.964912 | K55: 1425 | L55: 16/02/2026 | M55: CAJA | N55: 0141 | O55: TE001500000171 | P55: Asiento de CAJA (01/09/2025 - 280226) | Q55: Extracción de Caja 001500000171 Obs: 16-02-2026 Mov Lodge | R55: DT - Nafta generadores | S55: 000000000208 | T55: Ejercicio 2025/2026
C56: Delta | D56: DEL | E56: =+VLOOKUP(F56,Resumen_Base!$B$6:$F$69,5,0) -> Electricity | F56: 5247 | G56: Combustible y Lub- Elect-Gener | H56: =+D56&F56 -> DEL5247 | I56: 67850 | J56: 47.614035 | K56: 1425 | L56: 23/02/2026 | M56: CAJA | N56: 0141 | O56: TE001500000179 | P56: Asiento de CAJA (01/09/2025 - 280226) | Q56: Extracción de Caja 001500000179 Obs: 23-02-2026 Mov Lodge | R56: DT - Nafta generadores | S56: 000000000212 | T56: Ejercicio 2025/2026
... C135: Delta | D135: DEL | E135: =+VLOOKUP(F135,Resumen_Base!$B$6:$F$69,5,0) -> Maintenance Lodge | F135: 5252 | G135: Mantenimiento Rep-Lodge | H135: =+D135&F135 -> DEL5252 | I135: 10800 | J135: 7.5 | K135: 1440 | L135: 09/02/2026 | M135: CAJA | N135: 0141 | O135: TE001500000166 | P135: Asiento de CAJA (01/09/2025 - 280226) | Q135: Extracción de Caja 001500000166 Obs: 09-02-2026 Mov Lodge | R135: DT - Velas deco noche | S135: 000000000206 | T135: Ejercicio 2025/2026
A136: Pasa a uniformes | B136: 5252Mantenimiento Rep-Lodge | C136: Delta | D136: DEL | E136: =+VLOOKUP(F136,Resumen_Base!$B$6:$F$69,5,0) -> Work uniforms for personnel (employees) | F136: 5220 | G136: Uniformes | H136: =+D136&F136 -> DEL5220 | I136: 176000 | J136: 124.38163 | K136: 1415 | L136: 28/02/2026 | M136: CAJA | N136: 0141 | O136: TE001500000191 | P136: Asiento de CAJA (01/09/2025 - 280226) | Q136: Extracción de Caja 001500000191 Obs: 28-02-2026 Mov Lodge | R136: DT - 2 remeras 1 pantalón 1 bermudas Alexis mantenimiento | S136: 000000000218 | T136: Ejercicio 2025/2026
C137: Delta | D137: DEL | E137: =+VLOOKUP(F137,Resumen_Base!$B$6:$F$69,5,0) -> Maintenance Lodge | F137: 5252 | G137: Mantenimiento Rep-Lodge | H137: =+D137&F137 -> DEL5252 | I137: 176000 | J137: 124.38163 | K137: 1415 | L137: 28/02/2026 | M137: CAJA | N137: 0141 | O137: TE001500000192 | P137: Asiento de CAJA (01/09/2025 - 280226) | Q137: Extracción de Caja 001500000192 Obs: 28-02-2026 Mov Lodge | R137: DT - 2 remeras 1 pantalón 1 bermudas Alexis mantenimiento | S137: 000000000219 | T137: Ejercicio 2025/2026
C138: Delta | D138: DEL | E138: =+VLOOKUP(F138,Resumen_Base!$B$6:$F$69,5,0) -> Maintenance Lodge | F138: 5252 | G138: Mantenimiento Rep-Lodge | H138: =+D138&F138 -> DEL5252 | I138: -176000 | J138: -124.38163 | K138: 1415 | L138: 28/02/2026 | M138: CAJA | N138: 0141 | O138: TI001500000204 | P138: Asiento de CAJA (01/09/2025 - 280226) | Q138: Ingreso a Caja 001500000204 Obs: Reversión de documento | R138: DT - 2 remeras 1 pantalón 1 bermudas Alexis mantenimiento | S138: 000000000231 | T138: Ejercicio 2025/2026
C139: Delta | D139: DEL | E139: =+VLOOKUP(F139,Resumen_Base!$B$6:$F$69,5,0) -> Maintenance Lodge | F139: 5252 | G139: Mantenimiento Rep-Lodge | H139: =+D139&F139 -> DEL5252 | I139: 76000 | J139: 52.777778 | K139: 1440 | L139: 09/02/2026 | M139: CAJA | N139: 0141 | O139: TE001500000166 | P139: Asiento de CAJA (01/09/2025 - 280226) | Q139: Extracción de Caja 001500000166 Obs: 09-02-2026 Mov Lodge | R139: DT - Alexis compra carbón para el Lodge | S139: 000000000206 | T139: Ejercicio 2025/2026
C140: Delta | D140: DEL | E140: =+VLOOKUP(F140,Resumen_Base!$B$6:$F$69,5,0) -> Maintenance Lodge | F140: 5252 | G140: Mantenimiento Rep-Lodge | H140: =+D140&F140 -> DEL5252 | I140: 76200 | J140: 53.85159 | K140: 1415 | L140: 28/02/2026 | M140: CAJA | N140: 0141 | O140: TE001500000191 | P140: Asiento de CAJA (01/09/2025 - 280226) | Q140: Extracción de Caja 001500000191 Obs: 28-02-2026 Mov Lodge | R140: DT - Artículos de ferretería, cetol, tornillos, tanza desmalezadora | S140: 000000000218 | T140: Ejercicio 2025/2026
C141: Delta | D141: DEL | E141: =+VLOOKUP(F141,Resumen_Base!$B$6:$F$69,5,0) -> Maintenance Lodge | F141: 5252 | G141: Mantenimiento Rep-Lodge | H141: =+D141&F141 -> DEL5252 | I141: 76200 | J141: 53.85159 | K141: 1415 | L141: 28/02/2026 | M141: CAJA | N141: 0141 | O141: TE001500000192 | P141: Asiento de CAJA (01/09/2025 - 280226) | Q141: Extracción de Caja 001500000192 Obs: 28-02-2026 Mov Lodge | R141: DT - Artículos de ferretería, cetol, tornillos, tanza desmalezadora | S141: 000000000219 | T141: Ejercicio 2025/2026
C142: Delta | D142: DEL | E142: =+VLOOKUP(F142,Resumen_Base!$B$6:$F$69,5,0) -> Maintenance Lodge | F142: 5252 | G142: Mantenimiento Rep-Lodge | H142: =+D142&F142 -> DEL5252 | I142: -76200 | J142: -53.85159 | K142: 1415 | L142: 28/02/2026 | M142: CAJA | N142: 0141 | O142: TI001500000204 | P142: Asiento de CAJA (01/09/2025 - 280226) | Q142: Ingreso a Caja 001500000204 Obs: Reversión de documento | R142: DT - Artículos de ferretería, cetol, tornillos, tanza desmalezadora | S142: 000000000231 | T142: Ejercicio 2025/2026
C143: Delta | D143: DEL | E143: =+VLOOKUP(F143,Resumen_Base!$B$6:$F$69,5,0) -> Maintenance Lodge | F143: 5252 | G143: Mantenimiento Rep-Lodge | H143: =+D143&F143 -> DEL5252 | I143: 40500 | J143: 28.621908 | K143: 1415 | L143: 28/02/2026 | M143: CAJA | N143: 0141 | O143: TE001500000191 | P143: Asiento de CAJA (01/09/2025 - 280226) | Q143: Extracción de Caja 001500000191 Obs: 28-02-2026 Mov Lodge | R143: DT - Cadena motosierra Lodge | S143: 000000000218 | T143: Ejercicio 2025/2026
C144: Delta | D144: DEL | E144: =+VLOOKUP(F144,Resumen_Base!$B$6:$F$69,5,0) -> Maintenance Lodge | F144: 5252 | G144: Mantenimiento Rep-Lodge | H144: =+D144&F144 -> DEL5252 | I144: 40500 | J144: 28.621908 | K144: 1415 | L144: 28/02/2026 | M144: CAJA | N144: 0141 | O144: TE001500000192 | P144: Asiento de CAJA (01/09/2025 - 280226) | Q144: Extracción de Caja 001500000192 Obs: 28-02-2026 Mov Lodge | R144: DT - Cadena motosierra Lodge | S144: 000000000219 | T144: Ejercicio 2025/2026
C145: Delta | D145: DEL | E145: =+VLOOKUP(F145,Resumen_Base!$B$6:$F$69,5,0) -> Maintenance Lodge | F145: 5252 | G145: Mantenimiento Rep-Lodge | H145: =+D145&F145 -> DEL5252 | I145: -40500 | J145: -28.621908 | K145: 1415 | L145: 28/02/2026 | M145: CAJA | N145: 0141 | O145: TI001500000204 | P145: Asiento de CAJA (01/09/2025 - 280226) | Q145: Ingreso a Caja 001500000204 Obs: Reversión de documento | R145: DT - Cadena motosierra Lodge | S145: 000000000231 | T145: Ejercicio 2025/2026
C146: Delta | D146: DEL | E146: =+VLOOKUP(F146,Resumen_Base!$B$6:$F$69,5,0) -> Maintenance Lodge | F146: 5252 | G146: Mantenimiento Rep-Lodge | H146: =+D146&F146 -> DEL5252 | I146: 40231 | J146: 27.938194 | K146: 1440 | L146: 09/02/2026 | M146: CAJA | N146: 0141 | O146: TE001500000166 | P146: Asiento de CAJA (01/09/2025 - 280226) | Q146: Extracción de Caja 001500000166 Obs: 09-02-2026 Mov Lodge | R146: DT - Compra Carrefour | S146: 000000000206 | T146: Ejercicio 2025/2026
C147: Delta | D147: DEL | E147: =+VLOOKUP(F147,Resumen_Base!$B$6:$F$69,5,0) -> Maintenance Lodge | F147: 5252 | G147: Mantenimiento Rep-Lodge | H147: =+D147&F147 -> DEL5252 | I147: 73000 | J147: 51.590106 | K147: 1415 | L147: 28/02/2026 | M147: CAJA | N147: 0141 | O147: TE001500000191 | P147: Asiento de CAJA (01/09/2025 - 280226) | Q147: Extracción de Caja 001500000191 Obs: 28-02-2026 Mov Lodge | R147: DT - Compra de pinceles y aguarrás | S147: 000000000218 | T147: Ejercicio 2025/2026
C148: Delta | D148: DEL | E148: =+VLOOKUP(F148,Resumen_Base!$B$6:$F$69,5,0) -> Maintenance Lodge | F148: 5252 | G148: Mantenimiento Rep-Lodge | H148: =+D148&F148 -> DEL5252 | I148: 73000 | J148: 51.590106 | K148: 1415 | L148: 28/02/2026 | M148: CAJA | N148: 0141 | O148: TE001500000192 | P148: Asiento de CAJA (01/09/2025 - 280226) | Q148: Extracción de Caja 001500000192 Obs: 28-02-2026 Mov Lodge | R148: DT - Compra de pinceles y aguarrás | S148: 000000000219 | T148: Ejercicio 2025/2026
... C156: Delta | D156: DEL | E156: =+VLOOKUP(F156,Resumen_Base!$B$6:$F$69,5,0) -> Maintenance Lodge | F156: 5252 | G156: Mantenimiento Rep-Lodge | H156: =+D156&F156 -> DEL5252 | I156: -29275 | J156: -20.689046 | K156: 1415 | L156: 28/02/2026 | M156: CAJA | N156: 0141 | O156: TI001500000204 | P156: Asiento de CAJA (01/09/2025 - 280226) | Q156: Ingreso a Caja 001500000204 Obs: Reversión de documento | R156: DT - Luces para guirnaldas | S156: 000000000231 | T156: Ejercicio 2025/2026
A157: Pasar USD 1000 a M y Utiles cambio termotanqui | B157: 5252Mantenimiento Rep-Lodge | C157: Delta | D157: DEL | E157: =+VLOOKUP(F157,Resumen_Base!$B$6:$F$69,5,0) -> Maintenance Lodge | F157: 5252 | G157: Mantenimiento Rep-Lodge | H157: =+D157&F157 -> DEL5252 | I157: =+J157*K157 -> 570000 | J157: 400 | K157: 1425 | L157: 23/02/2026 | M157: CAJA | N157: 0141 | O157: TE001500000178 | P157: Asiento de CAJA (01/09/2025 - 280226) | Q157: Extracción de Caja 001500000178 Obs: 23-02-2026 Mov Lodge | R157: DT - Pago a Rolando por: primer canilla debajo de casa Noel para limpiar playa, reemplazo de termota | S157: 000000000211 | T157: Ejercicio 2025/2026
A158: Pasar USD 1000 a M y Utiles cambio termotanqui | B158: 5252Mantenimiento Rep-Lodge | C158: Delta | D158: DEL | E158: =+VLOOKUP(F158,Resumen_Base!$B$6:$F$69,5,0) -> Fixed Asset's Payments (Investments) Mejoras/equipamiento Lodge | F158: 12020301 | G158: Muebles y útiles | H158: =+D158&F158 -> DEL12020301 | I158: =+J158*K158 -> 1425000 | J158: 1000 | K158: 1425 | L158: 23/02/2026 | M158: CAJA | N158: 0141 | O158: TE001500000178 | P158: Asiento de CAJA (01/09/2025 - 280226) | Q158: Extracción de Caja 001500000178 Obs: 23-02-2026 Mov Lodge | R158: DT - Pago a Rolando por: primer canilla debajo de casa Noel para limpiar playa, reemplazo de termota | S158: 000000000211 | T158: Ejercicio 2025/2026
C160: Delta | D160: DEL | E160: =+VLOOKUP(F160,Resumen_Base!$B$6:$F$69,5,0) -> Maintenance Lodge | F160: 5252 | G160: Mantenimiento Rep-Lodge | H160: =+D160&F160 -> DEL5252 | I160: 100000 | J160: 69.444444 | K160: 1440 | L160: 09/02/2026 | M160: CAJA | N160: 0141 | O160: TE001500000166 | P160: Asiento de CAJA (01/09/2025 - 280226) | Q160: Extracción de Caja 001500000166 Obs: 09-02-2026 Mov Lodge | R160: DT - Pago adicional a Rolando por llevarse residuos y balanqueria hasta Ecosec 2 veces | S160: 000000000206 | T160: Ejercicio 2025/2026
C161: Delta | D161: DEL | E161: =+VLOOKUP(F161,Resumen_Base!$B$6:$F$69,5,0) -> Maintenance Lodge | F161: 5252 | G161: Mantenimiento Rep-Lodge | H161: =+D161&F161 -> DEL5252 | I161: 12000 | J161: 8.4805654 | K161: 1415 | L161: 28/02/2026 | M161: CAJA | N161: 0141 | O161: TE001500000191 | P161: Asiento de CAJA (01/09/2025 - 280226) | Q161: Extracción de Caja 001500000191 Obs: 28-02-2026 Mov Lodge | R161: DT - Pago Remis a Madero por llevar blanqueria a Ecosec | S161: 000000000218 | T161: Ejercicio 2025/2026
C162: Delta | D162: DEL | E162: =+VLOOKUP(F162,Resumen_Base!$B$6:$F$69,5,0) -> Maintenance Lodge | F162: 5252 | G162: Mantenimiento Rep-Lodge | H162: =+D162&F162 -> DEL5252 | I162: 12000 | J162: 8.4805654 | K162: 1415 | L162: 28/02/2026 | M162: CAJA | N162: 0141 | O162: TE001500000192 | P162: Asiento de CAJA (01/09/2025 - 280226) | Q162: Extracción de Caja 001500000192 Obs: 28-02-2026 Mov Lodge | R162: DT - Pago Remis a Madero por llevar blanqueria a Ecosec | S162: 000000000219 | T162: Ejercicio 2025/2026
C163: Delta | D163: DEL | E163: =+VLOOKUP(F163,Resumen_Base!$B$6:$F$69,5,0) -> Maintenance Lodge | F163: 5252 | G163: Mantenimiento Rep-Lodge | H163: =+D163&F163 -> DEL5252 | I163: -12000 | J163: -8.4805654 | K163: 1415 | L163: 28/02/2026 | M163: CAJA | N163: 0141 | O163: TI001500000204 | P163: Asiento de CAJA (01/09/2025 - 280226) | Q163: Ingreso a Caja 001500000204 Obs: Reversión de documento | R163: DT - Pago Remis a Madero por llevar blanqueria a Ecosec | S163: 000000000231 | T163: Ejercicio 2025/2026
C164: Delta | D164: DEL | E164: =+VLOOKUP(F164,Resumen_Base!$B$6:$F$69,5,0) -> Maintenance Lodge | F164: 5252 | G164: Mantenimiento Rep-Lodge | H164: =+D164&F164 -> DEL5252 | I164: 40000 | J164: 27.777778 | K164: 1440 | L164: 09/02/2026 | M164: CAJA | N164: 0141 | O164: TE001500000166 | P164: Asiento de CAJA (01/09/2025 - 280226) | Q164: Extracción de Caja 001500000166 Obs: 09-02-2026 Mov Lodge | R164: DT - Perfuminas para habitaciones de huéspedes | S164: 000000000206 | T164: Ejercicio 2025/2026
C165: Delta | D165: DEL | E165: =+VLOOKUP(F165,Resumen_Base!$B$6:$F$69,5,0) -> Maintenance Lodge | F165: 5252 | G165: Mantenimiento Rep-Lodge | H165: =+D165&F165 -> DEL5252 | I165: 40000 | J165: 27.777778 | K165: 1440 | L165: 09/02/2026 | M165: CAJA | N165: 0141 | O165: TE001500000166 | P165: Asiento de CAJA (01/09/2025 - 280226) | Q165: Extracción de Caja 001500000166 Obs: 09-02-2026 Mov Lodge | R165: DT - Plantas | S165: 000000000206 | T165: Ejercicio 2025/2026
C166: Delta | D166: DEL | E166: =+VLOOKUP(F166,Resumen_Base!$B$6:$F$69,5,0) -> Maintenance Lodge | F166: 5252 | G166: Mantenimiento Rep-Lodge | H166: =+D166&F166 -> DEL5252 | I166: 13000 | J166: 9.122807 | K166: 1425 | L166: 16/02/2026 | M166: CAJA | N166: 0141 | O166: TE001500000171 | P166: Asiento de CAJA (01/09/2025 - 280226) | Q166: Extracción de Caja 001500000171 Obs: 16-02-2026 Mov Lodge | R166: DT - Reparación arranque motosierra Lodge | S166: 000000000208 | T166: Ejercicio 2025/2026
C167: Delta | D167: DEL | E167: =+VLOOKUP(F167,Resumen_Base!$B$6:$F$69,5,0) -> Maintenance Lodge | F167: 5252 | G167: Mantenimiento Rep-Lodge | H167: =+D167&F167 -> DEL5252 | I167: 20484 | J167: 14.374737 | K167: 1425 | L167: 16/02/2026 | M167: CAJA | N167: 0141 | O167: TE001500000171 | P167: Asiento de CAJA (01/09/2025 - 280226) | Q167: Extracción de Caja 001500000171 Obs: 16-02-2026 Mov Lodge | R167: DT - Repuesto difusor perfumes para habitaciones de huéspedes | S167: 000000000208 | T167: Ejercicio 2025/2026
C168: Delta | D168: DEL | E168: =+VLOOKUP(F168,Resumen_Base!$B$6:$F$69,5,0) -> Maintenance Lodge | F168: 5252 | G168: Mantenimiento Rep-Lodge | H168: =+D168&F168 -> DEL5252 | I168: 19000 | J168: 13.194444 | K168: 1440 | L168: 09/02/2026 | M168: CAJA | N168: 0141 | O168: TE001500000166 | P168: Asiento de CAJA (01/09/2025 - 280226) | Q168: Extracción de Caja 001500000166 Obs: 09-02-2026 Mov Lodge | R168: DT - Repuesto filtro toma de agua de río | S168: 000000000206 | T168: Ejercicio 2025/2026
C169: Delta | D169: DEL | E169: =+VLOOKUP(F169,Resumen_Base!$B$6:$F$69,5,0) -> Maintenance Lodge | F169: 5252 | G169: Mantenimiento Rep-Lodge | H169: =+D169&F169 -> DEL5252 | I169: 81100 | J169: 56.319444 | K169: 1440 | L169: 09/02/2026 | M169: CAJA | N169: 0141 | O169: TE001500000166 | P169: Asiento de CAJA (01/09/2025 - 280226) | Q169: Extracción de Caja 001500000166 Obs: 09-02-2026 Mov Lodge | R169: DT - Repuestos desmalezadora del Lodge, aceite, grasa, cabezal | S169: 000000000206 | T169: Ejercicio 2025/2026
C170: Delta | D170: DEL | E170: =+VLOOKUP(F170,Resumen_Base!$B$6:$F$69,5,0) -> Maintenance Lodge | F170: 5252 | G170: Mantenimiento Rep-Lodge | H170: =+D170&F170 -> DEL5252 | I170: 124085 | J170: 87.69258 | K170: 1415 | L170: 28/02/2026 | M170: CAJA | N170: 0141 | O170: TE001500000191 | P170: Asiento de CAJA (01/09/2025 - 280226) | Q170: Extracción de Caja 001500000191 Obs: 28-02-2026 Mov Lodge | R170: DT - Semillas césped | S170: 000000000218 | T170: Ejercicio 2025/2026
C171: Delta | D171: DEL | E171: =+VLOOKUP(F171,Resumen_Base!$B$6:$F$69,5,0) -> Maintenance Lodge | F171: 5252 | G171: Mantenimiento Rep-Lodge | H171: =+D171&F171 -> DEL5252 | I171: 124085 | J171: 87.69258 | K171: 1415 | L171: 28/02/2026 | M171: CAJA | N171: 0141 | O171: TE001500000192 | P171: Asiento de CAJA (01/09/2025 - 280226) | Q171: Extracción de Caja 001500000192 Obs: 28-02-2026 Mov Lodge | R171: DT - Semillas césped | S171: 000000000219 | T171: Ejercicio 2025/2026
... C226: Delta | D226: DEL | E226: =+VLOOKUP(F226,Resumen_Base!$B$6:$F$69,5,0) -> Food & Wine | F226: 5257 | G226: Bebidas Blncas,Cervzas y Gaseo | H226: =+D226&F226 -> DEL5257 | I226: 70000 | J226: 49.122807 | K226: 1425 | L226: 16/02/2026 | M226: CAJA | N226: 0141 | O226: TE001500000171 | P226: Asiento de CAJA (01/09/2025 - 280226) | Q226: Extracción de Caja 001500000171 Obs: 16-02-2026 Mov Lodge | R226: DT - Hielo para heladoras | S226: 000000000208 | T226: Ejercicio 2025/2026
A227: Pasa a Comida | B227: 5259Combustible y Lub - Leña | C227: Delta | D227: DEL | E227: =+VLOOKUP(F227,Resumen_Base!$B$6:$F$69,5,0) -> Food & Wine | F227: 5250 | G227: Comidas y refrigerios | H227: =+D227&F227 -> DEL5250 | I227: 39000 | J227: 27.561837 | K227: 1415 | L227: 28/02/2026 | M227: CAJA | N227: 0141 | O227: TE001500000191 | P227: Asiento de CAJA (01/09/2025 - 280226) | Q227: Extracción de Caja 001500000191 Obs: 28-02-2026 Mov Lodge | R227: DT - 10 bolsas de carbón | S227: 000000000218 | T227: Ejercicio 2025/2026
A228: Pasa a Comida | B228: 5259Combustible y Lub - Leña | C228: Delta | D228: DEL | E228: =+VLOOKUP(F228,Resumen_Base!$B$6:$F$69,5,0) -> Food & Wine | F228: 5250 | G228: Comidas y refrigerios | H228: =+D228&F228 -> DEL5250 | I228: 39000 | J228: 27.561837 | K228: 1415 | L228: 28/02/2026 | M228: CAJA | N228: 0141 | O228: TE001500000192 | P228: Asiento de CAJA (01/09/2025 - 280226) | Q228: Extracción de Caja 001500000192 Obs: 28-02-2026 Mov Lodge | R228: DT - 10 bolsas de carbón | S228: 000000000219 | T228: Ejercicio 2025/2026
A229: Pasa a Comida | B229: 5259Combustible y Lub - Leña | C229: Delta | D229: DEL | E229: =+VLOOKUP(F229,Resumen_Base!$B$6:$F$69,5,0) -> Food & Wine | F229: 5250 | G229: Comidas y refrigerios | H229: =+D229&F229 -> DEL5250 | I229: -39000 | J229: -27.561837 | K229: 1415 | L229: 28/02/2026 | M229: CAJA | N229: 0141 | O229: TI001500000204 | P229: Asiento de CAJA (01/09/2025 - 280226) | Q229: Ingreso a Caja 001500000204 Obs: Reversión de documento | R229: DT - 10 bolsas de carbón | S229: 000000000231 | T229: Ejercicio 2025/2026
A230: Esto es Comida | B230: 5263Servicios - Otros Operativos | C230: Delta | D230: DEL | E230: =+VLOOKUP(F230,Resumen_Base!$B$6:$F$69,5,0) -> Food & Wine | F230: 5250 | G230: Comidas y refrigerios | H230: =+D230&F230 -> DEL5250 | I230: 15000 | J230: 10.416667 | K230: 1440 | L230: 09/02/2026 | M230: CAJA | N230: 0141 | O230: TE001500000166 | P230: Asiento de CAJA (01/09/2025 - 280226) | Q230: Extracción de Caja 001500000166 Obs: 09-02-2026 Mov Lodge | R230: DT - Ayuda de carga y descarga en guardería la Baie día de compras | S230: 000000000206 | T230: Ejercicio 2025/2026
C231: Delta | D231: DEL | E231: =+VLOOKUP(F231,Resumen_Base!$B$6:$F$69,5,0) -> Miscellaneous & Shipping | F231: 5263 | G231: Servicios - Otros Operativos | H231: =+D231&F231 -> DEL5263 | I231: 140000 | J231: 98.245614 | K231: 1425 | L231: 16/02/2026 | M231: CAJA | N231: 0141 | O231: TE001500000171 | P231: Asiento de CAJA (01/09/2025 - 280226) | Q231: Extracción de Caja 001500000171 Obs: 16-02-2026 Mov Lodge | R231: DT - Pago a Rolando por hacernos compras, llevarse residuos del Lodge y llevar y traer blanqueria | S231: 000000000208 | T231: Ejercicio 2025/2026
C232: Delta | D232: DEL | E232: =+VLOOKUP(F232,Resumen_Base!$B$6:$F$69,5,0) -> Miscellaneous & Shipping | F232: 5263 | G232: Servicios - Otros Operativos | H232: =+D232&F232 -> DEL5263 | I232: 120000 | J232: 84.210526 | K232: 1425 | L232: 23/02/2026 | M232: CAJA | N232: 0141 | O232: TE001500000179 | P232: Asiento de CAJA (01/09/2025 - 280226) | Q232: Extracción de Caja 001500000179 Obs: 23-02-2026 Mov Lodge | R232: DT - Pago adicional a Rolando por logística de blanqueria, residuos y hacer y traernos compras | S232: 000000000212 | T232: Ejercicio 2025/2026
A233: Esto es comida | B233: 5263Servicios - Otros Operativos | C233: Delta | D233: DEL | E233: =+VLOOKUP(F233,Resumen_Base!$B$6:$F$69,5,0) -> Food & Wine | F233: 5250 | G233: Comidas y refrigerios | H233: =+D233&F233 -> DEL5250 | I233: 25000 | J233: 17.361111 | K233: 1440 | L233: 09/02/2026 | M233: CAJA | N233: 0141 | O233: TE001500000166 | P233: Asiento de CAJA (01/09/2025 - 280226) | Q233: Extracción de Caja 001500000166 Obs: 09-02-2026 Mov Lodge | R233: DT - Pago Remis Madero camioneta soporte día de compras | S233: 000000000206 | T233: Ejercicio 2025/2026
C234: Delta | D234: DEL | E234: =+VLOOKUP(F234,Resumen_Base!$B$6:$F$69,5,0) -> Miscellaneous & Shipping | F234: 5263 | G234: Servicios - Otros Operativos | H234: =+D234&F234 -> DEL5263 | I234: 350000 | J234: 245.61404 | K234: 1425 | L234: 20/02/2026 | M234: CAJA | N234: 0141 | O234: TE001500000187 | P234: Asiento de CAJA (01/09/2025 - 280226) | Q234: Extracción de Caja 001500000187 Obs: Movimiento_Cajas_Bancos_Semana 25-26 al 20-02-2026 | R234: DT-Servicio Mensajeria Mensual Enlace - Enero F.Fijo Oper. Al 20-02-2026 | S234: 000000000216 | T234: Ejercicio 2025/2026
C235: Delta | D235: DEL | E235: =+VLOOKUP(F235,Resumen_Base!$B$6:$F$69,5,0) -> Maintenance Lodge | F235: 5283 | G235: Mantenimiento Comida Perros | H235: =+D235&F235 -> DEL5283 | I235: 39996 | J235: 27.775 | K235: 1440 | L235: 09/02/2026 | M235: CAJA | N235: 0141 | O235: TE001500000166 | P235: Asiento de CAJA (01/09/2025 - 280226) | Q235: Extracción de Caja 001500000166 Obs: 09-02-2026 Mov Lodge | R235: DT - Alimento mascotas | S235: 000000000206 | T235: Ejercicio 2025/2026
C236: Delta | D236: DEL | E236: =+VLOOKUP(F236,Resumen_Base!$B$6:$F$69,5,0) -> Maintenance Lodge | F236: 5283 | G236: Mantenimiento Comida Perros | H236: =+D236&F236 -> DEL5283 | I236: 14400 | J236: 10 | K236: 1440 | L236: 09/02/2026 | M236: CAJA | N236: 0141 | O236: TE001500000166 | P236: Asiento de CAJA (01/09/2025 - 280226) | Q236: Extracción de Caja 001500000166 Obs: 09-02-2026 Mov Lodge | R236: DT - Alimento mascotas | S236: 000000000206 | T236: Ejercicio 2025/2026
C237: Delta | D237: DEL | E237: =+VLOOKUP(F237,Resumen_Base!$B$6:$F$69,5,0) -> Food & Wine | F237: 5289 | G237: Comidas Fuera Temp / Empleados | H237: =+D237&F237 -> DEL5289 | I237: 11700 | J237: 8.2105263 | K237: 1425 | L237: 16/02/2026 | M237: CAJA | N237: 0141 | O237: TE001500000171 | P237: Asiento de CAJA (01/09/2025 - 280226) | Q237: Extracción de Caja 001500000171 Obs: 16-02-2026 Mov Lodge | R237: DT - Pan para personal | S237: 000000000208 | T237: Ejercicio 2025/2026
C238: Delta | D238: DEL | E238: =+VLOOKUP(F238,Resumen_Base!$B$6:$F$69,5,0) -> Food & Wine | F238: 5289 | G238: Comidas Fuera Temp / Empleados | H238: =+D238&F238 -> DEL5289 | I238: 36900 | J238: 25.625 | K238: 1440 | L238: 09/02/2026 | M238: CAJA | N238: 0141 | O238: TE001500000166 | P238: Asiento de CAJA (01/09/2025 - 280226) | Q238: Extracción de Caja 001500000166 Obs: 09-02-2026 Mov Lodge | R238: DT - pan personal | S238: 000000000206 | T238: Ejercicio 2025/2026
C239: Delta | D239: DEL | E239: =+VLOOKUP(F239,Resumen_Base!$B$6:$F$69,5,0) -> Food & Wine | F239: 5289 | G239: Comidas Fuera Temp / Empleados | H239: =+D239&F239 -> DEL5289 | I239: 46900 | J239: 33.144876 | K239: 1415 | L239: 28/02/2026 | M239: CAJA | N239: 0141 | O239: TE001500000191 | P239: Asiento de CAJA (01/09/2025 - 280226) | Q239: Extracción de Caja 001500000191 Obs: 28-02-2026 Mov Lodge | R239: DT - Panadería personal | S239: 000000000218 | T239: Ejercicio 2025/2026
C240: Delta | D240: DEL | E240: =+VLOOKUP(F240,Resumen_Base!$B$6:$F$69,5,0) -> Food & Wine | F240: 5289 | G240: Comidas Fuera Temp / Empleados | H240: =+D240&F240 -> DEL5289 | I240: 46900 | J240: 33.144876 | K240: 1415 | L240: 28/02/2026 | M240: CAJA | N240: 0141 | O240: TE001500000192 | P240: Asiento de CAJA (01/09/2025 - 280226) | Q240: Extracción de Caja 001500000192 Obs: 28-02-2026 Mov Lodge | R240: DT - Panadería personal | S240: 000000000219 | T240: Ejercicio 2025/2026
C241: Delta | D241: DEL | E241: =+VLOOKUP(F241,Resumen_Base!$B$6:$F$69,5,0) -> Food & Wine | F241: 5289 | G241: Comidas Fuera Temp / Empleados | H241: =+D241&F241 -> DEL5289 | I241: -46900 | J241: -33.144876 | K241: 1415 | L241: 28/02/2026 | M241: CAJA | N241: 0141 | O241: TI001500000204 | P241: Asiento de CAJA (01/09/2025 - 280226) | Q241: Ingreso a Caja 001500000204 Obs: Reversión de documento | R241: DT - Panadería personal | S241: 000000000231 | T241: Ejercicio 2025/2026
C242: Delta | D242: DEL | E242: =+VLOOKUP(F242,Resumen_Base!$B$6:$F$69,5,0) -> Food & Wine | F242: 5291 | G242: Comida / Fletes | H242: =+D242&F242 -> DEL5291 | I242: 40000 | J242: 28.268551 | K242: 1415 | L242: 28/02/2026 | M242: CAJA | N242: 0141 | O242: TE001500000191 | P242: Asiento de CAJA (01/09/2025 - 280226) | Q242: Extracción de Caja 001500000191 Obs: 28-02-2026 Mov Lodge | R242: DT - Pago ayuda carga descarga compras mayoristas en la Baie | S242: 000000000218 | T242: Ejercicio 2025/2026
C243: Delta | D243: DEL | E243: =+VLOOKUP(F243,Resumen_Base!$B$6:$F$69,5,0) -> Food & Wine | F243: 5291 | G243: Comida / Fletes | H243: =+D243&F243 -> DEL5291 | I243: 40000 | J243: 28.268551 | K243: 1415 | L243: 28/02/2026 | M243: CAJA | N243: 0141 | O243: TE001500000192 | P243: Asiento de CAJA (01/09/2025 - 280226) | Q243: Extracción de Caja 001500000192 Obs: 28-02-2026 Mov Lodge | R243: DT - Pago ayuda carga descarga compras mayoristas en la Baie | S243: 000000000219 | T243: Ejercicio 2025/2026
C244: Delta | D244: DEL | E244: =+VLOOKUP(F244,Resumen_Base!$B$6:$F$69,5,0) -> Food & Wine | F244: 5291 | G244: Comida / Fletes | H244: =+D244&F244 -> DEL5291 | I244: -40000 | J244: -28.268551 | K244: 1415 | L244: 28/02/2026 | M244: CAJA | N244: 0141 | O244: TI001500000204 | P244: Asiento de CAJA (01/09/2025 - 280226) | Q244: Ingreso a Caja 001500000204 Obs: Reversión de documento | R244: DT - Pago ayuda carga descarga compras mayoristas en la Baie | S244: 000000000231 | T244: Ejercicio 2025/2026
C245: Delta | D245: DEL | E245: =+VLOOKUP(F245,Resumen_Base!$B$6:$F$69,5,0) -> Food & Wine | F245: 5291 | G245: Comida / Fletes | H245: =+D245&F245 -> DEL5291 | I245: 76000 | J245: 53.710247 | K245: 1415 | L245: 28/02/2026 | M245: CAJA | N245: 0141 | O245: TE001500000191 | P245: Asiento de CAJA (01/09/2025 - 280226) | Q245: Extracción de Caja 001500000191 Obs: 28-02-2026 Mov Lodge | R245: DT - Pago total a Remis Madero en día de compras por utilitarios para compras mayorista pasos, carne | S245: 000000000218 | T245: Ejercicio 2025/2026
... C251: Delta | D251: DEL | E251: =+VLOOKUP(F251,Resumen_Base!$B$6:$F$69,5,0) -> Food & Wine | F251: 5291 | G251: Comida / Fletes | H251: =+D251&F251 -> DEL5291 | I251: -4400 | J251: -3.1095406 | K251: 1415 | L251: 28/02/2026 | M251: CAJA | N251: 0141 | O251: TI001500000204 | P251: Asiento de CAJA (01/09/2025 - 280226) | Q251: Ingreso a Caja 001500000204 Obs: Reversión de documento | R251: DT - Uber con compras de Carrefour a Baie | S251: 000000000231 | T251: Ejercicio 2025/2026
A254: reimputar de Sueldo Guías a costo transfer unos usd 800 de 4 transfers de Pablo | C254: Delta | D254: DEL | E254: =+VLOOKUP(F254,Resumen_Base!$B$6:$F$69,5,0) -> Guides | F254: 5227 | G254: Remuneraciones Guías | H254: =+D254&F254 -> DEL5227 | J254: -800 | L254: 46081 | M254: CAJA | N254: 0141
A255: 280 usd de sueldo guias a Combustible vehículos-botes. | C255: Delta | D255: DEL | E255: =+VLOOKUP(F255,Resumen_Base!$B$6:$F$69,5,0) -> Guides | F255: 5227 | G255: Remuneraciones Guías | H255: =+D255&F255 -> DEL5227 | J255: -280 | L255: 46081 | M255: CAJA | N255: 0141
A256: 280 usd de sueldo guias a Combustible vehículos-botes. | C256: Delta | D256: DEL | E256: =+VLOOKUP(F256,Resumen_Base!$B$6:$F$69,5,0) -> Electricity - Gas for Boats & Vehicles | F256: 5248 | G256: Combustibles y Lub. - Vehiculos y Botes | H256: =+D256&F256 -> DEL5248 | J256: 280 | L256: 46081 | M256: CAJA | N256: 0141
A259: INSERT | B259: INSERT | C259: INSERT | D259: INSERT | E259: INSERT | F259: INSERT | G259: INSERT | H259: INSERT | I259: INSERT | J259: INSERT | K259: INSERT | L259: INSERT | M259: INSERT | N259: INSERT | O259: INSERT | P259: INSERT | Q259: INSERT | R259: INSERT | S259: INSERT | T259: INSERT | U259: INSERT | V259: INSERT | W259: INSERT
A262: reimputar de Sueldo Guías a costo transfer unos usd 800 de 4 transfers de Pablo | F262: 5210 | G262: Traslado Aerop. Lodge | J262: 800 | L262: 46081 | M262: CAJA | N262: 0141
A263: De este movimiento pasar usd 350 a costo transfers | F263: 5210 | G263: Traslado Aerop. Lodge | I263: =+J263*K263 -> 504000 | J263: 350 | K263: 1440 | L263: 09/02/2026 | M263: CAJA | N263: 0141 | O263: TE001500000167 | P263: Asiento de CAJA (01/09/2025 - 280226) | Q263: Extracción de Caja 001500000167 Obs: 09-02-2026 Mov Lodge | R263: DT - Pago a Pablo guia por 3 full day + 1 Transfer | S263: 000000000207 | T263: Ejercicio 2025/2026
C265: Delta | F265: 11010101 | G265: Caja $ Administración | I265: 2500000 | J265: 1736.1111 | K265: 1440 | L265: 06/02/2026 | M265: CAJA | N265: 0149 | O265: TA001500000168 | P265: Asiento de CAJA (01/09/2025 - 280226) | Q265: Canje de Valores 001500000168 Obs: DEL-Cambio $ 2,500,000 | R265: Canje de Valores 001500000168 Obs: DEL-Cambio $ 2,500,000 | S265: 000000000202 | T265: Ejercicio 2025/2026
C266: Delta | F266: 11010101 | G266: Caja $ Administración | I266: 2200000 | J266: 1543.8596 | K266: 1425 | L266: 13/02/2026 | M266: CAJA | N266: 0149 | O266: TA001500000172 | P266: Asiento de CAJA (01/09/2025 - 280226) | Q266: Canje de Valores 001500000172 Obs: DEL-Cambio $ 2,200,000 | R266: Canje de Valores 001500000172 Obs: DEL-Cambio $ 2,200,000 | S266: 000000000203 | T266: Ejercicio 2025/2026
C267: Delta | F267: 11010101 | G267: Caja $ Administración | I267: 1100000 | J267: 771.92982 | K267: 1425 | L267: 20/02/2026 | M267: CAJA | N267: 0149 | O267: TA001500000182 | P267: Asiento de CAJA (01/09/2025 - 280226) | Q267: Canje de Valores 001500000182 Obs: DEL-Cambio $ 1,100,000 | R267: Canje de Valores 001500000182 Obs: DEL-Cambio $ 1,100,000 | S267: 000000000204 | T267: Ejercicio 2025/2026
C268: Delta | F268: 11010101 | G268: Caja $ Administración | I268: 7100000 | J268: 5017.6678 | K268: 1415 | L268: 27/02/2026 | M268: CAJA | N268: 0149 | O268: TA001500000193 | P268: Asiento de CAJA (01/09/2025 - 280226) | Q268: Canje de Valores 001500000193 Obs: DEL-Cambio $ 7,100,000 | R268: Canje de Valores 001500000193 Obs: DEL-Cambio $ 7,100,000 | S268: 000000000205 | T268: Ejercicio 2025/2026
C269: Delta | F269: 11010101 | G269: Caja $ Administración | I269: -257724 | J269: -180.85895 | K269: 1425 | L269: 20/02/2026 | M269: CAJA | N269: 0141 | O269: TE001500000187 | P269: Asiento de CAJA (01/09/2025 - 280226) | Q269: Extracción de Caja 001500000187 Obs: Movimiento_Cajas_Bancos_Semana 25-26 al 20-02-2026 | R269: DT-2 Cámara de Seguridad Solar Gadnic Lente Dual FHD Conexion Inalambrica Panel Solar Visión Nocturn | S269: 000000000216 | T269: Ejercicio 2025/2026
C270: Delta | F270: 11010101 | G270: Caja $ Administración | I270: -40088 | J270: -28.13193 | K270: 1425 | L270: 20/02/2026 | M270: CAJA | N270: 0141 | O270: TE001500000187 | P270: Asiento de CAJA (01/09/2025 - 280226) | Q270: Extracción de Caja 001500000187 Obs: Movimiento_Cajas_Bancos_Semana 25-26 al 20-02-2026 | R270: DT-4 Cajon Cosechero Canasto Plastico Apilable Super Reforzado Vc Negro F.Fijo Oper. Al 20-02-2026 | S270: 000000000216 | T270: Ejercicio 2025/2026
C271: Delta | F271: 11010101 | G271: Caja $ Administración | I271: -53014 | J271: -37.202807 | K271: 1425 | L271: 20/02/2026 | M271: CAJA | N271: 0141 | O271: TE001500000187 | P271: Asiento de CAJA (01/09/2025 - 280226) | Q271: Extracción de Caja 001500000187 Obs: Movimiento_Cajas_Bancos_Semana 25-26 al 20-02-2026 | R271: DT-4 Pan Lactal 24x10x10 Sin Tapa Cocina Panaderia Pizzeria Molde Gris F.Fijo Oper. Al 20-02-2026 | S271: 000000000216 | T271: Ejercicio 2025/2026
C272: Delta | F272: 11010101 | G272: Caja $ Administración | I272: -323000 | J272: -228.26855 | K272: 1415 | L272: 28/02/2026 | M272: CAJA | N272: 0141 | O272: TE001500000201 | P272: Asiento de CAJA (01/09/2025 - 280226) | Q272: Extracción de Caja 001500000201 Obs: Movimiento_Cajas_Bancos_Semana 25-26 al 06-03-2026 | R272: DT-Alexis Carra - Honorarios mantenimiento Febrero 2026 Pagos Frank Garrahan- Al 06-03-2026 | S272: 000000000223 | T272: Ejercicio 2025/2026
C273: Delta | F273: 11010101 | G273: Caja $ Administración | I273: -5760000 | J273: -4070.6714 | K273: 1415 | L273: 27/02/2026 | M273: CAJA | N273: 0141 | O273: TE001500000195 | P273: Asiento de CAJA (01/09/2025 - 280226) | Q273: Extracción de Caja 001500000195 Obs: Movimiento_Cajas_Bancos_Semana 25-26 al 27-02-2026 | R273: DT-Caja Lodge F.Fijo Oper. Al 27-02-2026 | S273: 000000000221 | T273: Ejercicio 2025/2026
C274: Delta | F274: 11010101 | G274: Caja $ Administración | I274: -2059263 | J274: -1445.0968 | K274: 1425 | L274: 13/02/2026 | M274: CAJA | N274: 0141 | O274: TE001500000177 | P274: Asiento de CAJA (01/09/2025 - 280226) | Q274: Extracción de Caja 001500000177 Obs: Movimiento_Cajas_Bancos_Semana 25-26 al 13-02-2026 | R274: DT-Carnes y Verduras - Segunda Quincena Enero Pagos Depsa Valores. Al 13-02-2026 | S274: 000000000210 | T274: Ejercicio 2025/2026
...

Sheet Mov_Analizados_Mar26
G2: Ver Telefonos
G3: Ver Gastos devengados | I3: $ | J3: USD | K3: TC
G4: Ver Luz Devengada | H4: Food & Wine | I4: =+SUMIF($E$10:$E$138,H4,$I$10:$I$138) -> 6490170 | J4: =+SUMIF($E$10:$E$138,H4,$J$10:$J$138) -> 4622.3707 | K4: =+I4/J4 -> 1404.0782
G7: =+IF(I7+J7=0,"Ok","Check") -> Ok | I7: =ROUND(SUM(I10:I318),0)+2 -> 0 | J7: =ROUND(SUM(J10:J318),0) -> 0
E8: Rubro | G8: =+Resumen_Base!C1 -> Ok
B9: =+F9&G9 | D9: DEL | E9: =+VLOOKUP(F9,Resumen_Base!$B$6:$F$69,5,0) -> #N/A | H9: =+D9&F9 -> DEL | I9: =SUM(I10:I138) -> 33993184 | J9: =SUM(J10:J138) -> 24157.839
B10: Cuenta Anterior | D10: Lodge | E10: Concepto | F10: Cuenta | G10: Nombre | I10: monto $ | J10: monto USD | K10: TC | L10: Fecha | M10: Subdiario | N10: Div | O10: Datos del comprobante | P10: Sujeto | Q10: CUIT | R10: Observación asiento | S10: Clase de Asiento | T10: Origen del comprobante | U10: Observación del comprobante | V10: Comentario renglón asiento | W10: Asiento | X10: Control | Z10: monto USD | AA10: tc | AC10: Fecha | AD10: Subdiario | AE10: Div | AF10: Datos del comprobante | AG10: Sujeto | AH10: CUIT | AI10: Observación asiento | AJ10: Clase de Asiento | AK10: Origen del comprobante | AL10: Observación del comprobante | AM10: Comentario renglón asiento | AN10: Asiento
C13: Delta | D13: DEL | E13: =+VLOOKUP(F13,Resumen_Base!$B$6:$F$69,5,0) -> Communications - Phone, internet and satellite TV | F13: 5209 | G13: Comunicaciones e Internet | H13: =+D13&F13 -> DEL5209 | I13: 4973.7 | J13: 3.54 | K13: 1405 | L13: 31/03/2026 | M13: CAJA | N13: 0141 | O13: Extracción de Caja | P13: TE001500000226 | Q13: Extracción de Caja 001500000226 Obs: Movimiento_Cajas_Bancos_Semana 25-26 al 03-04-2026 | S13: DT- TriSW- AMEX - Marzo 2026- =DLOSPOTIFY CABA AR- -02/27/2026
C14: Delta | D14: DEL | E14: =+VLOOKUP(F14,Resumen_Base!$B$6:$F$69,5,0) -> Communications - Phone, internet and satellite TV | F14: 5209 | G14: Comunicaciones e Internet | H14: =+D14&F14 -> DEL5209 | I14: 38567.25 | J14: 27.45 | K14: 1405 | L14: 31/03/2026 | M14: CAJA | N14: 0141 | O14: Extracción de Caja | P14: TE001500000226 | Q14: Extracción de Caja 001500000226 Obs: Movimiento_Cajas_Bancos_Semana 25-26 al 03-04-2026 | S14: DT- TriSW- AMEX - Marzo 2026- =DLOSTARLINK CABA AR- -02/23/2026
C15: Delta | D15: DEL | E15: =+VLOOKUP(F15,Resumen_Base!$B$6:$F$69,5,0) -> Electricity | F15: 5259 | G15: Combustible y Lub - Leña | H15: =+D15&F15 -> DEL5259 | I15: 8600 | J15: 6.1428571 | K15: 1400 | L15: 16/03/2026 | M15: CAJA | N15: 0141 | O15: Extracción de Caja | P15: TE001500000207 | Q15: Extracción de Caja 001500000207 Obs: 16-03-2026 Mov Lodge | S15: DT - Carbón
C16: Delta | D16: DEL | E16: =+VLOOKUP(F16,Resumen_Base!$B$6:$F$69,5,0) -> Electricity | F16: 5247 | G16: Combustible y Lub- Elect-Gener | H16: =+D16&F16 -> DEL5247 | I16: 79200 | J16: 55.971731 | K16: 1415 | L16: 23/03/2026 | M16: CAJA | N16: 0141 | O16: Extracción de Caja | P16: TE001500000214 | Q16: Extracción de Caja 001500000214 Obs: 23-03-2026 Mov Lodge | S16: DT - Nafta generadores
C17: Delta | D17: DEL | E17: =+VLOOKUP(F17,Resumen_Base!$B$6:$F$69,5,0) -> Electricity | F17: 5247 | G17: Combustible y Lub- Elect-Gener | H17: =+D17&F17 -> DEL5247 | I17: 117000 | J17: 83.274021 | K17: 1405 | L17: 31/03/2026 | M17: CAJA | N17: 0141 | O17: Extracción de Caja | P17: TE001500000223 | Q17: Extracción de Caja 001500000223 Obs: 31-03-2026 Mov Lodge | S17: DT - Nafta generadores
C18: Delta | D18: DEL | E18: =+VLOOKUP(F18,Resumen_Base!$B$6:$F$69,5,0) -> Electricity - Gas for Boats & Vehicles | F18: 5248 | G18: Combustible y Lub-Vehiculo Bot | H18: =+D18&F18 -> DEL5248 | I18: 198000 | J18: 140.42553 | K18: 1410 | L18: 09/03/2026 | M18: CAJA | N18: 0141 | O18: Extracción de Caja | P18: TE001500000198 | Q18: Extracción de Caja 001500000198 Obs: 09-03-2026 Mov Lodge | S18: DT - Nafta almacén Alejandro compra Noel para guiada por Uruguay
C19: Delta | D19: DEL | E19: =+VLOOKUP(F19,Resumen_Base!$B$6:$F$69,5,0) -> Electricity - Gas for Boats & Vehicles | F19: 5248 | G19: Combustible y Lub-Vehiculo Bot | H19: =+D19&F19 -> DEL5248 | I19: 229354 | J19: 162.66241 | K19: 1410 | L19: 09/03/2026 | M19: CAJA | N19: 0141 | O19: Extracción de Caja | P19: TE001500000198 | Q19: Extracción de Caja 001500000198 Obs: 09-03-2026 Mov Lodge | S19: DT - Nafta compra Noe
C20: Delta | D20: DEL | E20: =+VLOOKUP(F20,Resumen_Base!$B$6:$F$69,5,0) -> Electricity - Gas for Boats & Vehicles | F20: 5248 | G20: Combustible y Lub-Vehiculo Bot | H20: =+D20&F20 -> DEL5248 | I20: 167194 | J20: 118.5773 | K20: 1410 | L20: 09/03/2026 | M20: CAJA | N20: 0141 | O20: Extracción de Caja | P20: TE001500000198 | Q20: Extracción de Caja 001500000198 Obs: 09-03-2026 Mov Lodge | S20: DT - Nafta compra Noel
C21: Delta | D21: DEL | E21: =+VLOOKUP(F21,Resumen_Base!$B$6:$F$69,5,0) -> Electricity - Gas for Boats & Vehicles | F21: 5248 | G21: Combustible y Lub-Vehiculo Bot | H21: =+D21&F21 -> DEL5248 | I21: 40011 | J21: 28.276325 | K21: 1415 | L21: 23/03/2026 | M21: CAJA | N21: 0141 | O21: Extracción de Caja | P21: TE001500000214 | Q21: Extracción de Caja 001500000214 Obs: 23-03-2026 Mov Lodge | S21: DT - Nafta lancha
C22: Delta | D22: DEL | E22: =+VLOOKUP(F22,Resumen_Base!$B$6:$F$69,5,0) -> Electricity - Gas for Boats & Vehicles | F22: 5248 | G22: Combustible y Lub-Vehiculo Bot | H22: =+D22&F22 -> DEL5248 | I22: 77000 | J22: 54.416961 | K22: 1415 | L22: 23/03/2026 | M22: CAJA | N22: 0141 | O22: Extracción de Caja | P22: TE001500000214 | Q22: Extracción de Caja 001500000214 Obs: 23-03-2026 Mov Lodge | S22: DT - Nafta lancha
C23: Delta | D23: DEL | E23: =+VLOOKUP(F23,Resumen_Base!$B$6:$F$69,5,0) -> Electricity - Gas for Boats & Vehicles | F23: 5248 | G23: Combustible y Lub-Vehiculo Bot | H23: =+D23&F23 -> DEL5248 | I23: 167000 | J23: 118.86121 | K23: 1405 | L23: 31/03/2026 | M23: CAJA | N23: 0141 | O23: Extracción de Caja | P23: TE001500000223 | Q23: Extracción de Caja 001500000223 Obs: 31-03-2026 Mov Lodge | S23: DT - Nafta lancha lodge
C24: Delta | D24: DEL | E24: =+VLOOKUP(F24,Resumen_Base!$B$6:$F$69,5,0) -> Electricity - Gas for Boats & Vehicles | F24: 5248 | G24: Combustible y Lub-Vehiculo Bot | H24: =+D24&F24 -> DEL5248 | I24: 110000 | J24: 78.291815 | K24: 1405 | L24: 31/03/2026 | M24: CAJA | N24: 0141 | O24: Extracción de Caja | P24: TE001500000223 | Q24: Extracción de Caja 001500000223 Obs: 31-03-2026 Mov Lodge | S24: DT - Nafta lancha lodge
... C119: Delta | D119: DEL | E119: =+VLOOKUP(F119,Resumen_Base!$B$6:$F$69,5,0) -> Services/House | F119: 5226 | G119: Remuneraciones Servicios | H119: =+D119&F119 -> DEL5226 | I119: 1584800 | J119: 1120 | K119: 1415 | L119: 23/03/2026 | M119: CAJA | N119: 0141 | O119: Extracción de Caja | P119: TE001500000215 | Q119: Extracción de Caja 001500000215 Obs: 23-03-2026 Mov Lodge | S119: DT - Pago salario Karina mucama camarera mes febrero
C120: Delta | D120: DEL | E120: =+VLOOKUP(F120,Resumen_Base!$B$6:$F$69,5,0) -> Shop | F120: 4104 | G120: Ventas Shop | H120: =+D120&F120 -> DEL4104 | I120: -91975 | J120: -65 | K120: 1415 | L120: 23/03/2026 | M120: VENTAS | N120: 0141 | O120: Factura de Venta | P120: 0001500000023 | Q120: F B 000000006320 | S120: Ref. nota de Venta: DEL25 Obs.:23-03-2026_CLIENTES | T120: 000000000252
C121: Delta | D121: DEL | E121: =+VLOOKUP(F121,Resumen_Base!$B$6:$F$69,5,0) -> Shop | F121: 4104 | G121: Ventas Shop | H121: =+D121&F121 -> DEL4104 | I121: -245000 | J121: -175 | K121: 1400 | L121: 16/03/2026 | M121: VENTAS | N121: 0141 | O121: Factura de Venta | P121: 0001500000022 | Q121: F B 000000005969 | S121: Ref. nota de Venta: DEL78 Obs.:16-03-2026_CLIENTES | T121: 000000000251
C122: Delta | D122: DEL | E122: =+VLOOKUP(F122,Resumen_Base!$B$6:$F$69,5,0) -> Shop | F122: 4104 | G122: Ventas Shop | H122: =+D122&F122 -> DEL4104 | I122: -133000 | J122: -95 | K122: 1400 | L122: 16/03/2026 | M122: VENTAS | N122: 0141 | O122: Factura de Venta | P122: 0001500000022 | Q122: F B 000000005969 | S122: Ref. nota de Venta: DEL78 Obs.:16-03-2026_CLIENTES | T122: 000000000251
C123: Delta | D123: DEL | E123: =+VLOOKUP(F123,Resumen_Base!$B$6:$F$69,5,0) -> Shop | F123: 4104 | G123: Ventas Shop | H123: =+D123&F123 -> DEL4104 | I123: -33600 | J123: -24 | K123: 1400 | L123: 16/03/2026 | M123: VENTAS | N123: 0141 | O123: Factura de Venta | P123: 0001500000022 | Q123: F B 000000005969 | S123: Ref. nota de Venta: DEL78 Obs.:16-03-2026_CLIENTES | T123: 000000000251
C124: Delta | D124: DEL | E124: =+VLOOKUP(F124,Resumen_Base!$B$6:$F$69,5,0) -> Social Security Contributions | F124: 5237 | G124: Cargas Sociales Managers | H124: =+D124&F124 -> DEL5237 | I124: 276785 | J124: 197 | K124: 1405 | L124: 31/03/2026 | M124: CAJA | N124: 0141 | O124: Extracción de Caja | P124: TE001500000226 | Q124: Extracción de Caja 001500000226 Obs: Movimiento_Cajas_Bancos_Semana 25-26 al 03-04-2026 | S124: DEL- Reintegro Cargas Sociales TA 03-2026 - Managers
C125: Delta | D125: DEL | E125: =+VLOOKUP(F125,Resumen_Base!$B$6:$F$69,5,0) -> Social Security Contributions | F125: 5235 | G125: Cargas Sociales Servicios | H125: =+D125&F125 -> DEL5235 | I125: 783990 | J125: 558 | K125: 1405 | L125: 31/03/2026 | M125: CAJA | N125: 0141 | O125: Extracción de Caja | P125: TE001500000226 | Q125: Extracción de Caja 001500000226 Obs: Movimiento_Cajas_Bancos_Semana 25-26 al 03-04-2026 | S125: DEL- Reintegro Cargas Sociales TA 03-2026 - Servicios
C126: Delta | D126: DEL | E126: =+VLOOKUP(F126,Resumen_Base!$B$6:$F$69,5,0) -> Travel for personnel (employees) | F126: 5255 | G126: Movilidad y Viaticos-Locales | H126: =+D126&F126 -> DEL5255 | I126: 43200 | J126: 30.530035 | K126: 1415 | L126: 23/03/2026 | M126: CAJA | N126: 0141 | O126: Extracción de Caja | P126: TE001500000214 | Q126: Extracción de Caja 001500000214 Obs: 23-03-2026 Mov Lodge | S126: DT - Almuerzo en tigre Noel
C127: Delta | D127: DEL | E127: =+VLOOKUP(F127,Resumen_Base!$B$6:$F$69,5,0) -> Travel for personnel (employees) | F127: 5255 | G127: Movilidad y Viaticos-Locales | H127: =+D127&F127 -> DEL5255 | I127: 20000 | J127: 14.285714 | K127: 1400 | L127: 16/03/2026 | M127: CAJA | N127: 0141 | O127: Extracción de Caja | P127: TE001500000207 | Q127: Extracción de Caja 001500000207 Obs: 16-03-2026 Mov Lodge | S127: DT - Pago adicional a Alexis por ir a buscar a Fabián guía a la hostería los Pecanes
C128: Delta | D128: DEL | E128: =+VLOOKUP(F128,Resumen_Base!$B$6:$F$69,5,0) -> Travel for personnel (employees) | F128: 5255 | G128: Movilidad y Viaticos-Locales | H128: =+D128&F128 -> DEL5255 | I128: 900 | J128: 0.6360424 | K128: 1415 | L128: 23/03/2026 | M128: CAJA | N128: 0141 | O128: Extracción de Caja | P128: TE001500000214 | Q128: Extracción de Caja 001500000214 Obs: 23-03-2026 Mov Lodge | S128: DT - Peaje Noel
C129: Delta | D129: DEL | E129: =+VLOOKUP(F129,Resumen_Base!$B$6:$F$69,5,0) -> Travel for personnel (employees) | F129: 5255 | G129: Movilidad y Viaticos-Locales | H129: =+D129&F129 -> DEL5255 | I129: 48600 | J129: 34.714286 | K129: 1400 | L129: 16/03/2026 | M129: CAJA | N129: 0141 | O129: Extracción de Caja | P129: TE001500000207 | Q129: Extracción de Caja 001500000207 Obs: 16-03-2026 Mov Lodge | S129: DT - Viaticos Fabián guía
C130: Delta | D130: DEL | E130: =+VLOOKUP(F130,Resumen_Base!$B$6:$F$69,5,0) -> Travel for personnel (employees) | F130: 5255 | G130: Movilidad y Viaticos-Locales | H130: =+D130&F130 -> DEL5255 | I130: 33600 | J130: 23.829787 | K130: 1410 | L130: 09/03/2026 | M130: CAJA | N130: 0141 | O130: Extracción de Caja | P130: TE001500000198 | Q130: Extracción de Caja 001500000198 Obs: 09-03-2026 Mov Lodge | S130: DT - Viaticos Fabián guía, salida febrero e ingreso marzo
C131: Delta | D131: DEL | E131: =+VLOOKUP(F131,Resumen_Base!$B$6:$F$69,5,0) -> Work uniforms for personnel (employees) | F131: 5220 | G131: Uniformes | H131: =+D131&F131 -> DEL5220 | I131: 155238.1 | J131: 110.48975 | K131: 1405 | L131: 31/03/2026 | M131: CAJA | N131: 0141 | O131: Extracción de Caja | P131: TE001500000227 | Q131: Extracción de Caja 001500000227 Obs: Movimiento_Cajas_Bancos_Semana 25-26 al 03-04-2026 | S131: DT-Anticipo 50% - Uniformes managers - temporada 2026 - Uniformes Express F.Fijo Oper. Al 27-03-2026
C132: Delta | D132: DEL | E132: =+VLOOKUP(F132,Resumen_Base!$B$6:$F$69,5,0) -> Work uniforms for personnel (employees) | F132: 5220 | G132: Uniformes | H132: =+D132&F132 -> DEL5220 | I132: 44333.33 | J132: 31.553972 | K132: 1405 | L132: 31/03/2026 | M132: CAJA | N132: 0141 | O132: Extracción de Caja | P132: TE001500000227 | Q132: Extracción de Caja 001500000227 Obs: Movimiento_Cajas_Bancos_Semana 25-26 al 03-04-2026 | S132: DT-Reposición Campera Soft Shell con logo - Temporada 2026 - Elvio Braman F.Fijo Oper. Al 27-03-2026
C133: Delta | D133: DEL | E133: =+VLOOKUP(F133,Resumen_Base!$B$6:$F$69,5,0) -> Work uniforms for personnel (employees) | F133: 5220 | G133: Uniformes | H133: =+D133&F133 -> DEL5220 | I133: 33142.86 | J133: 23.589224 | K133: 1405 | L133: 31/03/2026 | M133: CAJA | N133: 0141 | O133: Extracción de Caja | P133: TE001500000227 | Q133: Extracción de Caja 001500000227 Obs: Movimiento_Cajas_Bancos_Semana 25-26 al 03-04-2026 | S133: DT-Reposición Chaleco Matelaseado Negro Housekeeping + Chaleco Matelaseado Managers Hombre - Tempora
C134: Delta | D134: DEL | E134: =+VLOOKUP(F134,Resumen_Base!$B$6:$F$69,5,0) -> Work uniforms for personnel (employees) | F134: 5220 | G134: Uniformes | H134: =+D134&F134 -> DEL5220 | I134: 41571.43 | J134: 29.588206 | K134: 1405 | L134: 31/03/2026 | M134: CAJA | N134: 0141 | O134: Extracción de Caja | P134: TE001500000227 | Q134: Extracción de Caja 001500000227 Obs: Movimiento_Cajas_Bancos_Semana 25-26 al 03-04-2026 | S134: DT-Reposición uniformes camisas HSK - temporada 2026 - Eileen Folgado F.Fijo Oper. Al 27-03-2026
C135: Delta | D135: DEL | E135: =+VLOOKUP(F135,Resumen_Base!$B$6:$F$69,5,0) -> Work uniforms for personnel (employees) | F135: 5220 | G135: Uniformes | H135: =+D135&F135 -> DEL5220 | I135: 453227.14 | J135: 322.58159 | K135: 1405 | L135: 31/03/2026 | M135: CAJA | N135: 0141 | O135: Extracción de Caja | P135: TE001500000227 | Q135: Extracción de Caja 001500000227 Obs: Movimiento_Cajas_Bancos_Semana 25-26 al 03-04-2026 | S135: DT-Reposición uniformes cocina - temporada 2026 - Savastano F.Fijo Oper. Al 27-03-2026
A138: INSERT | B138: INSERT | C138: INSERT | D138: INSERT | E138: INSERT | F138: INSERT | G138: INSERT | H138: INSERT | I138: INSERT | J138: INSERT | K138: INSERT | L138: INSERT | M138: INSERT | N138: INSERT | O138: INSERT | P138: INSERT | Q138: INSERT | R138: INSERT | S138: INSERT | T138: INSERT | U138: INSERT | V138: INSERT | W138: INSERT
D141: Delta | F141: 11010101 | G141: Caja $ Administración | I141: 2000000 | J141: 1428.5714 | K141: 1400 | L141: 13/03/2026 | M141: CAJA | N141: 0149 | O141: Canje de Valores | P141: TA001500000209 | Q141: Canje de Valores 001500000209 Obs: DEL-Cambio $ 2,000,000 | S141: Canje de Valores 001500000209 Obs: DEL-Cambio $ 2,000,000
D142: Delta | F142: 11010101 | G142: Caja $ Administración | I142: 2700000 | J142: 1908.1272 | K142: 1415 | L142: 20/03/2026 | M142: CAJA | N142: 0149 | O142: Canje de Valores | P142: TA001500000217 | Q142: Canje de Valores 001500000217 Obs: DEL-Cambio $ 2,700,000 | S142: Canje de Valores 001500000217 Obs: DEL-Cambio $ 2,700,000
D143: Delta | F143: 11010101 | G143: Caja $ Administración | I143: -155238.1 | J143: -110.48975 | K143: 1405 | L143: 31/03/2026 | M143: CAJA | N143: 0141 | O143: Extracción de Caja | P143: TE001500000227 | Q143: Extracción de Caja 001500000227 Obs: Movimiento_Cajas_Bancos_Semana 25-26 al 03-04-2026 | S143: DT-Anticipo 50% - Uniformes managers - temporada 2026 - Uniformes Express F.Fijo Oper. Al 27-03-2026
D144: Delta | F144: 11010101 | G144: Caja $ Administración | I144: -2260000 | J144: -1597.1731 | K144: 1415 | L144: 20/03/2026 | M144: CAJA | N144: 0141 | O144: Extracción de Caja | P144: TE001500000218 | Q144: Extracción de Caja 001500000218 Obs: Movimiento_Cajas_Bancos_Semana 25-26 al 20-03-2026 | S144: DT-Caja Lodge - enviado viernes 13-03 Guarderia F.Fijo Oper. Al 20-03-2026
D145: Delta | F145: 11010101 | G145: Caja $ Administración | I145: -4730000 | J145: -3366.548 | K145: 1405 | L145: 31/03/2026 | M145: CAJA | N145: 0141 | O145: Extracción de Caja | P145: TE001500000227 | Q145: Extracción de Caja 001500000227 Obs: Movimiento_Cajas_Bancos_Semana 25-26 al 03-04-2026 | S145: DT-Caja Lodge F.Fijo Oper. Al 27-03-2026
D146: Delta | F146: 11010101 | G146: Caja $ Administración | I146: -1802286 | J146: -1282.7658 | K146: 1405 | L146: 31/03/2026 | M146: CAJA | N146: 0141 | O146: Extracción de Caja | P146: TE001500000227 | Q146: Extracción de Caja 001500000227 Obs: Movimiento_Cajas_Bancos_Semana 25-26 al 03-04-2026 | S146: DT-Compra carnes y verduras semana 13/3 Pagos Frank Garrahan- Al 27-03-2026
D147: Delta | F147: 11010101 | G147: Caja $ Administración | I147: -1995459 | J147: -1425.3279 | K147: 1400 | L147: 13/03/2026 | M147: CAJA | N147: 0141 | O147: Extracción de Caja | P147: TE001500000210 | Q147: Extracción de Caja 001500000210 Obs: Movimiento_Cajas_Bancos_Semana 25-26 al 13-03-2026 | S147: DT-Compra de carnes y verduras realizada el dia Viernes 27/2 para cubrir Marzo Pagos Frank Garrahan-
D148: Delta | F148: 11010101 | G148: Caja $ Administración | I148: -162499 | J148: -115.65765 | K148: 1405 | L148: 31/03/2026 | M148: CAJA | N148: 0141 | O148: Extracción de Caja | P148: TE001500000227 | Q148: Extracción de Caja 001500000227 Obs: Movimiento_Cajas_Bancos_Semana 25-26 al 03-04-2026 | S148: DT-Compra marco digital frameo 10.1 F.Fijo Oper. Al 27-03-2026
D149: Delta | F149: 11010101 | G149: Caja $ Administración | I149: -800000 | J149: -569.39502 | K149: 1405 | L149: 31/03/2026 | M149: CAJA | N149: 0141 | O149: Extracción de Caja | P149: TE001500000227 | Q149: Extracción de Caja 001500000227 Obs: Movimiento_Cajas_Bancos_Semana 25-26 al 03-04-2026 | S149: DT-Mayorista Paso (Periodo del 01/4 al 30/4) Pagos Frank Garrahan- Al 27-03-2026
D150: Delta | F150: 11010101 | G150: Caja $ Administración | I150: -144600 | J150: -102.19081 | K150: 1415 | L150: 20/03/2026 | M150: CAJA | N150: 0141 | O150: Extracción de Caja | P150: TE001500000218 | Q150: Extracción de Caja 001500000218 Obs: Movimiento_Cajas_Bancos_Semana 25-26 al 20-03-2026 | S150: DT-Reposicion articulos de pesca - Compra articulos de pesca realizada por Noel el Sabado 7/3 Pagos
D151: Delta | F151: 11010101 | G151: Caja $ Administración | I151: -44333.33 | J151: -31.553972 | K151: 1405 | L151: 31/03/2026 | M151: CAJA | N151: 0141 | O151: Extracción de Caja | P151: TE001500000227 | Q151: Extracción de Caja 001500000227 Obs: Movimiento_Cajas_Bancos_Semana 25-26 al 03-04-2026 | S151: DT-Reposición Campera Soft Shell con logo - Temporada 2026 - Elvio Braman F.Fijo Oper. Al 27-03-2026
D152: Delta | F152: 11010101 | G152: Caja $ Administración | I152: -33142.86 | J152: -23.589224 | K152: 1405 | L152: 31/03/2026 | M152: CAJA | N152: 0141 | O152: Extracción de Caja | P152: TE001500000227 | Q152: Extracción de Caja 001500000227 Obs: Movimiento_Cajas_Bancos_Semana 25-26 al 03-04-2026 | S152: DT-Reposición Chaleco Matelaseado Negro Housekeeping + Chaleco Matelaseado Managers Hombre - Tempora
... D281: Delta | F281: 11010104 | G281: Caja U$S Lodge | I281: -2292300 | J281: -1620 | K281: 1415 | L281: 23/03/2026 | M281: CAJA | N281: 0141 | O281: Extracción de Caja | P281: TE001500000215 | Q281: Extracción de Caja 001500000215 Obs: 23-03-2026 Mov Lodge | S281: DT - Pago salario mío mes febrero
