Workbook
Name _____Rt12: #REF!
Name _____Rt12: #REF!
Name _____Rt12: #REF!
Name _____Rt12: #REF!
Name ____Rt12: #REF!
Name ____Rt12: #REF!
Name ____Rt12: #REF!
Name ____Rt12: #REF!
Name ___Rt12: #REF!
Name ___Rt12: #REF!
Name ___Rt12: #REF!
Name ___Rt12: #REF!
Name __Rt12: #REF!
Name __Rt12: #REF!
Name __Rt12: #REF!
Name __Rt12: #REF!
Name _Rt12: #REF!
Name _Rt12: #REF!
Name _Rt12: #REF!
Name _Rt12: #REF!
Name A: #REF!
Name A: #REF!
Name AJUSTES: #REF!
Name AJUSTES: #REF!
Name AJUSTES: #REF!
Name AJUSTES: #REF!
Name AJUSTES: #REF!
Name AJUSTES: #REF!
Name AJUSTES: #REF!
Name AJUSTES: #REF!
Name AJUSTES: #REF!
Name AJUSTES: #REF!
Name Assumptions: #REF!
Name Assumptions: #REF!
Name Assumptions: #REF!
Name Assumptions: #REF!
Name BuiltIn_Print_Area: #REF!
Name BuiltIn_Print_Area: #REF!
Name BuiltIn_Print_Area: #REF!
Name BuiltIn_Print_Area: #REF!
Name BuiltIn_Print_Area___0: #REF!
Name BuiltIn_Print_Area___0: #REF!
Name BuiltIn_Print_Area___0: #REF!
Name BuiltIn_Print_Area___0: #REF!
Name BuiltIn_Print_Titles: #REF!
Name BuiltIn_Print_Titles: #REF!
Name BuiltIn_Print_Titles: #REF!
Name BuiltIn_Print_Titles: #REF!
Name BuiltIn_Print_Titles___0: #REF!
Name BuiltIn_Print_Titles___0: #REF!
Name BuiltIn_Print_Titles___0: #REF!
Name BuiltIn_Print_Titles___0: #REF!
Name CASH_FLOW: #N/A
Name CodigoLodge: #REF!
Name CodigoLodge: #REF!
Name CodigoLodge: #REF!
Name CodigoLodge: #REF!
Name Costo: #REF!
Name Costo: #REF!
Name Costo: #REF!

Sheet Ajustes y Comentarios

Sheet Mov_Analizados_Sept25 - Dic25
J1: =SUM(J2:J5) -> 200020.27 | K1: =+J1-J9 -> 0
G2: Ver Telefonos | I2: CAR | J2: =+SUMIF($D$10:$D$1038,I2,$J$10:$J$1038) -> 148947.6 | K2: =+J2-Resumen_Base!J220 -> 0
G3: Ver Gastos devengados | I3: SJ | J3: =+SUMIF($D$10:$D$1038,I3,$J$10:$J$1038) -> 23309.96 | K3: =+J3-Resumen_Base!J28 -> 0
G4: Ver Luz Devengada | I4: UL | J4: =+SUMIF($D$10:$D$1038,I4,$J$10:$J$1038) -> 27762.716 | K4: =+J4-Resumen_Base!J93 -> 0
G7: =+IF(I7+J7=0,"Ok","Check") -> Ok | I7: =ROUND(SUM(I10:I3108),0) -> 0 | J7: =ROUND(SUM(J10:J3108),0) -> 0
D8: FL | E8: Rubro | G8: =+Resumen_Base!D1 -> Ok
B9: =+F9&G9 | D9: =+VLOOKUP(F9,Resumen_Base!$C$8:$F$26,4,0) -> #N/A | E9: =+VLOOKUP(F9,Resumen_Base!$C$8:$G$287,5,0) -> #N/A | H9: =+D9&F9 -> #N/A | I9: =SUM(I10:I1038) -> 3.1037681e+08 | J9: =SUM(J10:J1038) -> 200020.27
A10: Ajustes | B10: Cuenta Anterior | D10: Lodge | E10: Concepto | F10: Codigo Cuenta | G10: Cuenta Contable | I10: Saldo - $ | J10: Saldo - u$s | K10: Tipo cambio | L10: Fecha | M10: Modulo | N10: Cod Centro Costo | O10: gestionid | P10: Detalle | Q10: Observaciones | R10: Observación Adicional | S10: Número | T10: Ejercicio | U10: Observación del comprobante | V10: Comentario renglón asiento | W10: Asiento | X10: Control | Z10: monto USD | AA10: tc | AC10: Fecha | AD10: Subdiario | AE10: Div | AF10: Datos del comprobante | AG10: Sujeto | AH10: CUIT | AI10: Observación asiento | AJ10: Clase de Asiento | AK10: Origen del comprobante | AL10: Observación del comprobante | AM10: Comentario renglón asiento | AN10: Asiento
D12: SJ | E12: =+VLOOKUP(F12,Resumen_Base!$C$8:$G$287,5,0) -> Fixed Asset's Payments (Investments) Mejoras/equipamiento Lodge | F12: 12020103 | G12: Mejoras de Inmueb y Terrenos | H12: =+D12&F12 -> SJ12020103 | I12: 903319.3 | J12: 649.87 | K12: 1390 | L12: 30/09/2025 | M12: CAJA | N12: 0121 | O12: TH001400000043 | P12: Asiento de CAJA (01/09/2025 - 31/08/2026) | Q12: Extracción de Banco 001400000043 Obs: 30-09-2025 Mov Lodge | R12: SJ - inversion inmuebles SJ | S12: 000000000072 | T12: Ejercicio 2025/2026
A13: ESTO ES TODO URUGUAY LODGE | D13: UL | E13: =+VLOOKUP(F13,Resumen_Base!$C$8:$G$287,5,0) -> Fixed Asset's Payments (Investments) Mejoras/equipamiento Lodge | F13: 12020103 | G13: Mejoras de Inmueb y Terrenos | H13: =+D13&F13 -> UL12020103 | I13: 9230000 | J13: 6500 | K13: 1420 | L13: 23/11/2025 | M13: CAJA | N13: 0121 | O13: TE001400000144 | P13: Asiento de CAJA (01/09/2025 - 31/08/2026) | Q13: Extracción de Caja 001400000144 Obs: 23-11-2025 Mov Lodge | R13: SJ - fachada valle de soba constructor | S13: 000000000222 | T13: Ejercicio 2025/2026
D14: UL | E14: =+VLOOKUP(F14,Resumen_Base!$C$8:$G$287,5,0) -> Fixed Asset's Payments (Investments) Mejoras/equipamiento Lodge | F14: 12020103 | G14: Mejoras de Inmueb y Terrenos | H14: =+D14&F14 -> UL12020103 | I14: 1420 | J14: 1 | K14: 1420 | L14: 16/11/2025 | M14: CAJA | N14: 0121 | O14: TH001400000125 | P14: Asiento de CAJA (01/09/2025 - 31/08/2026) | Q14: Extracción de Banco 001400000125 Obs: 16-11-2025 Mov Lodge | R14: SJ - deb comi | S14: 000000000230 | T14: Ejercicio 2025/2026
D15: UL | E15: =+VLOOKUP(F15,Resumen_Base!$C$8:$G$287,5,0) -> Fixed Asset's Payments (Investments) Mejoras/equipamiento Lodge | F15: 12020103 | G15: Mejoras de Inmueb y Terrenos | H15: =+D15&F15 -> UL12020103 | I15: 284000 | J15: 200 | K15: 1420 | L15: 16/11/2025 | M15: CAJA | N15: 0121 | O15: TH001400000125 | P15: Asiento de CAJA (01/09/2025 - 31/08/2026) | Q15: Extracción de Banco 001400000125 Obs: 16-11-2025 Mov Lodge | R15: SJ - obra valle ruben perez | S15: 000000000230 | T15: Ejercicio 2025/2026
D16: UL | E16: =+VLOOKUP(F16,Resumen_Base!$C$8:$G$287,5,0) -> Fixed Asset's Payments (Investments) Mejoras/equipamiento Lodge | F16: 12020103 | G16: Mejoras de Inmueb y Terrenos | H16: =+D16&F16 -> UL12020103 | I16: 710000 | J16: 500 | K16: 1420 | L16: 16/11/2025 | M16: CAJA | N16: 0121 | O16: TH001400000125 | P16: Asiento de CAJA (01/09/2025 - 31/08/2026) | Q16: Extracción de Banco 001400000125 Obs: 16-11-2025 Mov Lodge | R16: SJ - obra valle ruben perez | S16: 000000000230 | T16: Ejercicio 2025/2026
D17: UL | E17: =+VLOOKUP(F17,Resumen_Base!$C$8:$G$287,5,0) -> Fixed Asset's Payments (Investments) Mejoras/equipamiento Lodge | F17: 12020103 | G17: Mejoras de Inmueb y Terrenos | H17: =+D17&F17 -> UL12020103 | I17: 1420 | J17: 1 | K17: 1420 | L17: 16/11/2025 | M17: CAJA | N17: 0121 | O17: TH001400000125 | P17: Asiento de CAJA (01/09/2025 - 31/08/2026) | Q17: Extracción de Banco 001400000125 Obs: 16-11-2025 Mov Lodge | R17: SJ - deb comi | S17: 000000000230 | T17: Ejercicio 2025/2026
D18: UL | E18: =+VLOOKUP(F18,Resumen_Base!$C$8:$G$287,5,0) -> Fixed Asset's Payments (Investments) Mejoras/equipamiento Lodge | F18: 12020103 | G18: Mejoras de Inmueb y Terrenos | H18: =+D18&F18 -> UL12020103 | I18: 710000 | J18: 500 | K18: 1420 | L18: 07/12/2025 | M18: CAJA | N18: 0121 | O18: TH001400000168 | P18: Asiento de CAJA (01/09/2025 - 31/08/2026) | Q18: Extracción de Banco 001400000168 Obs: 07-12-2025 Mov Lodge | R18: SJ - obra Valle de Soba Ruben Perez | S18: 000000000242 | T18: Ejercicio 2025/2026
D19: UL | E19: =+VLOOKUP(F19,Resumen_Base!$C$8:$G$287,5,0) -> Fixed Asset's Payments (Investments) Mejoras/equipamiento Lodge | F19: 12020103 | G19: Mejoras de Inmueb y Terrenos | H19: =+D19&F19 -> UL12020103 | I19: 710000 | J19: 500 | K19: 1420 | L19: 07/12/2025 | M19: CAJA | N19: 0121 | O19: TH001400000168 | P19: Asiento de CAJA (01/09/2025 - 31/08/2026) | Q19: Extracción de Banco 001400000168 Obs: 07-12-2025 Mov Lodge | R19: SJ - obra Valle de Soba Ruben Perez | S19: 000000000242 | T19: Ejercicio 2025/2026
D20: UL | E20: =+VLOOKUP(F20,Resumen_Base!$C$8:$G$287,5,0) -> Fixed Asset's Payments (Investments) Mejoras/equipamiento Lodge | F20: 12020103 | G20: Mejoras de Inmueb y Terrenos | H20: =+D20&F20 -> UL12020103 | I20: 710000 | J20: 500 | K20: 1420 | L20: 07/12/2025 | M20: CAJA | N20: 0121 | O20: TH001400000168 | P20: Asiento de CAJA (01/09/2025 - 31/08/2026) | Q20: Extracción de Banco 001400000168 Obs: 07-12-2025 Mov Lodge | R20: SJ - obra Valle de Soba Ruben Perez | S20: 000000000242 | T20: Ejercicio 2025/2026
D21: UL | E21: =+VLOOKUP(F21,Resumen_Base!$C$8:$G$287,5,0) -> Fixed Asset's Payments (Investments) Mejoras/equipamiento Lodge | F21: 12020103 | G21: Mejoras de Inmueb y Terrenos | H21: =+D21&F21 -> UL12020103 | I21: 1420 | J21: 1 | K21: 1420 | L21: 07/12/2025 | M21: CAJA | N21: 0121 | O21: TH001400000168 | P21: Asiento de CAJA (01/09/2025 - 31/08/2026) | Q21: Extracción de Banco 001400000168 Obs: 07-12-2025 Mov Lodge | R21: SJ - obra Valle de Soba Ruben Perez | S21: 000000000242 | T21: Ejercicio 2025/2026
D22: UL | E22: =+VLOOKUP(F22,Resumen_Base!$C$8:$G$287,5,0) -> Fixed Asset's Payments (Investments) Mejoras/equipamiento Lodge | F22: 12020103 | G22: Mejoras de Inmueb y Terrenos | H22: =+D22&F22 -> UL12020103 | I22: 710000 | J22: 500 | K22: 1420 | L22: 07/12/2025 | M22: CAJA | N22: 0121 | O22: TH001400000168 | P22: Asiento de CAJA (01/09/2025 - 31/08/2026) | Q22: Extracción de Banco 001400000168 Obs: 07-12-2025 Mov Lodge | R22: SJ - obra Valle de Soba Ruben Perez | S22: 000000000242 | T22: Ejercicio 2025/2026
D23: UL | E23: =+VLOOKUP(F23,Resumen_Base!$C$8:$G$287,5,0) -> Fixed Asset's Payments (Investments) Mejoras/equipamiento Lodge | F23: 12020103 | G23: Mejoras de Inmueb y Terrenos | H23: =+D23&F23 -> UL12020103 | I23: 1420 | J23: 1 | K23: 1420 | L23: 07/12/2025 | M23: CAJA | N23: 0121 | O23: TH001400000168 | P23: Asiento de CAJA (01/09/2025 - 31/08/2026) | Q23: Extracción de Banco 001400000168 Obs: 07-12-2025 Mov Lodge | R23: SJ - obra Valle de Soba Ruben Perez | S23: 000000000242 | T23: Ejercicio 2025/2026
D24: UL | E24: =+VLOOKUP(F24,Resumen_Base!$C$8:$G$287,5,0) -> Fixed Asset's Payments (Investments) Mejoras/equipamiento Lodge | F24: 12020103 | G24: Mejoras de Inmueb y Terrenos | H24: =+D24&F24 -> UL12020103 | I24: 7395360 | J24: 5208 | K24: 1420 | L24: 21/12/2025 | M24: CAJA | N24: 0121 | O24: TE001400000186 | P24: Asiento de CAJA (01/09/2025 - 31/08/2026) | Q24: Extracción de Caja 001400000186 Obs: 21-12-2025 Mov Lodge | R24: SJ - devolucion a sofi barran que presto para empezar obra en valle de soba | S24: 000000000283 | T24: Ejercicio 2025/2026
D25: UL | E25: =+VLOOKUP(F25,Resumen_Base!$C$8:$G$287,5,0) -> Fixed Asset's Payments (Investments) Mejoras/equipamiento Lodge | F25: 12020103 | G25: Mejoras de Inmueb y Terrenos | H25: =+D25&F25 -> UL12020103 | I25: 2130000 | J25: 1500 | K25: 1420 | L25: 21/12/2025 | M25: CAJA | N25: 0121 | O25: TE001400000186 | P25: Asiento de CAJA (01/09/2025 - 31/08/2026) | Q25: Extracción de Caja 001400000186 Obs: 21-12-2025 Mov Lodge | R25: SJ - a favor obra valle de soba | S25: 000000000283 | T25: Ejercicio 2025/2026
... D39: CAR | E39: =+VLOOKUP(F39,Resumen_Base!$C$8:$G$287,5,0) -> Fixed Asset's Payments (Investments) Mejoras/equipamiento Lodge | F39: 12020103 | G39: Mejoras de Inmueb y Terrenos | H39: =+D39&F39 -> CAR12020103 | I39: 9165000 | J39: 6500 | K39: 1410 | L39: 12/10/2025 | M39: CAJA | N39: 0123 | O39: TH001400000056 | P39: Asiento de CAJA (01/09/2025 - 31/08/2026) | Q39: Extracción de Banco 001400000056 Obs: 12-10-2025 Mov Lodge | R39: CAR - mejoras inmuebles | S39: 000000000075 | T39: Ejercicio 2025/2026
D40: CAR | E40: =+VLOOKUP(F40,Resumen_Base!$C$8:$G$287,5,0) -> Fixed Asset's Payments (Investments) Mejoras/equipamiento Lodge | F40: 12020103 | G40: Mejoras de Inmueb y Terrenos | H40: =+D40&F40 -> CAR12020103 | I40: -9750000 | J40: -6500 | K40: 1500 | L40: 27/10/2025 | M40: CAJA | N40: 0123 | O40: TD001400000097 | P40: Asiento de CAJA (01/09/2025 - 31/08/2026) | Q40: Depósito a Banco 001400000097 Obs: CAR - Recupero Mejoras inmuebles y terrenos | S40: 000000000158 | T40: Ejercicio 2025/2026
A41: PAGAN LOS DUEÑOS DE LA PROPIEDAD | D41: CAR | E41: =+VLOOKUP(F41,Resumen_Base!$C$8:$G$287,5,0) -> Fixed Asset's Payments (Investments) Mejoras/equipamiento Lodge | F41: 12020103 | G41: Mejoras de Inmueb y Terrenos | H41: =+D41&F41 -> CAR12020103 | I41: 101941.8 | J41: 71.79 | K41: 1420 | L41: 23/11/2025 | M41: CAJA | N41: 0123 | O41: TE001400000144 | P41: Asiento de CAJA (01/09/2025 - 31/08/2026) | Q41: Extracción de Caja 001400000144 Obs: 23-11-2025 Mov Lodge | R41: CAR - OBRA COCINA: barraca | S41: 000000000222 | T41: Ejercicio 2025/2026
A42: PAGAN LOS DUEÑOS DE LA PROPIEDAD | D42: CAR | E42: =+VLOOKUP(F42,Resumen_Base!$C$8:$G$287,5,0) -> Fixed Asset's Payments (Investments) Mejoras/equipamiento Lodge | F42: 12020103 | G42: Mejoras de Inmueb y Terrenos | H42: =+D42&F42 -> CAR12020103 | I42: 4260000 | J42: 3000 | K42: 1420 | L42: 23/11/2025 | M42: CAJA | N42: 0123 | O42: TE001400000144 | P42: Asiento de CAJA (01/09/2025 - 31/08/2026) | Q42: Extracción de Caja 001400000144 Obs: 23-11-2025 Mov Lodge | R42: CAR - OBRA COCINA: honorarios albanil | S42: 000000000222 | T42: Ejercicio 2025/2026
A43: PAGAN LOS DUEÑOS DE LA PROPIEDAD | D43: CAR | E43: =+VLOOKUP(F43,Resumen_Base!$C$8:$G$287,5,0) -> Fixed Asset's Payments (Investments) Mejoras/equipamiento Lodge | F43: 12020103 | G43: Mejoras de Inmueb y Terrenos | H43: =+D43&F43 -> CAR12020103 | I43: 5212820 | J43: 3671 | K43: 1420 | L43: 23/11/2025 | M43: CAJA | N43: 0123 | O43: TE001400000144 | P43: Asiento de CAJA (01/09/2025 - 31/08/2026) | Q43: Extracción de Caja 001400000144 Obs: 23-11-2025 Mov Lodge | R43: CAR - materiales barraca | S43: 000000000222 | T43: Ejercicio 2025/2026
A44: PAGAN LOS DUEÑOS DE LA PROPIEDAD | D44: CAR | E44: =+VLOOKUP(F44,Resumen_Base!$C$8:$G$287,5,0) -> Fixed Asset's Payments (Investments) Mejoras/equipamiento Lodge | F44: 12020103 | G44: Mejoras de Inmueb y Terrenos | H44: =+D44&F44 -> CAR12020103 | I44: 291284.6 | J44: 205.13 | K44: 1420 | L44: 23/11/2025 | M44: CAJA | N44: 0123 | O44: TE001400000144 | P44: Asiento de CAJA (01/09/2025 - 31/08/2026) | Q44: Extracción de Caja 001400000144 Obs: 23-11-2025 Mov Lodge | R44: CAR - OBRA COCINA: babetas | S44: 000000000222 | T44: Ejercicio 2025/2026
A45: PAGAN LOS DUEÑOS DE LA PROPIEDAD | D45: CAR | E45: =+VLOOKUP(F45,Resumen_Base!$C$8:$G$287,5,0) -> Fixed Asset's Payments (Investments) Mejoras/equipamiento Lodge | F45: 12020103 | G45: Mejoras de Inmueb y Terrenos | H45: =+D45&F45 -> CAR12020103 | I45: 889104.6 | J45: 626.13 | K45: 1420 | L45: 23/11/2025 | M45: CAJA | N45: 0123 | O45: TE001400000144 | P45: Asiento de CAJA (01/09/2025 - 31/08/2026) | Q45: Extracción de Caja 001400000144 Obs: 23-11-2025 Mov Lodge | R45: CAR - OBRA COCINA: materiales | S45: 000000000222 | T45: Ejercicio 2025/2026
A46: PAGAN LOS DUEÑOS DE LA PROPIEDAD | D46: CAR | E46: =+VLOOKUP(F46,Resumen_Base!$C$8:$G$287,5,0) -> Fixed Asset's Payments (Investments) Mejoras/equipamiento Lodge | F46: 12020103 | G46: Mejoras de Inmueb y Terrenos | H46: =+D46&F46 -> CAR12020103 | I46: 586417.4 | J46: 412.97 | K46: 1420 | L46: 23/11/2025 | M46: CAJA | N46: 0123 | O46: TE001400000144 | P46: Asiento de CAJA (01/09/2025 - 31/08/2026) | Q46: Extracción de Caja 001400000144 Obs: 23-11-2025 Mov Lodge | R46: CAR - OBRA COCINA: materiales | S46: 000000000222 | T46: Ejercicio 2025/2026
D47: CAR | E47: =+VLOOKUP(F47,Resumen_Base!$C$8:$G$287,5,0) -> Fixed Asset's Payments (Investments) Mejoras/equipamiento Lodge | F47: 12020103 | G47: Mejoras de Inmueb y Terrenos | H47: =+D47&F47 -> CAR12020103 | I47: 555915.8 | J47: 391.49 | K47: 1420 | L47: 23/11/2025 | M47: CAJA | N47: 0123 | O47: TE001400000144 | P47: Asiento de CAJA (01/09/2025 - 31/08/2026) | Q47: Extracción de Caja 001400000144 Obs: 23-11-2025 Mov Lodge | R47: CAR - ferreteria varios para cambio de luces en jardin y pintura muebles exterior | S47: 000000000222 | T47: Ejercicio 2025/2026
D48: CAR | E48: =+VLOOKUP(F48,Resumen_Base!$C$8:$G$287,5,0) -> Fixed Asset's Payments (Investments) Mejoras/equipamiento Lodge | F48: 12020103 | G48: Mejoras de Inmueb y Terrenos | H48: =+D48&F48 -> CAR12020103 | I48: 801760.4 | J48: 564.62 | K48: 1420 | L48: 23/11/2025 | M48: CAJA | N48: 0123 | O48: TE001400000144 | P48: Asiento de CAJA (01/09/2025 - 31/08/2026) | Q48: Extracción de Caja 001400000144 Obs: 23-11-2025 Mov Lodge | R48: CAR - Pintura pileta | S48: 000000000222 | T48: Ejercicio 2025/2026
A49: PAGAN LOS DUEÑOS DE LA PROPIEDAD | D49: CAR | E49: =+VLOOKUP(F49,Resumen_Base!$C$8:$G$287,5,0) -> Fixed Asset's Payments (Investments) Mejoras/equipamiento Lodge | F49: 12020103 | G49: Mejoras de Inmueb y Terrenos | H49: =+D49&F49 -> CAR12020103 | I49: 138364.8 | J49: 97.44 | K49: 1420 | L49: 23/11/2025 | M49: CAJA | N49: 0123 | O49: TE001400000144 | P49: Asiento de CAJA (01/09/2025 - 31/08/2026) | Q49: Extracción de Caja 001400000144 Obs: 23-11-2025 Mov Lodge | R49: CAR - OBRA COCINA: retiro de escombros | S49: 000000000222 | T49: Ejercicio 2025/2026
A50: PAGAN LOS DUEÑOS DE LA PROPIEDAD | D50: CAR | E50: =+VLOOKUP(F50,Resumen_Base!$C$8:$G$287,5,0) -> Fixed Asset's Payments (Investments) Mejoras/equipamiento Lodge | F50: 12020103 | G50: Mejoras de Inmueb y Terrenos | H50: =+D50&F50 -> CAR12020103 | I50: 673591.2 | J50: 474.36 | K50: 1420 | L50: 30/11/2025 | M50: CAJA | N50: 0123 | O50: TE001400000157 | P50: Asiento de CAJA (01/09/2025 - 31/08/2026) | Q50: Extracción de Caja 001400000157 Obs: 30-11-2025 Mov Lodge | R50: CAR - OBRA COCINA: ferreteria | S50: 000000000225 | T50: Ejercicio 2025/2026
A51: PAGAN LOS DUEÑOS DE LA PROPIEDAD | D51: CAR | E51: =+VLOOKUP(F51,Resumen_Base!$C$8:$G$287,5,0) -> Fixed Asset's Payments (Investments) Mejoras/equipamiento Lodge | F51: 12020103 | G51: Mejoras de Inmueb y Terrenos | H51: =+D51&F51 -> CAR12020103 | I51: 695800 | J51: 490 | K51: 1420 | L51: 30/11/2025 | M51: CAJA | N51: 0123 | O51: TE001400000157 | P51: Asiento de CAJA (01/09/2025 - 31/08/2026) | Q51: Extracción de Caja 001400000157 Obs: 30-11-2025 Mov Lodge | R51: CAR - OBRA COCINA: puerta nueva | S51: 000000000225 | T51: Ejercicio 2025/2026
A52: PAGAN LOS DUEÑOS DE LA PROPIEDAD | D52: CAR | E52: =+VLOOKUP(F52,Resumen_Base!$C$8:$G$287,5,0) -> Fixed Asset's Payments (Investments) Mejoras/equipamiento Lodge | F52: 12020103 | G52: Mejoras de Inmueb y Terrenos | H52: =+D52&F52 -> CAR12020103 | I52: 1136000 | J52: 800 | K52: 1420 | L52: 21/12/2025 | M52: CAJA | N52: 0123 | O52: TE001400000186 | P52: Asiento de CAJA (01/09/2025 - 31/08/2026) | Q52: Extracción de Caja 001400000186 Obs: 21-12-2025 Mov Lodge | R52: CAR - OBRA COCINA: albanil | S52: 000000000283 | T52: Ejercicio 2025/2026
A53: PAGAN LOS DUEÑOS DE LA PROPIEDAD | D53: CAR | E53: =+VLOOKUP(F53,Resumen_Base!$C$8:$G$287,5,0) -> Fixed Asset's Payments (Investments) Mejoras/equipamiento Lodge | F53: 12020103 | G53: Mejoras de Inmueb y Terrenos | H53: =+D53&F53 -> CAR12020103 | I53: 984060 | J53: 693 | K53: 1420 | L53: 21/12/2025 | M53: CAJA | N53: 0123 | O53: TE001400000186 | P53: Asiento de CAJA (01/09/2025 - 31/08/2026) | Q53: Extracción de Caja 001400000186 Obs: 21-12-2025 Mov Lodge | R53: CAR - OBRA COCINA: ferreteria | S53: 000000000283 | T53: Ejercicio 2025/2026
A54: PAGAN LOS DUEÑOS DE LA PROPIEDAD | D54: CAR | E54: =+VLOOKUP(F54,Resumen_Base!$C$8:$G$287,5,0) -> Fixed Asset's Payments (Investments) Mejoras/equipamiento Lodge | F54: 12020103 | G54: Mejoras de Inmueb y Terrenos | H54: =+D54&F54 -> CAR12020103 | I54: 1136000 | J54: 800 | K54: 1420 | L54: 21/12/2025 | M54: CAJA | N54: 0123 | O54: TE001400000186 | P54: Asiento de CAJA (01/09/2025 - 31/08/2026) | Q54: Extracción de Caja 001400000186 Obs: 21-12-2025 Mov Lodge | R54: CAR - OBRA COCINA: albanil | S54: 000000000283 | T54: Ejercicio 2025/2026
D55: CAR | E55: =+VLOOKUP(F55,Resumen_Base!$C$8:$G$287,5,0) -> Fixed Asset's Payments (Investments) Mejoras/equipamiento Lodge | F55: 12020103 | G55: Mejoras de Inmueb y Terrenos | H55: =+D55&F55 -> CAR12020103 | I55: 1491000 | J55: 1050 | K55: 1420 | L55: 21/12/2025 | M55: CAJA | N55: 0123 | O55: TE001400000186 | P55: Asiento de CAJA (01/09/2025 - 31/08/2026) | Q55: Extracción de Caja 001400000186 Obs: 21-12-2025 Mov Lodge | R55: CAR - PERGOLA NUEVA ESTACIONAMIENTO: balasto y maquinas | S55: 000000000283 | T55: Ejercicio 2025/2026
A56: PAGAN LOS DUEÑOS DE LA PROPIEDAD | D56: CAR | E56: =+VLOOKUP(F56,Resumen_Base!$C$8:$G$287,5,0) -> Fixed Asset's Payments (Investments) Mejoras/equipamiento Lodge | F56: 12020103 | G56: Mejoras de Inmueb y Terrenos | H56: =+D56&F56 -> CAR12020103 | I56: 1420000 | J56: 1000 | K56: 1420 | L56: 21/12/2025 | M56: CAJA | N56: 0123 | O56: TE001400000186 | P56: Asiento de CAJA (01/09/2025 - 31/08/2026) | Q56: Extracción de Caja 001400000186 Obs: 21-12-2025 Mov Lodge | R56: CAR - OBRA COCINA: albanil | S56: 000000000283 | T56: Ejercicio 2025/2026
A57: PAGAN LOS DUEÑOS DE LA PROPIEDAD | D57: CAR | E57: =+VLOOKUP(F57,Resumen_Base!$C$8:$G$287,5,0) -> Fixed Asset's Payments (Investments) Mejoras/equipamiento Lodge | F57: 12020103 | G57: Mejoras de Inmueb y Terrenos | H57: =+D57&F57 -> CAR12020103 | I57: 471440 | J57: 332 | K57: 1420 | L57: 21/12/2025 | M57: CAJA | N57: 0123 | O57: TE001400000186 | P57: Asiento de CAJA (01/09/2025 - 31/08/2026) | Q57: Extracción de Caja 001400000186 Obs: 21-12-2025 Mov Lodge | R57: CAR - OBRA COCINA: pintura | S57: 000000000283 | T57: Ejercicio 2025/2026
A58: PAGAN LOS DUEÑOS DE LA PROPIEDAD | D58: CAR | E58: =+VLOOKUP(F58,Resumen_Base!$C$8:$G$287,5,0) -> Fixed Asset's Payments (Investments) Mejoras/equipamiento Lodge | F58: 12020103 | G58: Mejoras de Inmueb y Terrenos | H58: =+D58&F58 -> CAR12020103 | I58: 1470000 | J58: 1000 | K58: 1470 | L58: 31/12/2025 | M58: CAJA | N58: 0123 | O58: TE001400000202 | P58: Asiento de CAJA (01/09/2025 - 31/08/2026) | Q58: Extracción de Caja 001400000202 Obs: 31-12-2025 Mov Lodge | R58: CAR - OBRA COCINA: albanil | S58: 000000000289 | T58: Ejercicio 2025/2026
A59: PAGAN LOS DUEÑOS DE LA PROPIEDAD | D59: CAR | E59: =+VLOOKUP(F59,Resumen_Base!$C$8:$G$287,5,0) -> Fixed Asset's Payments (Investments) Mejoras/equipamiento Lodge | F59: 12020103 | G59: Mejoras de Inmueb y Terrenos | H59: =+D59&F59 -> CAR12020103 | I59: 3528000 | J59: 2400 | K59: 1470 | L59: 31/12/2025 | M59: CAJA | N59: 0123 | O59: TE001400000202 | P59: Asiento de CAJA (01/09/2025 - 31/08/2026) | Q59: Extracción de Caja 001400000202 Obs: 31-12-2025 Mov Lodge | R59: CAR - OBRA COCINA: albanil saldo final | S59: 000000000289 | T59: Ejercicio 2025/2026
A60: PAGAN LOS DUEÑOS DE LA PROPIEDAD | D60: CAR | E60: =+VLOOKUP(F60,Resumen_Base!$C$8:$G$287,5,0) -> Fixed Asset's Payments (Investments) Mejoras/equipamiento Lodge | F60: 12020103 | G60: Mejoras de Inmueb y Terrenos | H60: =+D60&F60 -> CAR12020103 | I60: 313110 | J60: 213 | K60: 1470 | L60: 31/12/2025 | M60: CAJA | N60: 0123 | O60: TE001400000202 | P60: Asiento de CAJA (01/09/2025 - 31/08/2026) | Q60: Extracción de Caja 001400000202 Obs: 31-12-2025 Mov Lodge | R60: CAR - OBRA COCINA, corralon | S60: 000000000289 | T60: Ejercicio 2025/2026
D61: CAR | E61: =+VLOOKUP(F61,Resumen_Base!$C$8:$G$287,5,0) -> Fixed Asset's Payments (Investments) Mejoras/equipamiento Lodge | F61: 12020103 | G61: Mejoras de Inmueb y Terrenos | H61: =+D61&F61 -> CAR12020103 | I61: 242550 | J61: 165 | K61: 1470 | L61: 31/12/2025 | M61: CAJA | N61: 0123 | O61: TE001400000202 | P61: Asiento de CAJA (01/09/2025 - 31/08/2026) | Q61: Extracción de Caja 001400000202 Obs: 31-12-2025 Mov Lodge | R61: CAR - palos para ESTACIONAMIENTO | S61: 000000000289 | T61: Ejercicio 2025/2026
D62: CAR | E62: =+VLOOKUP(F62,Resumen_Base!$C$8:$G$287,5,0) -> Fixed Asset's Payments (Investments) Mejoras/equipamiento Lodge | F62: 12020103 | G62: Mejoras de Inmueb y Terrenos | H62: =+D62&F62 -> CAR12020103 | I62: 735000 | J62: 500 | K62: 1470 | L62: 31/12/2025 | M62: CAJA | N62: 0123 | O62: TE001400000202 | P62: Asiento de CAJA (01/09/2025 - 31/08/2026) | Q62: Extracción de Caja 001400000202 Obs: 31-12-2025 Mov Lodge | R62: CAR - agregado de yeso desde el lado del comedor | S62: 000000000289 | T62: Ejercicio 2025/2026
D63: CAR | E63: =+VLOOKUP(F63,Resumen_Base!$C$8:$G$287,5,0) -> Fixed Asset's Payments (Investments) Mejoras/equipamiento Lodge | F63: 12020301 | G63: Muebles y útiles | H63: =+D63&F63 -> CAR12020301 | I63: 24131.99 | J63: 16.087993 | K63: 1500 | L63: 31/10/2025 | M63: CAJA | N63: 0123 | O63: TE001400000089 | P63: Asiento de CAJA (01/09/2025 - 31/08/2026) | Q63: Extracción de Caja 001400000089 Obs: Movimiento_Cajas_Bancos_Semana 25-26 al 31-10-2025 | R63: CAR-Compra 2 Aplique Spot 1 Luz Dicroica Led Móvil Pared Techo Completo F.Fijo Oper. Al 31-10-2025 | S63: 000000000168 | T63: Ejercicio 2025/2026
D64: CAR | E64: =+VLOOKUP(F64,Resumen_Base!$C$8:$G$287,5,0) -> Fixed Asset's Payments (Investments) Mejoras/equipamiento Lodge | F64: 12020301 | G64: Muebles y útiles | H64: =+D64&F64 -> CAR12020301 | I64: 383400 | J64: 270 | K64: 1420 | L64: 23/11/2025 | M64: CAJA | N64: 0123 | O64: TE001400000144 | P64: Asiento de CAJA (01/09/2025 - 31/08/2026) | Q64: Extracción de Caja 001400000144 Obs: 23-11-2025 Mov Lodge | R64: CAR - mesa de cafe | S64: 000000000222 | T64: Ejercicio 2025/2026
D65: CAR | E65: =+VLOOKUP(F65,Resumen_Base!$C$8:$G$287,5,0) -> Fixed Asset's Payments (Investments) Mejoras/equipamiento Lodge | F65: 12020301 | G65: Muebles y útiles | H65: =+D65&F65 -> CAR12020301 | I65: 882000 | J65: 600 | K65: 1470 | L65: 31/12/2025 | M65: CAJA | N65: 0123 | O65: TE001400000202 | P65: Asiento de CAJA (01/09/2025 - 31/08/2026) | Q65: Extracción de Caja 001400000202 Obs: 31-12-2025 Mov Lodge | R65: CAR - extension mesa principal | S65: 000000000289 | T65: Ejercicio 2025/2026
A66: GASTOS VARIOS | B66: 12020501Equipos Computación/Software | D66: CAR | E66: =+VLOOKUP(F66,Resumen_Base!$C$8:$G$287,5,0) -> Miscellaneous & Shipping | F66: 5219 | G66: Gastos Varios | H66: =+D66&F66 -> CAR5219 | I66: 7057.4 | J66: 4.97 | K66: 1420 | L66: 30/09/2025 | M66: CAJA | N66: 0123 | O66: TE001400000038 | P66: Asiento de CAJA (01/09/2025 - 31/08/2026) | Q66: Extracción de Caja 001400000038 Obs: 30-09-2025 Mov Lodge | R66: CAR - Compra de tinta negra para impresora | S66: 000000000065 | T66: Ejercicio 2025/2026
D67: CAR | E67: =+VLOOKUP(F67,Resumen_Base!$C$8:$G$287,5,0) -> Fixed Asset's Payments (Investments) Mejoras/equipamiento Lodge | F67: 12020901 | G67: Vajillas | H67: =+D67&F67 -> CAR12020901 | I67: 27888.8 | J67: 19.64 | K67: 1420 | L67: 30/09/2025 | M67: CAJA | N67: 0123 | O67: TE001400000038 | P67: Asiento de CAJA (01/09/2025 - 31/08/2026) | Q67: Extracción de Caja 001400000038 Obs: 30-09-2025 Mov Lodge | R67: CAR - Vasos de whisky compra en carmelo urgencia reposicion rapida | S67: 000000000065 | T67: Ejercicio 2025/2026
D68: CAR | E68: =+VLOOKUP(F68,Resumen_Base!$C$8:$G$287,5,0) -> Fixed Asset's Payments (Investments) Armas | F68: 120211 | G68: Armas- Escopetas - Equip Field | H68: =+D68&F68 -> CAR120211 | I68: 26880.6 | J68: 18.93 | K68: 1420 | L68: 21/09/2025 | M68: CAJA | N68: 0123 | O68: TH001400000014 | P68: Asientos de Cajas | Q68: Extracción de Banco 001400000014 Obs: 21-09-2025 Mov Lodge | R68: CAR - certificados inspeccion thata | S68: 000000000025 | T68: Ejercicio 2025/2026
D69: CAR | E69: =+VLOOKUP(F69,Resumen_Base!$C$8:$G$287,5,0) -> Fixed Asset's Payments (Investments) Armas | F69: 120211 | G69: Armas- Escopetas - Equip Field | H69: =+D69&F69 -> CAR120211 | I69: 381880.6 | J69: 268.93 | K69: 1420 | L69: 31/12/2025 | M69: CAJA | N69: 0123 | O69: TH001400000203 | P69: Asiento de CAJA (01/09/2025 - 31/08/2026) | Q69: Extracción de Banco 001400000203 Obs: 31-12-2025 Mov Lodge | R69: CAR - renovacion guia de armas | S69: 000000000297 | T69: Ejercicio 2025/2026
D70: CAR | E70: =+VLOOKUP(F70,Resumen_Base!$C$8:$G$287,5,0) -> Tips | F70: 210609 | G70: Propinas a pagar | H70: =+D70&F70 -> CAR210609 | I70: -568000 | J70: -400 | K70: 1420 | L70: 21/09/2025 | M70: VENTAS | N70: 0123 | O70: VF000000000733B | P70: Asiento de VENTAS | Q70: F B 000000000733 | R70: Ref. nota de Venta: CAR.3 Obs.:21-09-2025_CLIENTES | S70: 000000000041 | T70: Ejercicio 2025/2026
D71: CAR | E71: =+VLOOKUP(F71,Resumen_Base!$C$8:$G$287,5,0) -> Tips | F71: 210609 | G71: Propinas a pagar | H71: =+D71&F71 -> CAR210609 | I71: -852000 | J71: -600 | K71: 1420 | L71: 21/09/2025 | M71: VENTAS | N71: 0123 | O71: VF000000000733B | P71: Asiento de VENTAS | Q71: F B 000000000733 | R71: Ref. nota de Venta: CAR.3 Obs.:21-09-2025_CLIENTES | S71: 000000000041 | T71: Ejercicio 2025/2026
D72: CAR | E72: =+VLOOKUP(F72,Resumen_Base!$C$8:$G$287,5,0) -> Tips | F72: 210609 | G72: Propinas a pagar | H72: =+D72&F72 -> CAR210609 | I72: -568000 | J72: -400 | K72: 1420 | L72: 21/09/2025 | M72: VENTAS | N72: 0123 | O72: VF000000000734B | P72: Asiento de VENTAS | Q72: F B 000000000734 | R72: Ref. nota de Venta: CAR.3 Obs.:21-09-2025_CLIENTES | S72: 000000000042 | T72: Ejercicio 2025/2026
D73: CAR | E73: =+VLOOKUP(F73,Resumen_Base!$C$8:$G$287,5,0) -> Tips | F73: 210609 | G73: Propinas a pagar | H73: =+D73&F73 -> CAR210609 | I73: -142000 | J73: -100 | K73: 1420 | L73: 21/09/2025 | M73: VENTAS | N73: 0123 | O73: VF000000000734B | P73: Asiento de VENTAS | Q73: F B 000000000734 | R73: Ref. nota de Venta: CAR.3 Obs.:21-09-2025_CLIENTES | S73: 000000000042 | T73: Ejercicio 2025/2026
D74: CAR | E74: =+VLOOKUP(F74,Resumen_Base!$C$8:$G$287,5,0) -> Tips | F74: 210609 | G74: Propinas a pagar | H74: =+D74&F74 -> CAR210609 | I74: -568000 | J74: -400 | K74: 1420 | L74: 21/09/2025 | M74: VENTAS | N74: 0123 | O74: VF000000000735B | P74: Asiento de VENTAS | Q74: F B 000000000735 | R74: Ref. nota de Venta: CAR.3 Obs.:21-09-2025_CLIENTES | S74: 000000000043 | T74: Ejercicio 2025/2026
D75: CAR | E75: =+VLOOKUP(F75,Resumen_Base!$C$8:$G$287,5,0) -> Tips | F75: 210609 | G75: Propinas a pagar | H75: =+D75&F75 -> CAR210609 | I75: -467180 | J75: -329 | K75: 1420 | L75: 21/09/2025 | M75: VENTAS | N75: 0123 | O75: VF000000000736B | P75: Asiento de VENTAS | Q75: F B 000000000736 | R75: Ref. nota de Venta: CAR.3 Obs.:21-09-2025_CLIENTES | S75: 000000000044 | T75: Ejercicio 2025/2026
D76: CAR | E76: =+VLOOKUP(F76,Resumen_Base!$C$8:$G$287,5,0) -> Tips | F76: 210609 | G76: Propinas a pagar | H76: =+D76&F76 -> CAR210609 | I76: -568000 | J76: -400 | K76: 1420 | L76: 21/09/2025 | M76: VENTAS | N76: 0123 | O76: VF000000000736B | P76: Asiento de VENTAS | Q76: F B 000000000736 | R76: Ref. nota de Venta: CAR.3 Obs.:21-09-2025_CLIENTES | S76: 000000000044 | T76: Ejercicio 2025/2026
D77: CAR | E77: =+VLOOKUP(F77,Resumen_Base!$C$8:$G$287,5,0) -> Tips | F77: 210609 | G77: Propinas a pagar | H77: =+D77&F77 -> CAR210609 | I77: -426000 | J77: -300 | K77: 1420 | L77: 21/09/2025 | M77: VENTAS | N77: 0123 | O77: VF000000000737B | P77: Asiento de VENTAS | Q77: F B 000000000737 | R77: Ref. nota de Venta: CAR.3 Obs.:21-09-2025_CLIENTES | S77: 000000000045 | T77: Ejercicio 2025/2026
D78: CAR | E78: =+VLOOKUP(F78,Resumen_Base!$C$8:$G$287,5,0) -> Tips | F78: 210609 | G78: Propinas a pagar | H78: =+D78&F78 -> CAR210609 | I78: -497000 | J78: -350 | K78: 1420 | L78: 21/09/2025 | M78: VENTAS | N78: 0123 | O78: VF000000000738B | P78: Asiento de VENTAS | Q78: F B 000000000738 | R78: Ref. nota de Venta: CAR.3 Obs.:21-09-2025_CLIENTES | S78: 000000000046 | T78: Ejercicio 2025/2026
... D126: CAR | E126: =+VLOOKUP(F126,Resumen_Base!$C$8:$G$287,5,0) -> Tips | F126: 210609 | G126: Propinas a pagar | H126: =+D126&F126 -> CAR210609 | I126: -1440000 | J126: -960 | K126: 1500 | L126: 26/10/2025 | M126: VENTAS | N126: 0123 | O126: VF000000001579B | P126: Asiento de VENTAS (01/09/2025 - 31/08/2026) | Q126: F B 000000001579 | R126: Ref. nota de Venta: CA.DU30 Obs.:26-10-2025_CLIENTES | S126: 000000000147 | T126: Ejercicio 2025/2026
D127: CAR | E127: =+VLOOKUP(F127,Resumen_Base!$C$8:$G$287,5,0) -> Tips | F127: 210609 | G127: Propinas a pagar | H127: =+D127&F127 -> CAR210609 | I127: -585000 | J127: -390 | K127: 1500 | L127: 22/10/2025 | N127: 0123 | P127: AJUSTE PROPINAS A REMUNERACIONES SERVICIOS | Q127: Pago de tips septiembre paloma Marchetti Housekeeping | R127: Propinas a pagar | S127: 000000000149 | T127: Ejercicio 2025/2026
D128: CAR | E128: =+VLOOKUP(F128,Resumen_Base!$C$8:$G$287,5,0) -> Tips | F128: 210609 | G128: Propinas a pagar | H128: =+D128&F128 -> CAR210609 | I128: -585000 | J128: -390 | K128: 1500 | L128: 22/10/2025 | N128: 0123 | P128: AJUSTE PROPINAS A REMUNERACIONES SERVICIOS | Q128: Pago de tips septiembre yuliana Gonzales Camarera | R128: Propinas a pagar | S128: 000000000149 | T128: Ejercicio 2025/2026
D129: CAR | E129: =+VLOOKUP(F129,Resumen_Base!$C$8:$G$287,5,0) -> Tips | F129: 210609 | G129: Propinas a pagar | H129: =+D129&F129 -> CAR210609 | I129: -585000 | J129: -390 | K129: 1500 | L129: 22/10/2025 | N129: 0123 | P129: AJUSTE PROPINAS A REMUNERACIONES SERVICIOS | Q129: Pago de tios septiembre Valeria olmedo Housekeeping | R129: Propinas a pagar | S129: 000000000149 | T129: Ejercicio 2025/2026
D130: CAR | E130: =+VLOOKUP(F130,Resumen_Base!$C$8:$G$287,5,0) -> Tips | F130: 210609 | G130: Propinas a pagar | H130: =+D130&F130 -> CAR210609 | I130: -585000 | J130: -390 | K130: 1500 | L130: 22/10/2025 | N130: 0123 | P130: AJUSTE PROPINAS A REMUNERACIONES SERVICIOS | Q130: Pago tips septiembre stefania Housekeepi g | R130: Propinas a pagar | S130: 000000000149 | T130: Ejercicio 2025/2026
D131: CAR | E131: =+VLOOKUP(F131,Resumen_Base!$C$8:$G$287,5,0) -> Tips | F131: 210609 | G131: Propinas a pagar | H131: =+D131&F131 -> CAR210609 | I131: -810000 | J131: -540 | K131: 1500 | L131: 22/10/2025 | N131: 0123 | P131: AJUSTE PROPINAS A REMUNERACIONES SERVICIOS | Q131: Pago tips septiembre Sabrina Sous cheff | R131: Propinas a pagar | S131: 000000000149 | T131: Ejercicio 2025/2026
D132: CAR | E132: =+VLOOKUP(F132,Resumen_Base!$C$8:$G$287,5,0) -> Tips | F132: 210609 | G132: Propinas a pagar | H132: =+D132&F132 -> CAR210609 | I132: -465000 | J132: -310 | K132: 1500 | L132: 22/10/2025 | N132: 0123 | P132: AJUSTE PROPINAS A REMUNERACIONES SERVICIOS | Q132: Pago tips septiembre a Santiago de Mantenimiento | R132: Propinas a pagar | S132: 000000000149 | T132: Ejercicio 2025/2026
D133: CAR | E133: =+VLOOKUP(F133,Resumen_Base!$C$8:$G$287,5,0) -> Tips | F133: 210609 | G133: Propinas a pagar | H133: =+D133&F133 -> CAR210609 | I133: -930000 | J133: -620 | K133: 1500 | L133: 22/10/2025 | N133: 0123 | P133: AJUSTE PROPINAS A REMUNERACIONES SERVICIOS | Q133: Tips cheff Rafael anzola | R133: Propinas a pagar | S133: 000000000149 | T133: Ejercicio 2025/2026
D134: CAR | E134: =+VLOOKUP(F134,Resumen_Base!$C$8:$G$287,5,0) -> Extras | F134: 4103 | G134: Ventas de Extras | H134: =+D134&F134 -> CAR4103 | I134: -180000 | J134: -120 | K134: 1500 | L134: 26/10/2025 | M134: VENTAS | N134: 0123 | O134: VF000000001571B | P134: Asiento de VENTAS (01/09/2025 - 31/08/2026) | Q134: F B 000000001571 | R134: Ref. nota de Venta: CA.DU14 Obs.:26-10-2025_CLIENTES | S134: 000000000139 | T134: Ejercicio 2025/2026
D135: CAR | E135: =+VLOOKUP(F135,Resumen_Base!$C$8:$G$287,5,0) -> Extras | F135: 4103 | G135: Ventas de Extras | H135: =+D135&F135 -> CAR4103 | I135: -40500 | J135: -27 | K135: 1500 | L135: 26/10/2025 | M135: VENTAS | N135: 0123 | O135: VF000000001572B | P135: Asiento de VENTAS (01/09/2025 - 31/08/2026) | Q135: F B 000000001572 | R135: Ref. nota de Venta: CA.DU14 Obs.:26-10-2025_CLIENTES | S135: 000000000140 | T135: Ejercicio 2025/2026
D136: CAR | E136: =+VLOOKUP(F136,Resumen_Base!$C$8:$G$287,5,0) -> Extras | F136: 4103 | G136: Ventas de Extras | H136: =+D136&F136 -> CAR4103 | I136: -195000 | J136: -130 | K136: 1500 | L136: 26/10/2025 | M136: VENTAS | N136: 0123 | O136: VF000000001576B | P136: Asiento de VENTAS (01/09/2025 - 31/08/2026) | Q136: F B 000000001576 | R136: Ref. nota de Venta: CA.DU25 Obs.:26-10-2025_CLIENTES | S136: 000000000144 | T136: Ejercicio 2025/2026
D137: CAR | E137: =+VLOOKUP(F137,Resumen_Base!$C$8:$G$287,5,0) -> Shop | F137: 4104 | G137: Ventas Shop | H137: =+D137&F137 -> CAR4104 | I137: -56800 | J137: -40 | K137: 1420 | L137: 21/09/2025 | M137: VENTAS | N137: 0123 | O137: VF000000000736B | P137: Asiento de VENTAS | Q137: F B 000000000736 | R137: Ref. nota de Venta: CAR.3 Obs.:21-09-2025_CLIENTES | S137: 000000000044 | T137: Ejercicio 2025/2026
D138: CAR | E138: =+VLOOKUP(F138,Resumen_Base!$C$8:$G$287,5,0) -> Shop | F138: 4104 | G138: Ventas Shop | H138: =+D138&F138 -> CAR4104 | I138: -56800 | J138: -40 | K138: 1420 | L138: 21/09/2025 | M138: VENTAS | N138: 0123 | O138: VF000000000742B | P138: Asiento de VENTAS | Q138: F B 000000000742 | R138: Ref. nota de Venta: CAR.3 Obs.:21-09-2025_CLIENTES | S138: 000000000050 | T138: Ejercicio 2025/2026
D139: CAR | E139: =+VLOOKUP(F139,Resumen_Base!$C$8:$G$287,5,0) -> Shop | F139: 4104 | G139: Ventas Shop | H139: =+D139&F139 -> CAR4104 | I139: -324300 | J139: -230 | K139: 1410 | L139: 30/09/2025 | M139: VENTAS | N139: 0123 | O139: VF000000000905B | P139: Asiento de VENTAS (01/09/2025 - 31/08/2026) | Q139: F B 000000000905 | R139: Ref. nota de Venta: CA.DU1 Obs.:30-09-2025_CLIENTES | S139: 000000000100 | T139: Ejercicio 2025/2026
D140: CAR | E140: =+VLOOKUP(F140,Resumen_Base!$C$8:$G$287,5,0) -> Shop | F140: 4104 | G140: Ventas Shop | H140: =+D140&F140 -> CAR4104 | I140: -155100 | J140: -110 | K140: 1410 | L140: 30/09/2025 | M140: VENTAS | N140: 0123 | O140: VF000000000905B | P140: Asiento de VENTAS (01/09/2025 - 31/08/2026) | Q140: F B 000000000905 | R140: Ref. nota de Venta: CA.DU1 Obs.:30-09-2025_CLIENTES | S140: 000000000100 | T140: Ejercicio 2025/2026
D141: CAR | E141: =+VLOOKUP(F141,Resumen_Base!$C$8:$G$287,5,0) -> Shop | F141: 4104 | G141: Ventas Shop | H141: =+D141&F141 -> CAR4104 | I141: -246750 | J141: -175 | K141: 1410 | L141: 30/09/2025 | M141: VENTAS | N141: 0123 | O141: VF000000000906B | P141: Asiento de VENTAS (01/09/2025 - 31/08/2026) | Q141: F B 000000000906 | R141: Ref. nota de Venta: CA.DU1 Obs.:30-09-2025_CLIENTES | S141: 000000000101 | T141: Ejercicio 2025/2026
D142: CAR | E142: =+VLOOKUP(F142,Resumen_Base!$C$8:$G$287,5,0) -> Shop | F142: 4104 | G142: Ventas Shop | H142: =+D142&F142 -> CAR4104 | I142: -35250 | J142: -25 | K142: 1410 | L142: 30/09/2025 | M142: VENTAS | N142: 0123 | O142: VF000000000906B | P142: Asiento de VENTAS (01/09/2025 - 31/08/2026) | Q142: F B 000000000906 | R142: Ref. nota de Venta: CA.DU1 Obs.:30-09-2025_CLIENTES | S142: 000000000101 | T142: Ejercicio 2025/2026
D143: CAR | E143: =+VLOOKUP(F143,Resumen_Base!$C$8:$G$287,5,0) -> Shop | F143: 4104 | G143: Ventas Shop | H143: =+D143&F143 -> CAR4104 | I143: -98700 | J143: -70 | K143: 1410 | L143: 30/09/2025 | M143: VENTAS | N143: 0123 | O143: VF000000000908B | P143: Asiento de VENTAS (01/09/2025 - 31/08/2026) | Q143: F B 000000000908 | R143: Ref. nota de Venta: CA.DU19 Obs.:30-09-2025_CLIENTES | S143: 000000000103 | T143: Ejercicio 2025/2026
D144: CAR | E144: =+VLOOKUP(F144,Resumen_Base!$C$8:$G$287,5,0) -> Shop | F144: 4104 | G144: Ventas Shop | H144: =+D144&F144 -> CAR4104 | I144: -35250 | J144: -25 | K144: 1410 | L144: 30/09/2025 | M144: VENTAS | N144: 0123 | O144: VF000000000908B | P144: Asiento de VENTAS (01/09/2025 - 31/08/2026) | Q144: F B 000000000908 | R144: Ref. nota de Venta: CA.DU19 Obs.:30-09-2025_CLIENTES | S144: 000000000103 | T144: Ejercicio 2025/2026
D145: CAR | E145: =+VLOOKUP(F145,Resumen_Base!$C$8:$G$287,5,0) -> Shop | F145: 4104 | G145: Ventas Shop | H145: =+D145&F145 -> CAR4104 | I145: -35250 | J145: -25 | K145: 1410 | L145: 30/09/2025 | M145: VENTAS | N145: 0123 | O145: VF000000000908B | P145: Asiento de VENTAS (01/09/2025 - 31/08/2026) | Q145: F B 000000000908 | R145: Ref. nota de Venta: CA.DU19 Obs.:30-09-2025_CLIENTES | S145: 000000000103 | T145: Ejercicio 2025/2026
... D168: CAR | E168: =+VLOOKUP(F168,Resumen_Base!$C$8:$G$287,5,0) -> Shop | F168: 4104 | G168: Ventas Shop | H168: =+D168&F168 -> CAR4104 | I168: -37500 | J168: -25 | K168: 1500 | L168: 26/10/2025 | M168: VENTAS | N168: 0123 | O168: VF000000001577B | P168: Asiento de VENTAS (01/09/2025 - 31/08/2026) | Q168: F B 000000001577 | R168: Ref. nota de Venta: CA.DU30 Obs.:26-10-2025_CLIENTES | S168: 000000000145 | T168: Ejercicio 2025/2026
D169: CAR | E169: =+VLOOKUP(F169,Resumen_Base!$C$8:$G$287,5,0) -> Shop | F169: 4104 | G169: Ventas Shop | H169: =+D169&F169 -> CAR4104 | I169: -154760 | J169: -106 | K169: 1460 | L169: 31/10/2025 | M169: CAJA | N169: 0123 | O169: TI001400000095 | P169: Asiento de CAJA (01/09/2025 - 31/08/2026) | Q169: Ingreso a Caja 001400000095 Obs: SHOP EDUARDO SARTORELLI | S169: 000000000183 | T169: Ejercicio 2025/2026
D170: CAR | E170: =+VLOOKUP(F170,Resumen_Base!$C$8:$G$287,5,0) -> Extras | F170: 4110 | G170: Ventas Extras - Lavandería | H170: =+D170&F170 -> CAR4110 | I170: -75000 | J170: -50 | K170: 1500 | L170: 26/10/2025 | M170: VENTAS | N170: 0123 | O170: VF000000001569B | P170: Asiento de VENTAS (01/09/2025 - 31/08/2026) | Q170: F B 000000001569 | R170: Ref. nota de Venta: CA.DU14 Obs.:26-10-2025_CLIENTES | S170: 000000000137 | T170: Ejercicio 2025/2026
D171: CAR | E171: =+VLOOKUP(F171,Resumen_Base!$C$8:$G$287,5,0) -> Extras | F171: 4110 | G171: Ventas Extras - Lavandería | H171: =+D171&F171 -> CAR4110 | I171: -75000 | J171: -50 | K171: 1500 | L171: 26/10/2025 | M171: VENTAS | N171: 0123 | O171: VF000000001570B | P171: Asiento de VENTAS (01/09/2025 - 31/08/2026) | Q171: F B 000000001570 | R171: Ref. nota de Venta: CA.DU14 Obs.:26-10-2025_CLIENTES | S171: 000000000138 | T171: Ejercicio 2025/2026
D172: CAR | E172: =+VLOOKUP(F172,Resumen_Base!$C$8:$G$287,5,0) -> Extras | F172: 4110 | G172: Ventas Extras - Lavandería | H172: =+D172&F172 -> CAR4110 | I172: -60000 | J172: -40 | K172: 1500 | L172: 26/10/2025 | M172: VENTAS | N172: 0123 | O172: VF000000001573B | P172: Asiento de VENTAS (01/09/2025 - 31/08/2026) | Q172: F B 000000001573 | R172: Ref. nota de Venta: CA.DU2 Obs.:26-10-2025_CLIENTES | S172: 000000000141 | T172: Ejercicio 2025/2026
D173: CAR | E173: =+VLOOKUP(F173,Resumen_Base!$C$8:$G$287,5,0) -> Extras | F173: 4110 | G173: Ventas Extras - Lavandería | H173: =+D173&F173 -> CAR4110 | I173: -150000 | J173: -100 | K173: 1500 | L173: 26/10/2025 | M173: VENTAS | N173: 0123 | O173: VF000000001575B | P173: Asiento de VENTAS (01/09/2025 - 31/08/2026) | Q173: F B 000000001575 | R173: Ref. nota de Venta: CA.DU2 Obs.:26-10-2025_CLIENTES | S173: 000000000143 | T173: Ejercicio 2025/2026
D174: CAR | E174: =+VLOOKUP(F174,Resumen_Base!$C$8:$G$287,5,0) -> Extras | F174: 4110 | G174: Ventas Extras - Lavandería | H174: =+D174&F174 -> CAR4110 | I174: -105000 | J174: -70 | K174: 1500 | L174: 26/10/2025 | M174: VENTAS | N174: 0123 | O174: VF000000001576B | P174: Asiento de VENTAS (01/09/2025 - 31/08/2026) | Q174: F B 000000001576 | R174: Ref. nota de Venta: CA.DU25 Obs.:26-10-2025_CLIENTES | S174: 000000000144 | T174: Ejercicio 2025/2026
D175: CAR | E175: =+VLOOKUP(F175,Resumen_Base!$C$8:$G$287,5,0) -> Extras | F175: 4112 | G175: Ventas Extras - Masajes | H175: =+D175&F175 -> CAR4112 | I175: -177500 | J175: -125 | K175: 1420 | L175: 21/09/2025 | M175: VENTAS | N175: 0123 | O175: VF000000000733B | P175: Asiento de VENTAS | Q175: F B 000000000733 | R175: Ref. nota de Venta: CAR.3 Obs.:21-09-2025_CLIENTES | S175: 000000000041 | T175: Ejercicio 2025/2026
D176: CAR | E176: =+VLOOKUP(F176,Resumen_Base!$C$8:$G$287,5,0) -> Extras | F176: 4112 | G176: Ventas Extras - Masajes | H176: =+D176&F176 -> CAR4112 | I176: -177500 | J176: -125 | K176: 1420 | L176: 21/09/2025 | M176: VENTAS | N176: 0123 | O176: VF000000000740B | P176: Asiento de VENTAS | Q176: F B 000000000740 | R176: Ref. nota de Venta: CAR.3 Obs.:21-09-2025_CLIENTES | S176: 000000000048 | T176: Ejercicio 2025/2026
D177: CAR | E177: =+VLOOKUP(F177,Resumen_Base!$C$8:$G$287,5,0) -> Extras | F177: 4112 | G177: Ventas Extras - Masajes | H177: =+D177&F177 -> CAR4112 | I177: -177500 | J177: -125 | K177: 1420 | L177: 21/09/2025 | M177: VENTAS | N177: 0123 | O177: VF000000000741B | P177: Asiento de VENTAS | Q177: F B 000000000741 | R177: Ref. nota de Venta: CAR.3 Obs.:21-09-2025_CLIENTES | S177: 000000000049 | T177: Ejercicio 2025/2026
D178: CAR | E178: =+VLOOKUP(F178,Resumen_Base!$C$8:$G$287,5,0) -> Extras | F178: 4112 | G178: Ventas Extras - Masajes | H178: =+D178&F178 -> CAR4112 | I178: -177500 | J178: -125 | K178: 1420 | L178: 21/09/2025 | M178: VENTAS | N178: 0123 | O178: VF000000000742B | P178: Asiento de VENTAS | Q178: F B 000000000742 | R178: Ref. nota de Venta: CAR.3 Obs.:21-09-2025_CLIENTES | S178: 000000000050 | T178: Ejercicio 2025/2026
D179: CAR | E179: =+VLOOKUP(F179,Resumen_Base!$C$8:$G$287,5,0) -> Extras | F179: 4112 | G179: Ventas Extras - Masajes | H179: =+D179&F179 -> CAR4112 | I179: -176250 | J179: -125 | K179: 1410 | L179: 30/09/2025 | M179: VENTAS | N179: 0123 | O179: VF000000000904B | P179: Asiento de VENTAS (01/09/2025 - 31/08/2026) | Q179: F B 000000000904 | R179: Ref. nota de Venta: CA.DU1 Obs.:30-09-2025_CLIENTES | S179: 000000000099 | T179: Ejercicio 2025/2026
D180: CAR | E180: =+VLOOKUP(F180,Resumen_Base!$C$8:$G$287,5,0) -> Extras | F180: 4112 | G180: Ventas Extras - Masajes | H180: =+D180&F180 -> CAR4112 | I180: -176250 | J180: -125 | K180: 1410 | L180: 30/09/2025 | M180: VENTAS | N180: 0123 | O180: VF000000000905B | P180: Asiento de VENTAS (01/09/2025 - 31/08/2026) | Q180: F B 000000000905 | R180: Ref. nota de Venta: CA.DU1 Obs.:30-09-2025_CLIENTES | S180: 000000000100 | T180: Ejercicio 2025/2026
D181: CAR | E181: =+VLOOKUP(F181,Resumen_Base!$C$8:$G$287,5,0) -> Extras | F181: 4112 | G181: Ventas Extras - Masajes | H181: =+D181&F181 -> CAR4112 | I181: -126900 | J181: -90 | K181: 1410 | L181: 30/09/2025 | M181: VENTAS | N181: 0123 | O181: VF000000000906B | P181: Asiento de VENTAS (01/09/2025 - 31/08/2026) | Q181: F B 000000000906 | R181: Ref. nota de Venta: CA.DU1 Obs.:30-09-2025_CLIENTES | S181: 000000000101 | T181: Ejercicio 2025/2026
... D221: SJ | E221: =+VLOOKUP(F221,Resumen_Base!$C$8:$G$287,5,0) -> Field: | F221: 5207 | G221: Acceso/Alquiler Campos | H221: =+D221&F221 -> SJ5207 | I221: 1207000 | J221: 850 | K221: 1420 | L221: 07/12/2025 | M221: CAJA | N221: 0121 | O221: TH001400000168 | P221: Asiento de CAJA (01/09/2025 - 31/08/2026) | Q221: Extracción de Banco 001400000168 Obs: 07-12-2025 Mov Lodge | R221: SJ - entrada campos octubre Palomares | S221: 000000000242 | T221: Ejercicio 2025/2026
A222: AJUSTAR DE SJ A CARMELO | D222: CAR | E222: =+VLOOKUP(F222,Resumen_Base!$C$8:$G$287,5,0) -> Field: | F222: 5207 | G222: Acceso/Alquiler Campos | H222: =+D222&F222 -> CAR5207 | I222: 639000 | J222: 450 | K222: 1420 | L222: 07/12/2025 | M222: CAJA | N222: 0121 | O222: TH001400000168 | P222: Asiento de CAJA (01/09/2025 - 31/08/2026) | Q222: Extracción de Banco 001400000168 Obs: 07-12-2025 Mov Lodge | R222: SJ - entrada campos reembolso cotubre a Long Carmelo | S222: 000000000242 | T222: Ejercicio 2025/2026
D223: SJ | E223: =+VLOOKUP(F223,Resumen_Base!$C$8:$G$287,5,0) -> Field: | F223: 5207 | G223: Acceso/Alquiler Campos | H223: =+D223&F223 -> SJ5207 | I223: 2698 | J223: 1.9 | K223: 1420 | L223: 07/12/2025 | M223: CAJA | N223: 0121 | O223: TH001400000168 | P223: Asiento de CAJA (01/09/2025 - 31/08/2026) | Q223: Extracción de Banco 001400000168 Obs: 07-12-2025 Mov Lodge | R223: SJ - deb comi | S223: 000000000242 | T223: Ejercicio 2025/2026
D224: SJ | E224: =+VLOOKUP(F224,Resumen_Base!$C$8:$G$287,5,0) -> Field: | F224: 5207 | G224: Acceso/Alquiler Campos | H224: =+D224&F224 -> SJ5207 | I224: 2698 | J224: 1.9 | K224: 1420 | L224: 07/12/2025 | M224: CAJA | N224: 0121 | O224: TH001400000168 | P224: Asiento de CAJA (01/09/2025 - 31/08/2026) | Q224: Extracción de Banco 001400000168 Obs: 07-12-2025 Mov Lodge | R224: SJ - deb comi | S224: 000000000242 | T224: Ejercicio 2025/2026
...

Sheet Mov_Analizados_Nov_21
G2: Ver Telefonos
G3: Ver Gastos devengados
G4: Ver Luz Devengada
G5: Ver REVERSAS VINOS
G7: =+IF(I7+J7=0,"Ok","Check") -> Ok | I7: =ROUND(SUM(I10:I166),0) -> 0 | J7: =ROUND(SUM(J10:J166),0) -> 0
D8: FL | E8: Rubro | G8: =+Resumen_Base!D1 -> Ok
B9: =+F9&$C$9&G9 | D9: =+VLOOKUP(F9,Resumen_Base!$C$8:$F$26,4,0) -> #N/A | E9: =+VLOOKUP(F9,Resumen_Base!$C$8:$G$156,5,0) -> #N/A | H9: =+D9&F9 -> #N/A | I9: =SUM(I10:I14) -> 0 | J9: =SUM(J10:J14) -> 0
B10: Cuenta Anterior | D10: Lodge | E10: Concepto | F10: Cuenta | G10: Nombre | I10: monto $ | J10: monto USD | K10: TC | L10: Fecha | M10: Subdiario | N10: Div | O10: Datos del comprobante | P10: Sujeto | Q10: CUIT | R10: Observación asiento | S10: Clase de Asiento | T10: Origen del comprobante | U10: Observación del comprobante | V10: Comentario renglón asiento | W10: Asiento | X10: Control | Z10: monto USD | AA10: tc | AC10: Fecha | AD10: Subdiario | AE10: Div | AF10: Datos del comprobante | AG10: Sujeto | AH10: CUIT | AI10: Observación asiento | AJ10: Clase de Asiento | AK10: Origen del comprobante | AL10: Observación del comprobante | AM10: Comentario renglón asiento | AN10: Asiento
A14: INSERT | B14: INSERT | C14: INSERT | D14: INSERT | E14: INSERT | F14: INSERT | G14: INSERT | H14: INSERT | I14: INSERT | J14: INSERT | K14: INSERT | L14: INSERT | M14: INSERT | N14: INSERT | O14: INSERT | P14: INSERT | Q14: INSERT | R14: INSERT | S14: INSERT | T14: INSERT | U14: INSERT | V14: INSERT | W14: INSERT
A20: INSERT | B20: INSERT | C20: INSERT | D20: INSERT | E20: INSERT | F20: INSERT | G20: INSERT | H20: INSERT | I20: INSERT | J20: INSERT | K20: INSERT | L20: INSERT | M20: INSERT | N20: INSERT | O20: INSERT | P20: INSERT | Q20: INSERT | R20: INSERT | S20: INSERT | T20: INSERT | U20: INSERT | V20: INSERT | W20: INSERT

Sheet Mov_Analizados_Dic_21
G2: Ver Telefonos
G3: Ver Gastos devengados
G4: Ver Luz Devengada
G5: Ver REVERSAS VINOS
G7: =+IF(I7+J7=0,"Ok","Check") -> Ok | I7: =ROUND(SUM(I10:I22),0) -> 0 | J7: =ROUND(SUM(J10:J22),0) -> 0
D8: FL | E8: Rubro | G8: Ok
B9: =+F9&$C$9&G9 | D9: =+VLOOKUP(F9,Resumen_Base!$C$8:$F$26,4,0) -> #N/A | E9: =+VLOOKUP(F9,Resumen_Base!$C$8:$G$156,5,0) -> #N/A | H9: =+D9&F9 -> #N/A | I9: =SUM(I10:I13) -> 0 | J9: =SUM(J10:J13) -> 0
B10: Cuenta Anterior | D10: Lodge | E10: Concepto | F10: Cuenta | G10: Nombre | I10: monto $ | J10: monto USD | K10: TC | L10: Fecha | M10: Subdiario | N10: Div | O10: Datos del comprobante | P10: Sujeto | Q10: CUIT | R10: Observación asiento | S10: Clase de Asiento | T10: Origen del comprobante | U10: Observación del comprobante | V10: Comentario renglón asiento | W10: Asiento | X10: Control | Z10: monto USD | AA10: tc | AC10: Fecha | AD10: Subdiario | AE10: Div | AF10: Datos del comprobante | AG10: Sujeto | AH10: CUIT | AI10: Observación asiento | AJ10: Clase de Asiento | AK10: Origen del comprobante | AL10: Observación del comprobante | AM10: Comentario renglón asiento | AN10: Asiento
A13: INSERT | B13: INSERT | C13: INSERT | D13: INSERT | E13: INSERT | F13: INSERT | G13: INSERT | H13: INSERT | I13: INSERT | J13: INSERT | K13: INSERT | L13: INSERT | M13: INSERT | N13: INSERT | O13: INSERT | P13: INSERT | Q13: INSERT | R13: INSERT | S13: INSERT | T13: INSERT | U13: INSERT | V13: INSERT | W13: INSERT
A22: INSERT | B22: INSERT | C22: INSERT | D22: INSERT | E22: INSERT | F22: INSERT | G22: INSERT | H22: INSERT | I22: INSERT | J22: INSERT | K22: INSERT | L22: INSERT | M22: INSERT | N22: INSERT | O22: INSERT | P22: INSERT | Q22: INSERT | R22: INSERT | S22: INSERT | T22: INSERT | U22: INSERT | V22: INSERT | W22: INSERT

Sheet Mov_Analizados_Ene_Feb 23
G2: Ver Telefonos
G3: Ver Gastos devengados
G4: Ver Luz Devengada
G5: Ver REVERSAS VINOS
G7: =+IF(I7+J7=0,"Ok","Check") -> Ok | I7: =ROUND(SUM(I10:I86),0) -> 0 | J7: =ROUND(SUM(J10:J86),0) -> 0
D8: FL | E8: Rubro | G8: =+Resumen_Base!D1 -> Ok
B9: =+F9&$C$9&G9 | D9: =+VLOOKUP(F9,Resumen_Base!$C$8:$F$26,4,0) -> #N/A | E9: =+VLOOKUP(F9,Resumen_Base!$C$8:$G$156,5,0) -> #N/A | H9: =+D9&F9 -> #N/A | I9: =SUM(I10:I13) -> 0 | J9: =SUM(J10:J13) -> 0
B10: Cuenta Anterior | D10: Lodge | E10: Concepto | F10: Cuenta | G10: Nombre | I10: monto $ | J10: monto USD | K10: TC | L10: Fecha | M10: Subdiario | N10: Div | O10: Datos del comprobante | P10: Sujeto | Q10: CUIT | R10: Observación asiento | S10: Clase de Asiento | T10: Origen del comprobante | U10: Observación del comprobante | V10: Comentario renglón asiento | W10: Asiento | X10: Control | Z10: monto USD | AA10: tc | AC10: Fecha | AD10: Subdiario | AE10: Div | AF10: Datos del comprobante | AG10: Sujeto | AH10: CUIT | AI10: Observación asiento | AJ10: Clase de Asiento | AK10: Origen del comprobante | AL10: Observación del comprobante | AM10: Comentario renglón asiento | AN10: Asiento
A13: INSERT | B13: INSERT | C13: INSERT | D13: INSERT | E13: INSERT | F13: INSERT | G13: INSERT | H13: INSERT | I13: INSERT | J13: INSERT | K13: INSERT | L13: INSERT | M13: INSERT | N13: INSERT | O13: INSERT | P13: INSERT | Q13: INSERT | R13: INSERT | S13: INSERT | T13: INSERT | U13: INSERT | V13: INSERT | W13: INSERT
A20: INSERT | B20: INSERT | C20: INSERT | D20: INSERT | E20: INSERT | F20: INSERT | G20: INSERT | H20: INSERT | I20: INSERT | J20: INSERT | K20: INSERT | L20: INSERT | M20: INSERT | N20: INSERT | O20: INSERT | P20: INSERT | Q20: INSERT | R20: INSERT | S20: INSERT | T20: INSERT | U20: INSERT | V20: INSERT | W20: INSERT

Sheet Mov_Analizados_Feb_22
G2: Ver Telefonos
G3: Ver Gastos devengados
G4: Ver Luz Devengada
G5: Ver REVERSAS VINOS
G7: =+IF(I7+J7=0,"Ok","Check") -> Ok | I7: =ROUND(SUM(I10:I47),0) -> 0 | J7: =ROUND(SUM(J10:J47),0) -> 0
D8: FL | E8: Rubro | G8: =+Resumen_Base!D1 -> Ok
B9: =+F9&$C$9&G9 | D9: =+VLOOKUP(F9,Resumen_Base!$C$8:$F$26,4,0) -> #N/A | E9: =+VLOOKUP(F9,Resumen_Base!$C$8:$G$156,5,0) -> #N/A | H9: =+D9&F9 -> #N/A | I9: =SUM(I10:I13) -> 0 | J9: =SUM(J10:J13) -> 0 | K9: =+AVERAGE(K10:K13) -> #DIV/0!
B10: Cuenta Anterior | D10: Lodge | E10: Concepto | F10: Cuenta | G10: Nombre | I10: monto $ | J10: monto USD | K10: TC | L10: Fecha | M10: Subdiario | N10: Div | O10: Datos del comprobante | P10: Sujeto | Q10: CUIT | R10: Observación asiento | S10: Clase de Asiento | T10: Origen del comprobante | U10: Observación del comprobante | V10: Comentario renglón asiento | W10: Asiento | X10: Control | Z10: monto USD | AA10: tc | AC10: Fecha | AD10: Subdiario | AE10: Div | AF10: Datos del comprobante | AG10: Sujeto | AH10: CUIT | AI10: Observación asiento | AJ10: Clase de Asiento | AK10: Origen del comprobante | AL10: Observación del comprobante | AM10: Comentario renglón asiento | AN10: Asiento
A13: INSERT | B13: INSERT | C13: INSERT | D13: INSERT | E13: INSERT | F13: INSERT | G13: INSERT | H13: INSERT | I13: INSERT | J13: INSERT | K13: INSERT | L13: INSERT | M13: INSERT | N13: INSERT | O13: INSERT | P13: INSERT | Q13: INSERT | R13: INSERT | S13: INSERT | T13: INSERT | U13: INSERT | V13: INSERT | W13: INSERT
A19: INSERT | B19: INSERT | C19: INSERT | D19: INSERT | E19: INSERT | F19: INSERT | G19: INSERT | H19: INSERT | I19: INSERT | J19: INSERT | K19: INSERT | L19: INSERT | M19: INSERT | N19: INSERT | O19: INSERT | P19: INSERT | Q19: INSERT | R19: INSERT | S19: INSERT | T19: INSERT | U19: INSERT | V19: INSERT | W19: INSERT

Sheet Mov_Analizados_Mar_23
A1: Campos | C1: Mant. Vehiculo Scouting
A2: CL | B2: =+#REF! -> #REF! | C2: CL | D2: =+#REF! -> #REF! | G2: Ver Telefonos
A3: FL | B3: =+#REF! -> #REF! | C3: FL | D3: =+#REF! -> #REF! | G3: Ver Gastos devengados
A4: Combustible | G4: Ver Luz Devengada
A5: CL | B5: =+#REF! -> #REF! | G5: Ver REVERSAS VINOS
A6: FL | B6: =+#REF! -> #REF!
A7: Permisos | G7: =+IF(I7+J7=0,"Ok","Check") -> Ok | I7: =ROUND(SUM(I10:I20),0) -> 0 | J7: =ROUND(SUM(J10:J20),0) -> 0
A8: CL | B8: =+#REF! -> #REF! | D8: FL | E8: Rubro | G8: =+Resumen_Base!D1 -> Ok
A9: FL | B9: =+#REF! -> #REF! | D9: =+VLOOKUP(F9,Resumen_Base!$C$8:$F$26,4,0) -> #N/A | E9: =+VLOOKUP(F9,Resumen_Base!$C$8:$G$156,5,0) -> #N/A | H9: =+D9&F9 -> #N/A | I9: =SUM(I10:I14) -> 0 | J9: =SUM(J10:J14) -> 0
B10: Cuenta Anterior | D10: Lodge | E10: Concepto | F10: Cuenta | G10: Nombre | I10: monto $ | J10: monto USD | K10: TC | L10: Fecha | M10: Subdiario | N10: Div | O10: Datos del comprobante | P10: Sujeto | Q10: CUIT | R10: Observación asiento | S10: Clase de Asiento | T10: Origen del comprobante | U10: Observación del comprobante | V10: Comentario renglón asiento | W10: Asiento | X10: Control | Z10: monto USD | AA10: tc | AC10: Fecha | AD10: Subdiario | AE10: Div | AF10: Datos del comprobante | AG10: Sujeto | AH10: CUIT | AI10: Observación asiento | AJ10: Clase de Asiento | AK10: Origen del comprobante | AL10: Observación del comprobante | AM10: Comentario renglón asiento | AN10: Asiento
A14: INSERT | B14: INSERT | C14: INSERT | D14: INSERT | E14: INSERT | F14: INSERT | G14: INSERT | H14: INSERT | I14: INSERT | J14: INSERT | K14: INSERT | L14: INSERT | M14: INSERT | N14: INSERT | O14: INSERT | P14: INSERT | Q14: INSERT | R14: INSERT | S14: INSERT | T14: INSERT | U14: INSERT | V14: INSERT | W14: INSERT
A20: INSERT | B20: INSERT | C20: INSERT | D20: INSERT | E20: INSERT | F20: INSERT | G20: INSERT | H20: INSERT | I20: INSERT | J20: INSERT | K20: INSERT | L20: INSERT | M20: INSERT | N20: INSERT | O20: INSERT | P20: INSERT | Q20: INSERT | R20: INSERT | S20: INSERT | T20: INSERT | U20: INSERT | V20: INSERT | W20: INSERT

Sheet Mov_Analizados_Abr_23
A1: Campos | C1: Mant. Vehiculo Scouting
A2: CL | B2: =+#REF! -> #REF! | C2: CL | D2: =+#REF! -> #REF! | G2: Ver Telefonos
A3: FL | B3: =+#REF! -> #REF! | C3: FL | D3: =+#REF! -> #REF! | G3: Ver Gastos devengados
A4: Combustible | G4: Ver Luz Devengada
A5: CL | B5: =+#REF! -> #REF! | G5: Ver REVERSAS VINOS
A6: FL | B6: =+#REF! -> #REF!
A7: Permisos | G7: =+IF(I7+J7=0,"Ok","Check") -> Ok | I7: =ROUND(SUM(I11:I33),0) -> 0 | J7: =ROUND(SUM(J11:J33),0) -> 0
A8: CL | B8: =+#REF! -> #REF! | D8: FL | E8: Rubro | G8: =+Resumen_Base!D1 -> Ok
A9: FL | B9: =+#REF! -> #REF! | D9: =+VLOOKUP(F9,Resumen_Base!$C$8:$F$26,4,0) -> #N/A | E9: =+VLOOKUP(F9,Resumen_Base!$C$8:$G$156,5,0) -> #N/A | H9: =+D9&F9 -> #N/A | I9: =SUM(I11:I14) -> 0 | J9: =SUM(J11:J14) -> 0
B10: =+F10&G10
B11: Cuenta Anterior | D11: Lodge | E11: Concepto | F11: Cuenta | G11: Nombre | I11: monto $ | J11: monto USD | K11: TC | L11: Fecha | M11: Subdiario | N11: Div | O11: Datos del comprobante | P11: Sujeto | Q11: CUIT | R11: Observación asiento | S11: Clase de Asiento | T11: Origen del comprobante | U11: Observación del comprobante | V11: Comentario renglón asiento | W11: Asiento | X11: Control | Z11: monto USD | AA11: tc | AC11: Fecha | AD11: Subdiario | AE11: Div | AF11: Datos del comprobante | AG11: Sujeto | AH11: CUIT | AI11: Observación asiento | AJ11: Clase de Asiento | AK11: Origen del comprobante | AL11: Observación del comprobante | AM11: Comentario renglón asiento | AN11: Asiento
A14: INSERT | B14: INSERT | C14: INSERT | D14: INSERT | E14: INSERT | F14: INSERT | G14: INSERT | H14: INSERT | I14: INSERT | J14: INSERT | K14: INSERT | L14: INSERT | M14: INSERT | N14: INSERT | O14: INSERT | P14: INSERT | Q14: INSERT | R14: INSERT | S14: INSERT | T14: INSERT | U14: INSERT | V14: INSERT | W14: INSERT
A20: INSERT | B20: INSERT | C20: INSERT | D20: INSERT | E20: INSERT | F20: INSERT | G20: INSERT | H20: INSERT | I20: INSERT | J20: INSERT | K20: INSERT | L20: INSERT | M20: INSERT | N20: INSERT | O20: INSERT | P20: INSERT | Q20: INSERT | R20: INSERT | S20: INSERT | T20: INSERT | U20: INSERT | V20: INSERT | W20: INSERT

Sheet Mov_Analizados_May_23
A1: Campos | C1: Mant. Vehiculo Scouting
A2: CL | B2: =+#REF! -> #REF! | C2: CL | D2: =+#REF! -> #REF! | G2: Ver Telefonos
A3: FL | B3: =+#REF! -> #REF! | C3: FL | D3: =+#REF! -> #REF! | G3: Ver Gastos devengados
A4: Combustible | G4: Ver Luz Devengada
A5: CL | B5: =+#REF! -> #REF! | G5: Ver REVERSAS VINOS
A6: FL | B6: =+#REF! -> #REF!
A7: Permisos | G7: =+IF(I7+J7=0,"Ok","Check") -> Ok | I7: =ROUND(SUM(I11:I18),0) -> 0 | J7: =ROUND(SUM(J11:J18),0) -> 0
A8: CL | B8: =+#REF! -> #REF! | D8: FL | E8: Rubro | G8: =+Resumen_Base!D1 -> Ok
A9: FL | B9: =+#REF! -> #REF! | D9: =+VLOOKUP(F9,Resumen_Base!$C$8:$F$26,4,0) -> #N/A | E9: =+VLOOKUP(F9,Resumen_Base!$C$8:$G$156,5,0) -> #N/A | H9: =+D9&F9 -> #N/A | I9: =SUM(I11:I14) -> 0 | J9: =SUM(J11:J14) -> 0
B11: Cuenta Anterior | D11: Lodge | E11: Concepto | F11: Cuenta | G11: Nombre | I11: monto $ | J11: monto USD | K11: TC | L11: Fecha | M11: Subdiario | N11: Div | O11: Datos del comprobante | P11: Sujeto | Q11: CUIT | R11: Observación asiento | S11: Clase de Asiento | T11: Origen del comprobante | U11: Observación del comprobante | V11: Comentario renglón asiento | W11: Asiento | X11: Control | Z11: monto USD | AA11: tc | AC11: Fecha | AD11: Subdiario | AE11: Div | AF11: Datos del comprobante | AG11: Sujeto | AH11: CUIT | AI11: Observación asiento | AJ11: Clase de Asiento | AK11: Origen del comprobante | AL11: Observación del comprobante | AM11: Comentario renglón asiento | AN11: Asiento
A14: INSERT | B14: INSERT | C14: INSERT | D14: INSERT | E14: INSERT | F14: INSERT | G14: INSERT | H14: INSERT | I14: INSERT | J14: INSERT | K14: INSERT | L14: INSERT | M14: INSERT | N14: INSERT | O14: INSERT | P14: INSERT | Q14: INSERT | R14: INSERT | S14: INSERT | T14: INSERT | U14: INSERT | V14: INSERT | W14: INSERT
A18: INSERT | B18: INSERT | C18: INSERT | D18: INSERT | E18: INSERT | F18: INSERT | G18: INSERT | H18: INSERT | I18: INSERT | J18: INSERT | K18: INSERT | L18: INSERT | M18: INSERT | N18: INSERT | O18: INSERT | P18: INSERT | Q18: INSERT | R18: INSERT | S18: INSERT | T18: INSERT | U18: INSERT | V18: INSERT | W18: INSERT

Sheet Mov_Analizados_Jun_22
G2: Ver Telefonos
G3: Ver Gastos devengados
G4: Ver Luz Devengada
G5: Ver REVERSAS VINOS
G7: =+IF(I7+J7=0,"Ok","Check") -> Ok | I7: =ROUND(SUM(I10:I17),0) -> 0 | J7: =ROUND(SUM(J10:J17),0) -> 0
D8: FL | E8: Rubro | G8: =+Resumen_Base!D1 -> Ok | K8: TC PROM
B9: =+F9&$C$9&G9 | D9: =+VLOOKUP(F9,Resumen_Base!$C$8:$F$26,4,0) -> #N/A | E9: =+VLOOKUP(F9,Resumen_Base!$C$8:$G$156,5,0) -> #N/A | H9: =+D9&F9 -> #N/A | I9: =SUM(I10:I14) -> 0 | J9: =SUM(J10:J14) -> 0 | K9: =+AVERAGE(K10:K17) -> #DIV/0!
B10: Cuenta Anterior | D10: Lodge | E10: Concepto | F10: Cuenta | G10: Nombre | I10: monto $ | J10: monto USD | K10: TC | L10: Fecha | M10: Subdiario | N10: Div | O10: Datos del comprobante | P10: Sujeto | Q10: CUIT | R10: Observación asiento | S10: Clase de Asiento | T10: Origen del comprobante | U10: Observación del comprobante | V10: Comentario renglón asiento | W10: Asiento | X10: Control | Z10: monto USD | AA10: tc | AC10: Fecha | AD10: Subdiario | AE10: Div | AF10: Datos del comprobante | AG10: Sujeto | AH10: CUIT | AI10: Observación asiento | AJ10: Clase de Asiento | AK10: Origen del comprobante | AL10: Observación del comprobante | AM10: Comentario renglón asiento | AN10: Asiento
A14: INSERT | B14: INSERT | C14: INSERT | D14: INSERT | E14: INSERT | F14: INSERT | G14: INSERT | H14: INSERT | I14: INSERT | J14: INSERT | K14: INSERT | L14: INSERT | M14: INSERT | N14: INSERT | O14: INSERT | P14: INSERT | Q14: INSERT | R14: INSERT | S14: INSERT | T14: INSERT | U14: INSERT | V14: INSERT | W14: INSERT
A17: INSERT | B17: INSERT | C17: INSERT | D17: INSERT | E17: INSERT | F17: INSERT | G17: INSERT | H17: INSERT | I17: INSERT | J17: INSERT | K17: INSERT | L17: INSERT | M17: INSERT | N17: INSERT | O17: INSERT | P17: INSERT | Q17: INSERT | R17: INSERT | S17: INSERT | T17: INSERT | U17: INSERT | V17: INSERT | W17: INSERT

Sheet Mov_Analizados_Jul_22
G2: Ver Telefonos
G3: Ver Gastos devengados
G4: Ver Luz Devengada
G5: Ver REVERSAS VINOS
G7: =+IF(I7+J7=0,"Ok","Check") -> Ok | I7: =ROUND(SUM(I10:I16),0) -> 0 | J7: =ROUND(SUM(J10:J16),0) -> 0
D8: FL | E8: Rubro | G8: =+Resumen_Base!D1 -> Ok
B9: =+F9&$C$9&G9 | D9: =+VLOOKUP(F9,Resumen_Base!$C$8:$F$26,4,0) -> #N/A | E9: =+VLOOKUP(F9,Resumen_Base!$C$8:$G$156,5,0) -> #N/A | H9: =+D9&F9 -> #N/A | I9: =SUM(I10:I13) -> 0 | J9: =SUM(J10:J13) -> 0
B10: Cuenta Anterior | D10: Lodge | E10: Concepto | F10: Cuenta | G10: Nombre | I10: monto $ | J10: monto USD | K10: TC | L10: Fecha | M10: Subdiario | N10: Div | O10: Datos del comprobante | P10: Sujeto | Q10: CUIT | R10: Observación asiento | S10: Clase de Asiento | T10: Origen del comprobante | U10: Observación del comprobante | V10: Comentario renglón asiento | W10: Asiento | X10: Control | Z10: monto USD | AA10: tc | AC10: Fecha | AD10: Subdiario | AE10: Div | AF10: Datos del comprobante | AG10: Sujeto | AH10: CUIT | AI10: Observación asiento | AJ10: Clase de Asiento | AK10: Origen del comprobante | AL10: Observación del comprobante | AM10: Comentario renglón asiento | AN10: Asiento
A13: INSERT | B13: INSERT | C13: INSERT | D13: INSERT | E13: INSERT | F13: INSERT | G13: INSERT | H13: INSERT | I13: INSERT | J13: INSERT | K13: INSERT | L13: INSERT | M13: INSERT | N13: INSERT | O13: INSERT | P13: INSERT | Q13: INSERT | R13: INSERT | S13: INSERT | T13: INSERT | U13: INSERT | V13: INSERT | W13: INSERT
A16: INSERT | B16: INSERT | C16: INSERT | D16: INSERT | E16: INSERT | F16: INSERT | G16: INSERT | H16: INSERT | I16: INSERT | J16: INSERT | K16: INSERT | L16: INSERT | M16: INSERT | N16: INSERT | O16: INSERT | P16: INSERT | Q16: INSERT | R16: INSERT | S16: INSERT | T16: INSERT | U16: INSERT | V16: INSERT | W16: INSERT

Sheet Mov_Analizados_Ago_22
G2: Ver Telefonos
G3: Ver Gastos devengados
G4: Ver Luz Devengada
G5: Ver REVERSAS VINOS
G7: =+IF(I7+J7=0,"Ok","Check") -> Ok | I7: =ROUND(SUM(I10:I16),0) -> 0 | J7: =ROUND(SUM(J10:J16),0) -> 0
D8: FL | E8: Rubro | G8: =+Resumen_Base!D1 -> Ok
B9: =+F9&$C$9&G9 | D9: =+VLOOKUP(F9,Resumen_Base!$C$8:$F$26,4,0) -> #N/A | E9: =+VLOOKUP(F9,Resumen_Base!$C$8:$G$156,5,0) -> #N/A | H9: =+D9&F9 -> #N/A | I9: =SUM(I10:I13) -> 0 | J9: =SUM(J10:J13) -> 0
B10: Cuenta Anterior | D10: Lodge | E10: Concepto | F10: Cuenta | G10: Nombre | I10: monto $ | J10: monto USD | K10: TC | L10: Fecha | M10: Subdiario | N10: Div | O10: Datos del comprobante | P10: Sujeto | Q10: CUIT | R10: Observación asiento | S10: Clase de Asiento | T10: Origen del comprobante | U10: Observación del comprobante | V10: Comentario renglón asiento | W10: Asiento | X10: Control | Z10: monto USD | AA10: tc | AC10: Fecha | AD10: Subdiario | AE10: Div | AF10: Datos del comprobante | AG10: Sujeto | AH10: CUIT | AI10: Observación asiento | AJ10: Clase de Asiento | AK10: Origen del comprobante | AL10: Observación del comprobante | AM10: Comentario renglón asiento | AN10: Asiento
A13: INSERT | B13: INSERT | C13: INSERT | D13: INSERT | E13: INSERT | F13: INSERT | G13: INSERT | H13: INSERT | I13: INSERT | J13: INSERT | K13: INSERT | L13: INSERT | M13: INSERT | N13: INSERT | O13: INSERT | P13: INSERT | Q13: INSERT | R13: INSERT | S13: INSERT | T13: INSERT | U13: INSERT | V13: INSERT | W13: INSERT
A16: INSERT | B16: INSERT | C16: INSERT | D16: INSERT | E16: INSERT | F16: INSERT | G16: INSERT | H16: INSERT | I16: INSERT | J16: INSERT | K16: INSERT | L16: INSERT | M16: INSERT | N16: INSERT | O16: INSERT | P16: INSERT | Q16: INSERT | R16: INSERT | S16: INSERT | T16: INSERT | U16: INSERT | V16: INSERT | W16: INSERT

Sheet Mov_Analizados_Ene 26
G2: Ver Telefonos
G3: Ver Gastos devengados
G4: Ver Luz Devengada
G5: Ver REVERSAS
G7: =+IF(I7+J7=0,"Ok","Check") -> Ok | I7: =ROUND(SUM(I10:I829),0) -> 0 | J7: =ROUND(SUM(J10:J829),0) -> 0
D8: FL | E8: Rubro | G8: =+Resumen_Base!D1 -> Ok
B9: =+F9&$C$9&G9 | D9: =+VLOOKUP(F9,Resumen_Base!$C$8:$F$26,4,0) -> #N/A | E9: =+VLOOKUP(F9,Resumen_Base!$C$8:$G$156,5,0) -> #N/A | H9: =+D9&F9 -> #N/A | I9: =SUM(I10:I330) -> 91745932 | J9: =SUM(J10:J330) -> 76869.01
B10: Cuenta Anterior | D10: Lodge | E10: Concepto | F10: Cuenta | G10: Nombre | I10: monto $ | J10: monto USD | K10: TC | L10: Fecha | M10: Subdiario | N10: Div | O10: Datos del comprobante | P10: Sujeto | Q10: CUIT | R10: Observación asiento | S10: Clase de Asiento | T10: Origen del comprobante | U10: Observación del comprobante | V10: Comentario renglón asiento | W10: Asiento | X10: Control | Z10: monto USD | AA10: tc | AC10: Fecha | AD10: Subdiario | AE10: Div | AF10: Datos del comprobante | AG10: Sujeto | AH10: CUIT | AI10: Observación asiento | AJ10: Clase de Asiento | AK10: Origen del comprobante | AL10: Observación del comprobante | AM10: Comentario renglón asiento | AN10: Asiento
C12: Uruguay | D12: CAR | E12: =+VLOOKUP(F12,Resumen_Base!$C$8:$G$287,5,0) -> Fixed Asset's Payments (Investments) Mejoras/equipamiento Lodge | F12: 12020301 | G12: Muebles y útiles | H12: =+D12&F12 -> CAR12020301 | I12: 1905648 | J12: 1287.6 | K12: 1480 | L12: 31/01/2026 | M12: CAJA | N12: 0123 | O12: TH001400000254 | P12: Asiento de CAJA (01/09/2025 - 31/08/2026) | Q12: Extracción de Banco 001400000254 Obs: 31-01-2026 Mov Lodge | R12: CAR - bastones magneticos para cartuchos usados | S12: 000000000341 | T12: Ejercicio 2025/2026
C13: Uruguay | D13: CAR | E13: =+VLOOKUP(F13,Resumen_Base!$C$8:$G$287,5,0) -> Fixed Asset's Payments (Investments) Mejoras/equipamiento Lodge | F13: 12020301 | G13: Muebles y útiles | H13: =+D13&F13 -> CAR12020301 | I13: 373404 | J13: 252.3 | K13: 1480 | L13: 26/01/2026 | M13: CAJA | N13: 0123 | O13: TE001400000225 | P13: Asiento de CAJA (01/09/2025 - 31/08/2026) | Q13: Extracción de Caja 001400000225 Obs: 26-01-2026 Mov Lodge | R13: CAR - Estanterías metálicas para depósito cocina | S13: 000000000327 | T13: Ejercicio 2025/2026
C14: Uruguay | D14: CAR | E14: =+VLOOKUP(F14,Resumen_Base!$C$8:$G$287,5,0) -> Fixed Asset's Payments (Investments) Mejoras/equipamiento Lodge | F14: 12020301 | G14: Muebles y útiles | H14: =+D14&F14 -> CAR12020301 | I14: 33735.99 | J14: 22.794588 | K14: 1480 | L14: 23/01/2026 | M14: CAJA | N14: 0123 | O14: TE001400000243 | P14: Asiento de CAJA (01/09/2025 - 31/08/2026) | Q14: Extracción de Caja 001400000243 Obs: Movimiento_Cajas_Bancos_Semana 25-26 al 23-01-2026 | R14: CAR-Compra perforadora 3 agujeros F.Fijo Oper. Al 23-01-2026 | S14: 000000000330 | T14: Ejercicio 2025/2026
C15: Uruguay | D15: CAR | E15: =+VLOOKUP(F15,Resumen_Base!$C$8:$G$287,5,0) -> Fixed Asset's Payments (Investments) Mejoras/equipamiento Lodge | F15: 12020601 | G15: Ropa Blanca | H15: =+D15&F15 -> CAR12020601 | I15: 78543.6 | J15: 53.07 | K15: 1480 | L15: 26/01/2026 | M15: CAJA | N15: 0123 | O15: TE001400000225 | P15: Asiento de CAJA (01/09/2025 - 31/08/2026) | Q15: Extracción de Caja 001400000225 Obs: 26-01-2026 Mov Lodge | R15: CAR - Envío ropa blanca surtex | S15: 000000000327 | T15: Ejercicio 2025/2026
C16: Uruguay | D16: CAR | E16: =+VLOOKUP(F16,Resumen_Base!$C$8:$G$287,5,0) -> Fixed Asset's Payments (Investments) Mejoras/equipamiento Lodge | F16: 12020901 | G16: Vajillas | H16: =+D16&F16 -> CAR12020901 | I16: 331520 | J16: 224 | K16: 1480 | L16: 31/01/2026 | M16: CAJA | N16: 0123 | O16: TE001400000248 | P16: Asiento de CAJA (01/09/2025 - 31/08/2026) | Q16: Extracción de Caja 001400000248 Obs: 31-01-2026 Mov Lodge | R16: CAR - 12 vasos trago largo + 12 vasos whiskey | S16: 000000000333 | T16: Ejercicio 2025/2026
C17: Uruguay | D17: CAR | E17: =+VLOOKUP(F17,Resumen_Base!$C$8:$G$287,5,0) -> Fixed Asset's Payments (Investments) Armas | F17: 120211 | G17: Armas- Escopetas - Equip Field | H17: =+D17&F17 -> CAR120211 | I17: 2812 | J17: 1.9 | K17: 1480 | L17: 26/01/2026 | M17: CAJA | N17: 0123 | O17: TH001400000236 | P17: Asiento de CAJA (01/09/2025 - 31/08/2026) | Q17: Extracción de Banco 001400000236 Obs: 26-01-2026 Mov Lodge | R17: CAR - deb comi | S17: 000000000337 | T17: Ejercicio 2025/2026
C18: Uruguay | D18: CAR | E18: =+VLOOKUP(F18,Resumen_Base!$C$8:$G$287,5,0) -> Fixed Asset's Payments (Investments) Armas | F18: 120211 | G18: Armas- Escopetas - Equip Field | H18: =+D18&F18 -> CAR120211 | I18: 289813.6 | J18: 195.82 | K18: 1480 | L18: 26/01/2026 | M18: CAJA | N18: 0123 | O18: TH001400000236 | P18: Asiento de CAJA (01/09/2025 - 31/08/2026) | Q18: Extracción de Banco 001400000236 Obs: 26-01-2026 Mov Lodge | R18: CAR - flete cartuchos Pablo Segovia | S18: 000000000337 | T18: Ejercicio 2025/2026
C19: Uruguay | D19: CAR | E19: =+VLOOKUP(F19,Resumen_Base!$C$8:$G$287,5,0) -> Fixed Asset's Payments (Investments) Armas | F19: 120211 | G19: Armas- Escopetas - Equip Field | H19: =+D19&F19 -> CAR120211 | I19: 999991.6 | J19: 675.67 | K19: 1480 | L19: 31/01/2026 | M19: CAJA | N19: 0123 | O19: TH001400000255 | P19: Asiento de CAJA (01/09/2025 - 31/08/2026) | Q19: Extracción de Banco 001400000255 Obs: 31-01-2026 Mov Lodge | R19: CAR - fundas escopetas carmelo | S19: 000000000342 | T19: Ejercicio 2025/2026
C20: Uruguay | D20: CAR | E20: =+VLOOKUP(F20,Resumen_Base!$C$8:$G$287,5,0) -> Tips | F20: 210609 | G20: Propinas a pagar | H20: =+D20&F20 -> CAR210609 | I20: -740000 | J20: -500 | K20: 1480 | L20: 29/01/2026 | M20: VENTAS | N20: 0123 | O20: VF000000004067B | P20: Asiento de VENTAS (01/09/2025 - 31/08/2026) | Q20: F B 000000004067 | R20: Ref. nota de Venta: CA.DU18 Obs.:31-01-2026_CLIENTES | S20: 000000000355 | T20: Ejercicio 2025/2026
C21: Uruguay | D21: CAR | E21: =+VLOOKUP(F21,Resumen_Base!$C$8:$G$287,5,0) -> Tips | F21: 210609 | G21: Propinas a pagar | H21: =+D21&F21 -> CAR210609 | I21: -1184000 | J21: -800 | K21: 1480 | L21: 29/01/2026 | M21: VENTAS | N21: 0123 | O21: VF000000004067B | P21: Asiento de VENTAS (01/09/2025 - 31/08/2026) | Q21: F B 000000004067 | R21: Ref. nota de Venta: CA.DU18 Obs.:31-01-2026_CLIENTES | S21: 000000000355 | T21: Ejercicio 2025/2026
C22: Uruguay | D22: CAR | E22: =+VLOOKUP(F22,Resumen_Base!$C$8:$G$287,5,0) -> Tips | F22: 210609 | G22: Propinas a pagar | H22: =+D22&F22 -> CAR210609 | I22: -532800 | J22: -360 | K22: 1480 | L22: 30/01/2026 | M22: VENTAS | N22: 0123 | O22: VF000000004068B | P22: Asiento de VENTAS (01/09/2025 - 31/08/2026) | Q22: F B 000000004068 | R22: Ref. nota de Venta: CA.DU18 Obs.:31-01-2026_CLIENTES | S22: 000000000356 | T22: Ejercicio 2025/2026
C23: Uruguay | D23: CAR | E23: =+VLOOKUP(F23,Resumen_Base!$C$8:$G$287,5,0) -> Tips | F23: 210609 | G23: Propinas a pagar | H23: =+D23&F23 -> CAR210609 | I23: -266400 | J23: -180 | K23: 1480 | L23: 30/01/2026 | M23: VENTAS | N23: 0123 | O23: VF000000004068B | P23: Asiento de VENTAS (01/09/2025 - 31/08/2026) | Q23: F B 000000004068 | R23: Ref. nota de Venta: CA.DU18 Obs.:31-01-2026_CLIENTES | S23: 000000000356 | T23: Ejercicio 2025/2026
... C121: Uruguay | D121: CAR | E121: =+VLOOKUP(F121,Resumen_Base!$C$8:$G$287,5,0) -> Guides | F121: 5227 | G121: Remuneraciones Guías | H121: =+D121&F121 -> CAR5227 | I121: 2368000 | J121: 1600 | K121: 1480 | L121: 26/01/2026 | M121: CAJA | N121: 0123 | O121: TH001400000236 | P121: Asiento de CAJA (01/09/2025 - 31/08/2026) | Q121: Extracción de Banco 001400000236 Obs: 26-01-2026 Mov Lodge | R121: CAR - Transaccion laboral Michel Cufre | S121: 000000000337 | T121: Ejercicio 2025/2026
A122: CAR | C122: Uruguay | D122: CAR | E122: =+VLOOKUP(F122,Resumen_Base!$C$8:$G$287,5,0) -> Manager | F122: 5228 | G122: Remuneraciones Managers | H122: =+D122&F122 -> CAR5228 | I122: 1171508.8 | J122: 791.56 | K122: 1480 | L122: 31/01/2026 | M122: CAJA | N122: 0121 | O122: TH001400000256 | P122: Asiento de CAJA (01/09/2025 - 31/08/2026) | Q122: Extracción de Banco 001400000256 Obs: 31-01-2026 Mov Lodge | R122: SJ - adelanto servicios personales enero Caro Horta | S122: 000000000343 | T122: Ejercicio 2025/2026
A123: CAR | C123: Uruguay | D123: CAR | E123: =+VLOOKUP(F123,Resumen_Base!$C$8:$G$287,5,0) -> Manager | F123: 5228 | G123: Remuneraciones Managers | H123: =+D123&F123 -> CAR5228 | I123: 2516000 | J123: 1700 | K123: 1480 | L123: 26/01/2026 | M123: CAJA | N123: 0121 | O123: TH001400000238 | P123: Asiento de CAJA (01/09/2025 - 31/08/2026) | Q123: Extracción de Banco 001400000238 Obs: 26-01-2026 Mov Lodge | R123: SJ - SP diciembre Sofia Barran | S123: 000000000339 | T123: Ejercicio 2025/2026
A124: CAR | C124: Uruguay | D124: CAR | E124: =+VLOOKUP(F124,Resumen_Base!$C$8:$G$287,5,0) -> Manager | F124: 5228 | G124: Remuneraciones Managers | H124: =+D124&F124 -> CAR5228 | I124: 444000 | J124: 300 | K124: 1480 | L124: 26/01/2026 | M124: CAJA | N124: 0121 | O124: TH001400000238 | P124: Asiento de CAJA (01/09/2025 - 31/08/2026) | Q124: Extracción de Banco 001400000238 Obs: 26-01-2026 Mov Lodge | R124: SJ - SP diciembre TAtiana Ribas | S124: 000000000339 | T124: Ejercicio 2025/2026
C125: Uruguay | D125: CAR | E125: =+VLOOKUP(F125,Resumen_Base!$C$8:$G$287,5,0) -> Manager | F125: 5228 | G125: Remuneraciones Managers | H125: =+D125&F125 -> CAR5228 | I125: 1480 | J125: 1 | K125: 1480 | L125: 26/01/2026 | M125: CAJA | N125: 0123 | O125: TH001400000236 | P125: Asiento de CAJA (01/09/2025 - 31/08/2026) | Q125: Extracción de Banco 001400000236 Obs: 26-01-2026 Mov Lodge | R125: CAR - deb comi | S125: 000000000337 | T125: Ejercicio 2025/2026
C126: Uruguay | D126: CAR | E126: =+VLOOKUP(F126,Resumen_Base!$C$8:$G$287,5,0) -> Manager | F126: 5228 | G126: Remuneraciones Managers | H126: =+D126&F126 -> CAR5228 | I126: 888000 | J126: 600 | K126: 1480 | L126: 26/01/2026 | M126: CAJA | N126: 0123 | O126: TH001400000236 | P126: Asiento de CAJA (01/09/2025 - 31/08/2026) | Q126: Extracción de Banco 001400000236 Obs: 26-01-2026 Mov Lodge | R126: CAR - medio aguimaldo Caro Horta | S126: 000000000337 | T126: Ejercicio 2025/2026
C127: Uruguay | D127: CAR | E127: =+VLOOKUP(F127,Resumen_Base!$C$8:$G$287,5,0) -> Manager | F127: 5228 | G127: Remuneraciones Managers | H127: =+D127&F127 -> CAR5228 | I127: 2029080 | J127: 1371 | K127: 1480 | L127: 26/01/2026 | M127: CAJA | N127: 0123 | O127: TH001400000236 | P127: Asiento de CAJA (01/09/2025 - 31/08/2026) | Q127: Extracción de Banco 001400000236 Obs: 26-01-2026 Mov Lodge | R127: CAR - sueldo diciembre Caro Horta | S127: 000000000337 | T127: Ejercicio 2025/2026
C128: Uruguay | D128: CAR | E128: =+VLOOKUP(F128,Resumen_Base!$C$8:$G$287,5,0) -> Gun Rental | F128: 5229 | G128: Alquiler Escopetas | H128: =+D128&F128 -> CAR5229 | I128: 2812 | J128: 1.9 | K128: 1480 | L128: 26/01/2026 | M128: CAJA | N128: 0123 | O128: TH001400000236 | P128: Asiento de CAJA (01/09/2025 - 31/08/2026) | Q128: Extracción de Banco 001400000236 Obs: 26-01-2026 Mov Lodge | R128: CAR - deb comi | S128: 000000000337 | T128: Ejercicio 2025/2026
C129: Uruguay | D129: CAR | E129: =+VLOOKUP(F129,Resumen_Base!$C$8:$G$287,5,0) -> Social Security Contributions | F129: 5235 | G129: Cargas Sociales Servicios | H129: =+D129&F129 -> CAR5235 | I129: 3504477.2 | J129: 2367.89 | K129: 1480 | L129: 26/01/2026 | M129: CAJA | N129: 0123 | O129: TH001400000236 | P129: Asiento de CAJA (01/09/2025 - 31/08/2026) | Q129: Extracción de Banco 001400000236 Obs: 26-01-2026 Mov Lodge | R129: CAR - Bps enero Carmelo | S129: 000000000337 | T129: Ejercicio 2025/2026
C130: Uruguay | D130: CAR | E130: =+VLOOKUP(F130,Resumen_Base!$C$8:$G$287,5,0) -> Social Security Contributions | F130: 5237 | G130: Cargas Sociales Managers | H130: =+D130&F130 -> CAR5237 | I130: 831686 | J130: 561.95 | K130: 1480 | L130: 26/01/2026 | M130: CAJA | N130: 0123 | O130: TH001400000236 | P130: Asiento de CAJA (01/09/2025 - 31/08/2026) | Q130: Extracción de Banco 001400000236 Obs: 26-01-2026 Mov Lodge | R130: CAR - bps , fonasa iva dic Caro Horta | S130: 000000000337 | T130: Ejercicio 2025/2026
C131: Uruguay | D131: CAR | E131: =+VLOOKUP(F131,Resumen_Base!$C$8:$G$287,5,0) -> Electricity | F131: 5247 | G131: Combustible y Lub- Elect-Gener | H131: =+D131&F131 -> CAR5247 | I131: 264698 | J131: 178.85 | K131: 1480 | L131: 26/01/2026 | M131: CAJA | N131: 0123 | O131: TH001400000236 | P131: Asiento de CAJA (01/09/2025 - 31/08/2026) | Q131: Extracción de Banco 001400000236 Obs: 26-01-2026 Mov Lodge | R131: CAR - Ute electricidad casa staff | S131: 000000000337 | T131: Ejercicio 2025/2026
C132: Uruguay | D132: CAR | E132: =+VLOOKUP(F132,Resumen_Base!$C$8:$G$287,5,0) -> Electricity | F132: 5247 | G132: Combustible y Lub- Elect-Gener | H132: =+D132&F132 -> CAR5247 | I132: 1019779.2 | J132: 689.04 | K132: 1480 | L132: 26/01/2026 | M132: CAJA | N132: 0123 | O132: TH001400000236 | P132: Asiento de CAJA (01/09/2025 - 31/08/2026) | Q132: Extracción de Banco 001400000236 Obs: 26-01-2026 Mov Lodge | R132: CAR - UTE electricidad Lodge Carmelo | S132: 000000000337 | T132: Ejercicio 2025/2026
C133: Uruguay | D133: CAR | E133: =+VLOOKUP(F133,Resumen_Base!$C$8:$G$287,5,0) -> Electricity - Gas for Boats & Vehicles | F133: 5248 | G133: Combustible y Lub-Vehiculo Bot | H133: =+D133&F133 -> CAR5248 | I133: 75381.6 | J133: 51.28 | K133: 1470 | L133: 12/01/2026 | M133: CAJA | N133: 0123 | O133: TE001400000213 | P133: Asiento de CAJA (01/09/2025 - 31/08/2026) | Q133: Extracción de Caja 001400000213 Obs: 12-01-2026 Mov Lodge | R133: CAR - Combustible | S133: 000000000290 | T133: Ejercicio 2025/2026
C134: Uruguay | D134: CAR | E134: =+VLOOKUP(F134,Resumen_Base!$C$8:$G$287,5,0) -> Electricity - Gas for Boats & Vehicles | F134: 5248 | G134: Combustible y Lub-Vehiculo Bot | H134: =+D134&F134 -> CAR5248 | I134: 2200360.4 | J134: 1486.73 | K134: 1480 | L134: 31/01/2026 | M134: CAJA | N134: 0123 | O134: TH001400000254 | P134: Asiento de CAJA (01/09/2025 - 31/08/2026) | Q134: Extracción de Banco 001400000254 Obs: 31-01-2026 Mov Lodge | R134: CAR - combustible vehiculos enero Servicios Carmelo | S134: 000000000341 | T134: Ejercicio 2025/2026
C135: Uruguay | D135: CAR | E135: =+VLOOKUP(F135,Resumen_Base!$C$8:$G$287,5,0) -> Electricity - Gas for Boats & Vehicles | F135: 5248 | G135: Combustible y Lub-Vehiculo Bot | H135: =+D135&F135 -> CAR5248 | I135: 1147000 | J135: 775 | K135: 1480 | L135: 31/01/2026 | M135: CAJA | N135: 0123 | O135: TH001400000255 | P135: Asiento de CAJA (01/09/2025 - 31/08/2026) | Q135: Extracción de Banco 001400000255 Obs: 31-01-2026 Mov Lodge | R135: CAR - combustible viajes varios Long | S135: 000000000342 | T135: Ejercicio 2025/2026
C136: Uruguay | D136: CAR | E136: =+VLOOKUP(F136,Resumen_Base!$C$8:$G$287,5,0) -> Electricity - Gas for Boats & Vehicles | F136: 5248 | G136: Combustible y Lub-Vehiculo Bot | H136: =+D136&F136 -> CAR5248 | I136: 2871.2 | J136: 1.94 | K136: 1480 | L136: 31/01/2026 | M136: CAJA | N136: 0123 | O136: TH001400000254 | P136: Asiento de CAJA (01/09/2025 - 31/08/2026) | Q136: Extracción de Banco 001400000254 Obs: 31-01-2026 Mov Lodge | R136: CAR - deb comi | S136: 000000000341 | T136: Ejercicio 2025/2026
... C270: Uruguay | D270: CAR | E270: =+VLOOKUP(F270,Resumen_Base!$C$8:$G$287,5,0) -> Food & Wine | F270: 5289 | G270: Comidas Fuera Temp / Empleados | H270: =+D270&F270 -> CAR5289 | I270: 52581.9 | J270: 35.77 | K270: 1470 | L270: 26/01/2026 | M270: CAJA | N270: 0123 | O270: TE001400000225 | P270: Asiento de CAJA (01/09/2025 - 31/08/2026) | Q270: Extracción de Caja 001400000225 Obs: 26-01-2026 Mov Lodge | R270: CAR - Comida santiago mantenimiento carmelo | S270: 000000000327 | T270: Ejercicio 2025/2026
A272: EXTRA CONTABLE REVERSAR EN ENERO 26 | D272: CAR | E272: =+VLOOKUP(F272,Resumen_Base!$C$8:$G$287,5,0) -> Transfer to and from the airport (local taxi) - Vehicle Rental | F272: 5225 | G272: Alquiler Camionetas/Lanchas | H272: =+D272&F272 -> CAR5225 | I272: 0 | J272: -991 | L272: 46013 | N272: 0123 | Q272: saldo nov Celmu Multcar
A273: EXTRA CONTABLE REVERSAR EN ENERO 26 | D273: CAR | E273: =+VLOOKUP(F273,Resumen_Base!$C$8:$G$287,5,0) -> Guides | F273: 5227 | G273: Remuneraciones Guías | H273: =+D273&F273 -> CAR5227 | I273: 0 | J273: -1600 | L273: 46013 | N273: 0123 | Q273: Transaccion laboral Michel Cufre
A274: EXTRA CONTABLE REVERSAR EN ENERO 26 | D274: CAR | E274: =+VLOOKUP(F274,Resumen_Base!$C$8:$G$287,5,0) -> Manager | F274: 5228 | G274: Remuneraciones Managers | H274: =+D274&F274 -> CAR5228 | I274: 0 | J274: -1371 | L274: 46013 | N274: 0123 | Q274: sueldo diciembre Caro Horta
A275: EXTRA CONTABLE REVERSAR EN ENERO 26 | D275: CAR | E275: =+VLOOKUP(F275,Resumen_Base!$C$8:$G$287,5,0) -> Social Security Contributions | F275: 5237 | G275: Cargas Sociales Managers | H275: =+D275&F275 -> CAR5237 | I275: 0 | J275: -561.95 | L275: 46013 | N275: 0123 | Q275: bps , fonasa iva dic Caro Horta
A276: EXTRA CONTABLE REVERSAR EN ENERO 26 | D276: CAR | E276: =+VLOOKUP(F276,Resumen_Base!$C$8:$G$287,5,0) -> Electricity - Gas for Boats & Vehicles | F276: 5248 | G276: Combustible y Lub-Vehiculo Bot | H276: =+D276&F276 -> CAR5248 | I276: 0 | J276: -103 | L276: 46013 | N276: 0123 | Q276: nafta tramites Caro Horta
A277: EXTRA CONTABLE REVERSAR EN ENERO 26 | D277: SJ | E277: =+VLOOKUP(F277,Resumen_Base!$C$8:$G$287,5,0) -> Communications - Phone, internet and satellite TV | F277: 5266 | G277: Comunicaciones Internet | H277: =+D277&F277 -> SJ5266 | I277: 0 | J277: -58 | L277: 46011 | N277: 0121 | Q277: telefoni antel internet
A278: EXTRA CONTABLE REVERSAR EN ENERO 26 | D278: UL | E278: =+VLOOKUP(F278,Resumen_Base!$C$8:$G$287,5,0) -> Communications - Phone, internet and satellite TV | F278: 5266 | G278: Comunicaciones Internet | H278: =+D278&F278 -> UL5266 | I278: 0 | J278: -60.655641 | L278: 46013 | N278: 0122 | Q278: internet starlink
A280: EXTRA CONTABLE REVERSAR EN FEBRERO 26 | D280: CAR | E280: =+VLOOKUP(F280,Resumen_Base!$C$8:$G$287,5,0) -> Field: | F280: 5207 | G280: Alquiler Campos | H280: =+D280&F280 -> CAR5207 | J280: 350 | L280: 46068 | N280: 0123 | R280: entrada campos enero Carlos Bianchi
A281: EXTRA CONTABLE REVERSAR EN FEBRERO 26 | D281: CAR | E281: =+VLOOKUP(F281,Resumen_Base!$C$8:$G$287,5,0) -> Field: | F281: 5207 | G281: Alquiler Campos | H281: =+D281&F281 -> CAR5207 | J281: 150 | L281: 46068 | N281: 0123 | R281: entrada campos enero Daniel Beron
A282: EXTRA CONTABLE REVERSAR EN FEBRERO 26 | D282: CAR | E282: =+VLOOKUP(F282,Resumen_Base!$C$8:$G$287,5,0) -> Field: | F282: 5207 | G282: Alquiler Campos | H282: =+D282&F282 -> CAR5207 | J282: 450 | L282: 46068 | N282: 0123 | R282: entrada campos enero Daniel Palomares
A283: EXTRA CONTABLE REVERSAR EN FEBRERO 26 | D283: CAR | E283: =+VLOOKUP(F283,Resumen_Base!$C$8:$G$287,5,0) -> Licenses / Permits (Fishing and Shooting) | F283: 5221 | G283: Permisos | H283: =+D283&F283 -> CAR5221 | J283: 600 | L283: 46068 | N283: 0123 | R283: honorarios enero Mati Vila
A284: EXTRA CONTABLE REVERSAR EN FEBRERO 26 | D284: CAR | E284: =+VLOOKUP(F284,Resumen_Base!$C$8:$G$287,5,0) -> Services/House | F284: 5226 | G284: Remuneraciones Servicios | H284: =+D284&F284 -> CAR5226 | J284: 115 | L284: 46063 | N284: 0123 | R284: Tips enero santiago mantenimiento
A285: EXTRA CONTABLE REVERSAR EN FEBRERO 26 | D285: CAR | E285: =+VLOOKUP(F285,Resumen_Base!$C$8:$G$287,5,0) -> Services/House | F285: 5226 | G285: Remuneraciones Servicios | H285: =+D285&F285 -> CAR5226 | J285: 145 | L285: 46062 | N285: 0123 | R285: Pago tips enero Paloma housekeeping
A286: EXTRA CONTABLE REVERSAR EN FEBRERO 26 | D286: CAR | E286: =+VLOOKUP(F286,Resumen_Base!$C$8:$G$287,5,0) -> Services/House | F286: 5226 | G286: Remuneraciones Servicios | H286: =+D286&F286 -> CAR5226 | J286: 231 | L286: 46062 | N286: 0123 | R286: Pago tips enero Rafael cocinero
A287: EXTRA CONTABLE REVERSAR EN FEBRERO 26 | D287: CAR | E287: =+VLOOKUP(F287,Resumen_Base!$C$8:$G$287,5,0) -> Services/House | F287: 5226 | G287: Remuneraciones Servicios | H287: =+D287&F287 -> CAR5226 | J287: 202 | L287: 46062 | N287: 0123 | R287: Pago tips enero Victoria cocinera
A288: EXTRA CONTABLE REVERSAR EN FEBRERO 26 | D288: CAR | E288: =+VLOOKUP(F288,Resumen_Base!$C$8:$G$287,5,0) -> Services/House | F288: 5226 | G288: Remuneraciones Servicios | H288: =+D288&F288 -> CAR5226 | J288: 145 | L288: 46062 | N288: 0123 | R288: Pago tips enero Yuliana camarera
A289: EXTRA CONTABLE REVERSAR EN FEBRERO 26 | D289: CAR | E289: =+VLOOKUP(F289,Resumen_Base!$C$8:$G$287,5,0) -> Services/House | F289: 5226 | G289: Remuneraciones Servicios | H289: =+D289&F289 -> CAR5226 | J289: 145 | L289: 46062 | N289: 0123 | R289: Pagos tips enero Valeria housekeeping
A290: EXTRA CONTABLE REVERSAR EN FEBRERO 26 | D290: CAR | E290: =+VLOOKUP(F290,Resumen_Base!$C$8:$G$287,5,0) -> Services/House | F290: 5226 | G290: Remuneraciones Servicios | H290: =+D290&F290 -> CAR5226 | J290: 938.41558 | L290: 46061 | N290: 0123 | R290: sueldo enero Paloma Marchetti
A291: EXTRA CONTABLE REVERSAR EN FEBRERO 26 | D291: CAR | E291: =+VLOOKUP(F291,Resumen_Base!$C$8:$G$287,5,0) -> Services/House | F291: 5226 | G291: Remuneraciones Servicios | H291: =+D291&F291 -> CAR5226 | J291: 920.90909 | L291: 46061 | N291: 0123 | R291: sueldo enero Stefany Suhr
... A324: EXTRA CONTABLE REVERSAR EN FEBRERO 26 | D324: SJ | E324: =+VLOOKUP(F324,Resumen_Base!$C$8:$G$287,5,0) -> Manager | F324: 5228 | G324: Remuneraciones Managers | H324: =+D324&F324 -> SJ5228 | J324: 700 | L324: 46068 | N324: 0121 | R324: complemento honorarios enero Caro Horta
A330: INSERT | B330: INSERT | C330: INSERT | D330: INSERT | E330: INSERT | F330: INSERT | G330: INSERT | H330: INSERT | I330: INSERT | J330: INSERT | K330: INSERT | L330: INSERT | M330: INSERT | N330: INSERT | O330: INSERT | P330: INSERT | Q330: INSERT | R330: INSERT | S330: INSERT | T330: INSERT | U330: INSERT | V330: INSERT | W330: INSERT
A331: EXTRA CONTABLE REVERSAR EN ENERO 26 | F331: 5313 | G331: Gastos y Comisiones Bancarias | I331: 0 | J331: -20 | L331: 46021 | N331: 0121 | Q331: gas man relacion
A332: EXTRA CONTABLE REVERSAR EN ENERO 26 | F332: 110305 | G332: Cartuchos | I332: 0 | J332: -1.9 | L332: 46013 | N332: 0123 | Q332: deb comi
A333: EXTRA CONTABLE REVERSAR EN ENERO 26 | F333: 110305 | G333: Cartuchos | I333: 0 | J333: -195.82 | L333: 46013 | N333: 0123 | Q333: flete cartuchos Pablo Segovia
A334: EXTRA CONTABLE REVERSAR EN ENERO 26 | F334: 110305 | G334: Cartuchos | I334: 0 | J334: -1.9 | L334: 46014 | N334: 0121 | Q334: deb comi
A335: EXTRA CONTABLE REVERSAR EN ENERO 26 | F335: 110305 | G335: Cartuchos | I335: 0 | J335: -195.82 | L335: 46014 | N335: 0121 | Q335: flete 4 cartuchos pablo segovia
A336: EXTRA CONTABLE REVERSAR EN ENERO 26 | I336: 0 | J336: 5161.0456
A337: EXTRA CONTABLE REVERSAR EN FEBRERO 26 | J337: -19588.688
C341: Uruguay | F341: 11010101 | G341: Caja $ Administración | I341: 1300000 | J341: 878.37838 | K341: 1480 | L341: 16/01/2026 | M341: CAJA | N341: 0129 | O341: TA001400000221 | P341: Asiento de CAJA (01/09/2025 - 31/08/2026) | Q341: Canje de Valores 001400000221 Obs: UY-Cambio $ 1,300,000 | R341: Canje de Valores 001400000221 Obs: UY-Cambio $ 1,300,000 | S341: 000000000312 | T341: Ejercicio 2025/2026
C342: Uruguay | F342: 11010101 | G342: Caja $ Administración | I342: 100000 | J342: 67.567568 | K342: 1480 | L342: 23/01/2026 | M342: CAJA | N342: 0129 | O342: TA001400000239 | P342: Asiento de CAJA (01/09/2025 - 31/08/2026) | Q342: Canje de Valores 001400000239 Obs: UY-Cambio $ 100,000 | R342: Canje de Valores 001400000239 Obs: UY-Cambio $ 100,000 | S342: 000000000314 | T342: Ejercicio 2025/2026
C343: Uruguay | F343: 11010101 | G343: Caja $ Administración | I343: 500000 | J343: 337.83784 | K343: 1480 | L343: 30/01/2026 | M343: CAJA | N343: 0129 | O343: TA001400000244 | P343: Asiento de CAJA (01/09/2025 - 31/08/2026) | Q343: Canje de Valores 001400000244 Obs: UY-Cambio $ 500,000 | R343: Canje de Valores 001400000244 Obs: UY-Cambio $ 500,000 | S343: 000000000315 | T343: Ejercicio 2025/2026
C344: Uruguay | F344: 11010101 | G344: Caja $ Administración | I344: -33735.99 | J344: -22.794588 | K344: 1480 | L344: 23/01/2026 | M344: CAJA | N344: 0123 | O344: TE001400000243 | P344: Asiento de CAJA (01/09/2025 - 31/08/2026) | Q344: Extracción de Caja 001400000243 Obs: Movimiento_Cajas_Bancos_Semana 25-26 al 23-01-2026 | R344: CAR-Compra perforadora 3 agujeros F.Fijo Oper. Al 23-01-2026 | S344: 000000000330 | T344: Ejercicio 2025/2026
C345: Uruguay | F345: 11010101 | G345: Caja $ Administración | I345: -558000 | J345: -377.02703 | K345: 1480 | L345: 31/01/2026 | M345: CAJA | N345: 0123 | O345: TE001400000266 | P345: Asiento de CAJA (01/09/2025 - 31/08/2026) | Q345: Extracción de Caja 001400000266 Obs: Movimiento_Cajas_Bancos_Semana 25-26 al 06-02-2026 | R345: CAR-Impresión 50 postales elite club + 400 score cards +300 WL F.Fijo Oper. Al 06-02-2026 - $ 558.00 | S345: 000000000368 | T345: Ejercicio 2025/2026
C346: Uruguay | F346: 11010101 | G346: Caja $ Administración | I346: -558000 | J346: -377.02703 | K346: 1480 | L346: 30/01/2026 | M346: CAJA | N346: 0123 | O346: TE001400000247 | P346: Asiento de CAJA (01/09/2025 - 31/08/2026) | Q346: Extracción de Caja 001400000247 Obs: Movimiento_Cajas_Bancos_Semana 25-26 al 30-01-2026 | R346: CAR-Impresiones 50 Postales elite club + 400 score cards 15x20 en 300gr con trazado + 300 postales f | S346: 000000000332 | T346: Ejercicio 2025/2026
C347: Uruguay | F347: 11010101 | G347: Caja $ Administración | I347: -91340 | J347: -61.716216 | K347: 1480 | L347: 16/01/2026 | M347: CAJA | N347: 0123 | O347: TE001400000223 | P347: Asiento de CAJA (01/09/2025 - 31/08/2026) | Q347: Extracción de Caja 001400000223 Obs: Movimiento_Cajas_Bancos_Semana 25-26 al 16-01-2026 | R347: CAR-Saldo 50 % - Latin Gráfica - impresión brochures x 20 unidades F.Fijo Oper. Al 16-01-2026 | S347: 000000000326 | T347: Ejercicio 2025/2026
C348: Uruguay | F348: 11010101 | G348: Caja $ Administración | I348: -28000 | J348: -18.918919 | K348: 1480 | L348: 16/01/2026 | M348: CAJA | N348: 0123 | O348: TE001400000223 | P348: Asiento de CAJA (01/09/2025 - 31/08/2026) | Q348: Extracción de Caja 001400000223 Obs: Movimiento_Cajas_Bancos_Semana 25-26 al 16-01-2026 | R348: CAR-Servicio Mensajeria Mensual - Diciembre - Logistica Enlace F.Fijo Oper. Al 16-01-2026 | S348: 000000000326 | T348: Ejercicio 2025/2026
C349: Uruguay | F349: 11010101 | G349: Caja $ Administración | I349: -1193670 | J349: -806.53378 | K349: 1480 | L349: 16/01/2026 | M349: CAJA | N349: 0123 | O349: TE001400000223 | P349: Asiento de CAJA (01/09/2025 - 31/08/2026) | Q349: Extracción de Caja 001400000223 Obs: Movimiento_Cajas_Bancos_Semana 25-26 al 16-01-2026 | R349: CAR-Uniformes completos cocina y delantales + uniformes mucamas - Savastano F.Fijo Oper. Al 16-01-20 | S349: 000000000326 | T349: Ejercicio 2025/2026
C350: Uruguay | F350: 11010102 | G350: Caja U$S Administración | I350: -1332000 | J350: -900 | K350: 1480 | L350: 30/01/2026 | M350: CAJA | N350: 0129 | O350: TE001400000246 | P350: Asiento de CAJA (01/09/2025 - 31/08/2026) | Q350: Extracción de Caja 001400000246 Obs: Movimiento_Cajas_Bancos_Semana 25-26 al 30-01-2026 | R350: UY- Maintenance Fees CC Monthly Fee 01/2026 | S350: 000000000331 | T350: Ejercicio 2025/2026
C351: Uruguay | F351: 11010102 | G351: Caja U$S Administración | I351: -1300002.4 | J351: -878.38 | K351: 1480 | L351: 16/01/2026 | M351: CAJA | N351: 0129 | O351: TA001400000221 | P351: Asiento de CAJA (01/09/2025 - 31/08/2026) | Q351: Canje de Valores 001400000221 Obs: UY-Cambio $ 1,300,000 | R351: Canje de Valores 001400000221 Obs: UY-Cambio $ 1,300,000 | S351: 000000000312 | T351: Ejercicio 2025/2026
C352: Uruguay | F352: 11010102 | G352: Caja U$S Administración | I352: -100003.6 | J352: -67.57 | K352: 1480 | L352: 23/01/2026 | M352: CAJA | N352: 0129 | O352: TA001400000239 | P352: Asiento de CAJA (01/09/2025 - 31/08/2026) | Q352: Canje de Valores 001400000239 Obs: UY-Cambio $ 100,000 | R352: Canje de Valores 001400000239 Obs: UY-Cambio $ 100,000 | S352: 000000000314 | T352: Ejercicio 2025/2026
... C807: Uruguay | F807: 5406 | G807: Comisiones Tarjetas Crédito | I807: 311939.6 | J807: 210.77 | K807: 1480 | L807: 31/01/2026 | M807: CAJA | N807: 0123 | O807: TE001400000271 | P807: Asiento de CAJA (2025-09-01 - 2026-08-31) | Q807: Extracción de Caja 001400000271 Obs: Movimiento_Cajas_Bancos_Semana 25-26 al 13-02-2026 | R807: CAR-TriSW Fee CC 01-2026 | S807: 000000000412 | T807: Ejercicio 2025/2026
A809: AJ 5313 | C809: Uruguay | F809: 8101 | G809: Transferencias entre Lodges | I809: 37000 | J809: 25 | K809: 1480 | L809: 26/01/2026 | M809: CAJA | N809: 0121 | O809: TH001400000238 | P809: Asiento de CAJA (01/09/2025 - 31/08/2026) | Q809: Extracción de Banco 001400000238 Obs: 26-01-2026 Mov Lodge | R809: SJ - deb comi ingreso oficina | S809: 000000000339 | T809: Ejercicio 2025/2026
A811: OK | C811: Uruguay | F811: 8101 | G811: Transferencias entre Lodges | I811: -9264.8 | J811: -6.26 | K811: 1480 | L811: 19/01/2026 | M811: CAJA | N811: 0122 | O811: TD001400000228 | P811: Asiento de CAJA (01/09/2025 - 31/08/2026) | Q811: Depósito a Banco 001400000228 Obs: 26-01-2026 Mov Lodge | R811: UL-Traspaso de SJ USD para fondear | S811: 000000000318 | T811: Ejercicio 2025/2026
A812: OK | C812: Uruguay | F812: 8101 | G812: Transferencias entre Lodges | I812: 9264.8 | J812: 6.26 | K812: 1480 | L812: 26/01/2026 | M812: CAJA | N812: 0121 | O812: TH001400000237 | P812: Asiento de CAJA (01/09/2025 - 31/08/2026) | Q812: Extracción de Banco 001400000237 Obs: 26-01-2026 Mov Lodge | R812: SJ - Traspaso para fondear UL $ | S812: 000000000338 | T812: Ejercicio 2025/2026
A813: OK | C813: Uruguay | F813: 8101 | G813: Transferencias entre Lodges | I813: -29600 | J813: -20 | K813: 1480 | L813: 19/01/2026 | M813: CAJA | N813: 0122 | O813: TD001400000229 | P813: Asiento de CAJA (01/09/2025 - 31/08/2026) | Q813: Depósito a Banco 001400000229 Obs: 26-01-2026 Mov Lodge | R813: UL-fondea de SJ USD para banking Card costo | S813: 000000000319 | T813: Ejercicio 2025/2026
A814: OK | C814: Uruguay | F814: 8101 | G814: Transferencias entre Lodges | I814: 29600 | J814: 20 | K814: 1480 | L814: 26/01/2026 | M814: CAJA | N814: 0121 | O814: TH001400000238 | P814: Asiento de CAJA (01/09/2025 - 31/08/2026) | Q814: Extracción de Banco 001400000238 Obs: 26-01-2026 Mov Lodge | R814: SJ - traspaso a UL USD | S814: 000000000339 | T814: Ejercicio 2025/2026
A815: OK | C815: Uruguay | F815: 8101 | G815: Transferencias entre Lodges | I815: -7400000 | J815: -5000 | K815: 1480 | L815: 19/01/2026 | M815: CAJA | N815: 0123 | O815: TD001400000230 | P815: Asiento de CAJA (01/09/2025 - 31/08/2026) | Q815: Depósito a Banco 001400000230 Obs: 26-01-2026 Mov Lodge | R815: CAR - traspaso de SJ USD | S815: 000000000320 | T815: Ejercicio 2025/2026
A816: OK | C816: Uruguay | F816: 8101 | G816: Transferencias entre Lodges | I816: 7400000 | J816: 5000 | K816: 1480 | L816: 26/01/2026 | M816: CAJA | N816: 0121 | O816: TH001400000238 | P816: Asiento de CAJA (01/09/2025 - 31/08/2026) | Q816: Extracción de Banco 001400000238 Obs: 26-01-2026 Mov Lodge | R816: SJ - traspaso a Carmelo USD | S816: 000000000339 | T816: Ejercicio 2025/2026
A817: OK | C817: Uruguay | F817: 8101 | G817: Transferencias entre Lodges | I817: -29400000 | J817: -20000 | K817: 1470 | L817: 12/01/2026 | M817: CAJA | N817: 0123 | O817: TI001400000226 | P817: Asiento de CAJA (01/09/2025 - 31/08/2026) | Q817: Ingreso a Caja 001400000226 Obs: CAR - Ingreso fondos oficina | R817: CAR - Ingreso fondos oficina | S817: 000000000346 | T817: Ejercicio 2025/2026
A818: OK | C818: Uruguay | F818: 8101 | G818: Transferencias entre Lodges | I818: 29400000 | J818: 20000 | K818: 1470 | L818: 09/01/2026 | M818: CAJA | N818: 0123 | O818: TE001400000215 | P818: Asiento de CAJA (01/09/2025 - 31/08/2026) | Q818: Extracción de Caja 001400000215 Obs: Movimiento_Cajas_Bancos_Semana 25-26 al 09-01-2026 | R818: CAR-Caja Carmelo - lleva Maria Capizzi F.Fijo Oper. Al 09-01-2026 | S818: 000000000292 | T818: Ejercicio 2025/2026
A820: DIF EN $ Y USD | C820: Uruguay | F820: 8101 | G820: Transferencias entre Lodges | I820: -390498 | J820: -263.85 | K820: 1480 | L820: 30/01/2026 | M820: CAJA | N820: 0122 | O820: TD001400000251 | P820: Asiento de CAJA (01/09/2025 - 31/08/2026) | Q820: Depósito a Banco 001400000251 Obs: TRaspaso de USD SJ | R820: TRaspaso de USD SJ | S820: 000000000323 | T820: Ejercicio 2025/2026
A821: DIF EN $ Y USD | C821: Uruguay | F821: 8101 | G821: Transferencias entre Lodges | I821: 391534 | J821: 264.55 | K821: 1480 | L821: 31/01/2026 | M821: CAJA | N821: 0121 | O821: TH001400000257 | P821: Asiento de CAJA (01/09/2025 - 31/08/2026) | Q821: Extracción de Banco 001400000257 Obs: 31-01-2026 Mov Lodge | R821: SJ - Traspaso a UL $ | S821: 000000000344 | T821: Ejercicio 2025/2026
A822: DIF EN $ Y USD | C822: Uruguay | F822: 8101 | G822: Transferencias entre Lodges | I822: -8843000 | J822: -5975 | K822: 1480 | L822: 19/01/2026 | M822: CAJA | N822: 0121 | O822: TD001400000232 | P822: Asiento de CAJA (01/09/2025 - 31/08/2026) | Q822: Depósito a Banco 001400000232 Obs: SJ - ingreso de OFCINA | R822: SJ - ingreso de OFCINA | S822: 000000000322 | T822: Ejercicio 2025/2026
... A825: DIF EN $ Y USD | C825: Uruguay | F825: 8101 | G825: Transferencias entre Lodges | I825: 54760000 | J825: 37000 | K825: 1480 | L825: 16/01/2026 | M825: CAJA | N825: 0123 | O825: TE001400000222 | P825: Asiento de CAJA (01/09/2025 - 31/08/2026) | Q825: Extracción de Caja 001400000222 Obs: Movimiento_Cajas_Bancos_Semana 25-26 al 16-01-2026 | R825: CAR- ValleySW- CARMELO LODGE SAS - (Carmelo Operating Needs - January)- | S825: 000000000325 | T825: Ejercicio 2025/2026
A829: INSERT | B829: INSERT | C829: INSERT | D829: INSERT | E829: INSERT | F829: INSERT | G829: INSERT | H829: INSERT | I829: INSERT | J829: INSERT | K829: INSERT | L829: INSERT | M829: INSERT | N829: INSERT | O829: INSERT | P829: INSERT | Q829: INSERT | R829: INSERT | S829: INSERT | T829: INSERT | U829: INSERT | V829: INSERT | W829: INSERT | X829: INSERT | Y829: INSERT | Z829: INSERT | AA829: INSERT | AB829: INSERT | AC829: INSERT | AD829: INSERT | AE829: INSERT | AF829: INSERT | AG829: INSERT | AH829: INSERT | AI829: INSERT | AJ829: INSERT | AK829: INSERT | AL829: INSERT | AM829: INSERT | AN829: INSERT

Sheet Mov_Analizados_Feb - Mar 26
G2: Ver Telefonos
G3: Ver Gastos devengados
G4: Ver Luz Devengada
G5: Ver REVERSAS
G7: =+IF(I7+J7=0,"Ok","Check") -> Ok | I7: =ROUND(SUM(I10:I3520),0) -> 0 | J7: =ROUND(SUM(J10:J3520),0) -> 0
D8: FL | E8: Rubro | G8: =+Resumen_Base!D1 -> Ok
B9: =+F9&$C$9&G9 | D9: =+VLOOKUP(F9,Resumen_Base!$C$8:$F$26,4,0) -> #N/A | E9: =+VLOOKUP(F9,Resumen_Base!$C$8:$G$156,5,0) -> #N/A | H9: =+D9&F9 -> #N/A | I9: =SUM(I10:I1378) -> 1.0077694e+08 | J9: =SUM(J10:J1378) -> 103144.36
A10: AJUSTES | B10: Cuenta Anterior | D10: Lodge | E10: Concepto | F10: Cuenta | G10: Nombre | I10: monto $ | J10: monto USD | K10: TC | L10: Fecha | M10: Subdiario | N10: Div | O10: Datos del comprobante | P10: Sujeto | Q10: CUIT | R10: Observación asiento | S10: Clase de Asiento | T10: Origen del comprobante | U10: Observación del comprobante | V10: Comentario renglón asiento | W10: Asiento | X10: Control | Z10: monto USD | AA10: tc | AC10: Fecha | AD10: Subdiario | AE10: Div | AF10: Datos del comprobante | AG10: Sujeto | AH10: CUIT | AI10: Observación asiento | AJ10: Clase de Asiento | AK10: Origen del comprobante | AL10: Observación del comprobante | AM10: Comentario renglón asiento | AN10: Asiento
C13: Uruguay | D13: SJ | E13: =+VLOOKUP(F13,Resumen_Base!$C$8:$G$156,5,0) -> Fixed Asset's Payments (Investments) Mejoras/equipamiento Lodge | F13: 12020103 | G13: Mejoras de Inmueb y Terrenos | H13: =+D13&F13 -> SJ12020103 | I13: 2707.5 | J13: 1.9 | K13: 1425 | L13: 16/02/2026 | M13: CAJA | N13: 0121 | O13: TH001400000277 | P13: Asiento de CAJA (2025-09-01 - 2026-08-31) | Q13: Extracción de Banco 001400000277 Obs: 16-02-2026 Mov Lodge | R13: SJ - deb comi | S13: 000000000417 | T13: Ejercicio 2025/2026
C14: Uruguay | D14: SJ | E14: =+VLOOKUP(F14,Resumen_Base!$C$8:$G$156,5,0) -> Fixed Asset's Payments (Investments) Mejoras/equipamiento Lodge | F14: 12020103 | G14: Mejoras de Inmueb y Terrenos | H14: =+D14&F14 -> SJ12020103 | I14: 370614 | J14: 260.08 | K14: 1425 | L14: 16/02/2026 | M14: CAJA | N14: 0121 | O14: TH001400000277 | P14: Asiento de CAJA (2025-09-01 - 2026-08-31) | Q14: Extracción de Banco 001400000277 Obs: 16-02-2026 Mov Lodge | R14: SJ - pintura arreglos San Juan | S14: 000000000417 | T14: Ejercicio 2025/2026
A15: ESTO ES URU LODGE | C15: Uruguay | D15: UL | E15: =+VLOOKUP(F15,Resumen_Base!$C$8:$G$156,5,0) -> Fixed Asset's Payments (Investments) Mejoras/equipamiento Lodge | F15: 12020103 | G15: Mejoras de Inmueb y Terrenos | H15: =+D15&F15 -> UL12020103 | I15: 6300395.2 | J15: 4421.33 | K15: 1425 | L15: 16/02/2026 | M15: CAJA | N15: 0121 | O15: TH001400000277 | P15: Asiento de CAJA (2025-09-01 - 2026-08-31) | Q15: Extracción de Banco 001400000277 Obs: 16-02-2026 Mov Lodge | R15: SJ - pintura fachada Valle de soba Crisoles | S15: 000000000417 | T15: Ejercicio 2025/2026
C16: Uruguay | D16: CAR | E16: =+VLOOKUP(F16,Resumen_Base!$C$8:$G$156,5,0) -> Fixed Asset's Payments (Investments) Mejoras/equipamiento Lodge | F16: 12020103 | G16: Mejoras de Inmueb y Terrenos | H16: =+D16&F16 -> CAR12020103 | I16: 52725 | J16: 37 | K16: 1425 | L16: 23/02/2026 | M16: CAJA | N16: 0123 | O16: TE001400000296 | P16: Asiento de CAJA (01/09/2025 - 310326) | Q16: Extracción de Caja 001400000296 Obs: 23-02-2026 Mov Lodge | R16: "CAR - Compra de antialgas y tornillo madera (1430 uruguayos)Se abono con usd" | S16: 000000000484 | T16: Ejercicio 2025/2026
C17: Uruguay | D17: CAR | E17: =+VLOOKUP(F17,Resumen_Base!$C$8:$G$156,5,0) -> Fixed Asset's Payments (Investments) Mejoras/equipamiento Lodge | F17: 12020103 | G17: Mejoras de Inmueb y Terrenos | H17: =+D17&F17 -> CAR12020103 | I17: 81225 | J17: 57 | K17: 1425 | L17: 16/02/2026 | M17: CAJA | N17: 0123 | O17: TE001400000283 | P17: Asiento de CAJA (2025-09-01 - 2026-08-31) | Q17: Extracción de Caja 001400000283 Obs: 16-02-2026 Mov Lodge | R17: CAR - Cañería instalaciones lavadero nuevo en galpón | S17: 000000000414 | T17: Ejercicio 2025/2026
C18: Uruguay | D18: CAR | E18: =+VLOOKUP(F18,Resumen_Base!$C$8:$G$156,5,0) -> Fixed Asset's Payments (Investments) Mejoras/equipamiento Lodge | F18: 12020103 | G18: Mejoras de Inmueb y Terrenos | H18: =+D18&F18 -> CAR12020103 | I18: 728175 | J18: 511 | K18: 1425 | L18: 23/02/2026 | M18: CAJA | N18: 0123 | O18: TE001400000296 | P18: Asiento de CAJA (01/09/2025 - 310326) | Q18: Extracción de Caja 001400000296 Obs: 23-02-2026 Mov Lodge | R18: CAR - Compra arena, varilla, hidrofogo, ticholo y pallet para obra casa staff | S18: 000000000484 | T18: Ejercicio 2025/2026
C19: Uruguay | D19: CAR | E19: =+VLOOKUP(F19,Resumen_Base!$C$8:$G$156,5,0) -> Fixed Asset's Payments (Investments) Mejoras/equipamiento Lodge | F19: 12020103 | G19: Mejoras de Inmueb y Terrenos | H19: =+D19&F19 -> CAR12020103 | I19: 145350 | J19: 102 | K19: 1425 | L19: 28/02/2026 | M19: CAJA | N19: 0123 | O19: TE001400000303 | P19: Asiento de CAJA (01/09/2025 - 310326) | Q19: Extracción de Caja 001400000303 Obs: 28-02-2026 Mov Lodge | R19: CAR - Compra de productos ferretería casa staff | S19: 000000000486 | T19: Ejercicio 2025/2026
C20: Uruguay | D20: CAR | E20: =+VLOOKUP(F20,Resumen_Base!$C$8:$G$156,5,0) -> Fixed Asset's Payments (Investments) Mejoras/equipamiento Lodge | F20: 12020103 | G20: Mejoras de Inmueb y Terrenos | H20: =+D20&F20 -> CAR12020103 | I20: 85372 | J20: 60.98 | K20: 1400 | L20: 16/03/2026 | M20: CAJA | N20: 0123 | O20: TE001400000329 | P20: Asiento de CAJA (01/09/2025 - 310326) | Q20: Extracción de Caja 001400000329 Obs: 16-03-2026 Mov Lodge | R20: CAR - Compra hierros para obra casa staff | S20: 000000000491 | T20: Ejercicio 2025/2026
C21: Uruguay | D21: CAR | E21: =+VLOOKUP(F21,Resumen_Base!$C$8:$G$156,5,0) -> Fixed Asset's Payments (Investments) Mejoras/equipamiento Lodge | F21: 12020103 | G21: Mejoras de Inmueb y Terrenos | H21: =+D21&F21 -> CAR12020103 | I21: 12825 | J21: 9 | K21: 1425 | L21: 23/02/2026 | M21: CAJA | N21: 0123 | O21: TE001400000296 | P21: Asiento de CAJA (01/09/2025 - 310326) | Q21: Extracción de Caja 001400000296 Obs: 23-02-2026 Mov Lodge | R21: CAR - Compra material arreglo pileta | S21: 000000000484 | T21: Ejercicio 2025/2026
A22: Pagan dueños propiedad | C22: Uruguay | D22: CAR | E22: =+VLOOKUP(F22,Resumen_Base!$C$8:$G$156,5,0) -> Fixed Asset's Payments (Investments) Mejoras/equipamiento Lodge | F22: 12020103 | G22: Mejoras de Inmueb y Terrenos | H22: =+D22&F22 -> CAR12020103 | I22: 882960 | J22: 624 | K22: 1415 | L22: 23/03/2026 | M22: CAJA | N22: 0123 | O22: TE001400000347 | P22: Asiento de CAJA (01/09/2025 - 310326) | Q22: Extracción de Caja 001400000347 Obs: 23-03-2026 Mov Lodge | R22: CAR - Compra materiales casa staff | S22: 000000000495 | T22: Ejercicio 2025/2026
A23: Pagan dueños propiedad | C23: Uruguay | D23: CAR | E23: =+VLOOKUP(F23,Resumen_Base!$C$8:$G$156,5,0) -> Fixed Asset's Payments (Investments) Mejoras/equipamiento Lodge | F23: 12020103 | G23: Mejoras de Inmueb y Terrenos | H23: =+D23&F23 -> CAR12020103 | I23: 732005 | J23: 521 | K23: 1405 | L23: 31/03/2026 | M23: CAJA | N23: 0123 | O23: TE001400000352 | P23: Asiento de CAJA (01/09/2025 - 310326) | Q23: Extracción de Caja 001400000352 Obs: 31-03-2026 Mov Lodge | R23: CAR - Compra materiales casa staff | S23: 000000000498 | T23: Ejercicio 2025/2026
A24: Pagan dueños propiedad | C24: Uruguay | D24: CAR | E24: =+VLOOKUP(F24,Resumen_Base!$C$8:$G$156,5,0) -> Fixed Asset's Payments (Investments) Mejoras/equipamiento Lodge | F24: 12020103 | G24: Mejoras de Inmueb y Terrenos | H24: =+D24&F24 -> CAR12020103 | I24: 1050000 | J24: 750 | K24: 1400 | L24: 16/03/2026 | M24: CAJA | N24: 0123 | O24: TE001400000329 | P24: Asiento de CAJA (01/09/2025 - 310326) | Q24: Extracción de Caja 001400000329 Obs: 16-03-2026 Mov Lodge | R24: CAR - Compra materiales obra casa staff | S24: 000000000491 | T24: Ejercicio 2025/2026
A25: Pagan dueños propiedad | C25: Uruguay | D25: CAR | E25: =+VLOOKUP(F25,Resumen_Base!$C$8:$G$156,5,0) -> Fixed Asset's Payments (Investments) Mejoras/equipamiento Lodge | F25: 12020103 | G25: Mejoras de Inmueb y Terrenos | H25: =+D25&F25 -> CAR12020103 | I25: 747120 | J25: 528 | K25: 1415 | L25: 28/02/2026 | M25: CAJA | N25: 0123 | O25: TE001400000303 | P25: Asiento de CAJA (01/09/2025 - 310326) | Q25: Extracción de Caja 001400000303 Obs: 28-02-2026 Mov Lodge | R25: CAR - Compra suministros obra casa staff | S25: 000000000486 | T25: Ejercicio 2025/2026
A26: Pagan dueños propiedad | C26: Uruguay | D26: CAR | E26: =+VLOOKUP(F26,Resumen_Base!$C$8:$G$156,5,0) -> Fixed Asset's Payments (Investments) Mejoras/equipamiento Lodge | F26: 12020103 | G26: Mejoras de Inmueb y Terrenos | H26: =+D26&F26 -> CAR12020103 | I26: 2186175 | J26: 1545 | K26: 1415 | L26: 28/02/2026 | M26: CAJA | N26: 0123 | O26: TE001400000303 | P26: Asiento de CAJA (01/09/2025 - 310326) | Q26: Extracción de Caja 001400000303 Obs: 28-02-2026 Mov Lodge | R26: CAR - Compra vidriería casa staff | S26: 000000000486 | T26: Ejercicio 2025/2026
A27: Pagan dueños propiedad | C27: Uruguay | D27: CAR | E27: =+VLOOKUP(F27,Resumen_Base!$C$8:$G$156,5,0) -> Fixed Asset's Payments (Investments) Mejoras/equipamiento Lodge | F27: 12020103 | G27: Mejoras de Inmueb y Terrenos | H27: =+D27&F27 -> CAR12020103 | I27: 1264500 | J27: 900 | K27: 1405 | L27: 31/03/2026 | M27: CAJA | N27: 0123 | O27: TE001400000352 | P27: Asiento de CAJA (01/09/2025 - 310326) | Q27: Extracción de Caja 001400000352 Obs: 31-03-2026 Mov Lodge | R27: CAR - Mano de obra casa staff | S27: 000000000498 | T27: Ejercicio 2025/2026
A28: Pagan dueños propiedad | C28: Uruguay | D28: CAR | E28: =+VLOOKUP(F28,Resumen_Base!$C$8:$G$156,5,0) -> Fixed Asset's Payments (Investments) Mejoras/equipamiento Lodge | F28: 12020103 | G28: Mejoras de Inmueb y Terrenos | H28: =+D28&F28 -> CAR12020103 | I28: 171820.8 | J28: 119.32 | K28: 1440 | L28: 09/02/2026 | M28: CAJA | N28: 0123 | O28: TE001400000258 | P28: Asiento de CAJA (01/09/2025 - 31/08/2026) | Q28: Extracción de Caja 001400000258 Obs: 09-02-2026 Mov Lodge | R28: CAR - Materiales obra casa staff | S28: 000000000367 | T28: Ejercicio 2025/2026
A29: Pagan dueños propiedad | C29: Uruguay | D29: CAR | E29: =+VLOOKUP(F29,Resumen_Base!$C$8:$G$156,5,0) -> Fixed Asset's Payments (Investments) Mejoras/equipamiento Lodge | F29: 12020103 | G29: Mejoras de Inmueb y Terrenos | H29: =+D29&F29 -> CAR12020103 | I29: 2448000 | J29: 1700 | K29: 1440 | L29: 09/02/2026 | M29: CAJA | N29: 0123 | O29: TE001400000258 | P29: Asiento de CAJA (01/09/2025 - 31/08/2026) | Q29: Extracción de Caja 001400000258 Obs: 09-02-2026 Mov Lodge | R29: CAR - Materiales obra casa staff | S29: 000000000367 | T29: Ejercicio 2025/2026
A30: Pagan dueños propiedad | C30: Uruguay | D30: CAR | E30: =+VLOOKUP(F30,Resumen_Base!$C$8:$G$156,5,0) -> Fixed Asset's Payments (Investments) Mejoras/equipamiento Lodge | F30: 12020103 | G30: Mejoras de Inmueb y Terrenos | H30: =+D30&F30 -> CAR12020103 | I30: 118275 | J30: 83 | K30: 1425 | L30: 16/02/2026 | M30: CAJA | N30: 0123 | O30: TE001400000283 | P30: Asiento de CAJA (2025-09-01 - 2026-08-31) | Q30: Extracción de Caja 001400000283 Obs: 16-02-2026 Mov Lodge | R30: CAR - Materiales obra casa staff | S30: 000000000414 | T30: Ejercicio 2025/2026
A31: Pagan dueños propiedad | C31: Uruguay | D31: CAR | E31: =+VLOOKUP(F31,Resumen_Base!$C$8:$G$156,5,0) -> Fixed Asset's Payments (Investments) Mejoras/equipamiento Lodge | F31: 12020103 | G31: Mejoras de Inmueb y Terrenos | H31: =+D31&F31 -> CAR12020103 | I31: 936000 | J31: 650 | K31: 1440 | L31: 16/02/2026 | M31: CAJA | N31: 0123 | O31: TE001400000283 | P31: Asiento de CAJA (2025-09-01 - 2026-08-31) | Q31: Extracción de Caja 001400000283 Obs: 16-02-2026 Mov Lodge | R31: CAR - Obra pozo séptico casa staff | S31: 000000000414 | T31: Ejercicio 2025/2026
A32: Pagan dueños propiedad | C32: Uruguay | D32: CAR | E32: =+VLOOKUP(F32,Resumen_Base!$C$8:$G$156,5,0) -> Fixed Asset's Payments (Investments) Mejoras/equipamiento Lodge | F32: 12020103 | G32: Mejoras de Inmueb y Terrenos | H32: =+D32&F32 -> CAR12020103 | I32: 2880000 | J32: 2000 | K32: 1440 | L32: 16/02/2026 | M32: CAJA | N32: 0123 | O32: TE001400000283 | P32: Asiento de CAJA (2025-09-01 - 2026-08-31) | Q32: Extracción de Caja 001400000283 Obs: 16-02-2026 Mov Lodge | R32: CAR - Pago en concepto de Mano de obra casa staff | S32: 000000000414 | T32: Ejercicio 2025/2026
A33: Pagan dueños propiedad | C33: Uruguay | D33: CAR | E33: =+VLOOKUP(F33,Resumen_Base!$C$8:$G$156,5,0) -> Fixed Asset's Payments (Investments) Mejoras/equipamiento Lodge | F33: 12020103 | G33: Mejoras de Inmueb y Terrenos | H33: =+D33&F33 -> CAR12020103 | I33: 1140000 | J33: 800 | K33: 1425 | L33: 23/02/2026 | M33: CAJA | N33: 0123 | O33: TE001400000296 | P33: Asiento de CAJA (01/09/2025 - 310326) | Q33: Extracción de Caja 001400000296 Obs: 23-02-2026 Mov Lodge | R33: CAR - Pago Walter Mano de obra | S33: 000000000484 | T33: Ejercicio 2025/2026
... A38: Pagan dueños propiedad | C38: Uruguay | D38: CAR | E38: =+VLOOKUP(F38,Resumen_Base!$C$8:$G$156,5,0) -> Fixed Asset's Payments (Investments) Mejoras/equipamiento Lodge | F38: 12020103 | G38: Mejoras de Inmueb y Terrenos | H38: =+D38&F38 -> CAR12020103 | I38: 846450 | J38: 594 | K38: 1425 | L38: 23/02/2026 | M38: CAJA | N38: 0123 | O38: TE001400000296 | P38: Asiento de CAJA (01/09/2025 - 310326) | Q38: Extracción de Caja 001400000296 Obs: 23-02-2026 Mov Lodge | R38: CAR - palos para realizar empalizada frente en casa staff | S38: 000000000484 | T38: Ejercicio 2025/2026
C39: Uruguay | D39: CAR | E39: =+VLOOKUP(F39,Resumen_Base!$C$8:$G$156,5,0) -> Fixed Asset's Payments (Investments) Mejoras/equipamiento Lodge | F39: 12020103 | G39: Mejoras de Inmueb y Terrenos | H39: =+D39&F39 -> CAR12020103 | I39: -83237375 | J39: -58825 | K39: 1415 | L39: 28/02/2026 | M39: CAJA | N39: 0123 | O39: TI001400000350 | P39: Asiento de CAJA (01/09/2025 - 310326) | Q39: Ingreso a Caja 001400000350 Obs: Movimiento_Cajas_Bancos_Semana 25-26 al 20-03-2026 | R39: CAR- recupero Obras ya abonadas 58,825 - contra Canon Anual 25/26 - 75k - USD 58,825 | S39: 000000000537 | T39: Ejercicio 2025/2026
C40: Uruguay | D40: SJ | E40: =+VLOOKUP(F40,Resumen_Base!$C$8:$G$156,5,0) -> Fixed Asset's Payments (Investments) Mejoras/equipamiento Lodge | F40: 12020301 | G40: Muebles y útiles | H40: =+D40&F40 -> SJ12020301 | I40: -88008 | J40: -61.76 | K40: 1425 | L40: 16/02/2026 | M40: CAJA | N40: 0121 | O40: TD001400000282 | P40: Asiento de CAJA (2025-09-01 - 2026-08-31) | Q40: Depósito a Banco 001400000282 Obs: 16-02-2026 Mov Lodge | R40: SJ - Credito por devolucion conservadoras de otro color 5252 CARMELO | S40: 000000000411 | T40: Ejercicio 2025/2026
C41: Uruguay | D41: SJ | E41: =+VLOOKUP(F41,Resumen_Base!$C$8:$G$156,5,0) -> Fixed Asset's Payments (Investments) Mejoras/equipamiento Lodge | F41: 12020301 | G41: Muebles y útiles | H41: =+D41&F41 -> SJ12020301 | I41: 835161.3 | J41: 590.22 | K41: 1415 | L41: 31/03/2026 | M41: CAJA | N41: 0121 | O41: TE001400000362 | P41: Asiento de CAJA (01/09/2025 - 310326) | Q41: Extracción de Caja 001400000362 Obs: Movimiento_Cajas_Bancos_Semana 25-26 al 03-04-2026 | R41: SJ- ValleySW- FORCE POST DEBIT Check # 1083 - DECOYS SAN JUAN HIGDON OUTDOORS | S41: 000000000500 | T41: Ejercicio 2025/2026
C42: Uruguay | D42: UL | E42: =+VLOOKUP(F42,Resumen_Base!$C$8:$G$156,5,0) -> Fixed Asset's Payments (Investments) Mejoras/equipamiento Lodge | F42: 12020301 | G42: Muebles y útiles | H42: =+D42&F42 -> UL12020301 | I42: 177030 | J42: 126 | K42: 1405 | L42: 31/03/2026 | M42: CAJA | N42: 0122 | O42: TE001400000361 | P42: Asiento de CAJA (01/09/2025 - 310326) | Q42: Extracción de Caja 001400000361 Obs: Movimiento_Cajas_Bancos_Semana 25-26 al 03-04-2026 | R42: UL-Cruzada PY-CTES Decoys Pagos Depsa Valores- Al 01-04-2026 | S42: 000000000499 | T42: Ejercicio 2025/2026
C43: Uruguay | D43: CAR | E43: =+VLOOKUP(F43,Resumen_Base!$C$8:$G$156,5,0) -> Fixed Asset's Payments (Investments) Mejoras/equipamiento Lodge | F43: 12020301 | G43: Muebles y útiles | H43: =+D43&F43 -> CAR12020301 | I43: 715680 | J43: 497 | K43: 1440 | L43: 09/02/2026 | M43: CAJA | N43: 0123 | O43: TE001400000258 | P43: Asiento de CAJA (01/09/2025 - 31/08/2026) | Q43: Extracción de Caja 001400000258 Obs: 09-02-2026 Mov Lodge | R43: CAR - Cocina a gas y termotanque 10 lts para armado cocina casa staff | S43: 000000000367 | T43: Ejercicio 2025/2026
C44: Uruguay | D44: CAR | E44: =+VLOOKUP(F44,Resumen_Base!$C$8:$G$156,5,0) -> Fixed Asset's Payments (Investments) Mejoras/equipamiento Lodge | F44: 12020301 | G44: Muebles y útiles | H44: =+D44&F44 -> CAR12020301 | I44: 591470 | J44: 418 | K44: 1415 | L44: 28/02/2026 | M44: CAJA | N44: 0123 | O44: TE001400000303 | P44: Asiento de CAJA (01/09/2025 - 310326) | Q44: Extracción de Caja 001400000303 Obs: 28-02-2026 Mov Lodge | R44: CAR - Compra freezer midea | S44: 000000000486 | T44: Ejercicio 2025/2026
C45: Uruguay | D45: CAR | E45: =+VLOOKUP(F45,Resumen_Base!$C$8:$G$156,5,0) -> Fixed Asset's Payments (Investments) Mejoras/equipamiento Lodge | F45: 12020301 | G45: Muebles y útiles | H45: =+D45&F45 -> CAR12020301 | I45: 3189340 | J45: 2278.1 | K45: 1400 | L45: 16/03/2026 | M45: CAJA | N45: 0123 | O45: TE001400000329 | P45: Asiento de CAJA (01/09/2025 - 310326) | Q45: Extracción de Caja 001400000329 Obs: 16-03-2026 Mov Lodge | R45: CAR - Compra lavadora y secadora | S45: 000000000491 | T45: Ejercicio 2025/2026
C46: Uruguay | D46: CAR | E46: =+VLOOKUP(F46,Resumen_Base!$C$8:$G$156,5,0) -> Fixed Asset's Payments (Investments) Mejoras/equipamiento Lodge | F46: 12020301 | G46: Muebles y útiles | H46: =+D46&F46 -> CAR12020301 | I46: 2653350 | J46: 1862 | K46: 1425 | L46: 16/02/2026 | N46: 0123 | P46: AJ TRASNF ENTRE LODGE SJ A CAR | Q46: completa pago Handys 5254 CARMELO | R46: completa pago Handys 5254 CARMELO | S46: 000000000455 | T46: Ejercicio 2025/2026
C47: Uruguay | D47: CAR | E47: =+VLOOKUP(F47,Resumen_Base!$C$8:$G$156,5,0) -> Fixed Asset's Payments (Investments) Mejoras/equipamiento Lodge | F47: 12020301 | G47: Muebles y útiles | H47: =+D47&F47 -> CAR12020301 | I47: 2707.5 | J47: 1.9 | K47: 1425 | L47: 16/02/2026 | N47: 0123 | P47: AJ TRASNF ENTRE LODGE SJ A CAR | Q47: deb comi compra handys CARMELO 5254 | R47: deb comi compra handys CARMELO 5254 | S47: 000000000455 | T47: Ejercicio 2025/2026
C48: Uruguay | D48: CAR | E48: =+VLOOKUP(F48,Resumen_Base!$C$8:$G$156,5,0) -> Fixed Asset's Payments (Investments) Mejoras/equipamiento Lodge | F48: 12020301 | G48: Muebles y útiles | H48: =+D48&F48 -> CAR12020301 | I48: 29953.5 | J48: 21.02 | K48: 1425 | L48: 16/02/2026 | N48: 0123 | P48: AJ TRASNF ENTRE LODGE SJ A CAR | Q48: jarra electrica Lodge 5252 CARMELO | R48: jarra electrica Lodge 5252 CARMELO | S48: 000000000455 | T48: Ejercicio 2025/2026
C49: Uruguay | D49: CAR | E49: =+VLOOKUP(F49,Resumen_Base!$C$8:$G$156,5,0) -> Fixed Asset's Payments (Investments) Mejoras/equipamiento Lodge | F49: 12020301 | G49: Muebles y útiles | H49: =+D49&F49 -> CAR12020301 | I49: -88008 | J49: -61.76 | K49: 1425 | L49: 16/02/2026 | N49: 0123 | P49: AJ TRASNF ENTRE LODGE SJ A CAR | Q49: Credito por devolucion conservadoras de otro color 5252 CARMELO | R49: Credito por devolucion conservadoras de otro color 5252 CARMELO | S49: 000000000455 | T49: Ejercicio 2025/2026
C50: Uruguay | D50: CAR | E50: =+VLOOKUP(F50,Resumen_Base!$C$8:$G$156,5,0) -> Fixed Asset's Payments (Investments) Mejoras/equipamiento Lodge | F50: 12020601 | G50: Ropa Blanca | H50: =+D50&F50 -> CAR12020601 | I50: 2736 | J50: 1.9 | K50: 1440 | L50: 09/02/2026 | M50: CAJA | N50: 0123 | O50: TH001400000263 | P50: Asiento de CAJA (01/09/2025 - 31/08/2026) | Q50: Extracción de Banco 001400000263 Obs: 09-02-2026 Mov Lodge | R50: CAR - deb comi | S50: 000000000371 | T50: Ejercicio 2025/2026
C51: Uruguay | D51: CAR | E51: =+VLOOKUP(F51,Resumen_Base!$C$8:$G$156,5,0) -> Fixed Asset's Payments (Investments) Mejoras/equipamiento Lodge | F51: 12020601 | G51: Ropa Blanca | H51: =+D51&F51 -> CAR12020601 | I51: 8178.7 | J51: 5.78 | K51: 1415 | L51: 28/02/2026 | M51: CAJA | N51: 0123 | O51: TE001400000303 | P51: Asiento de CAJA (01/09/2025 - 310326) | Q51: Extracción de Caja 001400000303 Obs: 28-02-2026 Mov Lodge | R51: CAR - Pago envío de laundry bags | S51: 000000000486 | T51: Ejercicio 2025/2026
C52: Uruguay | D52: CAR | E52: =+VLOOKUP(F52,Resumen_Base!$C$8:$G$156,5,0) -> Fixed Asset's Payments (Investments) Mejoras/equipamiento Lodge | F52: 12020601 | G52: Ropa Blanca | H52: =+D52&F52 -> CAR12020601 | I52: 2514240 | J52: 1746 | K52: 1440 | L52: 09/02/2026 | M52: CAJA | N52: 0123 | O52: TH001400000263 | P52: Asiento de CAJA (01/09/2025 - 31/08/2026) | Q52: Extracción de Banco 001400000263 Obs: 09-02-2026 Mov Lodge | R52: CAR - ropa blanca surtex | S52: 000000000371 | T52: Ejercicio 2025/2026
C53: Uruguay | D53: CAR | E53: =+VLOOKUP(F53,Resumen_Base!$C$8:$G$156,5,0) -> Fixed Asset's Payments (Investments) Mejoras/equipamiento Lodge | F53: 12020901 | G53: Vajillas | H53: =+D53&F53 -> CAR12020901 | I53: 120499.2 | J53: 83.68 | K53: 1440 | L53: 09/02/2026 | M53: CAJA | N53: 0123 | O53: TE001400000258 | P53: Asiento de CAJA (01/09/2025 - 31/08/2026) | Q53: Extracción de Caja 001400000258 Obs: 09-02-2026 Mov Lodge | R53: CAR - 12 copas cognac | S53: 000000000367 | T53: Ejercicio 2025/2026
C54: Uruguay | D54: CAR | E54: =+VLOOKUP(F54,Resumen_Base!$C$8:$G$156,5,0) -> Tips | F54: 210609 | G54: Propinas a pagar | H54: =+D54&F54 -> CAR210609 | I54: -570000 | J54: -400 | K54: 1425 | L54: 16/02/2026 | M54: VENTAS | N54: 0123 | O54: VF000000004655B | P54: Asiento de VENTAS (01/09/2025 - 31/08/2026) | Q54: F B 000000004655 | R54: Ref. nota de Venta: CA.DU12 Obs.:16-02-2026_CLIENTES | S54: 000000000425 | T54: Ejercicio 2025/2026
C55: Uruguay | D55: CAR | E55: =+VLOOKUP(F55,Resumen_Base!$C$8:$G$156,5,0) -> Tips | F55: 210609 | G55: Propinas a pagar | H55: =+D55&F55 -> CAR210609 | I55: -712500 | J55: -500 | K55: 1425 | L55: 16/02/2026 | M55: VENTAS | N55: 0123 | O55: VF000000004655B | P55: Asiento de VENTAS (01/09/2025 - 31/08/2026) | Q55: F B 000000004655 | R55: Ref. nota de Venta: CA.DU12 Obs.:16-02-2026_CLIENTES | S55: 000000000425 | T55: Ejercicio 2025/2026
C56: Uruguay | D56: CAR | E56: =+VLOOKUP(F56,Resumen_Base!$C$8:$G$156,5,0) -> Tips | F56: 210609 | G56: Propinas a pagar | H56: =+D56&F56 -> CAR210609 | I56: -912000 | J56: -640 | K56: 1425 | L56: 16/02/2026 | M56: VENTAS | N56: 0123 | O56: VF000000004656B | P56: Asiento de VENTAS (01/09/2025 - 31/08/2026) | Q56: F B 000000004656 | R56: Ref. nota de Venta: CA.DU12 Obs.:16-02-2026_CLIENTES | S56: 000000000426 | T56: Ejercicio 2025/2026
C57: Uruguay | D57: CAR | E57: =+VLOOKUP(F57,Resumen_Base!$C$8:$G$156,5,0) -> Tips | F57: 210609 | G57: Propinas a pagar | H57: =+D57&F57 -> CAR210609 | I57: -684000 | J57: -480 | K57: 1425 | L57: 16/02/2026 | M57: VENTAS | N57: 0123 | O57: VF000000004656B | P57: Asiento de VENTAS (01/09/2025 - 31/08/2026) | Q57: F B 000000004656 | R57: Ref. nota de Venta: CA.DU12 Obs.:16-02-2026_CLIENTES | S57: 000000000426 | T57: Ejercicio 2025/2026
C58: Uruguay | D58: CAR | E58: =+VLOOKUP(F58,Resumen_Base!$C$8:$G$156,5,0) -> Tips | F58: 210609 | G58: Propinas a pagar | H58: =+D58&F58 -> CAR210609 | I58: -855000 | J58: -600 | K58: 1425 | L58: 16/02/2026 | M58: VENTAS | N58: 0123 | O58: VF000000004657B | P58: Asiento de VENTAS (01/09/2025 - 31/08/2026) | Q58: F B 000000004657 | R58: Ref. nota de Venta: CA.DU12 Obs.:16-02-2026_CLIENTES | S58: 000000000427 | T58: Ejercicio 2025/2026
C59: Uruguay | D59: CAR | E59: =+VLOOKUP(F59,Resumen_Base!$C$8:$G$156,5,0) -> Tips | F59: 210609 | G59: Propinas a pagar | H59: =+D59&F59 -> CAR210609 | I59: -570000 | J59: -400 | K59: 1425 | L59: 16/02/2026 | M59: VENTAS | N59: 0123 | O59: VF000000004657B | P59: Asiento de VENTAS (01/09/2025 - 31/08/2026) | Q59: F B 000000004657 | R59: Ref. nota de Venta: CA.DU12 Obs.:16-02-2026_CLIENTES | S59: 000000000427 | T59: Ejercicio 2025/2026
C60: Uruguay | D60: CAR | E60: =+VLOOKUP(F60,Resumen_Base!$C$8:$G$156,5,0) -> Tips | F60: 210609 | G60: Propinas a pagar | H60: =+D60&F60 -> CAR210609 | I60: -855000 | J60: -600 | K60: 1425 | L60: 16/02/2026 | M60: VENTAS | N60: 0123 | O60: VF000000004658B | P60: Asiento de VENTAS (01/09/2025 - 31/08/2026) | Q60: F B 000000004658 | R60: Ref. nota de Venta: CA.DU12 Obs.:16-02-2026_CLIENTES | S60: 000000000428 | T60: Ejercicio 2025/2026
C61: Uruguay | D61: CAR | E61: =+VLOOKUP(F61,Resumen_Base!$C$8:$G$156,5,0) -> Tips | F61: 210609 | G61: Propinas a pagar | H61: =+D61&F61 -> CAR210609 | I61: -997500 | J61: -700 | K61: 1425 | L61: 16/02/2026 | M61: VENTAS | N61: 0123 | O61: VF000000004658B | P61: Asiento de VENTAS (01/09/2025 - 31/08/2026) | Q61: F B 000000004658 | R61: Ref. nota de Venta: CA.DU12 Obs.:16-02-2026_CLIENTES | S61: 000000000428 | T61: Ejercicio 2025/2026
... C677: Uruguay | D677: CAR | E677: =+VLOOKUP(F677,Resumen_Base!$C$8:$G$156,5,0) -> Extras | F677: 5104 | G677: Costo Masajes | H677: =+D677&F677 -> CAR5104 | I677: 313500 | J677: 220 | K677: 1425 | L677: 16/02/2026 | M677: CAJA | N677: 0123 | O677: TE001400000283 | P677: Asiento de CAJA (2025-09-01 - 2026-08-31) | Q677: Extracción de Caja 001400000283 Obs: 16-02-2026 Mov Lodge | R677: CAR - Pago masajes x4 | S677: 000000000414 | T677: Ejercicio 2025/2026
A678: EXTRA CONTABLE REVERSAR EN FEBRERO 26 | D678: CAR | E678: =+VLOOKUP(F678,Resumen_Base!$C$8:$G$287,5,0) -> Field: | F678: 5207 | G678: Alquiler Campos | H678: =+D678&F678 -> CAR5207 | J678: -350 | L678: 46068 | N678: 0123 | R678: entrada campos enero Carlos Bianchi
A679: EXTRA CONTABLE REVERSAR EN FEBRERO 26 | D679: CAR | E679: =+VLOOKUP(F679,Resumen_Base!$C$8:$G$287,5,0) -> Field: | F679: 5207 | G679: Alquiler Campos | H679: =+D679&F679 -> CAR5207 | J679: -150 | L679: 46068 | N679: 0123 | R679: entrada campos enero Daniel Beron
A680: EXTRA CONTABLE REVERSAR EN FEBRERO 26 | D680: CAR | E680: =+VLOOKUP(F680,Resumen_Base!$C$8:$G$287,5,0) -> Field: | F680: 5207 | G680: Alquiler Campos | H680: =+D680&F680 -> CAR5207 | J680: -450 | L680: 46068 | N680: 0123 | R680: entrada campos enero Daniel Palomares
C681: Uruguay | D681: CAR | E681: =+VLOOKUP(F681,Resumen_Base!$C$8:$G$156,5,0) -> Field: | F681: 5207 | G681: Acceso/Alquiler Campos | H681: =+D681&F681 -> CAR5207 | I681: 2707.5 | J681: 1.9 | K681: 1425 | L681: 16/02/2026 | M681: CAJA | N681: 0123 | O681: TH001400000275 | P681: Asiento de CAJA (2025-09-01 - 2026-08-31) | Q681: Extracción de Banco 001400000275 Obs: 16-02-2026 Mov Lodge | R681: CAR - deb comi | S681: 000000000415 | T681: Ejercicio 2025/2026
C682: Uruguay | D682: CAR | E682: =+VLOOKUP(F682,Resumen_Base!$C$8:$G$156,5,0) -> Field: | F682: 5207 | G682: Acceso/Alquiler Campos | H682: =+D682&F682 -> CAR5207 | I682: 2707.5 | J682: 1.9 | K682: 1425 | L682: 16/02/2026 | M682: CAJA | N682: 0123 | O682: TH001400000275 | P682: Asiento de CAJA (2025-09-01 - 2026-08-31) | Q682: Extracción de Banco 001400000275 Obs: 16-02-2026 Mov Lodge | R682: CAR - deb comi | S682: 000000000415 | T682: Ejercicio 2025/2026
C683: Uruguay | D683: CAR | E683: =+VLOOKUP(F683,Resumen_Base!$C$8:$G$156,5,0) -> Field: | F683: 5207 | G683: Acceso/Alquiler Campos | H683: =+D683&F683 -> CAR5207 | I683: 2707.5 | J683: 1.9 | K683: 1425 | L683: 16/02/2026 | M683: CAJA | N683: 0123 | O683: TH001400000275 | P683: Asiento de CAJA (2025-09-01 - 2026-08-31) | Q683: Extracción de Banco 001400000275 Obs: 16-02-2026 Mov Lodge | R683: CAR - deb comi | S683: 000000000415 | T683: Ejercicio 2025/2026
C684: Uruguay | D684: CAR | E684: =+VLOOKUP(F684,Resumen_Base!$C$8:$G$156,5,0) -> Field: | F684: 5207 | G684: Acceso/Alquiler Campos | H684: =+D684&F684 -> CAR5207 | I684: 2669.5 | J684: 1.9 | K684: 1405 | L684: 31/03/2026 | M684: CAJA | N684: 0123 | O684: TH001400000354 | P684: Asiento de CAJA (01/09/2025 - 310326) | Q684: Extracción de Banco 001400000354 Obs: 31-03-2026 Mov Lodge | R684: CAR - deb comi | S684: 000000000525 | T684: Ejercicio 2025/2026
C685: Uruguay | D685: CAR | E685: =+VLOOKUP(F685,Resumen_Base!$C$8:$G$156,5,0) -> Field: | F685: 5207 | G685: Acceso/Alquiler Campos | H685: =+D685&F685 -> CAR5207 | I685: 2736 | J685: 1.9 | K685: 1440 | L685: 09/02/2026 | M685: CAJA | N685: 0123 | O685: TH001400000263 | P685: Asiento de CAJA (01/09/2025 - 31/08/2026) | Q685: Extracción de Banco 001400000263 Obs: 09-02-2026 Mov Lodge | R685: CAR - deb comi entrada campos | S685: 000000000371 | T685: Ejercicio 2025/2026
C686: Uruguay | D686: CAR | E686: =+VLOOKUP(F686,Resumen_Base!$C$8:$G$156,5,0) -> Field: | F686: 5207 | G686: Acceso/Alquiler Campos | H686: =+D686&F686 -> CAR5207 | I686: 1194250 | J686: 850 | K686: 1405 | L686: 31/03/2026 | M686: CAJA | N686: 0123 | O686: TH001400000354 | P686: Asiento de CAJA (01/09/2025 - 310326) | Q686: Extracción de Banco 001400000354 Obs: 31-03-2026 Mov Lodge | R686: CAR - entrada campo adelantado marzo Mario Bianchi | S686: 000000000525 | T686: Ejercicio 2025/2026
C687: Uruguay | D687: CAR | E687: =+VLOOKUP(F687,Resumen_Base!$C$8:$G$156,5,0) -> Field: | F687: 5207 | G687: Acceso/Alquiler Campos | H687: =+D687&F687 -> CAR5207 | I687: 498750 | J687: 350 | K687: 1425 | L687: 16/02/2026 | M687: CAJA | N687: 0123 | O687: TH001400000275 | P687: Asiento de CAJA (2025-09-01 - 2026-08-31) | Q687: Extracción de Banco 001400000275 Obs: 16-02-2026 Mov Lodge | R687: CAR - entrada campos enero Carlos Bianchi | S687: 000000000415 | T687: Ejercicio 2025/2026
C688: Uruguay | D688: CAR | E688: =+VLOOKUP(F688,Resumen_Base!$C$8:$G$156,5,0) -> Field: | F688: 5207 | G688: Acceso/Alquiler Campos | H688: =+D688&F688 -> CAR5207 | I688: 213750 | J688: 150 | K688: 1425 | L688: 16/02/2026 | M688: CAJA | N688: 0123 | O688: TH001400000275 | P688: Asiento de CAJA (2025-09-01 - 2026-08-31) | Q688: Extracción de Banco 001400000275 Obs: 16-02-2026 Mov Lodge | R688: CAR - entrada campos enero Daniel Beron | S688: 000000000415 | T688: Ejercicio 2025/2026
C689: Uruguay | D689: CAR | E689: =+VLOOKUP(F689,Resumen_Base!$C$8:$G$156,5,0) -> Field: | F689: 5207 | G689: Acceso/Alquiler Campos | H689: =+D689&F689 -> CAR5207 | I689: 641250 | J689: 450 | K689: 1425 | L689: 16/02/2026 | M689: CAJA | N689: 0123 | O689: TH001400000275 | P689: Asiento de CAJA (2025-09-01 - 2026-08-31) | Q689: Extracción de Banco 001400000275 Obs: 16-02-2026 Mov Lodge | R689: CAR - entrada campos enero Daniel Palomares | S689: 000000000415 | T689: Ejercicio 2025/2026
C690: Uruguay | D690: CAR | E690: =+VLOOKUP(F690,Resumen_Base!$C$8:$G$156,5,0) -> Field: | F690: 5207 | G690: Acceso/Alquiler Campos | H690: =+D690&F690 -> CAR5207 | I690: 864000 | J690: 600 | K690: 1440 | L690: 09/02/2026 | M690: CAJA | N690: 0123 | O690: TH001400000263 | P690: Asiento de CAJA (01/09/2025 - 31/08/2026) | Q690: Extracción de Banco 001400000263 Obs: 09-02-2026 Mov Lodge | R690: CAR - entrada campos reembolos LONG | S690: 000000000371 | T690: Ejercicio 2025/2026
C691: Uruguay | D691: CAR | E691: =+VLOOKUP(F691,Resumen_Base!$C$8:$G$156,5,0) -> Canon Lodge/Labor Permits: | F691: 5208 | G691: Alquileres y Canon | H691: =+D691&F691 -> CAR5208 | I691: 741228 | J691: 520.16 | K691: 1425 | L691: 16/02/2026 | M691: CAJA | N691: 0123 | O691: TH001400000276 | P691: Asiento de CAJA (2025-09-01 - 2026-08-31) | Q691: Extracción de Banco 001400000276 Obs: 16-02-2026 Mov Lodge | R691: CAR - alquiler casa staff Carmelo | S691: 000000000416 | T691: Ejercicio 2025/2026
C692: Uruguay | D692: CAR | E692: =+VLOOKUP(F692,Resumen_Base!$C$8:$G$156,5,0) -> Canon Lodge/Labor Permits: | F692: 5208 | G692: Alquileres y Canon | H692: =+D692&F692 -> CAR5208 | I692: 712848.7 | J692: 503.78 | K692: 1415 | L692: 23/03/2026 | M692: CAJA | N692: 0123 | O692: TH001400000340 | P692: Asiento de CAJA (01/09/2025 - 310326) | Q692: Extracción de Banco 001400000340 Obs: 23-03-2026 Mov Lodge | R692: CAR - alquiler casa staff cordano Marzo | S692: 000000000522 | T692: Ejercicio 2025/2026
... C718: Uruguay | D718: SJ | E718: =+VLOOKUP(F718,Resumen_Base!$C$8:$G$156,5,0) -> Miscellaneous & Shipping | F718: 5219 | G718: Gastos Varios | H718: =+D718&F718 -> SJ5219 | I718: 15609.55 | J718: 11.11 | K718: 1405 | L718: 31/03/2026 | M718: CAJA | N718: 0121 | O718: TE001400000362 | P718: Asiento de CAJA (01/09/2025 - 310326) | Q718: Extracción de Caja 001400000362 Obs: Movimiento_Cajas_Bancos_Semana 25-26 al 03-04-2026 | R718: SJ-Diseño Tito - uniformes F.Fijo Oper. Al 03-04-2026 | S718: 000000000500 | T718: Ejercicio 2025/2026
A719: De gastos varios de SJ tenemos que pasar unos usd 800 a Carmelo que es monitoreo patos, asi queda balanceado | C719: Uruguay | D719: SJ | E719: =+VLOOKUP(F719,Resumen_Base!$C$8:$G$156,5,0) -> Miscellaneous & Shipping | F719: 5219 | G719: Gastos Varios | H719: =+D719&F719 -> SJ5219 | I719: 4531800 | J719: 3237 | K719: 1400 | L719: 13/03/2026 | M719: CAJA | N719: 0121 | O719: TE001400000333 | P719: Asiento de CAJA (01/09/2025 - 310326) | Q719: Extracción de Caja 001400000333 Obs: Movimiento_Cajas_Bancos_Semana 25-26 al 13-03-2026 | R719: SJ-Monitoreo de Patos F.Fijo Oper. Al 13-03-2026 | S719: 000000000494 | T719: Ejercicio 2025/2026
A720: De gastos varios de SJ tenemos que pasar unos usd 800 a Carmelo que es monitoreo patos, asi queda balanceado | C720: Uruguay | D720: SJ | E720: =+VLOOKUP(F720,Resumen_Base!$C$8:$G$156,5,0) -> Miscellaneous & Shipping | F720: 5219 | G720: Gastos Varios | H720: =+D720&F720 -> SJ5219 | I720: =+J720*K720 -> -1120000 | J720: -800 | K720: 1400 | L720: 13/03/2026 | M720: CAJA | N720: 0121 | O720: TE001400000333 | P720: Asiento de CAJA (01/09/2025 - 310326) | Q720: Extracción de Caja 001400000333 Obs: Movimiento_Cajas_Bancos_Semana 25-26 al 13-03-2026 | R720: SJ-Monitoreo de Patos F.Fijo Oper. Al 13-03-2026 | S720: 000000000494 | T720: Ejercicio 2025/2026
A721: De gastos varios de SJ tenemos que pasar unos usd 800 a Carmelo que es monitoreo patos, asi queda balanceado | C721: Uruguay | D721: CAR | E721: =+VLOOKUP(F721,Resumen_Base!$C$8:$G$156,5,0) -> Miscellaneous & Shipping | F721: 5219 | G721: Gastos Varios | H721: =+D721&F721 -> CAR5219 | I721: =+J721*K721 -> 1120000 | J721: 800 | K721: 1400 | L721: 13/03/2026 | M721: CAJA | N721: 0121 | O721: TE001400000333 | P721: Asiento de CAJA (01/09/2025 - 310326) | Q721: Extracción de Caja 001400000333 Obs: Movimiento_Cajas_Bancos_Semana 25-26 al 13-03-2026 | R721: SJ-Monitoreo de Patos F.Fijo Oper. Al 13-03-2026 | S721: 000000000494 | T721: Ejercicio 2025/2026
C722: Uruguay | D722: UL | E722: =+VLOOKUP(F722,Resumen_Base!$C$8:$G$156,5,0) -> Miscellaneous & Shipping | F722: 5219 | G722: Gastos Varios | H722: =+D722&F722 -> UL5219 | I722: 15609.55 | J722: 11.11 | K722: 1405 | L722: 31/03/2026 | M722: CAJA | N722: 0122 | O722: TE001400000362 | P722: Asiento de CAJA (01/09/2025 - 310326) | Q722: Extracción de Caja 001400000362 Obs: Movimiento_Cajas_Bancos_Semana 25-26 al 03-04-2026 | R722: UL -Diseño Tito - uniformes F.Fijo Oper. Al 03-04-2026 | S722: 000000000500 | T722: Ejercicio 2025/2026
C723: Uruguay | D723: CAR | E723: =+VLOOKUP(F723,Resumen_Base!$C$8:$G$156,5,0) -> Miscellaneous & Shipping | F723: 5219 | G723: Gastos Varios | H723: =+D723&F723 -> CAR5219 | I723: 8380.8 | J723: 5.82 | K723: 1440 | L723: 09/02/2026 | M723: CAJA | N723: 0123 | O723: TE001400000258 | P723: Asiento de CAJA (01/09/2025 - 31/08/2026) | Q723: Extracción de Caja 001400000258 Obs: 09-02-2026 Mov Lodge | R723: CAR - Art farmacia botiquín | S723: 000000000367 | T723: Ejercicio 2025/2026
C724: Uruguay | D724: CAR | E724: =+VLOOKUP(F724,Resumen_Base!$C$8:$G$156,5,0) -> Miscellaneous & Shipping | F724: 5219 | G724: Gastos Varios | H724: =+D724&F724 -> CAR5219 | I724: 59361.25 | J724: 42.25 | K724: 1405 | L724: 31/03/2026 | M724: CAJA | N724: 0123 | O724: TE001400000352 | P724: Asiento de CAJA (01/09/2025 - 310326) | Q724: Extracción de Caja 001400000352 Obs: 31-03-2026 Mov Lodge | R724: CAR - Compra artículos de librería | S724: 000000000498 | T724: Ejercicio 2025/2026
C725: Uruguay | D725: CAR | E725: =+VLOOKUP(F725,Resumen_Base!$C$8:$G$156,5,0) -> Miscellaneous & Shipping | F725: 5219 | G725: Gastos Varios | H725: =+D725&F725 -> CAR5219 | I725: 7740.05 | J725: 5.47 | K725: 1415 | L725: 09/03/2026 | M725: CAJA | N725: 0123 | O725: TE001400000314 | P725: Asiento de CAJA (01/09/2025 - 310326) | Q725: Extracción de Caja 001400000314 Obs: 09-03-2026 Mov Lodge | R725: CAR - Compra recibos comerciales | S725: 000000000487 | T725: Ejercicio 2025/2026
C726: Uruguay | D726: CAR | E726: =+VLOOKUP(F726,Resumen_Base!$C$8:$G$156,5,0) -> Miscellaneous & Shipping | F726: 5219 | G726: Gastos Varios | H726: =+D726&F726 -> CAR5219 | I726: 1103.7 | J726: 0.78 | K726: 1415 | L726: 09/03/2026 | M726: CAJA | N726: 0123 | O726: TE001400000314 | P726: Asiento de CAJA (01/09/2025 - 310326) | Q726: Extracción de Caja 001400000314 Obs: 09-03-2026 Mov Lodge | R726: CAR - Compra recibos comerciales (faltaron agregar 30 pesos) | S726: 000000000487 | T726: Ejercicio 2025/2026
C727: Uruguay | D727: CAR | E727: =+VLOOKUP(F727,Resumen_Base!$C$8:$G$156,5,0) -> Miscellaneous & Shipping | F727: 5219 | G727: Gastos Varios | H727: =+D727&F727 -> CAR5219 | I727: 7740.05 | J727: 5.47 | K727: 1415 | L727: 09/03/2026 | M727: CAJA | N727: 0123 | O727: TE001400000314 | P727: Asiento de CAJA (01/09/2025 - 310326) | Q727: Extracción de Caja 001400000314 Obs: 09-03-2026 Mov Lodge | R727: CAR - Compra resaltadores de colores | S727: 000000000487 | T727: Ejercicio 2025/2026
C728: Uruguay | D728: CAR | E728: =+VLOOKUP(F728,Resumen_Base!$C$8:$G$156,5,0) -> Miscellaneous & Shipping | F728: 5219 | G728: Gastos Varios | H728: =+D728&F728 -> CAR5219 | I728: 106428 | J728: 76.02 | K728: 1400 | L728: 23/03/2026 | M728: CAJA | N728: 0123 | O728: TE001400000347 | P728: Asiento de CAJA (01/09/2025 - 310326) | Q728: Extracción de Caja 001400000347 Obs: 23-03-2026 Mov Lodge | R728: CAR - Farmacia lodge | S728: 000000000495 | T728: Ejercicio 2025/2026
C729: Uruguay | D729: CAR | E729: =+VLOOKUP(F729,Resumen_Base!$C$8:$G$156,5,0) -> Miscellaneous & Shipping | F729: 5219 | G729: Gastos Varios | H729: =+D729&F729 -> CAR5219 | I729: 4747763.7 | J729: 3355.31 | K729: 1415 | L729: 09/03/2026 | M729: CAJA | N729: 0123 | O729: TH001400000305 | P729: Asiento de CAJA (01/09/2025 - 310326) | Q729: Extracción de Banco 001400000305 Obs: 09-03-2026 Mov Lodge | R729: CAR - gorros c logo y bordado regalo clientes | S729: 000000000509 | T729: Ejercicio 2025/2026
C730: Uruguay | D730: CAR | E730: =+VLOOKUP(F730,Resumen_Base!$C$8:$G$156,5,0) -> Miscellaneous & Shipping | F730: 5219 | G730: Gastos Varios | H730: =+D730&F730 -> CAR5219 | I730: 22151.1 | J730: 15.71 | K730: 1410 | L730: 09/03/2026 | M730: CAJA | N730: 0123 | O730: TE001400000314 | P730: Asiento de CAJA (01/09/2025 - 310326) | Q730: Extracción de Caja 001400000314 Obs: 09-03-2026 Mov Lodge | R730: CAR - Jarabe para la tos | S730: 000000000487 | T730: Ejercicio 2025/2026
C731: Uruguay | D731: CAR | E731: =+VLOOKUP(F731,Resumen_Base!$C$8:$G$156,5,0) -> Miscellaneous & Shipping | F731: 5219 | G731: Gastos Varios | H731: =+D731&F731 -> CAR5219 | I731: 13017.6 | J731: 9.04 | K731: 1440 | L731: 16/02/2026 | M731: CAJA | N731: 0123 | O731: TE001400000283 | P731: Asiento de CAJA (2025-09-01 - 2026-08-31) | Q731: Extracción de Caja 001400000283 Obs: 16-02-2026 Mov Lodge | R731: CAR - Librería carpetas | S731: 000000000414 | T731: Ejercicio 2025/2026
C732: Uruguay | D732: CAR | E732: =+VLOOKUP(F732,Resumen_Base!$C$8:$G$156,5,0) -> Miscellaneous & Shipping | F732: 5219 | G732: Gastos Varios | H732: =+D732&F732 -> CAR5219 | I732: 392661 | J732: 280.47214 | K732: 1400 | L732: 13/03/2026 | M732: CAJA | N732: 0123 | O732: TE001400000331 | P732: Asiento de CAJA (01/09/2025 - 310326) | Q732: Extracción de Caja 001400000331 Obs: Movimiento_Cajas_Bancos_Semana 25-26 al 13-03-2026 | R732: CAR-Adelanto 50 % -Gorras Elite Club - 90 unidades F.Fijo Oper. Al 13-03-2026 | S732: 000000000492 | T732: Ejercicio 2025/2026
C733: Uruguay | D733: CAR | E733: =+VLOOKUP(F733,Resumen_Base!$C$8:$G$156,5,0) -> Miscellaneous & Shipping | F733: 5219 | G733: Gastos Varios | H733: =+D733&F733 -> CAR5219 | I733: 15609.55 | J733: 11.11 | K733: 1405 | L733: 31/03/2026 | M733: CAJA | N733: 0123 | O733: TE001400000362 | P733: Asiento de CAJA (01/09/2025 - 310326) | Q733: Extracción de Caja 001400000362 Obs: Movimiento_Cajas_Bancos_Semana 25-26 al 03-04-2026 | R733: CAR-Diseño Tito - uniformes F.Fijo Oper. Al 03-04-2026 | S733: 000000000500 | T733: Ejercicio 2025/2026
... C756: Uruguay | D756: CAR | E756: =+VLOOKUP(F756,Resumen_Base!$C$8:$G$156,5,0) -> Work uniforms for personnel (employees) | F756: 5220 | G756: Uniformes | H756: =+D756&F756 -> CAR5220 | I756: 453227.14 | J756: 322.58159 | K756: 1405 | L756: 31/03/2026 | M756: CAJA | N756: 0123 | O756: TE001400000361 | P756: Asiento de CAJA (01/09/2025 - 310326) | Q756: Extracción de Caja 001400000361 Obs: Movimiento_Cajas_Bancos_Semana 25-26 al 03-04-2026 | R756: CAR-Reposición uniformes cocina - temporada 2026 - Savastano F.Fijo Oper. Al 27-03-2026 | S756: 000000000499 | T756: Ejercicio 2025/2026
C757: Uruguay | D757: CAR | E757: =+VLOOKUP(F757,Resumen_Base!$C$8:$G$156,5,0) -> Work uniforms for personnel (employees) | F757: 5220 | G757: Uniformes | H757: =+D757&F757 -> CAR5220 | I757: 383952 | J757: 269.44 | K757: 1425 | L757: 16/02/2026 | N757: 0123 | P757: AJ TRASNF ENTRE LODGE SJ A CAR | Q757: parte bombachas de campo bird boys nuevos 5220 CARMELO | R757: parte bombachas de campo bird boys nuevos 5220 CARMELO | S757: 000000000455 | T757: Ejercicio 2025/2026
C758: Uruguay | D758: CAR | E758: =+VLOOKUP(F758,Resumen_Base!$C$8:$G$156,5,0) -> Work uniforms for personnel (employees) | F758: 5220 | G758: Uniformes | H758: =+D758&F758 -> CAR5220 | I758: 2721.75 | J758: 1.91 | K758: 1425 | L758: 16/02/2026 | N758: 0123 | P758: AJ TRASNF ENTRE LODGE SJ A CAR | Q758: deb comi uniformes 5220 CARMELO | R758: deb comi uniformes 5220 CARMELO | S758: 000000000455 | T758: Ejercicio 2025/2026
C759: Uruguay | D759: CAR | E759: =+VLOOKUP(F759,Resumen_Base!$C$8:$G$156,5,0) -> Work uniforms for personnel (employees) | F759: 5220 | G759: Uniformes | H759: =+D759&F759 -> CAR5220 | I759: 959509.5 | J759: 673.34 | K759: 1425 | L759: 16/02/2026 | N759: 0123 | P759: AJ TRASNF ENTRE LODGE SJ A CAR | Q759: completa impermeable, termicas y mochilas 5220 Carmelo | R759: completa impermeable, termicas y mochilas 5220 Carmelo | S759: 000000000455 | T759: Ejercicio 2025/2026
A760: EXTRA CONTABLE REVERSAR EN FEBRERO 26 | D760: CAR | E760: =+VLOOKUP(F760,Resumen_Base!$C$8:$G$287,5,0) -> Licenses / Permits (Fishing and Shooting) | F760: 5221 | G760: Permisos | H760: =+D760&F760 -> CAR5221 | J760: -600 | L760: 46068 | N760: 0123 | R760: honorarios enero Mati Vila
C761: Uruguay | D761: CAR | E761: =+VLOOKUP(F761,Resumen_Base!$C$8:$G$156,5,0) -> Licenses / Permits (Fishing and Shooting) | F761: 5221 | G761: Permisos | H761: =+D761&F761 -> CAR5221 | I761: 2680607.4 | J761: 1901.14 | K761: 1410 | L761: 09/03/2026 | M761: CAJA | N761: 0123 | O761: TH001400000305 | P761: Asiento de CAJA (01/09/2025 - 310326) | Q761: Extracción de Banco 001400000305 Obs: 09-03-2026 Mov Lodge | R761: CAR - a favor de permisos Marzo Mati Vila | S761: 000000000509 | T761: Ejercicio 2025/2026
C762: Uruguay | D762: CAR | E762: =+VLOOKUP(F762,Resumen_Base!$C$8:$G$156,5,0) -> Licenses / Permits (Fishing and Shooting) | F762: 5221 | G762: Permisos | H762: =+D762&F762 -> CAR5221 | I762: 561772.8 | J762: 390.12 | K762: 1440 | L762: 09/02/2026 | M762: CAJA | N762: 0123 | O762: TH001400000262 | P762: Asiento de CAJA (01/09/2025 - 31/08/2026) | Q762: Extracción de Banco 001400000262 Obs: 09-02-2026 Mov Lodge | R762: CAR - a favor permisos febrero Mati Vila | S762: 000000000370 | T762: Ejercicio 2025/2026
C763: Uruguay | D763: CAR | E763: =+VLOOKUP(F763,Resumen_Base!$C$8:$G$156,5,0) -> Licenses / Permits (Fishing and Shooting) | F763: 5221 | G763: Permisos | H763: =+D763&F763 -> CAR5221 | I763: 1976898 | J763: 1412.07 | K763: 1400 | L763: 16/03/2026 | M763: CAJA | N763: 0123 | O763: TH001400000324 | P763: Asiento de CAJA (01/09/2025 - 310326) | Q763: Extracción de Banco 001400000324 Obs: 16-03-2026 Mov Lodge | R763: CAR - a favor permisos marzo Mati Vila | S763: 000000000516 | T763: Ejercicio 2025/2026
C764: Uruguay | D764: CAR | E764: =+VLOOKUP(F764,Resumen_Base!$C$8:$G$156,5,0) -> Licenses / Permits (Fishing and Shooting) | F764: 5221 | G764: Permisos | H764: =+D764&F764 -> CAR5221 | I764: 855000 | J764: 600 | K764: 1425 | L764: 16/02/2026 | M764: CAJA | N764: 0123 | O764: TH001400000275 | P764: Asiento de CAJA (2025-09-01 - 2026-08-31) | Q764: Extracción de Banco 001400000275 Obs: 16-02-2026 Mov Lodge | R764: CAR - honorarios enero Mati Vila | S764: 000000000415 | T764: Ejercicio 2025/2026
C765: Uruguay | D765: CAR | E765: =+VLOOKUP(F765,Resumen_Base!$C$8:$G$156,5,0) -> Licenses / Permits (Fishing and Shooting) | F765: 5221 | G765: Permisos | H765: =+D765&F765 -> CAR5221 | I765: 1736000 | J765: 1240 | K765: 1400 | L765: 16/03/2026 | M765: CAJA | N765: 0123 | O765: TH001400000325 | P765: Asiento de CAJA (01/09/2025 - 310326) | Q765: Extracción de Banco 001400000325 Obs: 16-03-2026 Mov Lodge | R765: CAR - honorarios Febrero Mati Vila | S765: 000000000517 | T765: Ejercicio 2025/2026
C766: Uruguay | D766: CAR | E766: =+VLOOKUP(F766,Resumen_Base!$C$8:$G$156,5,0) -> Licenses / Permits (Fishing and Shooting) | F766: 5221 | G766: Permisos | H766: =+D766&F766 -> CAR5221 | I766: 155100 | J766: 110 | K766: 1410 | L766: 09/03/2026 | M766: CAJA | N766: 0123 | O766: TE001400000314 | P766: Asiento de CAJA (01/09/2025 - 310326) | Q766: Extracción de Caja 001400000314 Obs: 09-03-2026 Mov Lodge | R766: CAR - Masajes x2 | S766: 000000000487 | T766: Ejercicio 2025/2026
C767: Uruguay | D767: CAR | E767: =+VLOOKUP(F767,Resumen_Base!$C$8:$G$156,5,0) -> Licenses / Permits (Fishing and Shooting) | F767: 5221 | G767: Permisos | H767: =+D767&F767 -> CAR5221 | I767: 966289.35 | J767: 682.89 | K767: 1415 | L767: 28/02/2026 | M767: CAJA | N767: 0123 | O767: TE001400000303 | P767: Asiento de CAJA (01/09/2025 - 310326) | Q767: Extracción de Caja 001400000303 Obs: 28-02-2026 Mov Lodge | R767: CAR - Pago permiso 26/02 | S767: 000000000486 | T767: Ejercicio 2025/2026
C768: Uruguay | D768: CAR | E768: =+VLOOKUP(F768,Resumen_Base!$C$8:$G$156,5,0) -> Licenses / Permits (Fishing and Shooting) | F768: 5221 | G768: Permisos | H768: =+D768&F768 -> CAR5221 | I768: 1225172.2 | J768: 859.77 | K768: 1425 | L768: 23/02/2026 | M768: CAJA | N768: 0123 | O768: TE001400000296 | P768: Asiento de CAJA (01/09/2025 - 310326) | Q768: Extracción de Caja 001400000296 Obs: 23-02-2026 Mov Lodge | R768: CAR - Pago permiso caza grupo 16/02 | S768: 000000000484 | T768: Ejercicio 2025/2026
C769: Uruguay | D769: CAR | E769: =+VLOOKUP(F769,Resumen_Base!$C$8:$G$156,5,0) -> Licenses / Permits (Fishing and Shooting) | F769: 5221 | G769: Permisos | H769: =+D769&F769 -> CAR5221 | I769: 994543.5 | J769: 705.35 | K769: 1410 | L769: 09/03/2026 | M769: CAJA | N769: 0123 | O769: TE001400000314 | P769: Asiento de CAJA (01/09/2025 - 310326) | Q769: Extracción de Caja 001400000314 Obs: 09-03-2026 Mov Lodge | R769: CAR - Pago permiso SMA | S769: 000000000487 | T769: Ejercicio 2025/2026
C770: Uruguay | D770: CAR | E770: =+VLOOKUP(F770,Resumen_Base!$C$8:$G$156,5,0) -> Licenses / Permits (Fishing and Shooting) | F770: 5221 | G770: Permisos | H770: =+D770&F770 -> CAR5221 | I770: 1083670 | J770: 774.05 | K770: 1400 | L770: 16/03/2026 | M770: CAJA | N770: 0123 | O770: TE001400000329 | P770: Asiento de CAJA (01/09/2025 - 310326) | Q770: Extracción de Caja 001400000329 Obs: 16-03-2026 Mov Lodge | R770: CAR - Pago permiso SMA | S770: 000000000491 | T770: Ejercicio 2025/2026
...

Sheet Mov_Analizados_Abr 24
G2: Ver Telefonos
G3: Ver Gastos devengados
G4: Ver Luz Devengada
G5: Ver REVERSAS
G7: =+IF(I7+J7=0,"Ok","Check") -> Ok | I7: =ROUND(SUM(I10:I20),0) -> 0 | J7: =ROUND(SUM(J10:J20),0) -> 0
D8: FL | E8: Rubro | G8: =+Resumen_Base!D1 -> Ok
B9: =+F9&$C$9&G9 | D9: =+VLOOKUP(F9,Resumen_Base!$C$8:$F$26,4,0) -> #N/A | E9: =+VLOOKUP(F9,Resumen_Base!$C$8:$G$156,5,0) -> #N/A | H9: =+D9&F9 -> #N/A | I9: =SUM(I10:I17) -> 0 | J9: =SUM(J10:J17) -> 0
B10: Cuenta Anterior | D10: Lodge | E10: Concepto | F10: Cuenta | G10: Nombre | I10: monto $ | J10: monto USD | K10: TC | L10: Fecha | M10: Subdiario | N10: Div | O10: Datos del comprobante | P10: Sujeto | Q10: CUIT | R10: Observación asiento | S10: Clase de Asiento | T10: Origen del comprobante | U10: Observación del comprobante | V10: Comentario renglón asiento | W10: Asiento | X10: Control | Z10: monto USD | AA10: tc | AC10: Fecha | AD10: Subdiario | AE10: Div | AF10: Datos del comprobante | AG10: Sujeto | AH10: CUIT | AI10: Observación asiento | AJ10: Clase de Asiento | AK10: Origen del comprobante | AL10: Observación del comprobante | AM10: Comentario renglón asiento | AN10: Asiento
A17: INSERT | B17: INSERT | C17: INSERT | D17: INSERT | E17: INSERT | F17: INSERT | G17: INSERT | H17: INSERT | I17: INSERT | J17: INSERT | K17: INSERT | L17: INSERT | M17: INSERT | N17: INSERT | O17: INSERT | P17: INSERT | Q17: INSERT | R17: INSERT | S17: INSERT | T17: INSERT | U17: INSERT | V17: INSERT | W17: INSERT
A20: INSERT | B20: INSERT | C20: INSERT | D20: INSERT | E20: INSERT | F20: INSERT | G20: INSERT | H20: INSERT | I20: INSERT | J20: INSERT | K20: INSERT | L20: INSERT | M20: INSERT | N20: INSERT | O20: INSERT | P20: INSERT | Q20: INSERT | R20: INSERT | S20: INSERT | T20: INSERT | U20: INSERT | V20: INSERT | W20: INSERT | X20: INSERT | Y20: INSERT | Z20: INSERT | AA20: INSERT | AB20: INSERT | AC20: INSERT | AD20: INSERT | AE20: INSERT | AF20: INSERT | AG20: INSERT | AH20: INSERT | AI20: INSERT | AJ20: INSERT | AK20: INSERT | AL20: INSERT | AM20: INSERT | AN20: INSERT

Sheet Mov_Analizados_Abr 26
H2: Ver Telefonos
H3: Ver Gastos devengados
H4: Ver Luz Devengada
H5: Ver REVERSAS
E7: =+VLOOKUP(G7,'Plan Cuentas Link Armado'!$E$3:$G$105,3,0) -> #N/A | H7: =+IF(J7+K7=0,"Ok","Check") -> Ok | J7: =ROUND(SUM(J10:J1992),0) -> 0 | K7: =ROUND(SUM(K10:K1992),0) -> 0
E8: Plan Cuentas Link Armado | F8: Rubro | H8: =+Resumen_Base!D1 -> Ok
C9: =+G9&$D$9&H9 | E9: =+VLOOKUP(G9,Resumen_Base!$C$8:$F$26,4,0) -> #N/A | F9: =+VLOOKUP(G9,Resumen_Base!$C$8:$G$156,5,0) -> #N/A | I9: =+E9&G9 -> #N/A | J9: =SUM(J10:J862) -> 1.2473711e+08 | K9: =SUM(K10:K862) -> 106145.93
C10: Cuenta Anterior | E10: Lodge | F10: Concepto | G10: Cuenta | H10: Nombre | J10: monto $ | K10: monto USD | L10: TC | M10: Fecha | N10: Subdiario | O10: Div | P10: Datos del comprobante | Q10: Sujeto | R10: CUIT | S10: Observación asiento | T10: Clase de Asiento | U10: Origen del comprobante | V10: Observación del comprobante | W10: Comentario renglón asiento | X10: Asiento | Y10: Control | AA10: monto USD | AB10: tc | AD10: Fecha | AE10: Subdiario | AF10: Div | AG10: Datos del comprobante | AH10: Sujeto | AI10: CUIT | AJ10: Observación asiento | AK10: Clase de Asiento | AL10: Origen del comprobante | AM10: Observación del comprobante | AN10: Comentario renglón asiento | AO10: Asiento
A12: Esto se imputa a Remuneraciones Guías | C12: 5208 Alquileres y Canon | D12: Uruguay | E12: SJ | F12: =+VLOOKUP(G12,Resumen_Base!$C$8:$G$156,5,0) -> Services/House | G12: 5226 | H12: Remuneraciones Servicios | I12: =+E12&G12 -> SJ5226 | J12: 1515011.5 | K12: 1078.3 | L12: 1405 | M12: 30/04/2026 | N12: CAJA | O12: 0121 | P12: TH001400000405 | Q12: Asiento de CAJA (01/09/2025 - 30042026) | R12: Extracción de Banco 001400000405 Obs: 30-04-2026 Mov Lodge | S12: SJ - alquiler casa guia en Flores primer mes | T12: 000000000934 | U12: Ejercicio 2025/2026
D13: Uruguay | E13: SJ | F13: =+VLOOKUP(G13,Resumen_Base!$C$8:$G$156,5,0) -> Canon Lodge/Labor Permits: | G13: 5208 | H13: Alquileres y Canon | I13: =+E13&G13 -> SJ5208 | J13: 21075000 | K13: 15000 | L13: 1405 | M13: 30/04/2026 | N13: CAJA | O13: 0121 | P13: TH001400000405 | Q13: Asiento de CAJA (01/09/2025 - 30042026) | R13: Extracción de Banco 001400000405 Obs: 30-04-2026 Mov Lodge | S13: SJ - arrendamiento San Juan Lodge primera mitad | T13: 000000000934 | U13: Ejercicio 2025/2026
D14: Uruguay | E14: SJ | F14: =+VLOOKUP(G14,Resumen_Base!$C$8:$G$156,5,0) -> Canon Lodge/Labor Permits: | G14: 5208 | H14: Alquileres y Canon | I14: =+E14&G14 -> SJ5208 | J14: 2669.5 | K14: 1.9 | L14: 1405 | M14: 30/04/2026 | N14: CAJA | O14: 0121 | P14: TH001400000405 | Q14: Asiento de CAJA (01/09/2025 - 30042026) | R14: Extracción de Banco 001400000405 Obs: 30-04-2026 Mov Lodge | S14: SJ - deb comi | T14: 000000000934 | U14: Ejercicio 2025/2026
D15: Uruguay | E15: SJ | F15: =+VLOOKUP(G15,Resumen_Base!$C$8:$G$156,5,0) -> Canon Lodge/Labor Permits: | G15: 5208 | H15: Alquileres y Canon | I15: =+E15&G15 -> SJ5208 | J15: 14050 | K15: 10 | L15: 1405 | M15: 30/04/2026 | N15: CAJA | O15: 0121 | P15: TH001400000405 | Q15: Asiento de CAJA (01/09/2025 - 30042026) | R15: Extracción de Banco 001400000405 Obs: 30-04-2026 Mov Lodge | S15: SJ - deb comi alquiler | T15: 000000000934 | U15: Ejercicio 2025/2026
D16: Uruguay | E16: SJ | F16: =+VLOOKUP(G16,Resumen_Base!$C$8:$G$156,5,0) -> Communications - Phone, internet and satellite TV | G16: 5266 | H16: Comunicaciones Internet | I16: =+E16&G16 -> SJ5266 | J16: 81180.9 | K16: 57.78 | L16: 1405 | M16: 30/04/2026 | N16: CAJA | O16: 0121 | P16: TH001400000404 | Q16: Asiento de CAJA (01/09/2025 - 30042026) | R16: Extracción de Banco 001400000404 Obs: 30-04-2026 Mov Lodge | S16: SJ - antel internet y comunicaciones | T16: 000000000933 | U16: Ejercicio 2025/2026
D17: Uruguay | E17: SJ | F17: =+VLOOKUP(G17,Resumen_Base!$C$8:$G$156,5,0) -> Communications - Phone, internet and satellite TV | G17: 5266 | H17: Comunicaciones Internet | I17: =+E17&G17 -> SJ5266 | J17: -1334.75 | K17: -0.95 | L17: 1405 | M17: 30/04/2026 | N17: CAJA | O17: 0121 | P17: TD001400000406 | Q17: Asiento de CAJA (01/09/2025 - 30042026) | R17: Depósito a Banco 001400000406 Obs: 30-04-2026 Mov Lodge | S17: SJ - red iva antel | T17: 000000000903 | U17: Ejercicio 2025/2026
D18: Uruguay | E18: SJ | F18: =+VLOOKUP(G18,Resumen_Base!$C$8:$G$156,5,0) -> Electricity | G18: 5247 | H18: Combustible y Lub- Elect-Gener | I18: =+E18&G18 -> SJ5247 | J18: 854169.75 | K18: 607.95 | L18: 1405 | M18: 30/04/2026 | N18: CAJA | O18: 0121 | P18: TH001400000405 | Q18: Asiento de CAJA (01/09/2025 - 30042026) | R18: Extracción de Banco 001400000405 Obs: 30-04-2026 Mov Lodge | S18: SJ - Ute electricidad San Juan Lodge abril | T18: 000000000934 | U18: Ejercicio 2025/2026
D19: Uruguay | E19: SJ | F19: =+VLOOKUP(G19,Resumen_Base!$C$8:$G$156,5,0) -> Electricity - Gas for Boats & Vehicles | G19: 5248 | H19: Combustible y Lub-Vehiculo Bot | I19: =+E19&G19 -> SJ5248 | J19: 144012.5 | K19: 102.5 | L19: 1405 | M19: 20/04/2026 | N19: CAJA | O19: 0121 | P19: TH001400000388 | Q19: Asiento de CAJA (01/09/2025 - 30042026) | R19: Extracción de Banco 001400000388 Obs: 20-04-2026 Mov Lodge | S19: SJ - combustible ida a SJ ida Manager nueva SJ | T19: 000000000927 | U19: Ejercicio 2025/2026
D20: Uruguay | E20: SJ | F20: =+VLOOKUP(G20,Resumen_Base!$C$8:$G$156,5,0) -> Electricity - Gas for Boats & Vehicles | G20: 5248 | H20: Combustible y Lub-Vehiculo Bot | I20: =+E20&G20 -> SJ5248 | J20: 140500 | K20: 100 | L20: 1405 | M20: 20/04/2026 | N20: CAJA | O20: 0121 | P20: TH001400000388 | Q20: Asiento de CAJA (01/09/2025 - 30042026) | R20: Extracción de Banco 001400000388 Obs: 20-04-2026 Mov Lodge | S20: SJ - combustible tramites caro horta marzo | T20: 000000000927 | U20: Ejercicio 2025/2026
D21: Uruguay | E21: SJ | F21: =+VLOOKUP(G21,Resumen_Base!$C$8:$G$156,5,0) -> Electricity - Gas for Boats & Vehicles | G21: 5248 | H21: Combustible y Lub-Vehiculo Bot | I21: =+E21&G21 -> SJ5248 | J21: 355998.9 | K21: 253.38 | L21: 1405 | M21: 20/04/2026 | N21: CAJA | O21: 0121 | P21: TH001400000388 | Q21: Asiento de CAJA (01/09/2025 - 30042026) | R21: Extracción de Banco 001400000388 Obs: 20-04-2026 Mov Lodge | S21: SJ - combustible traslado cartuchos y demas vueltas sj | T21: 000000000927 | U21: Ejercicio 2025/2026
D22: Uruguay | E22: SJ | F22: =+VLOOKUP(G22,Resumen_Base!$C$8:$G$156,5,0) -> Electricity - Gas for Boats & Vehicles | G22: 5248 | H22: Combustible y Lub-Vehiculo Bot | I22: =+E22&G22 -> SJ5248 | J22: 2697.6 | K22: 1.92 | L22: 1405 | M22: 20/04/2026 | N22: CAJA | O22: 0121 | P22: TH001400000388 | Q22: Asiento de CAJA (01/09/2025 - 30042026) | R22: Extracción de Banco 001400000388 Obs: 20-04-2026 Mov Lodge | S22: SJ - deb comi | T22: 000000000927 | U22: Ejercicio 2025/2026
D23: Uruguay | E23: SJ | F23: =+VLOOKUP(G23,Resumen_Base!$C$8:$G$156,5,0) -> Electricity - Gas for Boats & Vehicles | G23: 5248 | H23: Combustible y Lub-Vehiculo Bot | I23: =+E23&G23 -> SJ5248 | J23: 131437.75 | K23: 93.55 | L23: 1405 | M23: 30/04/2026 | N23: CAJA | O23: 0121 | P23: TH001400000404 | Q23: Asiento de CAJA (01/09/2025 - 30042026) | R23: Extracción de Banco 001400000404 Obs: 30-04-2026 Mov Lodge | S23: SJ - recarga viaje a montevideo nafta OROCH reembolso Felipe Olivera | T23: 000000000933 | U23: Ejercicio 2025/2026
D24: Uruguay | E24: SJ | F24: =+VLOOKUP(G24,Resumen_Base!$C$8:$G$156,5,0) -> Field: | G24: 5207 | H24: Acceso/Alquiler Campos | I24: =+E24&G24 -> SJ5207 | J24: 140500 | K24: 100 | L24: 1405 | M24: 30/04/2026 | N24: CAJA | O24: 0121 | P24: TH001400000405 | Q24: Asiento de CAJA (01/09/2025 - 30042026) | R24: Extracción de Banco 001400000405 Obs: 30-04-2026 Mov Lodge | S24: SJ - entrada campo San Juan reembolso felipe Olivera | T24: 000000000934 | U24: Ejercicio 2025/2026
... D393: Uruguay | E393: CAR | F393: =+VLOOKUP(G393,Resumen_Base!$C$8:$G$156,5,0) -> Miscellaneous & Shipping | G393: 5263 | H393: Servicios - Otros Operativos | I393: =+E393&G393 -> CAR5263 | J393: 287744 | K393: 204.8 | L393: 1405 | M393: 20/04/2026 | N393: CAJA | O393: 0123 | P393: TH001400000385 | Q393: Asiento de CAJA (01/09/2025 - 30042026) | R393: Extracción de Banco 001400000385 Obs: 20-04-2026 Mov Lodge | S393: CAR - emergencia medica semco abril | T393: 000000000926 | U393: Ejercicio 2025/2026
A394: COSTO EXTRAS | C394: 5263 Servicios - Otros Operativos | D394: Uruguay | E394: CAR | F394: =+VLOOKUP(G394,Resumen_Base!$C$8:$G$156,5,0) -> Extras | G394: 5285 | H394: Costo Ventas Extras | I394: =+E394&G394 -> CAR5285 | J394: 554975 | K394: 395 | L394: 1405 | M394: 20/04/2026 | N394: CAJA | O394: 0123 | P394: TE001400000387 | Q394: Asiento de CAJA (01/09/2025 - 30042026) | R394: Extracción de Caja 001400000387 Obs: 20-04-2026 Mov Lodge | S394: CAR - Golf | T394: 000000000913 | U394: Ejercicio 2025/2026
A395: COSTO EXTRAS | C395: 5263 Servicios - Otros Operativos | D395: Uruguay | E395: CAR | F395: =+VLOOKUP(G395,Resumen_Base!$C$8:$G$156,5,0) -> Extras | G395: 5285 | H395: Costo Ventas Extras | I395: =+E395&G395 -> CAR5285 | J395: 843000 | K395: 600 | L395: 1405 | M395: 20/04/2026 | N395: CAJA | O395: 0123 | P395: TE001400000387 | Q395: Asiento de CAJA (01/09/2025 - 30042026) | R395: Extracción de Caja 001400000387 Obs: 20-04-2026 Mov Lodge | S395: CAR - Golf | T395: 000000000913 | U395: Ejercicio 2025/2026
A396: COMIDA | C396: 5292 Permisos Control Ambiental/Patos | D396: Uruguay | E396: CAR | F396: =+VLOOKUP(G396,Resumen_Base!$C$8:$G$156,5,0) -> Food & Wine | G396: 5250 | H396: Comidas y refrigerios | I396: =+E396&G396 -> CAR5250 | J396: 1033728.8 | K396: 735.75 | L396: 1405 | M396: 20/04/2026 | N396: CAJA | O396: 0123 | P396: TH001400000385 | Q396: Asiento de CAJA (01/09/2025 - 30042026) | R396: Extracción de Banco 001400000385 Obs: 20-04-2026 Mov Lodge | S396: CAR - pelada de palomas todo marzo Franco Rigos | T396: 000000000926 | U396: Ejercicio 2025/2026
A397: COMIDA | C397: 5292 Permisos Control Ambiental/Patos | D397: Uruguay | E397: CAR | F397: =+VLOOKUP(G397,Resumen_Base!$C$8:$G$156,5,0) -> Food & Wine | G397: 5250 | H397: Comidas y refrigerios | I397: =+E397&G397 -> CAR5250 | J397: 35125 | K397: 25 | L397: 1405 | M397: 20/04/2026 | N397: CAJA | O397: 0123 | P397: TH001400000385 | Q397: Asiento de CAJA (01/09/2025 - 30042026) | R397: Extracción de Banco 001400000385 Obs: 20-04-2026 Mov Lodge | S397: CAR - pelada palomas marzo Felipe Olivera | T397: 000000000926 | U397: Ejercicio 2025/2026
A398: COMIDA | C398: 5292 Permisos Control Ambiental/Patos | D398: Uruguay | E398: CAR | F398: =+VLOOKUP(G398,Resumen_Base!$C$8:$G$156,5,0) -> Food & Wine | G398: 5250 | H398: Comidas y refrigerios | I398: =+E398&G398 -> CAR5250 | J398: 370568.75 | K398: 263.75 | L398: 1405 | M398: 20/04/2026 | N398: CAJA | O398: 0123 | P398: TH001400000385 | Q398: Asiento de CAJA (01/09/2025 - 30042026) | R398: Extracción de Banco 001400000385 Obs: 20-04-2026 Mov Lodge | S398: CAR - pelada palomas Victor Ramirez marzo | T398: 000000000926 | U398: Ejercicio 2025/2026
A399: COMIDA | C399: 5292 Permisos Control Ambiental/Patos | D399: Uruguay | E399: CAR | F399: =+VLOOKUP(G399,Resumen_Base!$C$8:$G$156,5,0) -> Food & Wine | G399: 5250 | H399: Comidas y refrigerios | I399: =+E399&G399 -> CAR5250 | J399: 172000.1 | K399: 122.42 | L399: 1405 | M399: 30/04/2026 | N399: CAJA | O399: 0123 | P399: TH001400000401 | Q399: Asiento de CAJA (01/09/2025 - 30042026) | R399: Extracción de Banco 001400000401 Obs: 30-04-2026 Mov Lodge | S399: CAR - palomas peladas victor ramirez donaciones | T399: 000000000930 | U399: Ejercicio 2025/2026
A400: COMIDA | C400: 5292 Permisos Control Ambiental/Patos | D400: Uruguay | E400: CAR | F400: =+VLOOKUP(G400,Resumen_Base!$C$8:$G$156,5,0) -> Food & Wine | G400: 5250 | H400: Comidas y refrigerios | I400: =+E400&G400 -> CAR5250 | J400: 250581.75 | K400: 178.35 | L400: 1405 | M400: 30/04/2026 | N400: CAJA | O400: 0123 | P400: TH001400000401 | Q400: Asiento de CAJA (01/09/2025 - 30042026) | R400: Extracción de Banco 001400000401 Obs: 30-04-2026 Mov Lodge | S400: CAR - pelada palomas primera quincena Franco Rigos | T400: 000000000930 | U400: Ejercicio 2025/2026
D401: Uruguay | E401: CAR | F401: =+VLOOKUP(G401,Resumen_Base!$C$8:$G$156,5,0) -> Propane | G401: 5249 | H401: Combustible y Lub- Gas | I401: =+E401&G401 -> CAR5249 | J401: 43203.75 | K401: 30.75 | L401: 1405 | M401: 20/04/2026 | N401: CAJA | O401: 0123 | P401: TE001400000387 | Q401: Asiento de CAJA (01/09/2025 - 30042026) | R401: Extracción de Caja 001400000387 Obs: 20-04-2026 Mov Lodge | S401: CAR - Compra de garrafa | T401: 000000000913 | U401: Ejercicio 2025/2026
D402: Uruguay | E402: CAR | F402: =+VLOOKUP(G402,Resumen_Base!$C$8:$G$156,5,0) -> Services/House | G402: 5226 | H402: Remuneraciones Servicios | I402: =+E402&G402 -> CAR5226 | J402: 1264500 | K402: 900 | L402: 1405 | M402: 13/04/2026 | N402: CAJA | O402: 0123 | P402: TE001400000368 | Q402: Asiento de CAJA (01/09/2025 - 30042026) | R402: Extracción de Caja 001400000368 Obs: 13-04-2026 Mov Lodge | S402: CAR - Sueldo marzo Santiago mantenimiento | T402: 000000000906 | U402: Ejercicio 2025/2026
D403: Uruguay | E403: CAR | F403: =+VLOOKUP(G403,Resumen_Base!$C$8:$G$156,5,0) -> Services/House | G403: 5226 | H403: Remuneraciones Servicios | I403: =+E403&G403 -> CAR5226 | J403: 930812.5 | K403: 662.5 | L403: 1405 | M403: 13/04/2026 | N403: CAJA | O403: 0123 | P403: TE001400000368 | Q403: Asiento de CAJA (01/09/2025 - 30042026) | R403: Extracción de Caja 001400000368 Obs: 13-04-2026 Mov Lodge | S403: CAR - Sueldo marzo Carmen cocinera | T403: 000000000906 | U403: Ejercicio 2025/2026
D404: Uruguay | E404: CAR | F404: =+VLOOKUP(G404,Resumen_Base!$C$8:$G$156,5,0) -> Services/House | G404: 5226 | H404: Remuneraciones Servicios | I404: =+E404&G404 -> CAR5226 | J404: 1952950 | K404: 1390 | L404: 1405 | M404: 13/04/2026 | N404: CAJA | O404: 0123 | P404: TE001400000368 | Q404: Asiento de CAJA (01/09/2025 - 30042026) | R404: Extracción de Caja 001400000368 Obs: 13-04-2026 Mov Lodge | S404: CAR - Tips marzo paloma | T404: 000000000906 | U404: Ejercicio 2025/2026
D405: Uruguay | E405: CAR | F405: =+VLOOKUP(G405,Resumen_Base!$C$8:$G$156,5,0) -> Services/House | G405: 5226 | H405: Remuneraciones Servicios | I405: =+E405&G405 -> CAR5226 | J405: 10991315 | K405: 7823 | L405: 1405 | M405: 13/04/2026 | N405: CAJA | O405: 0123 | P405: TE001400000368 | Q405: Asiento de CAJA (01/09/2025 - 30042026) | R405: Extracción de Caja 001400000368 Obs: 13-04-2026 Mov Lodge | S405: CAR - Tips marzo Santiago,Yuliana,Victoria , Rafael,Valeria | T405: 000000000906 | U405: Ejercicio 2025/2026
D406: Uruguay | E406: CAR | F406: =+VLOOKUP(G406,Resumen_Base!$C$8:$G$156,5,0) -> Services/House | G406: 5226 | H406: Remuneraciones Servicios | I406: =+E406&G406 -> CAR5226 | J406: 1957165 | K406: 1393 | L406: 1405 | M406: 13/04/2026 | N406: CAJA | O406: 0123 | P406: TE001400000368 | Q406: Asiento de CAJA (01/09/2025 - 30042026) | R406: Extracción de Caja 001400000368 Obs: 13-04-2026 Mov Lodge | S406: CAR - Tips marzo steffy | T406: 000000000906 | U406: Ejercicio 2025/2026
D407: Uruguay | E407: CAR | F407: =+VLOOKUP(G407,Resumen_Base!$C$8:$G$156,5,0) -> Services/House | G407: 5226 | H407: Remuneraciones Servicios | I407: =+E407&G407 -> CAR5226 | J407: -2107500 | K407: -1500 | L407: 1405 | M407: 20/04/2026 | N407: CAJA | O407: 0123 | P407: TD001400000382 | Q407: Asiento de CAJA (01/09/2025 - 30042026) | R407: Depósito a Banco 001400000382 Obs: 20-04-2026 Mov Lodge | S407: CAR - devolucion sueldo marzo adelantado Santi Carrato | T407: 000000000897 | U407: Ejercicio 2025/2026
D408: Uruguay | E408: CAR | F408: =+VLOOKUP(G408,Resumen_Base!$C$8:$G$156,5,0) -> Services/House | G408: 5226 | H408: Remuneraciones Servicios | I408: =+E408&G408 -> CAR5226 | J408: 263437.5 | K408: 187.5 | L408: 1405 | M408: 20/04/2026 | N408: CAJA | O408: 0123 | P408: TE001400000387 | Q408: Asiento de CAJA (01/09/2025 - 30042026) | R408: Extracción de Caja 001400000387 Obs: 20-04-2026 Mov Lodge | S408: CAR - Pago primera quincena abril ton | T408: 000000000913 | U408: Ejercicio 2025/2026
D409: Uruguay | E409: CAR | F409: =+VLOOKUP(G409,Resumen_Base!$C$8:$G$156,5,0) -> Services/House | G409: 5226 | H409: Remuneraciones Servicios | I409: =+E409&G409 -> CAR5226 | J409: 1269038.1 | K409: 903.23 | L409: 1405 | M409: 20/04/2026 | N409: CAJA | O409: 0123 | P409: TH001400000385 | Q409: Asiento de CAJA (01/09/2025 - 30042026) | R409: Extracción de Banco 001400000385 Obs: 20-04-2026 Mov Lodge | S409: CAR - sueldo marzo Paloma Marchetti | T409: 000000000926 | U409: Ejercicio 2025/2026
D410: Uruguay | E410: CAR | F410: =+VLOOKUP(G410,Resumen_Base!$C$8:$G$156,5,0) -> Services/House | G410: 5226 | H410: Remuneraciones Servicios | I410: =+E410&G410 -> CAR5226 | J410: 1245363.9 | K410: 886.38 | L410: 1405 | M410: 20/04/2026 | N410: CAJA | O410: 0123 | P410: TH001400000385 | Q410: Asiento de CAJA (01/09/2025 - 30042026) | R410: Extracción de Banco 001400000385 Obs: 20-04-2026 Mov Lodge | S410: CAR - sueldo marzo Stefany Suhr | T410: 000000000926 | U410: Ejercicio 2025/2026
D411: Uruguay | E411: CAR | F411: =+VLOOKUP(G411,Resumen_Base!$C$8:$G$156,5,0) -> Services/House | G411: 5226 | H411: Remuneraciones Servicios | I411: =+E411&G411 -> CAR5226 | J411: 1269038.1 | K411: 903.23 | L411: 1405 | M411: 20/04/2026 | N411: CAJA | O411: 0123 | P411: TH001400000385 | Q411: Asiento de CAJA (01/09/2025 - 30042026) | R411: Extracción de Banco 001400000385 Obs: 20-04-2026 Mov Lodge | S411: CAR - sueldo marzo Valeria Olmedo | T411: 000000000926 | U411: Ejercicio 2025/2026
D412: Uruguay | E412: CAR | F412: =+VLOOKUP(G412,Resumen_Base!$C$8:$G$156,5,0) -> Services/House | G412: 5226 | H412: Remuneraciones Servicios | I412: =+E412&G412 -> CAR5226 | J412: 1245363.9 | K412: 886.38 | L412: 1405 | M412: 20/04/2026 | N412: CAJA | O412: 0123 | P412: TH001400000385 | Q412: Asiento de CAJA (01/09/2025 - 30042026) | R412: Extracción de Banco 001400000385 Obs: 20-04-2026 Mov Lodge | S412: CAR - sueldo marzo Yuliana Gonzalez | T412: 000000000926 | U412: Ejercicio 2025/2026
... D576: Uruguay | E576: CAR | F576: =+VLOOKUP(G576,Resumen_Base!$C$8:$G$156,5,0) -> Work uniforms for personnel (employees) | G576: 5220 | H576: Uniformes | I576: =+E576&G576 -> CAR5220 | J576: 242000 | K576: 172.24199 | L576: 1405 | M576: 30/04/2026 | N576: CAJA | O576: 0123 | P576: TE001400000416 | Q576: Asiento de CAJA (01/09/2025 - 30042026) | R576: Extracción de Caja 001400000416 Obs: Movimiento_Cajas_Bancos_Semana 25-26 al 08-05-2026 | S576: CAR-6 chalecos Uniformes Carmelo Lodge Pagos Frank Garrahan- Al 08-05-2026 | T576: 000000000922 | U576: Ejercicio 2025/2026
B578: REVERSAR EN ABRIL 2026 (MOV MARZO APP CARGADOS EN ABRIL) | E578: CAR | F578: Electricity - Gas for Boats & Vehicles | G578: 5248 | H578: Combustibles y Lub. - Vehiculos y Botes | I578: =+E578&G578 -> CAR5248 | K578: -2781.025 | M578: 46112 | Q578: combustible vehiculos marzo Carmelo | R578: combustible vehiculos marzo Carmelo | S578: combustible vehiculos marzo Carmelo
B579: REVERSAR EN ABRIL 2026 (MOV MARZO APP CARGADOS EN ABRIL) | E579: CAR | F579: Electricity - Gas for Boats & Vehicles | G579: 5248 | H579: Combustibles y Lub. - Vehiculos y Botes | I579: =+E579&G579 -> CAR5248 | K579: -1.929 | M579: 46112 | Q579: deb comi | R579: deb comi | S579: deb comi
B580: REVERSAR EN ABRIL 2026 (MOV MARZO APP CARGADOS EN ABRIL) | E580: CAR | F580: Food & Wine | G580: 5250 | H580: Comidas y refrigerios | I580: =+E580&G580 -> CAR5250 | K580: -1890.9 | M580: 46112 | Q580: bebidas marzo Belater | R580: bebidas marzo Belater | S580: bebidas marzo Belater
B581: REVERSAR EN ABRIL 2026 (MOV MARZO APP CARGADOS EN ABRIL) | E581: CAR | F581: Food & Wine | G581: 5250 | H581: Comidas y refrigerios | I581: =+E581&G581 -> CAR5250 | K581: -542.575 | M581: 46112 | Q581: carnes especiales marzo Gourmeat | R581: carnes especiales marzo Gourmeat | S581: carnes especiales marzo Gourmeat
B582: REVERSAR EN ABRIL 2026 (MOV MARZO APP CARGADOS EN ABRIL) | E582: CAR | F582: Food & Wine | G582: 5250 | H582: Comidas y refrigerios | I582: =+E582&G582 -> CAR5250 | K582: -5.787 | M582: 46112 | Q582: deb comi | R582: deb comi | S582: deb comi
B583: REVERSAR EN ABRIL 2026 (MOV MARZO APP CARGADOS EN ABRIL) | E583: CAR | F583: Food & Wine | G583: 5250 | H583: Comidas y refrigerios | I583: =+E583&G583 -> CAR5250 | K583: -4923.3 | M583: 46112 | Q583: quesos y lacteos marzo FINESA | R583: quesos y lacteos marzo FINESA | S583: quesos y lacteos marzo FINESA
B584: REVERSAR EN ABRIL 2026 (MOV MARZO APP CARGADOS EN ABRIL) | E584: CAR | F584: Food & Wine | G584: 5250 | H584: Comidas y refrigerios | I584: =+E584&G584 -> CAR5250 | K584: -2775.075 | M584: 46112 | Q584: verduleria marzo Carmelo | R584: verduleria marzo Carmelo | S584: verduleria marzo Carmelo
B585: REVERSAR EN ABRIL 2026 (MOV MARZO APP CARGADOS EN ABRIL) | E585: CAR | F585: Guides | G585: 5227 | H585: Remuneraciones Guías | I585: =+E585&G585 -> CAR5227 | K585: -377.35 | M585: 46112 | Q585: adelanto sueldo marzo Santi Carrato | R585: adelanto sueldo marzo Santi Carrato | S585: adelanto sueldo marzo Santi Carrato
B586: REVERSAR EN ABRIL 2026 (MOV MARZO APP CARGADOS EN ABRIL) | E586: CAR | F586: Guides | G586: 5227 | H586: Remuneraciones Guías | I586: =+E586&G586 -> CAR5227 | K586: -446.25 | M586: 46112 | Q586: bb marzo 2 Agustin Borasich | R586: bb marzo 2 Agustin Borasich | S586: bb marzo 2 Agustin Borasich
B587: REVERSAR EN ABRIL 2026 (MOV MARZO APP CARGADOS EN ABRIL) | E587: CAR | F587: Guides | G587: 5227 | H587: Remuneraciones Guías | I587: =+E587&G587 -> CAR5227 | K587: -85 | M587: 46112 | Q587: bb marzo 2 Brando Ponce | R587: bb marzo 2 Brando Ponce | S587: bb marzo 2 Brando Ponce
B588: REVERSAR EN ABRIL 2026 (MOV MARZO APP CARGADOS EN ABRIL) | E588: CAR | F588: Guides | G588: 5227 | H588: Remuneraciones Guías | I588: =+E588&G588 -> CAR5227 | K588: -276.25 | M588: 46112 | Q588: bb marzo 2 edgardo martinez | R588: bb marzo 2 edgardo martinez | S588: bb marzo 2 edgardo martinez
B589: REVERSAR EN ABRIL 2026 (MOV MARZO APP CARGADOS EN ABRIL) | E589: CAR | F589: Guides | G589: 5227 | H589: Remuneraciones Guías | I589: =+E589&G589 -> CAR5227 | K589: -68.375 | M589: 46112 | Q589: bb marzo 2 franco Rigos | R589: bb marzo 2 franco Rigos | S589: bb marzo 2 franco Rigos
... B615: REVERSAR EN ABRIL 2026 (MOV MARZO APP CARGADOS EN ABRIL) | E615: CAR | F615: Miscellaneous & Shipping | G615: 5219 | H615: Gastos Varios | I615: =+E615&G615 -> CAR5219 | K615: -1.9295 | M615: 46112 | Q615: deb comi | R615: deb comi | S615: deb comi
B616: REVERSAR EN ABRIL 2026 (MOV MARZO APP CARGADOS EN ABRIL) - COMIDA | C616: 5292 PERMISOS CONTROL AMBIENTAL | E616: CAR | F616: Food & Wine | G616: 5250 | H616: Comidas y refrigerios | I616: =+E616&G616 -> CAR5250 | K616: -735.75 | M616: 46112 | Q616: pelada de palomas todo marzo Franco Rigos | R616: pelada de palomas todo marzo Franco Rigos | S616: pelada de palomas todo marzo Franco Rigos
B617: REVERSAR EN ABRIL 2026 (MOV MARZO APP CARGADOS EN ABRIL) - COMIDA | C617: 5292 PERMISOS CONTROL AMBIENTAL | E617: CAR | F617: Food & Wine | G617: 5250 | H617: Comidas y refrigerios | I617: =+E617&G617 -> CAR5250 | K617: -25 | M617: 46112 | Q617: pelada palomas marzo Felipe Olivera | R617: pelada palomas marzo Felipe Olivera | S617: pelada palomas marzo Felipe Olivera
B618: REVERSAR EN ABRIL 2026 (MOV MARZO APP CARGADOS EN ABRIL) - COMIDA | C618: 5292 PERMISOS CONTROL AMBIENTAL | E618: CAR | F618: Food & Wine | G618: 5250 | H618: Comidas y refrigerios | I618: =+E618&G618 -> CAR5250 | K618: -263.75 | M618: 46112 | Q618: pelada palomas Victor Ramirez marzo | R618: pelada palomas Victor Ramirez marzo | S618: pelada palomas Victor Ramirez marzo
B619: REVERSAR EN ABRIL 2026 (MOV MARZO APP CARGADOS EN ABRIL) | E619: CAR | F619: Services/House | G619: 5226 | H619: Remuneraciones Servicios | I619: =+E619&G619 -> CAR5226 | K619: -903.225 | M619: 46112 | Q619: sueldo marzo Paloma Marchetti | R619: sueldo marzo Paloma Marchetti | S619: sueldo marzo Paloma Marchetti
B620: REVERSAR EN ABRIL 2026 (MOV MARZO APP CARGADOS EN ABRIL) | E620: CAR | F620: Services/House | G620: 5226 | H620: Remuneraciones Servicios | I620: =+E620&G620 -> CAR5226 | K620: -886.375 | M620: 46112 | Q620: sueldo marzo Stefany Suhr | R620: sueldo marzo Stefany Suhr | S620: sueldo marzo Stefany Suhr
B621: REVERSAR EN ABRIL 2026 (MOV MARZO APP CARGADOS EN ABRIL) | E621: CAR | F621: Services/House | G621: 5226 | H621: Remuneraciones Servicios | I621: =+E621&G621 -> CAR5226 | K621: -903.225 | M621: 46112 | Q621: sueldo marzo Valeria Olmedo | R621: sueldo marzo Valeria Olmedo | S621: sueldo marzo Valeria Olmedo
B622: REVERSAR EN ABRIL 2026 (MOV MARZO APP CARGADOS EN ABRIL) | E622: CAR | F622: Services/House | G622: 5226 | H622: Remuneraciones Servicios | I622: =+E622&G622 -> CAR5226 | K622: -886.375 | M622: 46112 | Q622: sueldo marzo Yuliana Gonzalez | R622: sueldo marzo Yuliana Gonzalez | S622: sueldo marzo Yuliana Gonzalez
B623: REVERSAR EN ABRIL 2026 (MOV MARZO APP CARGADOS EN ABRIL) | E623: CAR | F623: Services/House | G623: 5226 | H623: Remuneraciones Servicios | I623: =+E623&G623 -> CAR5226 | K623: -1390 | M623: 46120 | Q623: Tips marzo paloma | R623: Tips marzo paloma | S623: Tips marzo paloma
B624: REVERSAR EN ABRIL 2026 (MOV MARZO APP CARGADOS EN ABRIL) | E624: CAR | F624: Services/House | G624: 5226 | H624: Remuneraciones Servicios | I624: =+E624&G624 -> CAR5226 | K624: -1393 | M624: 46120 | Q624: Tips marzo steffy | R624: Tips marzo steffy | S624: Tips marzo steffy
B625: REVERSAR EN ABRIL 2026 (MOV MARZO APP CARGADOS EN ABRIL) | E625: CAR | F625: Services/House | G625: 5226 | H625: Remuneraciones Servicios | I625: =+E625&G625 -> CAR5226 | K625: -7823 | M625: 46119 | Q625: Tips marzo Santiago,Yuliana,Victoria , Rafael,Valeria | R625: Tips marzo Santiago,Yuliana,Victoria , Rafael,Valeria | S625: Tips marzo Santiago,Yuliana,Victoria , Rafael,Valeria
B626: REVERSAR EN ABRIL 2026 (MOV MARZO APP CARGADOS EN ABRIL) | E626: CAR | F626: Services/House | G626: 5226 | H626: Remuneraciones Servicios | I626: =+E626&G626 -> CAR5226 | K626: -900 | M626: 46118 | Q626: Sueldo marzo Santiago mantenimiento | R626: Sueldo marzo Santiago mantenimiento | S626: Sueldo marzo Santiago mantenimiento
B627: REVERSAR EN ABRIL 2026 (MOV MARZO APP CARGADOS EN ABRIL) | E627: CAR | F627: Services/House | G627: 5226 | H627: Remuneraciones Servicios | I627: =+E627&G627 -> CAR5226 | K627: -662.5 | M627: 46120 | Q627: Sueldo marzo Carmen cocinera | R627: Sueldo marzo Carmen cocinera | S627: Sueldo marzo Carmen cocinera
B628: REVERSAR EN ABRIL 2026 (MOV MARZO APP CARGADOS EN ABRIL) | E628: CAR | F628: Social Security Contributions | G628: 5236 | H628: Cargas Sociales Guías | I628: =+E628&G628 -> CAR5236 | K628: -584.25 | M628: 46112 | Q628: iva y BPS Felipe Olivera | R628: iva y BPS Felipe Olivera | S628: iva y BPS Felipe Olivera
B629: REVERSAR EN ABRIL 2026 (MOV MARZO APP CARGADOS EN ABRIL) | E629: CAR | F629: Social Security Contributions | G629: 5236 | H629: Cargas Sociales Guías | I629: =+E629&G629 -> CAR5236 | K629: -412.5 | M629: 46112 | Q629: iva y bps marzo Juan Long | R629: iva y bps marzo Juan Long | S629: iva y bps marzo Juan Long
B630: REVERSAR EN ABRIL 2026 (MOV MARZO APP CARGADOS EN ABRIL) | E630: SJ | F630: Electricity - Gas for Boats & Vehicles | G630: 5248 | H630: Combustibles y Lub. - Vehiculos y Botes | I630: =+E630&G630 -> SJ5248 | K630: -100 | M630: 46112 | Q630: combustible tramites caro horta marzo | R630: combustible tramites caro horta marzo | S630: combustible tramites caro horta marzo
... B642: REVERSAR EN ABRIL 2026 (MOV MARZO APP CARGADOS EN ABRIL) | E642: CAR | F642: Guides | G642: 5227 | H642: Remuneraciones Guías | I642: =+E642&G642 -> CAR5227 | K642: 1500 | M642: 46112 | Q642: devolucion sueldo marzo adelantado Santi Carrato | R642: sueldo marzo Carrato luego devuelve | S642: sueldo marzo Carrato luego devuelve
B643: REVERSAR EN ABRIL 2026 (MOV MARZO APP CARGADOS EN ABRIL) | C643: 8101TRANSFERENCIA ENTRE LODGES | E643: CAR | F643: Electricity - Gas for Boats & Vehicles | G643: 5248 | H643: Combustibles y Lub. - Vehiculos y Botes | I643: =+E643&G643 -> CAR5248 | K643: -436.525 | M643: 46112 | Q643: combustible reembolso Long Carmelo 5248 | R643: combustible reembolso Long Carmelo 5248 | S643: combustible reembolso Long Carmelo 5248
B644: REVERSAR EN ABRIL 2026 (MOV MARZO APP CARGADOS EN ABRIL) | C644: 8101TRANSFERENCIA ENTRE LODGES | E644: CAR | F644: Field: | G644: 5207 | H644: Alquiler Campos | I644: =+E644&G644 -> CAR5207 | K644: -350 | M644: 46112 | Q644: alquiler entrada campo marzo Carmelo alcira cornu 5207 | R644: alquiler entrada campo marzo Carmelo alcira cornu 5207 | S644: alquiler entrada campo marzo Carmelo alcira cornu 5207
B645: REVERSAR EN ABRIL 2026 (MOV MARZO APP CARGADOS EN ABRIL) | C645: 8101TRANSFERENCIA ENTRE LODGES | E645: CAR | F645: Field: | G645: 5207 | H645: Alquiler Campos | I645: =+E645&G645 -> CAR5207 | K645: -1950 | M645: 46112 | Q645: alquiler entrada campos marzo CARMELO 5207 | R645: alquiler entrada campos marzo CARMELO 5207 | S645: alquiler entrada campos marzo CARMELO 5207
B646: REVERSAR EN ABRIL 2026 (MOV MARZO APP CARGADOS EN ABRIL) | C646: 8101TRANSFERENCIA ENTRE LODGES | E646: CAR | F646: Field: | G646: 5207 | H646: Alquiler Campos | I646: =+E646&G646 -> CAR5207 | K646: -450 | M646: 46112 | Q646: entrada campo marzo Andrea Rossi Carmelo 5207 | R646: entrada campo marzo Andrea Rossi Carmelo 5207 | S646: entrada campo marzo Andrea Rossi Carmelo 5207
B647: REVERSAR EN ABRIL 2026 (MOV MARZO APP CARGADOS EN ABRIL) | C647: 8101TRANSFERENCIA ENTRE LODGES | E647: CAR | F647: Field: | G647: 5207 | H647: Alquiler Campos | I647: =+E647&G647 -> CAR5207 | K647: -950 | M647: 46112 | Q647: entrada campo marzo Beron Carmelo 5207 | R647: entrada campo marzo Beron Carmelo 5207 | S647: entrada campo marzo Beron Carmelo 5207
B648: REVERSAR EN ABRIL 2026 (MOV MARZO APP CARGADOS EN ABRIL) | C648: 8101TRANSFERENCIA ENTRE LODGES | E648: CAR | F648: Field: | G648: 5207 | H648: Alquiler Campos | I648: =+E648&G648 -> CAR5207 | K648: -250 | M648: 46112 | Q648: entrada campo marzo Mario Bianchi Carmelo 5207 | R648: entrada campo marzo Mario Bianchi Carmelo 5207 | S648: entrada campo marzo Mario Bianchi Carmelo 5207
B649: REVERSAR EN ABRIL 2026 (MOV MARZO APP CARGADOS EN ABRIL) | C649: 8101TRANSFERENCIA ENTRE LODGES | E649: CAR | F649: Field: | G649: 5207 | H649: Alquiler Campos | I649: =+E649&G649 -> CAR5207 | K649: -1550 | M649: 46112 | Q649: entrada campo marzo Salvagno Carmelo 5207 | R649: entrada campo marzo Salvagno Carmelo 5207 | S649: entrada campo marzo Salvagno Carmelo 5207
B650: REVERSAR EN ABRIL 2026 (MOV MARZO APP CARGADOS EN ABRIL) | C650: 8101TRANSFERENCIA ENTRE LODGES | E650: CAR | F650: Field: | G650: 5207 | H650: Alquiler Campos | I650: =+E650&G650 -> CAR5207 | K650: -750 | M650: 46112 | Q650: entrada campo Palomares marzo Carmelo 5207 | R650: entrada campo Palomares marzo Carmelo 5207 | S650: entrada campo Palomares marzo Carmelo 5207
B651: REVERSAR EN ABRIL 2026 (MOV MARZO APP CARGADOS EN ABRIL) | C651: 8101TRANSFERENCIA ENTRE LODGES | E651: CAR | F651: Field: | G651: 5207 | H651: Alquiler Campos | I651: =+E651&G651 -> CAR5207 | K651: -100 | M651: 46112 | Q651: entrada campos marzo carmelo Dumestre 5207 | R651: entrada campos marzo carmelo Dumestre 5207 | S651: entrada campos marzo carmelo Dumestre 5207
B652: REVERSAR EN ABRIL 2026 (MOV MARZO APP CARGADOS EN ABRIL) | C652: 8101TRANSFERENCIA ENTRE LODGES | E652: CAR | F652: Food & Wine | G652: 5250 | H652: Comidas y refrigerios | I652: =+E652&G652 -> CAR5250 | K652: -438.425 | M652: 46112 | Q652: surtido staff y comida viakes reembolso LONG Carmelo 5250 | R652: surtido staff y comida viakes reembolso LONG Carmelo 5250 | S652: surtido staff y comida viakes reembolso LONG Carmelo 5250
B653: REVERSAR EN ABRIL 2026 (MOV MARZO APP CARGADOS EN ABRIL) | C653: 8101TRANSFERENCIA ENTRE LODGES | E653: CAR | F653: Maintenance Boats / Vehicles | G653: 5253 | H653: Mantenimiento y reposiciones-Vehiculos/Lanchas | I653: =+E653&G653 -> CAR5253 | K653: -456.575 | M653: 46112 | Q653: mantenimiento vehiculos carmelo reembolso Long 5253 carmelo | R653: mantenimiento vehiculos carmelo reembolso Long 5253 carmelo | S653: mantenimiento vehiculos carmelo reembolso Long 5253 carmelo
B654: REVERSAR EN ABRIL 2026 (MOV MARZO APP CARGADOS EN ABRIL) | C654: 8101TRANSFERENCIA ENTRE LODGES | E654: CAR | F654: Maintenance Equipment | G654: 5254 | H654: Mantenimiento y reposiciones - Equipos/Armas | I654: =+E654&G654 -> CAR5254 | K654: -243.6 | M654: 46112 | Q654: gastos mantenimiento equipo y material caceria cintas tapones LONG Carmelo 5254 | R654: gastos mantenimiento equipo y material caceria cintas tapones LONG Carmelo 5254 | S654: gastos mantenimiento equipo y material caceria cintas tapones LONG Carmelo 5254
B656: REVERSAR EN MAYO 2026 (MOV ABRIL APP CARGADOS EN MAYO) | E656: CAR | F656: =+VLOOKUP(G656,Resumen_Base!$C$8:$G$156,5,0) -> Field: | G656: 5207 | H656: Alquiler Campos | I656: =+E656&G656 -> CAR5207 | K656: 150 | M656: 46142 | O656: Carmelo Lodge | P656: 46157 | S656: campo abril Alcira cornu | U656: Banco Itau - USD
B657: REVERSAR EN MAYO 2026 (MOV ABRIL APP CARGADOS EN MAYO) | E657: CAR | F657: =+VLOOKUP(G657,Resumen_Base!$C$8:$G$156,5,0) -> Field: | G657: 5207 | H657: Alquiler Campos | I657: =+E657&G657 -> CAR5207 | K657: 2800 | M657: 46142 | O657: Carmelo Lodge | P657: 46157 | S657: campos abril Salvagno | U657: Banco Itau - USD
B658: REVERSAR EN MAYO 2026 (MOV ABRIL APP CARGADOS EN MAYO) | E658: CAR | F658: =+VLOOKUP(G658,Resumen_Base!$C$8:$G$156,5,0) -> Field: | G658: 5207 | H658: Alquiler Campos | I658: =+E658&G658 -> CAR5207 | K658: 7.6 | M658: 46142 | O658: Carmelo Lodge | P658: 46157 | S658: deb comi | U658: Banco Itau - USD
B659: REVERSAR EN MAYO 2026 (MOV ABRIL APP CARGADOS EN MAYO) | E659: CAR | F659: =+VLOOKUP(G659,Resumen_Base!$C$8:$G$156,5,0) -> Field: | G659: 5207 | H659: Alquiler Campos | I659: =+E659&G659 -> CAR5207 | K659: 2000 | M659: 46142 | O659: Carmelo Lodge | P659: 46157 | S659: reembolos varios campos abril Juan Long | U659: Banco Itau - USD
B660: REVERSAR EN MAYO 2026 (MOV ABRIL APP CARGADOS EN MAYO) | E660: CAR | F660: =+VLOOKUP(G660,Resumen_Base!$C$8:$G$156,5,0) -> Work uniforms for personnel (employees) | G660: 5220 | H660: Uniformes | I660: =+E660&G660 -> CAR5220 | K660: 564.10256 | M660: 46141 | O660: Carmelo Lodge | P660: 46143 | S660: Seña camperas guias Carmelo | U660: Banco Itau - UY
B661: REVERSAR EN MAYO 2026 (MOV ABRIL APP CARGADOS EN MAYO) | E661: CAR | F661: =+VLOOKUP(G661,Resumen_Base!$C$8:$G$156,5,0) -> Licenses / Permits (Fishing and Shooting) | G661: 5221 | H661: Permisos | I661: =+E661&G661 -> CAR5221 | K661: 880 | M661: 46142 | O661: Carmelo Lodge | P661: 46157 | S661: Honorarios abril Mati Vila | U661: Banco Itau - USD
B662: REVERSAR EN MAYO 2026 (MOV ABRIL APP CARGADOS EN MAYO) | E662: CAR | F662: =+VLOOKUP(G662,Resumen_Base!$C$8:$G$156,5,0) -> Transfer to and from the airport (local taxi) - Vehicle Rental | G662: 5225 | H662: Alquiler Camionetas/Lanchas | I662: =+E662&G662 -> CAR5225 | K662: 3712 | M662: 46142 | O662: Carmelo Lodge | P662: 46159 | S662: alquiler camionetas Multicar abril | U662: Banco Itau - USD
B663: REVERSAR EN MAYO 2026 (MOV ABRIL APP CARGADOS EN MAYO) | E663: CAR | F663: =+VLOOKUP(G663,Resumen_Base!$C$8:$G$156,5,0) -> Services/House | G663: 5226 | H663: Remuneraciones Servicios | I663: =+E663&G663 -> CAR5226 | K663: 926.38462 | M663: 46142 | O663: Carmelo Lodge | P663: 46158 | S663: sueldo abril paloma marchetti | U663: Banco Itau - UY
B664: REVERSAR EN MAYO 2026 (MOV ABRIL APP CARGADOS EN MAYO) | E664: CAR | F664: =+VLOOKUP(G664,Resumen_Base!$C$8:$G$156,5,0) -> Services/House | G664: 5226 | H664: Remuneraciones Servicios | I664: =+E664&G664 -> CAR5226 | K664: 909.10256 | M664: 46142 | O664: Carmelo Lodge | P664: 46158 | S664: sueldo abril stefany suhr | U664: Banco Itau - UY
B665: REVERSAR EN MAYO 2026 (MOV ABRIL APP CARGADOS EN MAYO) | E665: CAR | F665: =+VLOOKUP(G665,Resumen_Base!$C$8:$G$156,5,0) -> Services/House | G665: 5226 | H665: Remuneraciones Servicios | I665: =+E665&G665 -> CAR5226 | K665: 926.38462 | M665: 46142 | O665: Carmelo Lodge | P665: 46158 | S665: sueldo abril Valeria Olmedo | U665: Banco Itau - UY
B666: REVERSAR EN MAYO 2026 (MOV ABRIL APP CARGADOS EN MAYO) | E666: CAR | F666: =+VLOOKUP(G666,Resumen_Base!$C$8:$G$156,5,0) -> Services/House | G666: 5226 | H666: Remuneraciones Servicios | I666: =+E666&G666 -> CAR5226 | K666: 909.10256 | M666: 46142 | O666: Carmelo Lodge | P666: 46158 | S666: sueldo abril yuliana gonzalez | U666: Banco Itau - UY
B667: REVERSAR EN MAYO 2026 (MOV ABRIL APP CARGADOS EN MAYO) | E667: CAR | F667: =+VLOOKUP(G667,Resumen_Base!$C$8:$G$156,5,0) -> Guides | G667: 5227 | H667: Remuneraciones Guías | I667: =+E667&G667 -> CAR5227 | K667: 457.69231 | M667: 46142 | O667: Carmelo Lodge | P667: 46158 | S667: bb abril 2 Brandon maidana | U667: Banco Itau - UY
... B700: REVERSAR EN MAYO 2026 (MOV ABRIL APP CARGADOS EN MAYO) | E700: CAR | F700: =+VLOOKUP(G700,Resumen_Base!$C$8:$G$156,5,0) -> Maintenance Lodge | G700: 5252 | H700: Mantenimiento y reposiciones - Lodge | I700: =+E700&G700 -> CAR5252 | K700: 277.97436 | M700: 46142 | O700: Carmelo Lodge | P700: 46158 | S700: mantenimiento jardines combustible | U700: Banco Itau - UY
A701: MUEBLES Y UTILES | B701: REVERSAR EN MAYO 2026 (MOV ABRIL APP CARGADOS EN MAYO) | C701: 5252 Mantenimiento y reposiciones - Lodge | E701: CAR | F701: =+VLOOKUP(G701,Resumen_Base!$C$8:$G$156,5,0) -> Fixed Asset's Payments (Investments) Mejoras/equipamiento Lodge | G701: 12020301 | H701: Muebles y útiles | I701: =+E701&G701 -> CAR12020301 | K701: 212.71795 | M701: 46142 | O701: Carmelo Lodge | P701: 46157 | S701: platos sue asado | U701: Banco Itau - UY
B702: REVERSAR EN MAYO 2026 (MOV ABRIL APP CARGADOS EN MAYO) | E702: CAR | F702: =+VLOOKUP(G702,Resumen_Base!$C$8:$G$156,5,0) -> Maintenance Boats / Vehicles | G702: 5253 | H702: Mantenimiento y reposiciones-Vehiculos/Lanchas | I702: =+E702&G702 -> CAR5253 | K702: 1.9420513 | M702: 46142 | O702: Carmelo Lodge | P702: 46158 | S702: deb comi | U702: Banco Itau - UY
B703: REVERSAR EN MAYO 2026 (MOV ABRIL APP CARGADOS EN MAYO) | E703: CAR | F703: =+VLOOKUP(G703,Resumen_Base!$C$8:$G$156,5,0) -> Maintenance Boats / Vehicles | G703: 5253 | H703: Mantenimiento y reposiciones-Vehiculos/Lanchas | I703: =+E703&G703 -> CAR5253 | K703: 13.923077 | M703: 46142 | O703: Carmelo Lodge | P703: 46158 | S703: sensor quemado master | U703: Banco Itau - UY
B704: REVERSAR EN MAYO 2026 (MOV ABRIL APP CARGADOS EN MAYO) | E704: CAR | F704: =+VLOOKUP(G704,Resumen_Base!$C$8:$G$156,5,0) -> Maintenance Boats / Vehicles | G704: 5253 | H704: Mantenimiento y reposiciones-Vehiculos/Lanchas | I704: =+E704&G704 -> CAR5253 | K704: 1.9420513 | M704: 46142 | O704: Carmelo Lodge | P704: 46157 | S704: deb comi | U704: Banco Itau - UY
...

Sheet Mov_Analizados_May 26
H2: Ver Telefonos
H3: Ver Gastos devengados
H4: Ver Luz Devengada
H5: Ver REVERSAS
E7: =+VLOOKUP(G7,'Plan Cuentas Link Armado'!$E$3:$G$105,3,0) -> #N/A | H7: =+IF(J7+K7=0,"Ok","Check") -> Ok | J7: =ROUND(SUM(J10:J2591),0) -> 0 | K7: =ROUND(SUM(K10:K2591),0) -> 0
E8: Plan Cuentas Link Armado | F8: Rubro | H8: =+Resumen_Base!D1 -> Ok
C9: =+G9&$D$9&H9 | E9: =+VLOOKUP(G9,Resumen_Base!$C$8:$F$26,4,0) -> #N/A | F9: =+VLOOKUP(G9,Resumen_Base!$C$8:$G$156,5,0) -> #N/A | I9: =+E9&G9 -> #N/A | J9: =SUM(J10:J1124) -> 94249258 | K9: =SUM(K10:K1124) -> 102188.3
C10: Cuenta Anterior | E10: Lodge | F10: Concepto | G10: Cuenta | H10: Nombre | J10: monto $ | K10: monto USD | L10: TC | M10: Fecha | N10: Subdiario | O10: Div | P10: Datos del comprobante | Q10: Sujeto | R10: CUIT | S10: Observación asiento | T10: Clase de Asiento | U10: Origen del comprobante | V10: Observación del comprobante | W10: Comentario renglón asiento | X10: Asiento | Y10: Control | AA10: monto USD | AB10: tc | AD10: Fecha | AE10: Subdiario | AF10: Div | AG10: Datos del comprobante | AH10: Sujeto | AI10: CUIT | AJ10: Observación asiento | AK10: Clase de Asiento | AL10: Origen del comprobante | AM10: Observación del comprobante | AN10: Comentario renglón asiento | AO10: Asiento
E13: SJ | F13: =+VLOOKUP(G13,Resumen_Base!$C$8:$G$156,5,0) -> Fixed Asset's Payments (Investments) Mejoras/equipamiento Lodge | G13: 12020103 | H13: Mejoras de Inmueb y Terrenos | I13: =+E13&G13 -> SJ12020103 | J13: 49638.65 | K13: 35.33 | L13: 1405 | M13: 18/05/2026 | N13: CAJA | O13: 0121 | P13: TH001400000428 | Q13: Asiento de CAJA (01/09/2025 - 310526) | R13: Extracción de Banco 001400000428 Obs: 18-05-2026 Mov Lodge | S13: SJ - encofrado y clavos para parrillero reembolso felipe olivera | T13: 000000001258 | U13: Ejercicio 2025/2026
E14: SJ | F14: =+VLOOKUP(G14,Resumen_Base!$C$8:$G$156,5,0) -> Fixed Asset's Payments (Investments) Mejoras/equipamiento Lodge | G14: 12020103 | H14: Mejoras de Inmueb y Terrenos | I14: =+E14&G14 -> SJ12020103 | J14: 279412.35 | K14: 198.87 | L14: 1405 | M14: 18/05/2026 | N14: CAJA | O14: 0121 | P14: TH001400000428 | Q14: Asiento de CAJA (01/09/2025 - 310526) | R14: Extracción de Banco 001400000428 Obs: 18-05-2026 Mov Lodge | S14: SJ - materiales para obra parrillero reebolso felipe Olivera | T14: 000000001258 | U14: Ejercicio 2025/2026
E15: CAR | F15: =+VLOOKUP(G15,Resumen_Base!$C$8:$G$156,5,0) -> Fixed Asset's Payments (Investments) Mejoras/equipamiento Lodge | G15: 12020103 | H15: Mejoras de Inmueb y Terrenos | I15: =+E15&G15 -> CAR12020103 | J15: 1405000 | K15: 1000 | L15: 1405 | M15: 15/05/2026 | N15: CAJA | O15: 0123 | P15: TE001400000436 | Q15: Asiento de CAJA (01/09/2025 - 310526) | R15: Extracción de Caja 001400000436 Obs: Movimiento_Cajas_Bancos_Semana 25-26 al 15-05-2026 | S15: CAR-Pago visita paisajistas a Carmelo Lodge Marzo 2026 F.Fijo Oper. Al 12-05-2026 | T15: 000000001248 | U15: Ejercicio 2025/2026
E16: SJ | F16: =+VLOOKUP(G16,Resumen_Base!$C$8:$G$156,5,0) -> Fixed Asset's Payments (Investments) Mejoras/equipamiento Lodge | G16: 12020201 | H16: Instalaciones | I16: =+E16&G16 -> SJ12020201 | J16: 68072.25 | K16: 48.45 | L16: 1405 | M16: 18/05/2026 | N16: CAJA | O16: 0121 | P16: TE001400000423 | Q16: Asiento de CAJA (01/09/2025 - 310526) | R16: Extracción de Caja 001400000423 Obs: 18-05-2026 Mov Lodge | S16: SJ - Kroser, reparaciones varias en lodge | T16: 000000001246 | U16: Ejercicio 2025/2026
E17: SJ | F17: =+VLOOKUP(G17,Resumen_Base!$C$8:$G$156,5,0) -> Fixed Asset's Payments (Investments) Mejoras/equipamiento Lodge | G17: 12020301 | H17: Muebles y útiles | I17: =+E17&G17 -> SJ12020301 | J17: 338338.05 | K17: 240.81 | L17: 1405 | M17: 18/05/2026 | N17: CAJA | O17: 0121 | P17: TH001400000431 | Q17: Asiento de CAJA (01/09/2025 - 310526) | R17: Extracción de Banco 001400000431 Obs: 18-05-2026 Mov Lodge | S17: SJ - sillas SJ | T17: 000000001261 | U17: Ejercicio 2025/2026
E18: SJ | F18: =+VLOOKUP(G18,Resumen_Base!$C$8:$G$156,5,0) -> Fixed Asset's Payments (Investments) Mejoras/equipamiento Lodge | G18: 12020301 | H18: Muebles y útiles | I18: =+E18&G18 -> SJ12020301 | J18: 151725.95 | K18: 107.99 | L18: 1405 | M18: 18/05/2026 | N18: CAJA | O18: 0121 | P18: TH001400000431 | Q18: Asiento de CAJA (01/09/2025 - 310526) | R18: Extracción de Banco 001400000431 Obs: 18-05-2026 Mov Lodge | S18: SJ - articulos parrilla pinzas etc para parrilero SJ | T18: 000000001261 | U18: Ejercicio 2025/2026
E19: SJ | F19: =+VLOOKUP(G19,Resumen_Base!$C$8:$G$156,5,0) -> Fixed Asset's Payments (Investments) Mejoras/equipamiento Lodge | G19: 12020301 | H19: Muebles y útiles | I19: =+E19&G19 -> SJ12020301 | J19: 69083 | K19: 48.65 | L19: 1420 | M19: 31/05/2026 | N19: CAJA | O19: 0121 | P19: TH001400000453 | Q19: Asiento de CAJA (01/09/2025 - 310526) | R19: Extracción de Banco 001400000453 Obs: 31-05-2026 Mov Lodge | S19: SJ - deb comi freezer | T19: 000000001265 | U19: Ejercicio 2025/2026
E20: SJ | F20: =+VLOOKUP(G20,Resumen_Base!$C$8:$G$156,5,0) -> Fixed Asset's Payments (Investments) Mejoras/equipamiento Lodge | G20: 12020301 | H20: Muebles y útiles | I20: =+E20&G20 -> SJ12020301 | J20: 1099648 | K20: 774.4 | L20: 1420 | M20: 31/05/2026 | N20: CAJA | O20: 0121 | P20: TH001400000454 | Q20: Asiento de CAJA (01/09/2025 - 310526) | R20: Extracción de Banco 001400000454 Obs: 31-05-2026 Mov Lodge | S20: SJ - reposiciones Lodge Sofi varias Ver | T20: 000000001266 | U20: Ejercicio 2025/2026
E21: SJ | F21: =+VLOOKUP(G21,Resumen_Base!$C$8:$G$156,5,0) -> Tips | G21: 210609 | H21: Propinas a pagar | I21: =+E21&G21 -> SJ210609 | J21: -2248000 | K21: -1600 | L21: 1405 | M21: 31/05/2026 | N21: CAJA | O21: 0121 | P21: TI001400000446 | Q21: Asiento de CAJA (01/09/2025 - 310526) | R21: Ingreso a Caja 001400000446 Obs: 31-05-2026 Mov Lodge | S21: SJ - Propinas | T21: 000000001273 | U21: Ejercicio 2025/2026
E22: SJ | F22: =+VLOOKUP(G22,Resumen_Base!$C$8:$G$156,5,0) -> Tips | G22: 210609 | H22: Propinas a pagar | I22: =+E22&G22 -> SJ210609 | J22: -2599250 | K22: -1850 | L22: 1405 | M22: 31/05/2026 | N22: CAJA | O22: 0121 | P22: TI001400000446 | Q22: Asiento de CAJA (01/09/2025 - 310526) | R22: Ingreso a Caja 001400000446 Obs: 31-05-2026 Mov Lodge | S22: SJ - Propinas | T22: 000000001273 | U22: Ejercicio 2025/2026
E23: SJ | F23: =+VLOOKUP(G23,Resumen_Base!$C$8:$G$156,5,0) -> Tips | G23: 210609 | H23: Propinas a pagar | I23: =+E23&G23 -> SJ210609 | J23: -2810000 | K23: -2000 | L23: 1405 | M23: 31/05/2026 | N23: CAJA | O23: 0121 | P23: TI001400000446 | Q23: Asiento de CAJA (01/09/2025 - 310526) | R23: Ingreso a Caja 001400000446 Obs: 31-05-2026 Mov Lodge | S23: SJ - tips | T23: 000000001273 | U23: Ejercicio 2025/2026
E24: SJ | F24: =+VLOOKUP(G24,Resumen_Base!$C$8:$G$156,5,0) -> Tips | G24: 210609 | H24: Propinas a pagar | I24: =+E24&G24 -> SJ210609 | J24: -4074500 | K24: -2900 | L24: 1405 | M24: 31/05/2026 | N24: CAJA | O24: 0121 | P24: TI001400000446 | Q24: Asiento de CAJA (01/09/2025 - 310526) | R24: Ingreso a Caja 001400000446 Obs: 31-05-2026 Mov Lodge | S24: SJ - Propinas | T24: 000000001273 | U24: Ejercicio 2025/2026
... E804: CAR | F804: =+VLOOKUP(G804,Resumen_Base!$C$8:$G$156,5,0) -> Miscellaneous & Shipping | G804: 5292 | H804: Permisos Control Ambiental/Patos | I804: =+E804&G804 -> CAR5292 | J804: 167265.25 | K804: 119.05 | L804: 1405 | M804: 31/05/2026 | N804: CAJA | O804: 0123 | P804: TH001400000451 | Q804: Asiento de CAJA (01/09/2025 - 310526) | R804: Extracción de Banco 001400000451 Obs: 31-05-2026 Mov Lodge | S804: CAR - pelada palomas para reserva de animales Victor Ramirez | T804: 000000001263 | U804: Ejercicio 2025/2026
B806: REVERSAR EN MAYO 2026 (MOV ABRIL APP CARGADOS EN MAYO) | E806: CAR | F806: Field: | G806: 5207 | H806: Alquiler Campos | I806: =+E806&G806 -> CAR5207 | K806: -150 | M806: 46142 | O806: Carmelo Lodge | P806: 46157 | S806: campo abril Alcira cornu | U806: Banco Itau - USD
B807: REVERSAR EN MAYO 2026 (MOV ABRIL APP CARGADOS EN MAYO) | E807: CAR | F807: Field: | G807: 5207 | H807: Alquiler Campos | I807: =+E807&G807 -> CAR5207 | K807: -2800 | M807: 46142 | O807: Carmelo Lodge | P807: 46157 | S807: campos abril Salvagno | U807: Banco Itau - USD
B808: REVERSAR EN MAYO 2026 (MOV ABRIL APP CARGADOS EN MAYO) | E808: CAR | F808: Field: | G808: 5207 | H808: Alquiler Campos | I808: =+E808&G808 -> CAR5207 | K808: -7.6 | M808: 46142 | O808: Carmelo Lodge | P808: 46157 | S808: deb comi | U808: Banco Itau - USD
B809: REVERSAR EN MAYO 2026 (MOV ABRIL APP CARGADOS EN MAYO) | E809: CAR | F809: Field: | G809: 5207 | H809: Alquiler Campos | I809: =+E809&G809 -> CAR5207 | K809: -2000 | M809: 46142 | O809: Carmelo Lodge | P809: 46157 | S809: reembolos varios campos abril Juan Long | U809: Banco Itau - USD
B810: REVERSAR EN MAYO 2026 (MOV ABRIL APP CARGADOS EN MAYO) | E810: CAR | F810: Work uniforms for personnel (employees) | G810: 5220 | H810: Uniformes | I810: =+E810&G810 -> CAR5220 | K810: -564.10256 | M810: 46141 | O810: Carmelo Lodge | P810: 46143 | S810: Seña camperas guias Carmelo | U810: Banco Itau - UY
B811: REVERSAR EN MAYO 2026 (MOV ABRIL APP CARGADOS EN MAYO) | E811: CAR | F811: Licenses / Permits (Fishing and Shooting) | G811: 5221 | H811: Permisos | I811: =+E811&G811 -> CAR5221 | K811: -880 | M811: 46142 | O811: Carmelo Lodge | P811: 46157 | S811: Honorarios abril Mati Vila | U811: Banco Itau - USD
B812: REVERSAR EN MAYO 2026 (MOV ABRIL APP CARGADOS EN MAYO) | E812: CAR | F812: Transfer to and from the airport (local taxi) - Vehicle Rental | G812: 5225 | H812: Alquiler Camionetas/Lanchas | I812: =+E812&G812 -> CAR5225 | K812: -3712 | M812: 46142 | O812: Carmelo Lodge | P812: 46159 | S812: alquiler camionetas Multicar abril | U812: Banco Itau - USD
B813: REVERSAR EN MAYO 2026 (MOV ABRIL APP CARGADOS EN MAYO) | E813: CAR | F813: Services/House | G813: 5226 | H813: Remuneraciones Servicios | I813: =+E813&G813 -> CAR5226 | K813: -926.38462 | M813: 46142 | O813: Carmelo Lodge | P813: 46158 | S813: sueldo abril paloma marchetti | U813: Banco Itau - UY
B814: REVERSAR EN MAYO 2026 (MOV ABRIL APP CARGADOS EN MAYO) | E814: CAR | F814: Services/House | G814: 5226 | H814: Remuneraciones Servicios | I814: =+E814&G814 -> CAR5226 | K814: -909.10256 | M814: 46142 | O814: Carmelo Lodge | P814: 46158 | S814: sueldo abril stefany suhr | U814: Banco Itau - UY
B815: REVERSAR EN MAYO 2026 (MOV ABRIL APP CARGADOS EN MAYO) | E815: CAR | F815: Services/House | G815: 5226 | H815: Remuneraciones Servicios | I815: =+E815&G815 -> CAR5226 | K815: -926.38462 | M815: 46142 | O815: Carmelo Lodge | P815: 46158 | S815: sueldo abril Valeria Olmedo | U815: Banco Itau - UY
B816: REVERSAR EN MAYO 2026 (MOV ABRIL APP CARGADOS EN MAYO) | E816: CAR | F816: Services/House | G816: 5226 | H816: Remuneraciones Servicios | I816: =+E816&G816 -> CAR5226 | K816: -909.10256 | M816: 46142 | O816: Carmelo Lodge | P816: 46158 | S816: sueldo abril yuliana gonzalez | U816: Banco Itau - UY
B817: REVERSAR EN MAYO 2026 (MOV ABRIL APP CARGADOS EN MAYO) | E817: CAR | F817: Guides | G817: 5227 | H817: Remuneraciones Guías | I817: =+E817&G817 -> CAR5227 | K817: -457.69231 | M817: 46142 | O817: Carmelo Lodge | P817: 46158 | S817: bb abril 2 Brandon maidana | U817: Banco Itau - UY
